{
  "type": "Feature",
  "properties": {
    "gn:admin1_code":"12.0",
    "gn:asciiname":"Kinombe",
    "gn:country_code":"BI",
    "gn:dem":1485,
    "gn:feature_class":"P",
    "gn:feature_code":"PPLL",
    "gn:name":"Kinombe",
    "gn:population":0,
    "gn:timezone":"Africa/Bujumbura",
    "iso:country":"BI",
    "wof:name":"Kinombe",
    "wof:placetype":"locality"
},
  "geometry": {"coordinates":[29.3176,-2.9529],"type":"Point"}
}