{
  "type": "Feature",
  "properties": {
    "gn:admin1_code":"19.0",
    "gn:asciiname":"Burenge",
    "gn:country_code":"BI",
    "gn:dem":1518,
    "gn:feature_class":"P",
    "gn:feature_code":"PPLL",
    "gn:name":"Burenge",
    "gn:population":0,
    "gn:timezone":"Africa/Bujumbura",
    "iso:country":"BI",
    "wof:name":"Burenge",
    "wof:placetype":"locality"
},
  "geometry": {"coordinates":[30.0119,-2.7301],"type":"Point"}
}