{
  "type": "Feature",
  "properties": {
    "gn:admin1_code":"23",
    "gn:asciiname":"Mutumba",
    "gn:country_code":"BI",
    "gn:dem":1872,
    "gn:feature_class":"P",
    "gn:feature_code":"PPLL",
    "gn:name":"Mutumba",
    "gn:population":0,
    "gn:timezone":"Africa/Bujumbura",
    "iso:country":"BI",
    "wof:name":"Mutumba",
    "wof:placetype":"locality"
},
  "geometry": {"coordinates":[29.6948,-3.6499],"type":"Point"}
}