{
  "type": "Feature",
  "properties": {
    "gn:admin1_code":"18.0",
    "gn:asciiname":"Nyarurambi",
    "gn:country_code":"BI",
    "gn:dem":1487,
    "gn:feature_class":"P",
    "gn:feature_code":"PPL",
    "gn:name":"Nyarurambi",
    "gn:population":0,
    "gn:timezone":"Africa/Bujumbura",
    "iso:country":"BI",
    "wof:name":"Nyarurambi",
    "wof:placetype":"locality"
},
  "geometry": {"coordinates":[30.27748,-3.1496],"type":"Point"}
}