{
  "type": "Feature",
  "properties": {
    "gn:admin1_code":"12.0",
    "gn:asciiname":"Mabayi",
    "gn:country_code":"BI",
    "gn:dem":1464,
    "gn:feature_class":"P",
    "gn:feature_code":"PPL",
    "gn:name":"Mabayi",
    "gn:population":0,
    "gn:timezone":"Africa/Bujumbura",
    "iso:country":"BI",
    "wof:name":"Mabayi",
    "wof:placetype":"locality"
},
  "geometry": {"coordinates":[29.24198,-2.70879],"type":"Point"}
}