{
  "type": "Feature",
  "properties": {
    "gn:admin1_code":"14.0",
    "gn:asciiname":"Kibuye",
    "gn:country_code":"BI",
    "gn:dem":1613,
    "gn:feature_class":"P",
    "gn:feature_code":"PPL",
    "gn:name":"Kibuye",
    "gn:population":0,
    "gn:timezone":"Africa/Bujumbura",
    "iso:country":"BI",
    "name:ben_x_preferred":[
        "\u0995\u09bf\u09ac\u09c1\u09df\u09c7"
    ],
    "name:ceb_x_preferred":[
        "Kibuye"
    ],
    "name:fas_x_preferred":[
        "\u06a9\u06cc\u0628\u0648\u06cc\u0647"
    ],
    "name:heb_x_preferred":[
        "\u05e7\u05d9\u05d1\u05d5\u05d9\u05d4"
    ],
    "name:hin_x_preferred":[
        "\u0915\u093f\u092c\u0941\u092f\u0947"
    ],
    "name:hun_x_preferred":[
        "Kibuye"
    ],
    "name:ind_x_preferred":[
        "Kibuye"
    ],
    "name:ita_x_preferred":[
        "Kibuye"
    ],
    "name:swe_x_preferred":[
        "Kibuye"
    ],
    "name:ukr_x_preferred":[
        "\u041a\u0456\u0431\u0443\u0454"
    ],
    "name:vie_x_preferred":[
        "Kibuye"
    ],
    "wof:name":"Kibuye",
    "wof:placetype":"locality"
},
  "geometry": {"coordinates":[30.2297,-3.1583],"type":"Point"}
}