{
  "type": "Feature",
  "properties": {
    "gn:admin1_code":"14.0",
    "gn:asciiname":"Kibuye",
    "gn:country_code":"BI",
    "gn:dem":1613,
    "gn:feature_class":"P",
    "gn:feature_code":"PPL",
    "gn:name":"Kibuye",
    "gn:population":0,
    "gn:timezone":"Africa/Bujumbura",
    "iso:country":"BI",
    "name:ceb_x_preferred":[
        "Kibuye"
    ],
    "name:swe_x_preferred":[
        "Kibuye"
    ],
    "wof:name":"Kibuye",
    "wof:placetype":"locality"
},
  "geometry": {"coordinates":[30.2297,-3.1583],"type":"Point"}
}