{
  "type": "Feature",
  "properties": {
    "gn:admin1_code":"13.0",
    "gn:asciiname":"Kibungo",
    "gn:country_code":"BI",
    "gn:dem":1636,
    "gn:feature_class":"P",
    "gn:feature_code":"PPLL",
    "gn:name":"Kibungo",
    "gn:population":0,
    "gn:timezone":"Africa/Bujumbura",
    "iso:country":"BI",
    "name:und_x_variant":[
        "Kibango",
        "Kibungo"
    ],
    "wof:name":"Kibungo",
    "wof:placetype":"locality"
},
  "geometry": {"coordinates":[29.8808,-3.2315],"type":"Point"}
}