{
  "type": "Feature",
  "properties": {
    "gn:admin1_code":"11",
    "gn:asciiname":"Kabeza",
    "gn:country_code":"BI",
    "gn:dem":1685,
    "gn:feature_class":"P",
    "gn:feature_code":"PPLL",
    "gn:name":"Kabeza",
    "gn:population":0,
    "gn:timezone":"Africa/Bujumbura",
    "iso:country":"BI",
    "wof:name":"Kabeza",
    "wof:placetype":"locality"
},
  "geometry": {"coordinates":[30.5894,-3.2153],"type":"Point"}
}