{
  "type": "Feature",
  "properties": {
    "gn:admin1_code":"22.0",
    "gn:asciiname":"Gahisi",
    "gn:country_code":"BI",
    "gn:dem":1687,
    "gn:feature_class":"P",
    "gn:feature_code":"PPLL",
    "gn:name":"Gahisi",
    "gn:population":0,
    "gn:timezone":"Africa/Bujumbura",
    "iso:country":"BI",
    "wof:name":"Gahisi",
    "wof:placetype":"locality"
},
  "geometry": {"coordinates":[29.7733,-3.2242],"type":"Point"}
}