{
  "type": "Feature",
  "properties": {
    "gn:admin1_code":"18.0",
    "gn:asciiname":"Mbizi",
    "gn:country_code":"BI",
    "gn:dem":1779,
    "gn:feature_class":"P",
    "gn:feature_code":"PPLL",
    "gn:name":"Mbizi",
    "gn:population":0,
    "gn:timezone":"Africa/Bujumbura",
    "iso:country":"BI",
    "name:bar_x_preferred":[
        "Mbizi"
    ],
    "name:deu_x_preferred":[
        "Mbizi"
    ],
    "wof:name":"Mbizi",
    "wof:placetype":"locality"
},
  "geometry": {"coordinates":[30.285,-2.9925],"type":"Point"}
}