{
  "type": "Feature",
  "properties": {
    "gn:admin1_code":"10",
    "gn:asciiname":"Bubunga",
    "gn:country_code":"BI",
    "gn:dem":1928,
    "gn:feature_class":"P",
    "gn:feature_code":"PPLL",
    "gn:name":"Bubunga",
    "gn:population":0,
    "gn:timezone":"Africa/Bujumbura",
    "iso:country":"BI",
    "wof:name":"Bubunga",
    "wof:placetype":"locality"
},
  "geometry": {"coordinates":[29.608,-3.806],"type":"Point"}
}