{
  "type": "Feature",
  "properties": {
    "gn:admin1_code":"11",
    "gn:asciiname":"Canika",
    "gn:country_code":"BI",
    "gn:dem":1400,
    "gn:feature_class":"P",
    "gn:feature_code":"PPL",
    "gn:name":"Canika",
    "gn:population":0,
    "gn:timezone":"Africa/Bujumbura",
    "iso:country":"BI",
    "wof:name":"Canika",
    "wof:placetype":"locality"
},
  "geometry": {"coordinates":[30.7646,-3.0763],"type":"Point"}
}