{
  "type": "Feature",
  "properties": {
    "gn:admin1_code":"11",
    "gn:asciiname":"Mazingi",
    "gn:country_code":"BI",
    "gn:dem":1584,
    "gn:feature_class":"P",
    "gn:feature_code":"PPLL",
    "gn:name":"Mazingi",
    "gn:population":0,
    "gn:timezone":"Africa/Bujumbura",
    "iso:country":"BI",
    "wof:name":"Mazingi",
    "wof:placetype":"locality"
},
  "geometry": {"coordinates":[30.82800000000001,-3.1513],"type":"Point"}
}