{
  "type": "Feature",
  "properties": {
    "gn:admin1_code":"22",
    "gn:asciiname":"Mpehe",
    "gn:country_code":"BI",
    "gn:dem":2114,
    "gn:feature_class":"P",
    "gn:feature_code":"PPLL",
    "gn:name":"Mpehe",
    "gn:population":0,
    "gn:timezone":"Africa/Bujumbura",
    "iso:country":"BI",
    "wof:name":"Mpehe",
    "wof:placetype":"locality"
},
  "geometry": {"coordinates":[29.5669,-3.3065],"type":"Point"}
}