{
  "type": "Feature",
  "properties": {
    "gn:admin1_code":"23",
    "gn:asciiname":"Buhoyo",
    "gn:country_code":"BI",
    "gn:dem":1641,
    "gn:feature_class":"P",
    "gn:feature_code":"PPLL",
    "gn:name":"Buhoyo",
    "gn:population":0,
    "gn:timezone":"Africa/Bujumbura",
    "iso:country":"BI",
    "wof:name":"Buhoyo",
    "wof:placetype":"locality"
},
  "geometry": {"coordinates":[29.8169,-3.4355],"type":"Point"}
}