{
  "type": "Feature",
  "properties": {
    "gn:admin1_code":"16.0",
    "gn:asciiname":"Ntamba",
    "gn:country_code":"BI",
    "gn:dem":1546,
    "gn:feature_class":"P",
    "gn:feature_code":"PPLL",
    "gn:name":"Ntamba",
    "gn:population":0,
    "gn:timezone":"Africa/Bujumbura",
    "iso:country":"BI",
    "name:hye_x_preferred":[
        "\u0546\u057f\u0561\u0574\u0562\u0561"
    ],
    "name:run_x_preferred":[
        "Ntamba"
    ],
    "wof:name":"Ntamba",
    "wof:placetype":"locality"
},
  "geometry": {"coordinates":[30.3406,-2.6098],"type":"Point"}
}