{
  "type": "Feature",
  "properties": {
    "gn:admin1_code":"19.0",
    "gn:asciiname":"Busiga",
    "gn:country_code":"BI",
    "gn:dem":1810,
    "gn:feature_class":"P",
    "gn:feature_code":"PPL",
    "gn:name":"Busiga",
    "gn:population":0,
    "gn:timezone":"Africa/Bujumbura",
    "iso:country":"BI",
    "wof:name":"Busiga",
    "wof:placetype":"locality"
},
  "geometry": {"coordinates":[29.73883,-2.87873],"type":"Point"}
}