{
  "type": "Feature",
  "properties": {
    "gn:admin1_code":"9.0",
    "gn:asciiname":"Muyange",
    "gn:country_code":"BI",
    "gn:dem":904,
    "gn:feature_class":"P",
    "gn:feature_code":"PPL",
    "gn:name":"Muyange",
    "gn:population":0,
    "gn:timezone":"Africa/Bujumbura",
    "iso:country":"BI",
    "name:run_x_preferred":[
        "Muyange"
    ],
    "wof:name":"Muyange",
    "wof:placetype":"locality"
},
  "geometry": {"coordinates":[29.3407,-3.13],"type":"Point"}
}