{
  "type": "Feature",
  "properties": {
    "gn:admin1_code":"21",
    "gn:asciiname":"Gatura",
    "gn:country_code":"BI",
    "gn:dem":1258,
    "gn:feature_class":"P",
    "gn:feature_code":"PPLL",
    "gn:name":"Gatura",
    "gn:population":0,
    "gn:timezone":"Africa/Bujumbura",
    "iso:country":"BI",
    "wof:name":"Gatura",
    "wof:placetype":"locality"
},
  "geometry": {"coordinates":[30.5731,-3.3585],"type":"Point"}
}