{
  "type": "Feature",
  "properties": {
    "gn:admin1_code":"11.0",
    "gn:asciiname":"Kingoro",
    "gn:country_code":"BI",
    "gn:dem":1466,
    "gn:feature_class":"P",
    "gn:feature_code":"PPLL",
    "gn:name":"Kingoro",
    "gn:population":0,
    "gn:timezone":"Africa/Bujumbura",
    "iso:country":"BI",
    "wof:name":"Kingoro",
    "wof:placetype":"locality"
},
  "geometry": {"coordinates":[30.5972,-2.9263],"type":"Point"}
}