{
  "type": "Feature",
  "properties": {
    "gn:admin1_code":"13",
    "gn:asciiname":"Kibugazi",
    "gn:country_code":"BI",
    "gn:dem":1644,
    "gn:feature_class":"P",
    "gn:feature_code":"PPLL",
    "gn:name":"Kibugazi",
    "gn:population":0,
    "gn:timezone":"Africa/Bujumbura",
    "iso:country":"BI",
    "wof:name":"Kibugazi",
    "wof:placetype":"locality"
},
  "geometry": {"coordinates":[29.9252,-3.5486],"type":"Point"}
}