{
  "type": "Feature",
  "properties": {
    "gn:admin1_code":"13",
    "gn:asciiname":"Muhumya",
    "gn:country_code":"BI",
    "gn:dem":1705,
    "gn:feature_class":"P",
    "gn:feature_code":"PPLL",
    "gn:name":"Muhumya",
    "gn:population":0,
    "gn:timezone":"Africa/Bujumbura",
    "iso:country":"BI",
    "wof:name":"Muhumya",
    "wof:placetype":"locality"
},
  "geometry": {"coordinates":[29.7981,-3.5547],"type":"Point"}
}