{
  "type": "Feature",
  "properties": {
    "gn:admin1_code":"22",
    "gn:asciiname":"Mukoni",
    "gn:country_code":"BI",
    "gn:dem":1982,
    "gn:feature_class":"P",
    "gn:feature_code":"PPLL",
    "gn:name":"Mukoni",
    "gn:population":0,
    "gn:timezone":"Africa/Bujumbura",
    "iso:country":"BI",
    "wof:name":"Mukoni",
    "wof:placetype":"locality"
},
  "geometry": {"coordinates":[29.6503,-3.3343],"type":"Point"}
}