{
  "type": "Feature",
  "properties": {
    "gn:admin1_code":"16.0",
    "gn:asciiname":"Gihohe",
    "gn:country_code":"BI",
    "gn:dem":1700,
    "gn:feature_class":"P",
    "gn:feature_code":"PPLL",
    "gn:name":"Gihohe",
    "gn:population":0,
    "gn:timezone":"Africa/Bujumbura",
    "iso:country":"BI",
    "wof:name":"Gihohe",
    "wof:placetype":"locality"
},
  "geometry": {"coordinates":[29.9664,-2.6381],"type":"Point"}
}