{
  "type": "Feature",
  "properties": {
    "gn:admin1_code":"9.0",
    "gn:asciiname":"Buhoro",
    "gn:country_code":"BI",
    "gn:dem":1418,
    "gn:feature_class":"P",
    "gn:feature_code":"PPLL",
    "gn:name":"Buhoro",
    "gn:population":0,
    "gn:timezone":"Africa/Bujumbura",
    "iso:country":"BI",
    "name:rus_x_preferred":[
        "\u0411\u0443\u0445\u043e\u0440\u043e"
    ],
    "name:swa_x_preferred":[
        "Buhoro"
    ],
    "wof:name":"Buhoro",
    "wof:placetype":"locality"
},
  "geometry": {"coordinates":[29.4127,-2.9684],"type":"Point"}
}