{
  "type": "Feature",
  "properties": {
    "gn:admin1_code":"26",
    "gn:asciiname":"Nyabigonzi",
    "gn:country_code":"BI",
    "gn:dem":923,
    "gn:feature_class":"P",
    "gn:feature_code":"PPLL",
    "gn:name":"Nyabigonzi",
    "gn:population":0,
    "gn:timezone":"Africa/Bujumbura",
    "iso:country":"BI",
    "wof:name":"Nyabigonzi",
    "wof:placetype":"locality"
},
  "geometry": {"coordinates":[29.4994,-4.0324],"type":"Point"}
}