{
  "type": "Feature",
  "properties": {
    "gn:admin1_code":"17",
    "gn:asciiname":"Gitanga",
    "gn:country_code":"BI",
    "gn:dem":1511,
    "gn:feature_class":"P",
    "gn:feature_code":"PPLL",
    "gn:name":"Gitanga",
    "gn:population":0,
    "gn:timezone":"Africa/Bujumbura",
    "iso:country":"BI",
    "wof:name":"Gitanga",
    "wof:placetype":"locality"
},
  "geometry": {"coordinates":[29.7907,-4.1354],"type":"Point"}
}