{
  "type": "Feature",
  "properties": {
    "gn:admin1_code":"17",
    "gn:asciiname":"Budatekwa",
    "gn:country_code":"BI",
    "gn:dem":1561,
    "gn:feature_class":"P",
    "gn:feature_code":"PPLL",
    "gn:name":"Budatekwa",
    "gn:population":0,
    "gn:timezone":"Africa/Bujumbura",
    "iso:country":"BI",
    "wof:name":"Budatekwa",
    "wof:placetype":"locality"
},
  "geometry": {"coordinates":[29.7849,-4.3957],"type":"Point"}
}