{
  "type": "Feature",
  "properties": {
    "gn:admin1_code":"16.0",
    "gn:asciiname":"Mukerwa",
    "gn:country_code":"BI",
    "gn:dem":1637,
    "gn:feature_class":"P",
    "gn:feature_code":"PPLL",
    "gn:name":"Mukerwa",
    "gn:population":0,
    "gn:timezone":"Africa/Bujumbura",
    "iso:country":"BI",
    "wof:name":"Mukerwa",
    "wof:placetype":"locality"
},
  "geometry": {"coordinates":[30.1911,-2.6035],"type":"Point"}
}