{
  "type": "Feature",
  "properties": {
    "gn:admin1_code":"18.0",
    "gn:asciiname":"Mageregere",
    "gn:country_code":"BI",
    "gn:dem":1597,
    "gn:feature_class":"P",
    "gn:feature_code":"PPLL",
    "gn:name":"Mageregere",
    "gn:population":0,
    "gn:timezone":"Africa/Bujumbura",
    "iso:country":"BI",
    "wof:name":"Mageregere",
    "wof:placetype":"locality"
},
  "geometry": {"coordinates":[30.1139,-2.8079],"type":"Point"}
}