{
  "type": "Feature",
  "properties": {
    "gn:admin1_code":"11",
    "gn:asciiname":"Kumuzu",
    "gn:country_code":"BI",
    "gn:dem":1565,
    "gn:feature_class":"P",
    "gn:feature_code":"PPLL",
    "gn:name":"Kumuzu",
    "gn:population":0,
    "gn:timezone":"Africa/Bujumbura",
    "iso:country":"BI",
    "wof:name":"Kumuzu",
    "wof:placetype":"locality"
},
  "geometry": {"coordinates":[30.5122,-3.2936],"type":"Point"}
}