{
  "type": "Feature",
  "properties": {
    "gn:admin1_code":"20",
    "gn:asciiname":"Bukemba",
    "gn:country_code":"BI",
    "gn:dem":1218,
    "gn:feature_class":"P",
    "gn:feature_code":"PPL",
    "gn:name":"Bukemba",
    "gn:population":0,
    "gn:timezone":"Africa/Bujumbura",
    "iso:country":"BI",
    "wof:name":"Bukemba",
    "wof:placetype":"locality"
},
  "geometry": {"coordinates":[30.0546,-3.9951],"type":"Point"}
}