{
  "type": "Feature",
  "properties": {
    "gn:admin1_code":"20",
    "gn:asciiname":"Gisoro",
    "gn:country_code":"BI",
    "gn:dem":1799,
    "gn:feature_class":"P",
    "gn:feature_code":"PPLL",
    "gn:name":"Gisoro",
    "gn:population":0,
    "gn:timezone":"Africa/Bujumbura",
    "iso:country":"BI",
    "name:und_x_variant":[
        "Kisoro",
        "Gisoro"
    ],
    "wof:name":"Gisoro",
    "wof:placetype":"locality"
},
  "geometry": {"coordinates":[30.2056,-3.706],"type":"Point"}
}