{
  "type": "Feature",
  "properties": {
    "gn:admin1_code":"11",
    "gn:asciiname":"Muvumu",
    "gn:country_code":"BI",
    "gn:dem":1663,
    "gn:feature_class":"P",
    "gn:feature_code":"PPL",
    "gn:name":"Muvumu",
    "gn:population":0,
    "gn:timezone":"Africa/Bujumbura",
    "iso:country":"BI",
    "wof:name":"Muvumu",
    "wof:placetype":"locality"
},
  "geometry": {"coordinates":[30.45602,-3.27894],"type":"Point"}
}