{
  "type": "Feature",
  "properties": {
    "gn:admin1_code":"21",
    "gn:asciiname":"Rusengo",
    "gn:country_code":"BI",
    "gn:dem":1646,
    "gn:feature_class":"P",
    "gn:feature_code":"PPL",
    "gn:name":"Rusengo",
    "gn:population":0,
    "gn:timezone":"Africa/Bujumbura",
    "iso:country":"BI",
    "wof:name":"Rusengo",
    "wof:placetype":"locality"
},
  "geometry": {"coordinates":[30.3512,-3.3962],"type":"Point"}
}