{
  "type": "Feature",
  "properties": {
    "gn:admin1_code":"16.0",
    "gn:asciiname":"Vumbi",
    "gn:country_code":"BI",
    "gn:dem":1653,
    "gn:feature_class":"P",
    "gn:feature_code":"PPLL",
    "gn:name":"Vumbi",
    "gn:population":0,
    "gn:timezone":"Africa/Bujumbura",
    "iso:country":"BI",
    "name:run_x_preferred":[
        "Vumbi"
    ],
    "wof:name":"Vumbi",
    "wof:placetype":"locality"
},
  "geometry": {"coordinates":[30.1042,-2.7189],"type":"Point"}
}