{
  "type": "Feature",
  "properties": {
    "gn:admin1_code":"13",
    "gn:asciiname":"Mugera",
    "gn:country_code":"BI",
    "gn:dem":1749,
    "gn:feature_class":"P",
    "gn:feature_code":"PPL",
    "gn:name":"Mugera",
    "gn:population":0,
    "gn:timezone":"Africa/Bujumbura",
    "iso:country":"BI",
    "wof:name":"Mugera",
    "wof:placetype":"locality"
},
  "geometry": {"coordinates":[29.9636,-3.32],"type":"Point"}
}