{
  "type": "Feature",
  "properties": {
    "gn:admin1_code":"12.0",
    "gn:asciiname":"Murama",
    "gn:country_code":"BI",
    "gn:dem":1181,
    "gn:feature_class":"P",
    "gn:feature_code":"PPLL",
    "gn:name":"Murama",
    "gn:population":0,
    "gn:timezone":"Africa/Bujumbura",
    "iso:country":"BI",
    "wof:name":"Murama",
    "wof:placetype":"locality"
},
  "geometry": {"coordinates":[29.0736,-2.7056],"type":"Point"}
}