{
  "type": "Feature",
  "properties": {
    "gn:admin1_code":"22",
    "gn:asciiname":"Nyarubari",
    "gn:country_code":"BI",
    "gn:dem":1837,
    "gn:feature_class":"P",
    "gn:feature_code":"PPLL",
    "gn:name":"Nyarubari",
    "gn:population":0,
    "gn:timezone":"Africa/Bujumbura",
    "iso:country":"BI",
    "wof:name":"Nyarubari",
    "wof:placetype":"locality"
},
  "geometry": {"coordinates":[29.6703,-3.3074],"type":"Point"}
}