{
  "type": "Feature",
  "properties": {
    "gn:admin1_code":"12.0",
    "gn:asciiname":"Muhingo",
    "gn:country_code":"BI",
    "gn:dem":1331,
    "gn:feature_class":"P",
    "gn:feature_code":"PPL",
    "gn:name":"Muhingo",
    "gn:population":0,
    "gn:timezone":"Africa/Bujumbura",
    "iso:country":"BI",
    "wof:name":"Muhingo",
    "wof:placetype":"locality"
},
  "geometry": {"coordinates":[29.1912,-2.7101],"type":"Point"}
}