{
  "type": "Feature",
  "properties": {
    "gn:admin1_code":"17",
    "gn:asciiname":"Marindye",
    "gn:country_code":"BI",
    "gn:dem":1537,
    "gn:feature_class":"P",
    "gn:feature_code":"PPLL",
    "gn:name":"Marindye",
    "gn:population":0,
    "gn:timezone":"Africa/Bujumbura",
    "iso:country":"BI",
    "wof:name":"Marindye",
    "wof:placetype":"locality"
},
  "geometry": {"coordinates":[29.8505,-4.1177],"type":"Point"}
}