{
  "type": "Feature",
  "properties": {
    "gn:admin1_code":"19.0",
    "gn:asciiname":"Kabere",
    "gn:country_code":"BI",
    "gn:dem":1702,
    "gn:feature_class":"P",
    "gn:feature_code":"PPL",
    "gn:name":"Kabere",
    "gn:population":0,
    "gn:timezone":"Africa/Bujumbura",
    "iso:country":"BI",
    "wof:name":"Kabere",
    "wof:placetype":"locality"
},
  "geometry": {"coordinates":[29.7692,-2.9332],"type":"Point"}
}