{
  "type": "Feature",
  "properties": {
    "gn:admin1_code":"18.0",
    "gn:asciiname":"Mangoma",
    "gn:country_code":"BI",
    "gn:dem":1514,
    "gn:feature_class":"P",
    "gn:feature_code":"PPLL",
    "gn:name":"Mangoma",
    "gn:population":0,
    "gn:timezone":"Africa/Bujumbura",
    "iso:country":"BI",
    "wof:name":"Mangoma",
    "wof:placetype":"locality"
},
  "geometry": {"coordinates":[30.4021,-2.6074],"type":"Point"}
}