{
  "type": "Feature",
  "properties": {
    "gn:admin1_code":"16.0",
    "gn:asciiname":"Murambi",
    "gn:country_code":"BI",
    "gn:dem":1374,
    "gn:feature_class":"P",
    "gn:feature_code":"PPLL",
    "gn:name":"Murambi",
    "gn:population":0,
    "gn:timezone":"Africa/Bujumbura",
    "iso:country":"BI",
    "name:ita_x_preferred":[
        "Murambi"
    ],
    "wof:name":"Murambi",
    "wof:placetype":"locality"
},
  "geometry": {"coordinates":[30.1383,-2.484],"type":"Point"}
}