{
  "type": "Feature",
  "properties": {
    "gn:admin1_code":"19.0",
    "gn:asciiname":"Shango",
    "gn:country_code":"BI",
    "gn:dem":1610,
    "gn:feature_class":"P",
    "gn:feature_code":"PPLL",
    "gn:name":"Shango",
    "gn:population":0,
    "gn:timezone":"Africa/Bujumbura",
    "iso:country":"BI",
    "name:bre_x_preferred":[
        "Chang\u00f3"
    ],
    "name:bul_x_preferred":[
        "\u0428\u0430\u043d\u0433\u043e"
    ],
    "name:cat_x_preferred":[
        "Xang\u00f3"
    ],
    "name:deu_x_preferred":[
        "Shango"
    ],
    "name:ell_x_preferred":[
        "\u03a3\u03ac\u03b3\u03ba\u03bf"
    ],
    "name:epo_x_preferred":[
        "\u015cangoo"
    ],
    "name:est_x_preferred":[
        "\u1e62\u00e0ng\u00f3"
    ],
    "name:fra_x_preferred":[
        "Shang\u00f4"
    ],
    "name:ita_x_preferred":[
        "Shango"
    ],
    "name:jpn_x_preferred":[
        "\u30b7\u30e3\u30f3\u30b4"
    ],
    "name:pol_x_preferred":[
        "Szango"
    ],
    "name:por_x_preferred":[
        "Xang\u00f4"
    ],
    "name:rus_x_preferred":[
        "\u0428\u0430\u043d\u0433\u043e"
    ],
    "name:spa_x_preferred":[
        "Chang\u00f3"
    ],
    "name:swe_x_preferred":[
        "Shango"
    ],
    "name:vie_x_preferred":[
        "Shango"
    ],
    "name:yor_x_preferred":[
        "\u1e62\u00e0ng\u00f3"
    ],
    "wof:name":"Shango",
    "wof:placetype":"locality"
},
  "geometry": {"coordinates":[29.8448,-2.9367],"type":"Point"}
}