{
  "type": "Feature",
  "properties": {
    "gn:admin1_code":"19.0",
    "gn:asciiname":"Shango",
    "gn:country_code":"BI",
    "gn:dem":1610,
    "gn:feature_class":"P",
    "gn:feature_code":"PPLL",
    "gn:name":"Shango",
    "gn:population":0,
    "gn:timezone":"Africa/Bujumbura",
    "iso:country":"BI",
    "wof:name":"Shango",
    "wof:placetype":"locality"
},
  "geometry": {"coordinates":[29.8448,-2.9367],"type":"Point"}
}