{
  "type": "Feature",
  "properties": {
    "gn:admin1_code":"9.0",
    "gn:asciiname":"Kunyange",
    "gn:country_code":"BI",
    "gn:dem":935,
    "gn:feature_class":"P",
    "gn:feature_code":"PPLL",
    "gn:name":"Kunyange",
    "gn:population":0,
    "gn:timezone":"Africa/Bujumbura",
    "iso:country":"BI",
    "wof:name":"Kunyange",
    "wof:placetype":"locality"
},
  "geometry": {"coordinates":[29.3904,-3.1228],"type":"Point"}
}