{
  "type": "Feature",
  "properties": {
    "gn:admin1_code":"14.0",
    "gn:asciiname":"Maruri",
    "gn:country_code":"BI",
    "gn:dem":1700,
    "gn:feature_class":"P",
    "gn:feature_code":"PPLL",
    "gn:name":"Maruri",
    "gn:population":0,
    "gn:timezone":"Africa/Bujumbura",
    "iso:country":"BI",
    "name:ceb_x_preferred":[
        "Maruri"
    ],
    "name:swe_x_preferred":[
        "Maruri"
    ],
    "wof:name":"Maruri",
    "wof:placetype":"locality"
},
  "geometry": {"coordinates":[29.9953,-3.1086],"type":"Point"}
}