{
  "type": "Feature",
  "properties": {
    "gn:admin1_code":"25",
    "gn:asciiname":"Migera",
    "gn:country_code":"BI",
    "gn:dem":1044,
    "gn:feature_class":"P",
    "gn:feature_code":"PPLL",
    "gn:name":"Migera",
    "gn:population":0,
    "gn:timezone":"Africa/Bujumbura",
    "iso:country":"BI",
    "wof:name":"Migera",
    "wof:placetype":"locality"
},
  "geometry": {"coordinates":[29.3606,-3.5688],"type":"Point"}
}