{
  "type": "Feature",
  "properties": {
    "gn:admin1_code":"19.0",
    "gn:asciiname":"Bitambwe",
    "gn:country_code":"BI",
    "gn:dem":1830,
    "gn:feature_class":"P",
    "gn:feature_code":"PPLL",
    "gn:name":"Bitambwe",
    "gn:population":0,
    "gn:timezone":"Africa/Bujumbura",
    "iso:country":"BI",
    "wof:name":"Bitambwe",
    "wof:placetype":"locality"
},
  "geometry": {"coordinates":[29.7247,-2.8755],"type":"Point"}
}