{
  "type": "Feature",
  "properties": {
    "gn:admin1_code":"25",
    "gn:asciiname":"Masama",
    "gn:country_code":"BI",
    "gn:dem":1203,
    "gn:feature_class":"P",
    "gn:feature_code":"PPLL",
    "gn:name":"Masama",
    "gn:population":0,
    "gn:timezone":"Africa/Bujumbura",
    "iso:country":"BI",
    "wof:name":"Masama",
    "wof:placetype":"locality"
},
  "geometry": {"coordinates":[29.3725,-3.5596],"type":"Point"}
}