{
  "type": "Feature",
  "properties": {
    "gn:admin1_code":"10",
    "gn:asciiname":"Muka",
    "gn:country_code":"BI",
    "gn:dem":1877,
    "gn:feature_class":"P",
    "gn:feature_code":"PPLL",
    "gn:name":"Muka",
    "gn:population":0,
    "gn:timezone":"Africa/Bujumbura",
    "iso:country":"BI",
    "wof:name":"Muka",
    "wof:placetype":"locality"
},
  "geometry": {"coordinates":[29.7374,-3.8296],"type":"Point"}
}