{
  "type": "Feature",
  "properties": {
    "gn:admin1_code":"9.0",
    "gn:asciiname":"Kidumbugo",
    "gn:country_code":"BI",
    "gn:dem":1447,
    "gn:feature_class":"P",
    "gn:feature_code":"PPLL",
    "gn:name":"Kidumbugo",
    "gn:population":0,
    "gn:timezone":"Africa/Bujumbura",
    "iso:country":"BI",
    "wof:name":"Kidumbugo",
    "wof:placetype":"locality"
},
  "geometry": {"coordinates":[29.3843,-2.9747],"type":"Point"}
}