{
  "type": "Feature",
  "properties": {
    "gn:admin1_code":"21.0",
    "gn:asciiname":"Miheno",
    "gn:country_code":"BI",
    "gn:dem":1425,
    "gn:feature_class":"P",
    "gn:feature_code":"PPL",
    "gn:name":"Miheno",
    "gn:population":0,
    "gn:timezone":"Africa/Bujumbura",
    "iso:country":"BI",
    "wof:name":"Miheno",
    "wof:placetype":"locality"
},
  "geometry": {"coordinates":[30.43261,-3.38383],"type":"Point"}
}