{
  "type": "Feature",
  "properties": {
    "gn:admin1_code":"9.0",
    "gn:asciiname":"Masha",
    "gn:country_code":"BI",
    "gn:dem":1105,
    "gn:feature_class":"P",
    "gn:feature_code":"PPL",
    "gn:name":"Masha",
    "gn:population":0,
    "gn:timezone":"Africa/Bujumbura",
    "iso:country":"BI",
    "name:deu_x_preferred":[
        "Mascha"
    ],
    "name:fra_x_preferred":[
        "Macha"
    ],
    "name:ltz_x_preferred":[
        "Mascha"
    ],
    "name:ron_x_preferred":[
        "Ma\u0219a"
    ],
    "name:srp_x_preferred":[
        "\u041c\u0430\u0448\u0430"
    ],
    "wof:name":"Masha",
    "wof:placetype":"locality"
},
  "geometry": {"coordinates":[29.4361,-3.1826],"type":"Point"}
}