{
  "type": "Feature",
  "properties": {
    "gn:admin1_code":"22.0",
    "gn:asciiname":"Rwantamba",
    "gn:country_code":"BI",
    "gn:dem":1974,
    "gn:feature_class":"P",
    "gn:feature_code":"PPLL",
    "gn:name":"Rwantamba",
    "gn:population":0,
    "gn:timezone":"Africa/Bujumbura",
    "iso:country":"BI",
    "wof:name":"Rwantamba",
    "wof:placetype":"locality"
},
  "geometry": {"coordinates":[29.629,-3.245],"type":"Point"}
}