{
  "type": "Feature",
  "properties": {
    "gn:admin1_code":"12.0",
    "gn:asciiname":"Busaga",
    "gn:country_code":"BI",
    "gn:dem":1274,
    "gn:feature_class":"P",
    "gn:feature_code":"PPLL",
    "gn:name":"Busaga",
    "gn:population":0,
    "gn:timezone":"Africa/Bujumbura",
    "iso:country":"BI",
    "wof:name":"Busaga",
    "wof:placetype":"locality"
},
  "geometry": {"coordinates":[29.1325,-2.7441],"type":"Point"}
}