{
  "type": "Feature",
  "properties": {
    "gn:admin1_code":"21",
    "gn:asciiname":"Gihambwe",
    "gn:country_code":"BI",
    "gn:dem":1210,
    "gn:feature_class":"P",
    "gn:feature_code":"PPLL",
    "gn:name":"Gihambwe",
    "gn:population":0,
    "gn:timezone":"Africa/Bujumbura",
    "iso:country":"BI",
    "wof:name":"Gihambwe",
    "wof:placetype":"locality"
},
  "geometry": {"coordinates":[30.3157,-3.5712],"type":"Point"}
}