{
  "type": "Feature",
  "properties": {
    "gn:admin1_code":"9.0",
    "gn:asciiname":"Mutobo",
    "gn:country_code":"BI",
    "gn:dem":1542,
    "gn:feature_class":"P",
    "gn:feature_code":"PPLL",
    "gn:name":"Mutobo",
    "gn:population":0,
    "gn:timezone":"Africa/Bujumbura",
    "iso:country":"BI",
    "wof:name":"Mutobo",
    "wof:placetype":"locality"
},
  "geometry": {"coordinates":[29.4612,-3.015],"type":"Point"}
}