{
  "type": "Feature",
  "properties": {
    "gn:admin1_code":"15.0",
    "gn:asciiname":"Nyabikere",
    "gn:country_code":"BI",
    "gn:dem":1720,
    "gn:feature_class":"P",
    "gn:feature_code":"PPLL",
    "gn:name":"Nyabikere",
    "gn:population":0,
    "gn:timezone":"Africa/Bujumbura",
    "iso:country":"BI",
    "wof:name":"Nyabikere",
    "wof:placetype":"locality"
},
  "geometry": {"coordinates":[29.7188,-2.9583],"type":"Point"}
}