{
  "type": "Feature",
  "properties": {
    "gn:admin1_code":"13",
    "gn:asciiname":"Canzu",
    "gn:country_code":"BI",
    "gn:dem":1732,
    "gn:feature_class":"P",
    "gn:feature_code":"PPLL",
    "gn:name":"Canzu",
    "gn:population":0,
    "gn:timezone":"Africa/Bujumbura",
    "iso:country":"BI",
    "name:und_x_variant":[
        "Chanzu",
        "Canzu"
    ],
    "wof:name":"Canzu",
    "wof:placetype":"locality"
},
  "geometry": {"coordinates":[30.0789,-3.6573],"type":"Point"}
}