{
  "type": "Feature",
  "properties": {
    "gn:admin1_code":"11.0",
    "gn:asciiname":"Kibungo",
    "gn:country_code":"BI",
    "gn:dem":1462,
    "gn:feature_class":"P",
    "gn:feature_code":"PPLL",
    "gn:name":"Kibungo",
    "gn:population":0,
    "gn:timezone":"Africa/Bujumbura",
    "iso:country":"BI",
    "name:cat_x_preferred":[
        "Kibungo"
    ],
    "name:ceb_x_preferred":[
        "Kibungo"
    ],
    "name:deu_x_preferred":[
        "Kibungo"
    ],
    "name:ell_x_preferred":[
        "\u039a\u03b9\u03bc\u03c0\u03bf\u03cd\u03bd\u03b3\u03ba\u03bf"
    ],
    "name:est_x_preferred":[
        "Kibungo"
    ],
    "name:eus_x_preferred":[
        "Kibungo"
    ],
    "name:fra_x_preferred":[
        "Kibungo"
    ],
    "name:hrv_x_preferred":[
        "Kibungo"
    ],
    "name:ita_x_preferred":[
        "Kibungo"
    ],
    "name:jpn_x_preferred":[
        "\u30ad\u30d6\u30f3\u30b4"
    ],
    "name:kor_x_preferred":[
        "\ud0a4\ubd95\uace0"
    ],
    "name:lit_x_preferred":[
        "Kibungas"
    ],
    "name:mrj_x_preferred":[
        "\u041a\u0438\u0431\u0443\u043d\u0433\u043e"
    ],
    "name:nld_x_preferred":[
        "Kibungo"
    ],
    "name:pol_x_preferred":[
        "Kibungo"
    ],
    "name:por_x_preferred":[
        "Kibungo"
    ],
    "name:ron_x_preferred":[
        "Kibungo"
    ],
    "name:rus_x_preferred":[
        "\u041a\u0438\u0431\u0443\u043d\u0433\u043e"
    ],
    "name:tur_x_preferred":[
        "Kibungo"
    ],
    "name:ukr_x_preferred":[
        "\u041a\u0456\u0431\u0443\u043d\u0433\u043e"
    ],
    "name:zho_x_preferred":[
        "\u57fa\u672c\u53e4"
    ],
    "wof:name":"Kibungo",
    "wof:placetype":"locality"
},
  "geometry": {"coordinates":[30.5275,-2.9754],"type":"Point"}
}