{
  "type": "Feature",
  "properties": {
    "gn:admin1_code":"9.0",
    "gn:asciiname":"Kabwitika",
    "gn:country_code":"BI",
    "gn:dem":1155,
    "gn:feature_class":"P",
    "gn:feature_code":"PPLL",
    "gn:name":"Kabwitika",
    "gn:population":0,
    "gn:timezone":"Africa/Bujumbura",
    "iso:country":"BI",
    "name:run_x_preferred":[
        "Kabwitika"
    ],
    "wof:name":"Kabwitika",
    "wof:placetype":"locality"
},
  "geometry": {"coordinates":[29.3778,-3.058],"type":"Point"}
}