{
  "type": "Feature",
  "properties": {
    "gn:admin1_code":"12.0",
    "gn:asciiname":"Rushiha",
    "gn:country_code":"BI",
    "gn:dem":1707,
    "gn:feature_class":"P",
    "gn:feature_code":"PPL",
    "gn:name":"Rushiha",
    "gn:population":0,
    "gn:timezone":"Africa/Bujumbura",
    "iso:country":"BI",
    "wof:name":"Rushiha",
    "wof:placetype":"locality"
},
  "geometry": {"coordinates":[29.243,-2.7314],"type":"Point"}
}