{
  "type": "Feature",
  "properties": {
    "gn:admin1_code":"15.0",
    "gn:asciiname":"Gacu",
    "gn:country_code":"BI",
    "gn:dem":1873,
    "gn:feature_class":"P",
    "gn:feature_code":"PPLL",
    "gn:name":"Gacu",
    "gn:population":0,
    "gn:timezone":"Africa/Bujumbura",
    "iso:country":"BI",
    "wof:name":"Gacu",
    "wof:placetype":"locality"
},
  "geometry": {"coordinates":[29.6168,-2.8911],"type":"Point"}
}