{
  "type": "Feature",
  "properties": {
    "gn:admin1_code":"25",
    "gn:asciiname":"Mugendo",
    "gn:country_code":"BI",
    "gn:dem":1784,
    "gn:feature_class":"P",
    "gn:feature_code":"PPLL",
    "gn:name":"Mugendo",
    "gn:population":0,
    "gn:timezone":"Africa/Bujumbura",
    "iso:country":"BI",
    "wof:name":"Mugendo",
    "wof:placetype":"locality"
},
  "geometry": {"coordinates":[29.4465,-3.4778],"type":"Point"}
}