{
  "type": "Feature",
  "properties": {
    "gn:admin1_code":"19.0",
    "gn:asciiname":"Rutobo",
    "gn:country_code":"BI",
    "gn:dem":1751,
    "gn:feature_class":"P",
    "gn:feature_code":"PPLL",
    "gn:name":"Rutobo",
    "gn:population":0,
    "gn:timezone":"Africa/Bujumbura",
    "iso:country":"BI",
    "wof:name":"Rutobo",
    "wof:placetype":"locality"
},
  "geometry": {"coordinates":[30.0719,-2.8486],"type":"Point"}
}