{
  "type": "Feature",
  "properties": {
    "gn:admin1_code":"18.0",
    "gn:asciiname":"Gisenyi",
    "gn:country_code":"BI",
    "gn:dem":1477,
    "gn:feature_class":"P",
    "gn:feature_code":"PPLL",
    "gn:name":"Gisenyi",
    "gn:population":0,
    "gn:timezone":"Africa/Bujumbura",
    "iso:country":"BI",
    "name:ara_x_preferred":[
        "\u062c\u064a\u0633\u0627\u064a\u0646\u064a"
    ],
    "name:cat_x_preferred":[
        "Gisenyi"
    ],
    "name:ceb_x_preferred":[
        "Gisenyi"
    ],
    "name:dan_x_preferred":[
        "Gisenyi"
    ],
    "name:deu_x_preferred":[
        "Gisenyi"
    ],
    "name:ell_x_preferred":[
        "\u0393\u03ba\u03b9\u03c3\u03ad\u03bd\u03b9"
    ],
    "name:est_x_preferred":[
        "Gisenyi"
    ],
    "name:eus_x_preferred":[
        "Gisenyi"
    ],
    "name:fra_x_preferred":[
        "Gisenyi"
    ],
    "name:heb_x_preferred":[
        "\u05d2\u05d9\u05e1\u05d0\u05e0\u05d9\u05d9"
    ],
    "name:hrv_x_preferred":[
        "Gisenyi"
    ],
    "name:hun_x_preferred":[
        "Gisenyi"
    ],
    "name:ita_x_preferred":[
        "Gisenyi"
    ],
    "name:jpn_x_preferred":[
        "\u30ae\u30bb\u30cb"
    ],
    "name:kor_x_preferred":[
        "\uae30\uc138\ub2c8"
    ],
    "name:lit_x_preferred":[
        "Gisenjis"
    ],
    "name:mon_x_preferred":[
        "\u0413\u0438\u0441\u044d\u043d\u044c\u0438"
    ],
    "name:mrj_x_preferred":[
        "\u0413\u0438\u0441\u0435\u043d\u044c\u0438"
    ],
    "name:nld_x_preferred":[
        "Gisenyi"
    ],
    "name:nor_x_preferred":[
        "Gisenyi"
    ],
    "name:pol_x_preferred":[
        "Gisenyi"
    ],
    "name:por_x_preferred":[
        "Gisenyi"
    ],
    "name:ron_x_preferred":[
        "Gisenyi"
    ],
    "name:rus_x_preferred":[
        "\u0413\u0438\u0441\u0435\u043d\u044c\u0438"
    ],
    "name:spa_x_preferred":[
        "Gisenyi"
    ],
    "name:swe_x_preferred":[
        "Gisenyi"
    ],
    "name:tur_x_preferred":[
        "Gisenyi"
    ],
    "name:zho_x_preferred":[
        "\u5409\u585e\u5c3c"
    ],
    "wof:name":"Gisenyi",
    "wof:placetype":"locality"
},
  "geometry": {"coordinates":[30.3563,-2.8478],"type":"Point"}
}