{
  "type": "Feature",
  "properties": {
    "gn:admin1_code":"18.0",
    "gn:asciiname":"Gisenyi",
    "gn:country_code":"BI",
    "gn:dem":1477,
    "gn:feature_class":"P",
    "gn:feature_code":"PPLL",
    "gn:name":"Gisenyi",
    "gn:population":0,
    "gn:timezone":"Africa/Bujumbura",
    "iso:country":"BI",
    "wof:name":"Gisenyi",
    "wof:placetype":"locality"
},
  "geometry": {"coordinates":[30.3563,-2.8478],"type":"Point"}
}