{
  "type": "Feature",
  "properties": {
    "gn:admin1_code":"22.0",
    "gn:asciiname":"Butwe",
    "gn:country_code":"BI",
    "gn:dem":1603,
    "gn:feature_class":"P",
    "gn:feature_code":"PPLL",
    "gn:name":"Butwe",
    "gn:population":0,
    "gn:timezone":"Africa/Bujumbura",
    "iso:country":"BI",
    "wof:name":"Butwe",
    "wof:placetype":"locality"
},
  "geometry": {"coordinates":[29.8343,-3.2309],"type":"Point"}
}