{
  "type": "Feature",
  "properties": {
    "gn:admin1_code":"14.0",
    "gn:asciiname":"Nyamashongore",
    "gn:country_code":"BI",
    "gn:dem":1562,
    "gn:feature_class":"P",
    "gn:feature_code":"PPL",
    "gn:name":"Nyamashongore",
    "gn:population":0,
    "gn:timezone":"Africa/Bujumbura",
    "iso:country":"BI",
    "wof:name":"Nyamashongore",
    "wof:placetype":"locality"
},
  "geometry": {"coordinates":[30.1562,-3.0632],"type":"Point"}
}