{
  "type": "Feature",
  "properties": {
    "gn:admin1_code":"23",
    "gn:asciiname":"Shana",
    "gn:country_code":"BI",
    "gn:dem":2035,
    "gn:feature_class":"P",
    "gn:feature_code":"PPLL",
    "gn:name":"Shana",
    "gn:population":0,
    "gn:timezone":"Africa/Bujumbura",
    "iso:country":"BI",
    "wof:name":"Shana",
    "wof:placetype":"locality"
},
  "geometry": {"coordinates":[29.6352,-3.459],"type":"Point"}
}