{
  "type": "Feature",
  "properties": {
    "gn:admin1_code":"23",
    "gn:asciiname":"Shana",
    "gn:country_code":"BI",
    "gn:dem":2035,
    "gn:feature_class":"P",
    "gn:feature_code":"PPLL",
    "gn:name":"Shana",
    "gn:population":0,
    "gn:timezone":"Africa/Bujumbura",
    "iso:country":"BI",
    "name:ceb_x_preferred":[
        "Shana"
    ],
    "name:deu_x_preferred":[
        "Shana"
    ],
    "name:ita_x_preferred":[
        "Shana"
    ],
    "name:jpn_x_preferred":[
        "\u30b7\u30a7\u30fc\u30ca"
    ],
    "name:nld_x_preferred":[
        "Shana"
    ],
    "name:swe_x_preferred":[
        "Shana"
    ],
    "name:tha_x_preferred":[
        "\u0e0a\u0e32\u0e19\u0e30"
    ],
    "wof:name":"Shana",
    "wof:placetype":"locality"
},
  "geometry": {"coordinates":[29.6352,-3.459],"type":"Point"}
}