{
  "type": "Feature",
  "properties": {
    "gn:admin1_code":"22.0",
    "gn:asciiname":"Ruce",
    "gn:country_code":"BI",
    "gn:dem":2152,
    "gn:feature_class":"P",
    "gn:feature_code":"PPLL",
    "gn:name":"Ruce",
    "gn:population":0,
    "gn:timezone":"Africa/Bujumbura",
    "iso:country":"BI",
    "wof:name":"Ruce",
    "wof:placetype":"locality"
},
  "geometry": {"coordinates":[29.54328,-3.30669],"type":"Point"}
}