{
  "type": "Feature",
  "properties": {
    "gn:admin1_code":"26",
    "gn:asciiname":"Kibozi",
    "gn:country_code":"BI",
    "gn:dem":972,
    "gn:feature_class":"P",
    "gn:feature_code":"PPLL",
    "gn:name":"Kibozi",
    "gn:population":0,
    "gn:timezone":"Africa/Bujumbura",
    "iso:country":"BI",
    "wof:name":"Kibozi",
    "wof:placetype":"locality"
},
  "geometry": {"coordinates":[29.3583,-3.7977],"type":"Point"}
}