{
  "type": "Feature",
  "properties": {
    "gn:admin1_code":"11.0",
    "gn:asciiname":"Muryankuru",
    "gn:country_code":"BI",
    "gn:dem":1587,
    "gn:feature_class":"P",
    "gn:feature_code":"PPL",
    "gn:name":"Muryankuru",
    "gn:population":0,
    "gn:timezone":"Africa/Bujumbura",
    "iso:country":"BI",
    "wof:name":"Muryankuru",
    "wof:placetype":"locality"
},
  "geometry": {"coordinates":[30.47346,-3.21104],"type":"Point"}
}