{
  "type": "Feature",
  "properties": {
    "gn:admin1_code":"18.0",
    "gn:asciiname":"Bisibe",
    "gn:country_code":"BI",
    "gn:dem":1471,
    "gn:feature_class":"P",
    "gn:feature_code":"PPLL",
    "gn:name":"Bisibe",
    "gn:population":0,
    "gn:timezone":"Africa/Bujumbura",
    "iso:country":"BI",
    "wof:name":"Bisibe",
    "wof:placetype":"locality"
},
  "geometry": {"coordinates":[30.3436,-2.8969],"type":"Point"}
}