{
  "type": "Feature",
  "properties": {
    "gn:admin1_code":"16.0",
    "gn:asciiname":"Kabira",
    "gn:country_code":"BI",
    "gn:dem":1417,
    "gn:feature_class":"P",
    "gn:feature_code":"PPLL",
    "gn:name":"Kabira",
    "gn:population":0,
    "gn:timezone":"Africa/Bujumbura",
    "iso:country":"BI",
    "wof:name":"Kabira",
    "wof:placetype":"locality"
},
  "geometry": {"coordinates":[30.1728,-2.5366],"type":"Point"}
}