{
  "type": "Feature",
  "properties": {
    "gn:admin1_code":"23",
    "gn:asciiname":"Ngorore",
    "gn:country_code":"BI",
    "gn:dem":1971,
    "gn:feature_class":"P",
    "gn:feature_code":"PPLL",
    "gn:name":"Ngorore",
    "gn:population":0,
    "gn:timezone":"Africa/Bujumbura",
    "iso:country":"BI",
    "wof:name":"Ngorore",
    "wof:placetype":"locality"
},
  "geometry": {"coordinates":[29.688,-3.4596],"type":"Point"}
}