{
  "type": "Feature",
  "properties": {
    "gn:admin1_code":"15.0",
    "gn:asciiname":"Ryamukona",
    "gn:country_code":"BI",
    "gn:dem":1822,
    "gn:feature_class":"P",
    "gn:feature_code":"PPLL",
    "gn:name":"Ryamukona",
    "gn:population":0,
    "gn:timezone":"Africa/Bujumbura",
    "iso:country":"BI",
    "wof:name":"Ryamukona",
    "wof:placetype":"locality"
},
  "geometry": {"coordinates":[29.5887,-2.8156],"type":"Point"}
}