{
  "type": "Feature",
  "properties": {
    "gn:admin1_code":"22",
    "gn:asciiname":"Kayogoro",
    "gn:country_code":"BI",
    "gn:dem":1993,
    "gn:feature_class":"P",
    "gn:feature_code":"PPLL",
    "gn:name":"Kayogoro",
    "gn:population":0,
    "gn:timezone":"Africa/Bujumbura",
    "iso:country":"BI",
    "wof:name":"Kayogoro",
    "wof:placetype":"locality"
},
  "geometry": {"coordinates":[29.6177,-3.2776],"type":"Point"}
}