{
  "type": "Feature",
  "properties": {
    "gn:admin1_code":"22.0",
    "gn:asciiname":"Nyakijwira",
    "gn:country_code":"BI",
    "gn:dem":1856,
    "gn:feature_class":"P",
    "gn:feature_code":"PPLL",
    "gn:name":"Nyakijwira",
    "gn:population":0,
    "gn:timezone":"Africa/Bujumbura",
    "iso:country":"BI",
    "wof:name":"Nyakijwira",
    "wof:placetype":"locality"
},
  "geometry": {"coordinates":[29.6903,-3.2189],"type":"Point"}
}