{
  "type": "Feature",
  "properties": {
    "gn:admin1_code":"19.0",
    "gn:asciiname":"Kigufi",
    "gn:country_code":"BI",
    "gn:dem":1521,
    "gn:feature_class":"P",
    "gn:feature_code":"PPLL",
    "gn:name":"Kigufi",
    "gn:population":0,
    "gn:timezone":"Africa/Bujumbura",
    "iso:country":"BI",
    "wof:name":"Kigufi",
    "wof:placetype":"locality"
},
  "geometry": {"coordinates":[29.9761,-2.7357],"type":"Point"}
}