{
  "type": "Feature",
  "properties": {
    "gn:admin1_code":"17",
    "gn:asciiname":"Ndoba",
    "gn:country_code":"BI",
    "gn:dem":1829,
    "gn:feature_class":"P",
    "gn:feature_code":"PPLL",
    "gn:name":"Ndoba",
    "gn:population":0,
    "gn:timezone":"Africa/Bujumbura",
    "iso:country":"BI",
    "wof:name":"Ndoba",
    "wof:placetype":"locality"
},
  "geometry": {"coordinates":[29.6808,-4.1505],"type":"Point"}
}