{
  "type": "Feature",
  "properties": {
    "gn:admin1_code":"19.0",
    "gn:asciiname":"Gicu",
    "gn:country_code":"BI",
    "gn:dem":1483,
    "gn:feature_class":"P",
    "gn:feature_code":"PPLL",
    "gn:name":"Gicu",
    "gn:population":0,
    "gn:timezone":"Africa/Bujumbura",
    "iso:country":"BI",
    "wof:name":"Gicu",
    "wof:placetype":"locality"
},
  "geometry": {"coordinates":[29.8629,-2.8085],"type":"Point"}
}