{
  "type": "Feature",
  "properties": {
    "gn:admin1_code":"11",
    "gn:asciiname":"Gasenyi",
    "gn:country_code":"BI",
    "gn:dem":1671,
    "gn:feature_class":"P",
    "gn:feature_code":"PPLL",
    "gn:name":"Gasenyi",
    "gn:population":0,
    "gn:timezone":"Africa/Bujumbura",
    "iso:country":"BI",
    "wof:name":"Gasenyi",
    "wof:placetype":"locality"
},
  "geometry": {"coordinates":[30.8313,-3.1746],"type":"Point"}
}