{
  "type": "Feature",
  "properties": {
    "gn:admin1_code":"9.0",
    "gn:asciiname":"Masama",
    "gn:country_code":"BI",
    "gn:dem":1327,
    "gn:feature_class":"P",
    "gn:feature_code":"PPLL",
    "gn:name":"Masama",
    "gn:population":0,
    "gn:timezone":"Africa/Bujumbura",
    "iso:country":"BI",
    "name:run_x_preferred":[
        "Masama"
    ],
    "wof:name":"Masama",
    "wof:placetype":"locality"
},
  "geometry": {"coordinates":[29.464,-3.2045],"type":"Point"}
}