{
  "type": "Feature",
  "properties": {
    "gn:admin1_code":"19.0",
    "gn:asciiname":"Kaganda",
    "gn:country_code":"BI",
    "gn:dem":1468,
    "gn:feature_class":"P",
    "gn:feature_code":"PPLL",
    "gn:name":"Kaganda",
    "gn:population":0,
    "gn:timezone":"Africa/Bujumbura",
    "iso:country":"BI",
    "wof:name":"Kaganda",
    "wof:placetype":"locality"
},
  "geometry": {"coordinates":[29.8697,-2.8143],"type":"Point"}
}