{
  "type": "Feature",
  "properties": {
    "gn:admin1_code":"20",
    "gn:asciiname":"Barega",
    "gn:country_code":"BI",
    "gn:dem":1447,
    "gn:feature_class":"P",
    "gn:feature_code":"PPLL",
    "gn:name":"Barega",
    "gn:population":0,
    "gn:timezone":"Africa/Bujumbura",
    "iso:country":"BI",
    "name:und_x_variant":[
        "Barege"
    ],
    "wof:name":"Barega",
    "wof:placetype":"locality"
},
  "geometry": {"coordinates":[29.9422,-3.9754],"type":"Point"}
}