{
  "type": "Feature",
  "properties": {
    "gn:admin1_code":"23",
    "gn:asciiname":"Kirambi",
    "gn:country_code":"BI",
    "gn:dem":2038,
    "gn:feature_class":"P",
    "gn:feature_code":"PPLL",
    "gn:name":"Kirambi",
    "gn:population":0,
    "gn:timezone":"Africa/Bujumbura",
    "iso:country":"BI",
    "wof:name":"Kirambi",
    "wof:placetype":"locality"
},
  "geometry": {"coordinates":[29.6408,-3.5062],"type":"Point"}
}