{
  "type": "Feature",
  "properties": {
    "gn:admin1_code":"10.0",
    "gn:asciiname":"Ruhando",
    "gn:country_code":"BI",
    "gn:dem":1841,
    "gn:feature_class":"P",
    "gn:feature_code":"PPLL",
    "gn:name":"Ruhando",
    "gn:population":0,
    "gn:timezone":"Africa/Bujumbura",
    "iso:country":"BI",
    "wof:name":"Ruhando",
    "wof:placetype":"locality"
},
  "geometry": {"coordinates":[29.8713,-3.8925],"type":"Point"}
}