{
  "type": "Feature",
  "properties": {
    "gn:admin1_code":"14.0",
    "gn:asciiname":"Gikobe",
    "gn:country_code":"BI",
    "gn:dem":1498,
    "gn:feature_class":"P",
    "gn:feature_code":"PPL",
    "gn:name":"Gikobe",
    "gn:population":0,
    "gn:timezone":"Africa/Bujumbura",
    "iso:country":"BI",
    "wof:name":"Gikobe",
    "wof:placetype":"locality"
},
  "geometry": {"coordinates":[30.0455,-3.1962],"type":"Point"}
}