{
  "type": "Feature",
  "properties": {
    "gn:admin1_code":"18",
    "gn:asciiname":"Kibande",
    "gn:country_code":"BI",
    "gn:dem":1750,
    "gn:feature_class":"P",
    "gn:feature_code":"PPL",
    "gn:name":"Kibande",
    "gn:population":0,
    "gn:timezone":"Africa/Bujumbura",
    "iso:country":"BI",
    "wof:name":"Kibande",
    "wof:placetype":"locality"
},
  "geometry": {"coordinates":[30.2896,-3.0136],"type":"Point"}
}