{
  "type": "Feature",
  "properties": {
    "gn:admin1_code":"12.0",
    "gn:asciiname":"Ndogomba",
    "gn:country_code":"BI",
    "gn:dem":1469,
    "gn:feature_class":"P",
    "gn:feature_code":"PPLL",
    "gn:name":"Ndogomba",
    "gn:population":0,
    "gn:timezone":"Africa/Bujumbura",
    "iso:country":"BI",
    "wof:name":"Ndogomba",
    "wof:placetype":"locality"
},
  "geometry": {"coordinates":[29.211,-2.7295],"type":"Point"}
}