{
  "type": "Feature",
  "properties": {
    "gn:admin1_code":"18.0",
    "gn:asciiname":"Muturura",
    "gn:country_code":"BI",
    "gn:dem":1677,
    "gn:feature_class":"P",
    "gn:feature_code":"PPLL",
    "gn:name":"Muturura",
    "gn:population":0,
    "gn:timezone":"Africa/Bujumbura",
    "iso:country":"BI",
    "wof:name":"Muturura",
    "wof:placetype":"locality"
},
  "geometry": {"coordinates":[30.3274,-2.8373],"type":"Point"}
}