{
  "type": "Feature",
  "properties": {
    "gn:admin1_code":"16.0",
    "gn:asciiname":"Murama",
    "gn:country_code":"BI",
    "gn:dem":1380,
    "gn:feature_class":"P",
    "gn:feature_code":"PPLL",
    "gn:name":"Murama",
    "gn:population":0,
    "gn:timezone":"Africa/Bujumbura",
    "iso:country":"BI",
    "wof:name":"Murama",
    "wof:placetype":"locality"
},
  "geometry": {"coordinates":[30.1553,-2.4653],"type":"Point"}
}