{
  "type": "Feature",
  "properties": {
    "gn:admin1_code":"21",
    "gn:asciiname":"Maramya",
    "gn:country_code":"BI",
    "gn:dem":1636,
    "gn:feature_class":"P",
    "gn:feature_code":"PPLL",
    "gn:name":"Maramya",
    "gn:population":0,
    "gn:timezone":"Africa/Bujumbura",
    "iso:country":"BI",
    "wof:name":"Maramya",
    "wof:placetype":"locality"
},
  "geometry": {"coordinates":[30.124,-3.5793],"type":"Point"}
}