{
  "type": "Feature",
  "properties": {
    "gn:admin1_code":"11",
    "gn:asciiname":"Gisoko",
    "gn:country_code":"BI",
    "gn:dem":1638,
    "gn:feature_class":"P",
    "gn:feature_code":"PPLL",
    "gn:name":"Gisoko",
    "gn:population":0,
    "gn:timezone":"Africa/Bujumbura",
    "iso:country":"BI",
    "wof:name":"Gisoko",
    "wof:placetype":"locality"
},
  "geometry": {"coordinates":[30.7814,-3.186],"type":"Point"}
}