{
  "type": "Feature",
  "properties": {
    "gn:admin1_code":"17",
    "gn:asciiname":"Marizi",
    "gn:country_code":"BI",
    "gn:dem":1284,
    "gn:feature_class":"P",
    "gn:feature_code":"PPLL",
    "gn:name":"Marizi",
    "gn:population":0,
    "gn:timezone":"Africa/Bujumbura",
    "iso:country":"BI",
    "wof:name":"Marizi",
    "wof:placetype":"locality"
},
  "geometry": {"coordinates":[30.0184,-4.2296],"type":"Point"}
}