{
  "type": "Feature",
  "properties": {
    "gn:admin1_code":"23",
    "gn:asciiname":"Mikangara",
    "gn:country_code":"BI",
    "gn:dem":1701,
    "gn:feature_class":"P",
    "gn:feature_code":"PPLL",
    "gn:name":"Mikangara",
    "gn:population":0,
    "gn:timezone":"Africa/Bujumbura",
    "iso:country":"BI",
    "wof:name":"Mikangara",
    "wof:placetype":"locality"
},
  "geometry": {"coordinates":[29.8235,-3.491],"type":"Point"}
}