{
  "type": "Feature",
  "properties": {
    "gn:admin1_code":"15.0",
    "gn:asciiname":"Nyabihanga",
    "gn:country_code":"BI",
    "gn:dem":2036,
    "gn:feature_class":"P",
    "gn:feature_code":"PPL",
    "gn:name":"Nyabihanga",
    "gn:population":0,
    "gn:timezone":"Africa/Bujumbura",
    "iso:country":"BI",
    "wof:name":"Nyabihanga",
    "wof:placetype":"locality"
},
  "geometry": {"coordinates":[29.565,-2.8216],"type":"Point"}
}