{
  "type": "Feature",
  "properties": {
    "gn:admin1_code":"18.0",
    "gn:asciiname":"Kwihigiro",
    "gn:country_code":"BI",
    "gn:dem":1514,
    "gn:feature_class":"P",
    "gn:feature_code":"PPLL",
    "gn:name":"Kwihigiro",
    "gn:population":0,
    "gn:timezone":"Africa/Bujumbura",
    "iso:country":"BI",
    "wof:name":"Kwihigiro",
    "wof:placetype":"locality"
},
  "geometry": {"coordinates":[30.4409,-2.5792],"type":"Point"}
}