{
  "type": "Feature",
  "properties": {
    "gn:admin1_code":"14.0",
    "gn:asciiname":"Kumutende",
    "gn:country_code":"BI",
    "gn:dem":1525,
    "gn:feature_class":"P",
    "gn:feature_code":"PPLL",
    "gn:name":"Kumutende",
    "gn:population":0,
    "gn:timezone":"Africa/Bujumbura",
    "iso:country":"BI",
    "name:und_x_variant":[
        "Kumetente",
        "Kumutente",
        "Kumutende"
    ],
    "wof:name":"Kumutende",
    "wof:placetype":"locality"
},
  "geometry": {"coordinates":[30.03991,-3.23709],"type":"Point"}
}