{
  "type": "Feature",
  "properties": {
    "gn:admin1_code":"18.0",
    "gn:asciiname":"Murago",
    "gn:country_code":"BI",
    "gn:dem":1542,
    "gn:feature_class":"P",
    "gn:feature_code":"PPLL",
    "gn:name":"Murago",
    "gn:population":0,
    "gn:timezone":"Africa/Bujumbura",
    "iso:country":"BI",
    "wof:name":"Murago",
    "wof:placetype":"locality"
},
  "geometry": {"coordinates":[30.4433,-2.6005],"type":"Point"}
}