{
  "type": "Feature",
  "properties": {
    "gn:admin1_code":"11",
    "gn:asciiname":"Mugera",
    "gn:country_code":"BI",
    "gn:dem":1481,
    "gn:feature_class":"P",
    "gn:feature_code":"PPL",
    "gn:name":"Mugera",
    "gn:population":0,
    "gn:timezone":"Africa/Bujumbura",
    "iso:country":"BI",
    "wof:name":"Mugera",
    "wof:placetype":"locality"
},
  "geometry": {"coordinates":[30.663,-3.0653],"type":"Point"}
}