{
  "type": "Feature",
  "properties": {
    "gn:admin1_code":"15.0",
    "gn:asciiname":"Rugoma",
    "gn:country_code":"BI",
    "gn:dem":1876,
    "gn:feature_class":"P",
    "gn:feature_code":"PPLL",
    "gn:name":"Rugoma",
    "gn:population":0,
    "gn:timezone":"Africa/Bujumbura",
    "iso:country":"BI",
    "wof:name":"Rugoma",
    "wof:placetype":"locality"
},
  "geometry": {"coordinates":[29.6472,-3.1552],"type":"Point"}
}