{
  "type": "Feature",
  "properties": {
    "gn:admin1_code":"18.0",
    "gn:asciiname":"Kibunda",
    "gn:country_code":"BI",
    "gn:dem":1376,
    "gn:feature_class":"P",
    "gn:feature_code":"PPLL",
    "gn:name":"Kibunda",
    "gn:population":0,
    "gn:timezone":"Africa/Bujumbura",
    "iso:country":"BI",
    "wof:name":"Kibunda",
    "wof:placetype":"locality"
},
  "geometry": {"coordinates":[30.4608,-2.4336],"type":"Point"}
}