{
  "type": "Feature",
  "properties": {
    "gn:admin1_code":"15.0",
    "gn:asciiname":"Gacokwe",
    "gn:country_code":"BI",
    "gn:dem":1679,
    "gn:feature_class":"P",
    "gn:feature_code":"PPLL",
    "gn:name":"Gacokwe",
    "gn:population":0,
    "gn:timezone":"Africa/Bujumbura",
    "iso:country":"BI",
    "wof:name":"Gacokwe",
    "wof:placetype":"locality"
},
  "geometry": {"coordinates":[29.7553,-3.1783],"type":"Point"}
}