{
  "type": "Feature",
  "properties": {
    "gn:admin1_code":"25",
    "gn:asciiname":"Vuma",
    "gn:country_code":"BI",
    "gn:dem":1716,
    "gn:feature_class":"P",
    "gn:feature_code":"PPLL",
    "gn:name":"Vuma",
    "gn:population":0,
    "gn:timezone":"Africa/Bujumbura",
    "iso:country":"BI",
    "wof:name":"Vuma",
    "wof:placetype":"locality"
},
  "geometry": {"coordinates":[29.5175,-3.322],"type":"Point"}
}