{
  "type": "Feature",
  "properties": {
    "gn:admin1_code":"21",
    "gn:asciiname":"Ngoma",
    "gn:country_code":"BI",
    "gn:dem":1538,
    "gn:feature_class":"P",
    "gn:feature_code":"PPL",
    "gn:name":"Ngoma",
    "gn:population":0,
    "gn:timezone":"Africa/Bujumbura",
    "iso:country":"BI",
    "wof:name":"Ngoma",
    "wof:placetype":"locality"
},
  "geometry": {"coordinates":[30.36637,-3.2814],"type":"Point"}
}