{
  "type": "Feature",
  "properties": {
    "gn:admin1_code":"22.0",
    "gn:asciiname":"Rweteto",
    "gn:country_code":"BI",
    "gn:dem":1899,
    "gn:feature_class":"P",
    "gn:feature_code":"PPLL",
    "gn:name":"Rweteto",
    "gn:population":0,
    "gn:timezone":"Africa/Bujumbura",
    "iso:country":"BI",
    "wof:name":"Rweteto",
    "wof:placetype":"locality"
},
  "geometry": {"coordinates":[29.622,-3.2121],"type":"Point"}
}