{
  "type": "Feature",
  "properties": {
    "gn:admin1_code":"17.0",
    "gn:asciiname":"Mukubano",
    "gn:country_code":"BI",
    "gn:dem":900,
    "gn:feature_class":"P",
    "gn:feature_code":"PPLL",
    "gn:name":"Mukubano",
    "gn:population":0,
    "gn:timezone":"Africa/Bujumbura",
    "iso:country":"BI",
    "wof:name":"Mukubano",
    "wof:placetype":"locality"
},
  "geometry": {"coordinates":[29.6751,-4.2883],"type":"Point"}
}