{
  "type": "Feature",
  "properties": {
    "gn:admin1_code":"18.0",
    "gn:asciiname":"Buvumbi",
    "gn:country_code":"BI",
    "gn:dem":1646,
    "gn:feature_class":"P",
    "gn:feature_code":"PPLL",
    "gn:name":"Buvumbi",
    "gn:population":0,
    "gn:timezone":"Africa/Bujumbura",
    "iso:country":"BI",
    "wof:name":"Buvumbi",
    "wof:placetype":"locality"
},
  "geometry": {"coordinates":[30.2652,-2.7409],"type":"Point"}
}