{
  "type": "Feature",
  "properties": {
    "gn:admin1_code":"14.0",
    "gn:asciiname":"Vyiniro",
    "gn:country_code":"BI",
    "gn:dem":1641,
    "gn:feature_class":"P",
    "gn:feature_code":"PPLL",
    "gn:name":"Vyiniro",
    "gn:population":0,
    "gn:timezone":"Africa/Bujumbura",
    "iso:country":"BI",
    "wof:name":"Vyiniro",
    "wof:placetype":"locality"
},
  "geometry": {"coordinates":[30.1768,-2.9858],"type":"Point"}
}