{
  "type": "Feature",
  "properties": {
    "gn:admin1_code":"19.0",
    "gn:asciiname":"Musezero",
    "gn:country_code":"BI",
    "gn:dem":1382,
    "gn:feature_class":"P",
    "gn:feature_code":"PPLL",
    "gn:name":"Musezero",
    "gn:population":0,
    "gn:timezone":"Africa/Bujumbura",
    "iso:country":"BI",
    "wof:name":"Musezero",
    "wof:placetype":"locality"
},
  "geometry": {"coordinates":[29.8378,-2.7839],"type":"Point"}
}