{
  "type": "Feature",
  "properties": {
    "gn:admin1_code":"20",
    "gn:asciiname":"Mura",
    "gn:country_code":"BI",
    "gn:dem":1208,
    "gn:feature_class":"P",
    "gn:feature_code":"PPLL",
    "gn:name":"Mura",
    "gn:population":0,
    "gn:timezone":"Africa/Bujumbura",
    "iso:country":"BI",
    "wof:name":"Mura",
    "wof:placetype":"locality"
},
  "geometry": {"coordinates":[30.2557,-3.7549],"type":"Point"}
}