{
  "type": "Feature",
  "properties": {
    "gn:admin1_code":"13.0",
    "gn:asciiname":"Mutoyi",
    "gn:country_code":"BI",
    "gn:dem":1669,
    "gn:feature_class":"P",
    "gn:feature_code":"PPLL",
    "gn:name":"Mutoyi",
    "gn:population":0,
    "gn:timezone":"Africa/Bujumbura",
    "iso:country":"BI",
    "wof:name":"Mutoyi",
    "wof:placetype":"locality"
},
  "geometry": {"coordinates":[29.9686,-3.2069],"type":"Point"}
}