{
  "type": "Feature",
  "properties": {
    "gn:admin1_code":"16.0",
    "gn:asciiname":"Bugorora",
    "gn:country_code":"BI",
    "gn:dem":1454,
    "gn:feature_class":"P",
    "gn:feature_code":"PPLL",
    "gn:name":"Bugorora",
    "gn:population":0,
    "gn:timezone":"Africa/Bujumbura",
    "iso:country":"BI",
    "wof:name":"Bugorora",
    "wof:placetype":"locality"
},
  "geometry": {"coordinates":[30.1668,-2.5973],"type":"Point"}
}