{
  "type": "Feature",
  "properties": {
    "gn:admin1_code":"11",
    "gn:asciiname":"Rwinyange",
    "gn:country_code":"BI",
    "gn:dem":1645,
    "gn:feature_class":"P",
    "gn:feature_code":"PPLL",
    "gn:name":"Rwinyange",
    "gn:population":0,
    "gn:timezone":"Africa/Bujumbura",
    "iso:country":"BI",
    "wof:name":"Rwinyange",
    "wof:placetype":"locality"
},
  "geometry": {"coordinates":[30.5223,-3.1689],"type":"Point"}
}