{
  "type": "Feature",
  "properties": {
    "gn:admin1_code":"12.0",
    "gn:asciiname":"Rwesero",
    "gn:country_code":"BI",
    "gn:dem":1358,
    "gn:feature_class":"P",
    "gn:feature_code":"PPL",
    "gn:name":"Rwesero",
    "gn:population":0,
    "gn:timezone":"Africa/Bujumbura",
    "iso:country":"BI",
    "wof:name":"Rwesero",
    "wof:placetype":"locality"
},
  "geometry": {"coordinates":[29.2337,-2.8936],"type":"Point"}
}