{
  "type": "Feature",
  "properties": {
    "gn:admin1_code":"19.0",
    "gn:asciiname":"Migende",
    "gn:country_code":"BI",
    "gn:dem":1533,
    "gn:feature_class":"P",
    "gn:feature_code":"PPLL",
    "gn:name":"Migende",
    "gn:population":0,
    "gn:timezone":"Africa/Bujumbura",
    "iso:country":"BI",
    "wof:name":"Migende",
    "wof:placetype":"locality"
},
  "geometry": {"coordinates":[29.7997,-2.7929],"type":"Point"}
}