{
  "type": "Feature",
  "properties": {
    "gn:admin1_code":"25",
    "gn:asciiname":"Gisarwe",
    "gn:country_code":"BI",
    "gn:dem":2261,
    "gn:feature_class":"P",
    "gn:feature_code":"PPLL",
    "gn:name":"Gisarwe",
    "gn:population":0,
    "gn:timezone":"Africa/Bujumbura",
    "iso:country":"BI",
    "wof:name":"Gisarwe",
    "wof:placetype":"locality"
},
  "geometry": {"coordinates":[29.5394,-3.4232],"type":"Point"}
}