{
  "type": "Feature",
  "properties": {
    "gn:admin1_code":"10.0",
    "gn:asciiname":"Musongati",
    "gn:country_code":"BI",
    "gn:dem":1866,
    "gn:feature_class":"P",
    "gn:feature_code":"PPLL",
    "gn:name":"Musongati",
    "gn:population":0,
    "gn:timezone":"Africa/Bujumbura",
    "iso:country":"BI",
    "wof:name":"Musongati",
    "wof:placetype":"locality"
},
  "geometry": {"coordinates":[29.8576,-3.9155],"type":"Point"}
}