{
  "type": "Feature",
  "properties": {
    "gn:admin1_code":"12.0",
    "gn:asciiname":"Bukinanyana",
    "gn:country_code":"BI",
    "gn:dem":1531,
    "gn:feature_class":"P",
    "gn:feature_code":"PPLL",
    "gn:name":"Bukinanyana",
    "gn:population":0,
    "gn:timezone":"Africa/Bujumbura",
    "iso:country":"BI",
    "wof:name":"Bukinanyana",
    "wof:placetype":"locality"
},
  "geometry": {"coordinates":[29.3256,-2.8973],"type":"Point"}
}