{
  "type": "Feature",
  "properties": {
    "gn:admin1_code":"21",
    "gn:asciiname":"Muyebe",
    "gn:country_code":"BI",
    "gn:dem":1273,
    "gn:feature_class":"P",
    "gn:feature_code":"PPL",
    "gn:name":"Muyebe",
    "gn:population":0,
    "gn:timezone":"Africa/Bujumbura",
    "iso:country":"BI",
    "name:run_x_preferred":[
        "Muyebe"
    ],
    "wof:name":"Muyebe",
    "wof:placetype":"locality"
},
  "geometry": {"coordinates":[30.4223,-3.4505],"type":"Point"}
}