{
  "type": "Feature",
  "properties": {
    "gn:admin1_code":"21",
    "gn:asciiname":"Murehe",
    "gn:country_code":"BI",
    "gn:dem":1389,
    "gn:feature_class":"P",
    "gn:feature_code":"PPLL",
    "gn:name":"Murehe",
    "gn:population":0,
    "gn:timezone":"Africa/Bujumbura",
    "iso:country":"BI",
    "wof:name":"Murehe",
    "wof:placetype":"locality"
},
  "geometry": {"coordinates":[30.269,-3.5268],"type":"Point"}
}