{
  "type": "Feature",
  "properties": {
    "gn:admin1_code":"9.0",
    "gn:asciiname":"Ruyange",
    "gn:country_code":"BI",
    "gn:dem":873,
    "gn:feature_class":"P",
    "gn:feature_code":"PPLL",
    "gn:name":"Ruyange",
    "gn:population":0,
    "gn:timezone":"Africa/Bujumbura",
    "iso:country":"BI",
    "wof:name":"Ruyange",
    "wof:placetype":"locality"
},
  "geometry": {"coordinates":[29.4115,-3.2433],"type":"Point"}
}