{
  "type": "Feature",
  "properties": {
    "gn:admin1_code":"23",
    "gn:asciiname":"Kabogi",
    "gn:country_code":"BI",
    "gn:dem":1821,
    "gn:feature_class":"P",
    "gn:feature_code":"PPLL",
    "gn:name":"Kabogi",
    "gn:population":0,
    "gn:timezone":"Africa/Bujumbura",
    "iso:country":"BI",
    "wof:name":"Kabogi",
    "wof:placetype":"locality"
},
  "geometry": {"coordinates":[29.7189,-3.3688],"type":"Point"}
}