{
  "type": "Feature",
  "properties": {
    "gn:admin1_code":"16.0",
    "gn:asciiname":"Nyabirembe",
    "gn:country_code":"BI",
    "gn:dem":1601,
    "gn:feature_class":"P",
    "gn:feature_code":"PPLL",
    "gn:name":"Nyabirembe",
    "gn:population":0,
    "gn:timezone":"Africa/Bujumbura",
    "iso:country":"BI",
    "wof:name":"Nyabirembe",
    "wof:placetype":"locality"
},
  "geometry": {"coordinates":[30.0711,-2.7028],"type":"Point"}
}