{
  "type": "Feature",
  "properties": {
    "gn:admin1_code":"18.0",
    "gn:asciiname":"Rubuye",
    "gn:country_code":"BI",
    "gn:dem":1454,
    "gn:feature_class":"P",
    "gn:feature_code":"PPLL",
    "gn:name":"Rubuye",
    "gn:population":0,
    "gn:timezone":"Africa/Bujumbura",
    "iso:country":"BI",
    "wof:name":"Rubuye",
    "wof:placetype":"locality"
},
  "geometry": {"coordinates":[30.4183,-2.9253],"type":"Point"}
}