{
  "type": "Feature",
  "properties": {
    "gn:admin1_code":"10",
    "gn:asciiname":"Kagomogomo",
    "gn:country_code":"BI",
    "gn:dem":2111,
    "gn:feature_class":"P",
    "gn:feature_code":"PPLL",
    "gn:name":"Kagomogomo",
    "gn:population":0,
    "gn:timezone":"Africa/Bujumbura",
    "iso:country":"BI",
    "wof:name":"Kagomogomo",
    "wof:placetype":"locality"
},
  "geometry": {"coordinates":[29.6281,-3.6699],"type":"Point"}
}