{
  "type": "Feature",
  "properties": {
    "gn:admin1_code":"18",
    "gn:asciiname":"Kigari",
    "gn:country_code":"BI",
    "gn:dem":1658,
    "gn:feature_class":"P",
    "gn:feature_code":"PPL",
    "gn:name":"Kigari",
    "gn:population":0,
    "gn:timezone":"Africa/Bujumbura",
    "iso:country":"BI",
    "wof:name":"Kigari",
    "wof:placetype":"locality"
},
  "geometry": {"coordinates":[30.28346,-3.04182],"type":"Point"}
}