{
  "type": "Feature",
  "properties": {
    "gn:admin1_code":"13",
    "gn:asciiname":"Nyamirambo",
    "gn:country_code":"BI",
    "gn:dem":1632,
    "gn:feature_class":"P",
    "gn:feature_code":"PPLL",
    "gn:name":"Nyamirambo",
    "gn:population":0,
    "gn:timezone":"Africa/Bujumbura",
    "iso:country":"BI",
    "name:ita_x_preferred":[
        "Nyamirambo"
    ],
    "wof:name":"Nyamirambo",
    "wof:placetype":"locality"
},
  "geometry": {"coordinates":[29.9311,-3.5346],"type":"Point"}
}