{
  "type": "Feature",
  "properties": {
    "gn:admin1_code":"19.0",
    "gn:asciiname":"Bitagazwa",
    "gn:country_code":"BI",
    "gn:dem":1501,
    "gn:feature_class":"P",
    "gn:feature_code":"PPLL",
    "gn:name":"Bitagazwa",
    "gn:population":0,
    "gn:timezone":"Africa/Bujumbura",
    "iso:country":"BI",
    "wof:name":"Bitagazwa",
    "wof:placetype":"locality"
},
  "geometry": {"coordinates":[30.0397,-2.8132],"type":"Point"}
}