{
  "type": "Feature",
  "properties": {
    "gn:admin1_code":"23",
    "gn:asciiname":"Kavumu",
    "gn:country_code":"BI",
    "gn:dem":1638,
    "gn:feature_class":"P",
    "gn:feature_code":"PPLL",
    "gn:name":"Kavumu",
    "gn:population":0,
    "gn:timezone":"Africa/Bujumbura",
    "iso:country":"BI",
    "wof:name":"Kavumu",
    "wof:placetype":"locality"
},
  "geometry": {"coordinates":[29.8128,-3.4162],"type":"Point"}
}