{
  "type": "Feature",
  "properties": {
    "gn:admin1_code":"20",
    "gn:asciiname":"Kamaramagambo",
    "gn:country_code":"BI",
    "gn:dem":1816,
    "gn:feature_class":"P",
    "gn:feature_code":"PPL",
    "gn:name":"Kamaramagambo",
    "gn:population":0,
    "gn:timezone":"Africa/Bujumbura",
    "iso:country":"BI",
    "wof:name":"Kamaramagambo",
    "wof:placetype":"locality"
},
  "geometry": {"coordinates":[30.0768,-3.7364],"type":"Point"}
}