{
  "type": "Feature",
  "properties": {
    "gn:admin1_code":"19.0",
    "gn:asciiname":"Mivo",
    "gn:country_code":"BI",
    "gn:dem":1678,
    "gn:feature_class":"P",
    "gn:feature_code":"PPL",
    "gn:name":"Mivo",
    "gn:population":0,
    "gn:timezone":"Africa/Bujumbura",
    "iso:country":"BI",
    "wof:name":"Mivo",
    "wof:placetype":"locality"
},
  "geometry": {"coordinates":[29.79471,-2.94139],"type":"Point"}
}