{
  "type": "Feature",
  "properties": {
    "gn:admin1_code":"21",
    "gn:asciiname":"Nyarusange",
    "gn:country_code":"BI",
    "gn:dem":1509,
    "gn:feature_class":"P",
    "gn:feature_code":"PPLL",
    "gn:name":"Nyarusange",
    "gn:population":0,
    "gn:timezone":"Africa/Bujumbura",
    "iso:country":"BI",
    "wof:name":"Nyarusange",
    "wof:placetype":"locality"
},
  "geometry": {"coordinates":[30.0992,-3.4372],"type":"Point"}
}