{
  "type": "Feature",
  "properties": {
    "gn:admin1_code":"25",
    "gn:asciiname":"Magarure",
    "gn:country_code":"BI",
    "gn:dem":1444,
    "gn:feature_class":"P",
    "gn:feature_code":"PPLL",
    "gn:name":"Magarure",
    "gn:population":0,
    "gn:timezone":"Africa/Bujumbura",
    "iso:country":"BI",
    "wof:name":"Magarure",
    "wof:placetype":"locality"
},
  "geometry": {"coordinates":[29.4544,-3.2773],"type":"Point"}
}