{
  "type": "Feature",
  "properties": {
    "gn:admin1_code":"14.0",
    "gn:asciiname":"Karwa",
    "gn:country_code":"BI",
    "gn:dem":1639,
    "gn:feature_class":"P",
    "gn:feature_code":"PPLL",
    "gn:name":"Karwa",
    "gn:population":0,
    "gn:timezone":"Africa/Bujumbura",
    "iso:country":"BI",
    "wof:name":"Karwa",
    "wof:placetype":"locality"
},
  "geometry": {"coordinates":[30.1365,-2.9702],"type":"Point"}
}