{
  "type": "Feature",
  "properties": {
    "gn:admin1_code":"25",
    "gn:asciiname":"Buhanda",
    "gn:country_code":"BI",
    "gn:dem":1526,
    "gn:feature_class":"P",
    "gn:feature_code":"PPLL",
    "gn:name":"Buhanda",
    "gn:population":0,
    "gn:timezone":"Africa/Bujumbura",
    "iso:country":"BI",
    "wof:name":"Buhanda",
    "wof:placetype":"locality"
},
  "geometry": {"coordinates":[29.4941,-3.3349],"type":"Point"}
}