{
  "type": "Feature",
  "properties": {
    "gn:admin1_code":"13",
    "gn:asciiname":"Nyamabuye",
    "gn:country_code":"BI",
    "gn:dem":1784,
    "gn:feature_class":"P",
    "gn:feature_code":"PPLL",
    "gn:name":"Nyamabuye",
    "gn:population":0,
    "gn:timezone":"Africa/Bujumbura",
    "iso:country":"BI",
    "wof:name":"Nyamabuye",
    "wof:placetype":"locality"
},
  "geometry": {"coordinates":[29.8283,-3.7183],"type":"Point"}
}