{
  "type": "Feature",
  "properties": {
    "gn:admin1_code":"25",
    "gn:asciiname":"Nkuri",
    "gn:country_code":"BI",
    "gn:dem":1480,
    "gn:feature_class":"P",
    "gn:feature_code":"PPLL",
    "gn:name":"Nkuri",
    "gn:population":0,
    "gn:timezone":"Africa/Bujumbura",
    "iso:country":"BI",
    "wof:name":"Nkuri",
    "wof:placetype":"locality"
},
  "geometry": {"coordinates":[29.4467,-3.3301],"type":"Point"}
}