{
  "type": "Feature",
  "properties": {
    "gn:admin1_code":"17",
    "gn:asciiname":"Gatanga",
    "gn:country_code":"BI",
    "gn:dem":1579,
    "gn:feature_class":"P",
    "gn:feature_code":"PPL",
    "gn:name":"Gatanga",
    "gn:population":0,
    "gn:timezone":"Africa/Bujumbura",
    "iso:country":"BI",
    "name:ceb_x_preferred":[
        "Gatanga"
    ],
    "name:swe_x_preferred":[
        "Gatanga"
    ],
    "wof:name":"Gatanga",
    "wof:placetype":"locality"
},
  "geometry": {"coordinates":[29.7766,-4.4019],"type":"Point"}
}