{
  "type": "Feature",
  "properties": {
    "gn:admin1_code":"19.0",
    "gn:asciiname":"Nyakabanda",
    "gn:country_code":"BI",
    "gn:dem":1613,
    "gn:feature_class":"P",
    "gn:feature_code":"PPLL",
    "gn:name":"Nyakabanda",
    "gn:population":0,
    "gn:timezone":"Africa/Bujumbura",
    "iso:country":"BI",
    "wof:name":"Nyakabanda",
    "wof:placetype":"locality"
},
  "geometry": {"coordinates":[29.9557,-2.9274],"type":"Point"}
}