{
  "type": "Feature",
  "properties": {
    "gn:admin1_code":"21",
    "gn:asciiname":"Kibari",
    "gn:country_code":"BI",
    "gn:dem":1270,
    "gn:feature_class":"P",
    "gn:feature_code":"PPLL",
    "gn:name":"Kibari",
    "gn:population":0,
    "gn:timezone":"Africa/Bujumbura",
    "iso:country":"BI",
    "wof:name":"Kibari",
    "wof:placetype":"locality"
},
  "geometry": {"coordinates":[30.3133,-3.6786],"type":"Point"}
}