{
  "type": "Feature",
  "properties": {
    "gn:admin1_code":"17",
    "gn:asciiname":"Mugoboka",
    "gn:country_code":"BI",
    "gn:dem":1626,
    "gn:feature_class":"P",
    "gn:feature_code":"PPLL",
    "gn:name":"Mugoboka",
    "gn:population":0,
    "gn:timezone":"Africa/Bujumbura",
    "iso:country":"BI",
    "wof:name":"Mugoboka",
    "wof:placetype":"locality"
},
  "geometry": {"coordinates":[29.8596,-4.1438],"type":"Point"}
}