{
  "type": "Feature",
  "properties": {
    "gn:admin1_code":"15.0",
    "gn:asciiname":"Bishuri",
    "gn:country_code":"BI",
    "gn:dem":1845,
    "gn:feature_class":"P",
    "gn:feature_code":"PPLL",
    "gn:name":"Bishuri",
    "gn:population":0,
    "gn:timezone":"Africa/Bujumbura",
    "iso:country":"BI",
    "wof:name":"Bishuri",
    "wof:placetype":"locality"
},
  "geometry": {"coordinates":[29.7515,-3.1974],"type":"Point"}
}