{
  "type": "Feature",
  "properties": {
    "gn:admin1_code":"13",
    "gn:asciiname":"Gisuru",
    "gn:country_code":"BI",
    "gn:dem":1608,
    "gn:feature_class":"P",
    "gn:feature_code":"PPLL",
    "gn:name":"Gisuru",
    "gn:population":0,
    "gn:timezone":"Africa/Bujumbura",
    "iso:country":"BI",
    "wof:name":"Gisuru",
    "wof:placetype":"locality"
},
  "geometry": {"coordinates":[29.8664,-3.3753],"type":"Point"}
}