{
  "type": "Feature",
  "properties": {
    "gn:admin1_code":"22",
    "gn:asciiname":"Martyazo",
    "gn:country_code":"BI",
    "gn:dem":1832,
    "gn:feature_class":"P",
    "gn:feature_code":"PPLL",
    "gn:name":"Martyazo",
    "gn:population":0,
    "gn:timezone":"Africa/Bujumbura",
    "iso:country":"BI",
    "name:deu_x_preferred":[
        "Martyazo"
    ],
    "name:ell_x_preferred":[
        "\u039c\u03b1\u03c1\u03c4\u03b9\u03ac\u03b6\u03bf"
    ],
    "name:nld_x_preferred":[
        "Martyazo"
    ],
    "name:por_x_preferred":[
        "Martyazo"
    ],
    "name:rus_x_preferred":[
        "\u041c\u0430\u0440\u0442\u0438\u0430\u0437\u043e"
    ],
    "wof:name":"Martyazo",
    "wof:placetype":"locality"
},
  "geometry": {"coordinates":[29.6855,-3.2972],"type":"Point"}
}