{
  "type": "Feature",
  "properties": {
    "gn:admin1_code":"22",
    "gn:asciiname":"Martyazo",
    "gn:country_code":"BI",
    "gn:dem":1832,
    "gn:feature_class":"P",
    "gn:feature_code":"PPLL",
    "gn:name":"Martyazo",
    "gn:population":0,
    "gn:timezone":"Africa/Bujumbura",
    "iso:country":"BI",
    "wof:name":"Martyazo",
    "wof:placetype":"locality"
},
  "geometry": {"coordinates":[29.6855,-3.2972],"type":"Point"}
}