{
  "type": "Feature",
  "properties": {
    "gn:admin1_code":"13",
    "gn:asciiname":"Kinyeregete",
    "gn:country_code":"BI",
    "gn:dem":1749,
    "gn:feature_class":"P",
    "gn:feature_code":"PPLL",
    "gn:name":"Kinyeregete",
    "gn:population":0,
    "gn:timezone":"Africa/Bujumbura",
    "iso:country":"BI",
    "wof:name":"Kinyeregete",
    "wof:placetype":"locality"
},
  "geometry": {"coordinates":[29.8612,-3.5901],"type":"Point"}
}