{
  "type": "Feature",
  "properties": {
    "gn:admin1_code":"17",
    "gn:asciiname":"Nganzu",
    "gn:country_code":"BI",
    "gn:dem":1817,
    "gn:feature_class":"P",
    "gn:feature_code":"PPLL",
    "gn:name":"Nganzu",
    "gn:population":0,
    "gn:timezone":"Africa/Bujumbura",
    "iso:country":"BI",
    "wof:name":"Nganzu",
    "wof:placetype":"locality"
},
  "geometry": {"coordinates":[29.8007,-4.0536],"type":"Point"}
}