{
  "type": "Feature",
  "properties": {
    "gn:admin1_code":"19.0",
    "gn:asciiname":"Kabari",
    "gn:country_code":"BI",
    "gn:dem":1662,
    "gn:feature_class":"P",
    "gn:feature_code":"PPLL",
    "gn:name":"Kabari",
    "gn:population":0,
    "gn:timezone":"Africa/Bujumbura",
    "iso:country":"BI",
    "wof:name":"Kabari",
    "wof:placetype":"locality"
},
  "geometry": {"coordinates":[30.1027,-2.8255],"type":"Point"}
}