{
  "type": "Feature",
  "properties": {
    "gn:admin1_code":"10",
    "gn:asciiname":"Mubuga",
    "gn:country_code":"BI",
    "gn:dem":1920,
    "gn:feature_class":"P",
    "gn:feature_code":"PPLL",
    "gn:name":"Mubuga",
    "gn:population":0,
    "gn:timezone":"Africa/Bujumbura",
    "iso:country":"BI",
    "wof:name":"Mubuga",
    "wof:placetype":"locality"
},
  "geometry": {"coordinates":[29.5868,-3.9058],"type":"Point"}
}