{
  "type": "Feature",
  "properties": {
    "gn:admin1_code":"24",
    "gn:asciiname":"Murukaramu",
    "gn:country_code":"BI",
    "gn:dem":784,
    "gn:feature_class":"P",
    "gn:feature_code":"PPLL",
    "gn:name":"Murukaramu",
    "gn:population":0,
    "gn:timezone":"Africa/Bujumbura",
    "iso:country":"BI",
    "wof:name":"Murukaramu",
    "wof:placetype":"locality"
},
  "geometry": {"coordinates":[29.3361,-3.3272],"type":"Point"}
}