{
  "type": "Feature",
  "properties": {
    "gn:admin1_code":"20",
    "gn:asciiname":"Nyange",
    "gn:country_code":"BI",
    "gn:dem":1187,
    "gn:feature_class":"P",
    "gn:feature_code":"PPLL",
    "gn:name":"Nyange",
    "gn:population":0,
    "gn:timezone":"Africa/Bujumbura",
    "iso:country":"BI",
    "wof:name":"Nyange",
    "wof:placetype":"locality"
},
  "geometry": {"coordinates":[30.2488,-3.7432],"type":"Point"}
}