{
  "type": "Feature",
  "properties": {
    "gn:admin1_code":"12.0",
    "gn:asciiname":"Cibitoke",
    "gn:country_code":"BI",
    "gn:dem":923,
    "gn:feature_class":"P",
    "gn:feature_code":"PPLL",
    "gn:name":"Cibitoke",
    "gn:population":0,
    "gn:timezone":"Africa/Bujumbura",
    "iso:country":"BI",
    "wof:name":"Cibitoke",
    "wof:placetype":"locality"
},
  "geometry": {"coordinates":[29.1158,-2.8937],"type":"Point"}
}