{
  "type": "Feature",
  "properties": {
    "gn:admin1_code":"12.0",
    "gn:asciiname":"Cibitoke",
    "gn:country_code":"BI",
    "gn:dem":923,
    "gn:feature_class":"P",
    "gn:feature_code":"PPLL",
    "gn:name":"Cibitoke",
    "gn:population":0,
    "gn:timezone":"Africa/Bujumbura",
    "iso:country":"BI",
    "name:ara_x_preferred":[
        "\u0633\u064a\u0628\u064a\u062a\u0648\u0643\u064a"
    ],
    "name:azb_x_preferred":[
        "\u0633\u06cc\u0628\u06cc\u062a\u0648\u06a9"
    ],
    "name:ceb_x_preferred":[
        "Cibitoke"
    ],
    "name:dan_x_preferred":[
        "Cibitoke"
    ],
    "name:deu_x_preferred":[
        "Cibitoke"
    ],
    "name:est_x_preferred":[
        "Cibitoke"
    ],
    "name:fas_x_preferred":[
        "\u0633\u06cc\u0628\u06cc\u062a\u0648\u06a9"
    ],
    "name:fra_x_preferred":[
        "Cibitoke"
    ],
    "name:frr_x_preferred":[
        "Cibitoke"
    ],
    "name:ind_x_preferred":[
        "Cibitoke"
    ],
    "name:ita_x_preferred":[
        "Cibitoke"
    ],
    "name:msa_x_preferred":[
        "Cibitoke"
    ],
    "name:nld_x_preferred":[
        "Cibitoke"
    ],
    "name:pol_x_preferred":[
        "Cibitoke"
    ],
    "name:ron_x_preferred":[
        "Cibitoke"
    ],
    "name:run_x_preferred":[
        "Cibitoke"
    ],
    "name:rus_x_preferred":[
        "\u0427\u0438\u0431\u0438\u0442\u043e\u043a\u0435"
    ],
    "name:swa_x_preferred":[
        "Cibitoke"
    ],
    "name:swe_x_preferred":[
        "Cibitoke"
    ],
    "name:urd_x_preferred":[
        "\u0633\u06cc\u0628\u06cc\u062a\u0648\u06a9\u06d2"
    ],
    "wof:name":"Cibitoke",
    "wof:placetype":"locality"
},
  "geometry": {"coordinates":[29.1158,-2.8937],"type":"Point"}
}