{
  "type": "Feature",
  "properties": {
    "gn:admin1_code":"23.0",
    "gn:asciiname":"Kigabiro",
    "gn:country_code":"BI",
    "gn:dem":1969,
    "gn:feature_class":"P",
    "gn:feature_code":"PPLL",
    "gn:name":"Kigabiro",
    "gn:population":0,
    "gn:timezone":"Africa/Bujumbura",
    "iso:country":"BI",
    "wof:name":"Kigabiro",
    "wof:placetype":"locality"
},
  "geometry": {"coordinates":[29.6492,-3.6242],"type":"Point"}
}