{
  "type": "Feature",
  "properties": {
    "gn:admin1_code":"22",
    "gn:asciiname":"Mugomere",
    "gn:country_code":"BI",
    "gn:dem":2100,
    "gn:feature_class":"P",
    "gn:feature_code":"PPLL",
    "gn:name":"Mugomere",
    "gn:population":0,
    "gn:timezone":"Africa/Bujumbura",
    "iso:country":"BI",
    "wof:name":"Mugomere",
    "wof:placetype":"locality"
},
  "geometry": {"coordinates":[29.5773,-3.3474],"type":"Point"}
}