{
  "type": "Feature",
  "properties": {
    "gn:admin1_code":"16.0",
    "gn:asciiname":"Kiruhura",
    "gn:country_code":"BI",
    "gn:dem":1379,
    "gn:feature_class":"P",
    "gn:feature_code":"PPLL",
    "gn:name":"Kiruhura",
    "gn:population":0,
    "gn:timezone":"Africa/Bujumbura",
    "iso:country":"BI",
    "wof:name":"Kiruhura",
    "wof:placetype":"locality"
},
  "geometry": {"coordinates":[30.1418,-2.5048],"type":"Point"}
}