{
  "type": "Feature",
  "properties": {
    "gn:admin1_code":"18.0",
    "gn:asciiname":"Mahonda",
    "gn:country_code":"BI",
    "gn:dem":1568,
    "gn:feature_class":"P",
    "gn:feature_code":"PPLL",
    "gn:name":"Mahonda",
    "gn:population":0,
    "gn:timezone":"Africa/Bujumbura",
    "iso:country":"BI",
    "wof:name":"Mahonda",
    "wof:placetype":"locality"
},
  "geometry": {"coordinates":[30.3653,-2.7545],"type":"Point"}
}