{
  "type": "Feature",
  "properties": {
    "gn:admin1_code":"14",
    "gn:asciiname":"Kigari",
    "gn:country_code":"BI",
    "gn:dem":1572,
    "gn:feature_class":"P",
    "gn:feature_code":"PPLL",
    "gn:name":"Kigari",
    "gn:population":0,
    "gn:timezone":"Africa/Bujumbura",
    "iso:country":"BI",
    "wof:name":"Kigari",
    "wof:placetype":"locality"
},
  "geometry": {"coordinates":[30.0629,-3.27],"type":"Point"}
}