{
  "type": "Feature",
  "properties": {
    "gn:admin1_code":"21",
    "gn:asciiname":"Kibonangoma",
    "gn:country_code":"BI",
    "gn:dem":1578,
    "gn:feature_class":"P",
    "gn:feature_code":"PPL",
    "gn:name":"Kibonangoma",
    "gn:population":0,
    "gn:timezone":"Africa/Bujumbura",
    "iso:country":"BI",
    "name:und_x_variant":[
        "Kibonangona"
    ],
    "wof:name":"Kibonangoma",
    "wof:placetype":"locality"
},
  "geometry": {"coordinates":[30.45597,-3.33809],"type":"Point"}
}