{
  "type": "Feature",
  "properties": {
    "gn:admin1_code":"22.0",
    "gn:asciiname":"Rutemba",
    "gn:country_code":"BI",
    "gn:dem":2267,
    "gn:feature_class":"P",
    "gn:feature_code":"PPLL",
    "gn:name":"Rutemba",
    "gn:population":0,
    "gn:timezone":"Africa/Bujumbura",
    "iso:country":"BI",
    "wof:name":"Rutemba",
    "wof:placetype":"locality"
},
  "geometry": {"coordinates":[29.56804,-3.36373],"type":"Point"}
}