{
  "type": "Feature",
  "properties": {
    "gn:admin1_code":"18.0",
    "gn:asciiname":"Nyagishiru",
    "gn:country_code":"BI",
    "gn:dem":1525,
    "gn:feature_class":"P",
    "gn:feature_code":"PPLL",
    "gn:name":"Nyagishiru",
    "gn:population":0,
    "gn:timezone":"Africa/Bujumbura",
    "iso:country":"BI",
    "wof:name":"Nyagishiru",
    "wof:placetype":"locality"
},
  "geometry": {"coordinates":[30.3295,-2.9869],"type":"Point"}
}