{
  "type": "Feature",
  "properties": {
    "gn:admin1_code":"23",
    "gn:asciiname":"Mbogora",
    "gn:country_code":"BI",
    "gn:dem":1708,
    "gn:feature_class":"P",
    "gn:feature_code":"PPLL",
    "gn:name":"Mbogora",
    "gn:population":0,
    "gn:timezone":"Africa/Bujumbura",
    "iso:country":"BI",
    "wof:name":"Mbogora",
    "wof:placetype":"locality"
},
  "geometry": {"coordinates":[29.7868,-3.4581],"type":"Point"}
}