{
  "type": "Feature",
  "properties": {
    "gn:admin1_code":"14.0",
    "gn:asciiname":"Cezi",
    "gn:country_code":"BI",
    "gn:dem":1566,
    "gn:feature_class":"P",
    "gn:feature_code":"PPL",
    "gn:name":"Cezi",
    "gn:population":0,
    "gn:timezone":"Africa/Bujumbura",
    "iso:country":"BI",
    "wof:name":"Cezi",
    "wof:placetype":"locality"
},
  "geometry": {"coordinates":[30.06741,-3.22513],"type":"Point"}
}