{
  "type": "Feature",
  "properties": {
    "gn:admin1_code":"13",
    "gn:asciiname":"Mwumba",
    "gn:country_code":"BI",
    "gn:dem":1736,
    "gn:feature_class":"P",
    "gn:feature_code":"PPLL",
    "gn:name":"Mwumba",
    "gn:population":0,
    "gn:timezone":"Africa/Bujumbura",
    "iso:country":"BI",
    "wof:name":"Mwumba",
    "wof:placetype":"locality"
},
  "geometry": {"coordinates":[29.9342,-3.6185],"type":"Point"}
}