{
  "type": "Feature",
  "properties": {
    "gn:admin1_code":"11",
    "gn:asciiname":"Gihinda",
    "gn:country_code":"BI",
    "gn:dem":1422,
    "gn:feature_class":"P",
    "gn:feature_code":"PPLL",
    "gn:name":"Gihinda",
    "gn:population":0,
    "gn:timezone":"Africa/Bujumbura",
    "iso:country":"BI",
    "wof:name":"Gihinda",
    "wof:placetype":"locality"
},
  "geometry": {"coordinates":[30.7138,-3.1348],"type":"Point"}
}