{
  "type": "Feature",
  "properties": {
    "gn:admin1_code":"23",
    "gn:asciiname":"Ruramba",
    "gn:country_code":"BI",
    "gn:dem":1838,
    "gn:feature_class":"P",
    "gn:feature_code":"PPLL",
    "gn:name":"Ruramba",
    "gn:population":0,
    "gn:timezone":"Africa/Bujumbura",
    "iso:country":"BI",
    "name:und_x_variant":[
        "Muramba",
        "Ruramba"
    ],
    "wof:name":"Ruramba",
    "wof:placetype":"locality"
},
  "geometry": {"coordinates":[29.7323,-3.544],"type":"Point"}
}