{
  "type": "Feature",
  "properties": {
    "gn:admin1_code":"20",
    "gn:asciiname":"Nkeyuke",
    "gn:country_code":"BI",
    "gn:dem":1689,
    "gn:feature_class":"P",
    "gn:feature_code":"PPLL",
    "gn:name":"Nkeyuke",
    "gn:population":0,
    "gn:timezone":"Africa/Bujumbura",
    "iso:country":"BI",
    "wof:name":"Nkeyuke",
    "wof:placetype":"locality"
},
  "geometry": {"coordinates":[30.0713,-3.7056],"type":"Point"}
}