{
  "type": "Feature",
  "properties": {
    "gn:admin1_code":"20",
    "gn:asciiname":"Kavumu",
    "gn:country_code":"BI",
    "gn:dem":1629,
    "gn:feature_class":"P",
    "gn:feature_code":"PPLL",
    "gn:name":"Kavumu",
    "gn:population":0,
    "gn:timezone":"Africa/Bujumbura",
    "iso:country":"BI",
    "name:und_x_variant":[
        "Ikavumu",
        "Kavumu"
    ],
    "wof:name":"Kavumu",
    "wof:placetype":"locality"
},
  "geometry": {"coordinates":[30.0634,-3.828],"type":"Point"}
}