{
  "type": "Feature",
  "properties": {
    "gn:admin1_code":"21",
    "gn:asciiname":"Ruhata",
    "gn:country_code":"BI",
    "gn:dem":1232,
    "gn:feature_class":"P",
    "gn:feature_code":"PPLL",
    "gn:name":"Ruhata",
    "gn:population":0,
    "gn:timezone":"Africa/Bujumbura",
    "iso:country":"BI",
    "wof:name":"Ruhata",
    "wof:placetype":"locality"
},
  "geometry": {"coordinates":[30.4792,-3.5279],"type":"Point"}
}