{
  "type": "Feature",
  "properties": {
    "gn:admin1_code":"9.0",
    "gn:asciiname":"Rwankima",
    "gn:country_code":"BI",
    "gn:dem":1715,
    "gn:feature_class":"P",
    "gn:feature_code":"PPLL",
    "gn:name":"Rwankima",
    "gn:population":0,
    "gn:timezone":"Africa/Bujumbura",
    "iso:country":"BI",
    "wof:name":"Rwankima",
    "wof:placetype":"locality"
},
  "geometry": {"coordinates":[29.457,-2.9858],"type":"Point"}
}