{
  "type": "Feature",
  "properties": {
    "gn:admin1_code":"16.0",
    "gn:asciiname":"Nyarugenge",
    "gn:country_code":"BI",
    "gn:dem":1533,
    "gn:feature_class":"P",
    "gn:feature_code":"PPLL",
    "gn:name":"Nyarugenge",
    "gn:population":0,
    "gn:timezone":"Africa/Bujumbura",
    "iso:country":"BI",
    "name:ita_x_preferred":[
        "Nyarugenge"
    ],
    "name:zho_x_preferred":[
        "\u5c3c\u4e9e\u9b6f\u5ca1\u71b1"
    ],
    "wof:name":"Nyarugenge",
    "wof:placetype":"locality"
},
  "geometry": {"coordinates":[30.003,-2.6034],"type":"Point"}
}