{
  "type": "Feature",
  "properties": {
    "gn:admin1_code":"15.0",
    "gn:asciiname":"Randa",
    "gn:country_code":"BI",
    "gn:dem":1835,
    "gn:feature_class":"P",
    "gn:feature_code":"PPLL",
    "gn:name":"Randa",
    "gn:population":0,
    "gn:timezone":"Africa/Bujumbura",
    "iso:country":"BI",
    "wof:name":"Randa",
    "wof:placetype":"locality"
},
  "geometry": {"coordinates":[29.6453,-2.8275],"type":"Point"}
}