{
  "type": "Feature",
  "properties": {
    "gn:admin1_code":"13",
    "gn:asciiname":"Nkingu",
    "gn:country_code":"BI",
    "gn:dem":1856,
    "gn:feature_class":"P",
    "gn:feature_code":"PPLL",
    "gn:name":"Nkingu",
    "gn:population":0,
    "gn:timezone":"Africa/Bujumbura",
    "iso:country":"BI",
    "wof:name":"Nkingu",
    "wof:placetype":"locality"
},
  "geometry": {"coordinates":[29.9595,-3.6337],"type":"Point"}
}