{
  "type": "Feature",
  "properties": {
    "gn:admin1_code":"21",
    "gn:asciiname":"Misugi",
    "gn:country_code":"BI",
    "gn:dem":1606,
    "gn:feature_class":"P",
    "gn:feature_code":"PPLL",
    "gn:name":"Misugi",
    "gn:population":0,
    "gn:timezone":"Africa/Bujumbura",
    "iso:country":"BI",
    "wof:name":"Misugi",
    "wof:placetype":"locality"
},
  "geometry": {"coordinates":[30.2381,-3.3734],"type":"Point"}
}