{
  "type": "Feature",
  "properties": {
    "gn:admin1_code":"26",
    "gn:asciiname":"Karama",
    "gn:country_code":"BI",
    "gn:dem":980,
    "gn:feature_class":"P",
    "gn:feature_code":"PPLL",
    "gn:name":"Karama",
    "gn:population":0,
    "gn:timezone":"Africa/Bujumbura",
    "iso:country":"BI",
    "name:ceb_x_preferred":[
        "Karama"
    ],
    "name:fra_x_preferred":[
        "Karama"
    ],
    "name:ita_x_preferred":[
        "Karama"
    ],
    "name:swe_x_preferred":[
        "Karama"
    ],
    "wof:name":"Karama",
    "wof:placetype":"locality"
},
  "geometry": {"coordinates":[29.3907,-3.8738],"type":"Point"}
}