{
  "type": "Feature",
  "properties": {
    "gn:admin1_code":"10",
    "gn:asciiname":"Gatanga",
    "gn:country_code":"BI",
    "gn:dem":2003,
    "gn:feature_class":"P",
    "gn:feature_code":"PPLL",
    "gn:name":"Gatanga",
    "gn:population":0,
    "gn:timezone":"Africa/Bujumbura",
    "iso:country":"BI",
    "name:ceb_x_preferred":[
        "Gatanga"
    ],
    "name:swe_x_preferred":[
        "Gatanga"
    ],
    "name:und_x_variant":[
        "Katanga",
        "Gatanga"
    ],
    "wof:name":"Gatanga",
    "wof:placetype":"locality"
},
  "geometry": {"coordinates":[29.7204,-4.0096],"type":"Point"}
}