{
  "type": "Feature",
  "properties": {
    "gn:admin1_code":"25",
    "gn:asciiname":"Mwaza",
    "gn:country_code":"BI",
    "gn:dem":1343,
    "gn:feature_class":"P",
    "gn:feature_code":"PPLL",
    "gn:name":"Mwaza",
    "gn:population":0,
    "gn:timezone":"Africa/Bujumbura",
    "iso:country":"BI",
    "wof:name":"Mwaza",
    "wof:placetype":"locality"
},
  "geometry": {"coordinates":[29.3812,-3.5356],"type":"Point"}
}