{
  "type": "Feature",
  "properties": {
    "gn:admin1_code":"14",
    "gn:asciiname":"Ngugo",
    "gn:country_code":"BI",
    "gn:dem":1519,
    "gn:feature_class":"P",
    "gn:feature_code":"PPLL",
    "gn:name":"Ngugo",
    "gn:population":0,
    "gn:timezone":"Africa/Bujumbura",
    "iso:country":"BI",
    "wof:name":"Ngugo",
    "wof:placetype":"locality"
},
  "geometry": {"coordinates":[30.1009,-3.2625],"type":"Point"}
}