{
  "type": "Feature",
  "properties": {
    "gn:admin1_code":"13",
    "gn:asciiname":"Kaguhu",
    "gn:country_code":"BI",
    "gn:dem":1637,
    "gn:feature_class":"P",
    "gn:feature_code":"PPLL",
    "gn:name":"Kaguhu",
    "gn:population":0,
    "gn:timezone":"Africa/Bujumbura",
    "iso:country":"BI",
    "wof:name":"Kaguhu",
    "wof:placetype":"locality"
},
  "geometry": {"coordinates":[29.7996,-3.285],"type":"Point"}
}