{
  "type": "Feature",
  "properties": {
    "gn:admin1_code":"16.0",
    "gn:asciiname":"Rwimivubu",
    "gn:country_code":"BI",
    "gn:dem":1408,
    "gn:feature_class":"P",
    "gn:feature_code":"PPLL",
    "gn:name":"Rwimivubu",
    "gn:population":0,
    "gn:timezone":"Africa/Bujumbura",
    "iso:country":"BI",
    "wof:name":"Rwimivubu",
    "wof:placetype":"locality"
},
  "geometry": {"coordinates":[29.9457,-2.5133],"type":"Point"}
}