{
  "type": "Feature",
  "properties": {
    "gn:admin1_code":"21",
    "gn:asciiname":"Kebuko",
    "gn:country_code":"BI",
    "gn:dem":1566,
    "gn:feature_class":"P",
    "gn:feature_code":"PPLL",
    "gn:name":"Kebuko",
    "gn:population":0,
    "gn:timezone":"Africa/Bujumbura",
    "iso:country":"BI",
    "wof:name":"Kebuko",
    "wof:placetype":"locality"
},
  "geometry": {"coordinates":[30.2249,-3.4381],"type":"Point"}
}