{
  "type": "Feature",
  "properties": {
    "gn:admin1_code":"14.0",
    "gn:asciiname":"Mumpame",
    "gn:country_code":"BI",
    "gn:dem":1634,
    "gn:feature_class":"P",
    "gn:feature_code":"PPL",
    "gn:name":"Mumpame",
    "gn:population":0,
    "gn:timezone":"Africa/Bujumbura",
    "iso:country":"BI",
    "wof:name":"Mumpame",
    "wof:placetype":"locality"
},
  "geometry": {"coordinates":[30.2155,-3.181],"type":"Point"}
}