{
  "type": "Feature",
  "properties": {
    "gn:admin1_code":"19.0",
    "gn:asciiname":"Gaheba",
    "gn:country_code":"BI",
    "gn:dem":1713,
    "gn:feature_class":"P",
    "gn:feature_code":"PPLL",
    "gn:name":"Gaheba",
    "gn:population":0,
    "gn:timezone":"Africa/Bujumbura",
    "iso:country":"BI",
    "wof:name":"Gaheba",
    "wof:placetype":"locality"
},
  "geometry": {"coordinates":[29.8309,-2.9609],"type":"Point"}
}