{
  "type": "Feature",
  "properties": {
    "gn:admin1_code":"20",
    "gn:asciiname":"Nyesasa",
    "gn:country_code":"BI",
    "gn:dem":1259,
    "gn:feature_class":"P",
    "gn:feature_code":"PPLL",
    "gn:name":"Nyesasa",
    "gn:population":0,
    "gn:timezone":"Africa/Bujumbura",
    "iso:country":"BI",
    "wof:name":"Nyesasa",
    "wof:placetype":"locality"
},
  "geometry": {"coordinates":[30.1411,-3.9383],"type":"Point"}
}