{
  "type": "Feature",
  "properties": {
    "gn:admin1_code":"19.0",
    "gn:asciiname":"Gitaramuka",
    "gn:country_code":"BI",
    "gn:dem":1790,
    "gn:feature_class":"P",
    "gn:feature_code":"PPLL",
    "gn:name":"Gitaramuka",
    "gn:population":0,
    "gn:timezone":"Africa/Bujumbura",
    "iso:country":"BI",
    "wof:name":"Gitaramuka",
    "wof:placetype":"locality"
},
  "geometry": {"coordinates":[30.0767,-2.9357],"type":"Point"}
}