{
  "type": "Feature",
  "properties": {
    "gn:admin1_code":"10",
    "gn:asciiname":"Gitumba",
    "gn:country_code":"BI",
    "gn:dem":1894,
    "gn:feature_class":"P",
    "gn:feature_code":"PPLL",
    "gn:name":"Gitumba",
    "gn:population":0,
    "gn:timezone":"Africa/Bujumbura",
    "iso:country":"BI",
    "wof:name":"Gitumba",
    "wof:placetype":"locality"
},
  "geometry": {"coordinates":[29.6641,-3.8093],"type":"Point"}
}