{
  "type": "Feature",
  "properties": {
    "gn:admin1_code":"25",
    "gn:asciiname":"Kiziba",
    "gn:country_code":"BI",
    "gn:dem":1507,
    "gn:feature_class":"P",
    "gn:feature_code":"PPLL",
    "gn:name":"Kiziba",
    "gn:population":0,
    "gn:timezone":"Africa/Bujumbura",
    "iso:country":"BI",
    "wof:name":"Kiziba",
    "wof:placetype":"locality"
},
  "geometry": {"coordinates":[29.4909,-3.2652],"type":"Point"}
}