{
  "type": "Feature",
  "properties": {
    "gn:admin1_code":"16.0",
    "gn:asciiname":"Gihama",
    "gn:country_code":"BI",
    "gn:dem":1402,
    "gn:feature_class":"P",
    "gn:feature_code":"PPLL",
    "gn:name":"Gihama",
    "gn:population":0,
    "gn:timezone":"Africa/Bujumbura",
    "iso:country":"BI",
    "wof:name":"Gihama",
    "wof:placetype":"locality"
},
  "geometry": {"coordinates":[30.2913,-2.6267],"type":"Point"}
}