{
  "type": "Feature",
  "properties": {
    "gn:admin1_code":"22",
    "gn:asciiname":"Renga",
    "gn:country_code":"BI",
    "gn:dem":1872,
    "gn:feature_class":"P",
    "gn:feature_code":"PPLL",
    "gn:name":"Renga",
    "gn:population":0,
    "gn:timezone":"Africa/Bujumbura",
    "iso:country":"BI",
    "wof:name":"Renga",
    "wof:placetype":"locality"
},
  "geometry": {"coordinates":[29.6794,-3.3194],"type":"Point"}
}