{
  "type": "Feature",
  "properties": {
    "gn:admin1_code":"22",
    "gn:asciiname":"Renga",
    "gn:country_code":"BI",
    "gn:dem":1872,
    "gn:feature_class":"P",
    "gn:feature_code":"PPLL",
    "gn:name":"Renga",
    "gn:population":0,
    "gn:timezone":"Africa/Bujumbura",
    "iso:country":"BI",
    "name:bel_x_preferred":[
        "\u0420\u044d\u043d\u0433\u0430"
    ],
    "name:ces_x_preferred":[
        "Renga"
    ],
    "name:deu_x_preferred":[
        "Renga"
    ],
    "name:fin_x_preferred":[
        "Renga"
    ],
    "name:fra_x_preferred":[
        "Renga"
    ],
    "name:fry_x_preferred":[
        "Renga"
    ],
    "name:heb_x_preferred":[
        "\u05e8\u05e0\u05d2\u05d4"
    ],
    "name:hrv_x_preferred":[
        "Renga"
    ],
    "name:hun_x_preferred":[
        "Renga"
    ],
    "name:hye_x_preferred":[
        "\u054c\u0565\u0576\u0563\u0561"
    ],
    "name:ita_x_preferred":[
        "Renga"
    ],
    "name:ltz_x_preferred":[
        "Renga"
    ],
    "name:nld_x_preferred":[
        "Renga"
    ],
    "name:por_x_preferred":[
        "Renga"
    ],
    "name:ron_x_preferred":[
        "Renga"
    ],
    "name:rus_x_preferred":[
        "\u0420\u044d\u043d\u0433\u0430"
    ],
    "name:slk_x_preferred":[
        "Renga"
    ],
    "name:snd_x_preferred":[
        "\u0631\u064a\u0646\u06af\u0627"
    ],
    "name:spa_x_preferred":[
        "Renga"
    ],
    "name:tur_x_preferred":[
        "Renga"
    ],
    "name:ukr_x_preferred":[
        "\u0420\u0435\u043d\u0491\u0430"
    ],
    "wof:name":"Renga",
    "wof:placetype":"locality"
},
  "geometry": {"coordinates":[29.6794,-3.3194],"type":"Point"}
}