{
  "type": "Feature",
  "properties": {
    "gn:admin1_code":"21",
    "gn:asciiname":"Gicike",
    "gn:country_code":"BI",
    "gn:dem":1216,
    "gn:feature_class":"P",
    "gn:feature_code":"PPLL",
    "gn:name":"Gicike",
    "gn:population":0,
    "gn:timezone":"Africa/Bujumbura",
    "iso:country":"BI",
    "wof:name":"Gicike",
    "wof:placetype":"locality"
},
  "geometry": {"coordinates":[30.4038,-3.6007],"type":"Point"}
}