{
  "type": "Feature",
  "properties": {
    "gn:admin1_code":"13",
    "gn:asciiname":"Gabuke",
    "gn:country_code":"BI",
    "gn:dem":1495,
    "gn:feature_class":"P",
    "gn:feature_code":"PPLL",
    "gn:name":"Gabuke",
    "gn:population":0,
    "gn:timezone":"Africa/Bujumbura",
    "iso:country":"BI",
    "wof:name":"Gabuke",
    "wof:placetype":"locality"
},
  "geometry": {"coordinates":[29.9702,-3.3454],"type":"Point"}
}