{
  "type": "Feature",
  "properties": {
    "gn:admin1_code":"15.0",
    "gn:asciiname":"Gahwenzi",
    "gn:country_code":"BI",
    "gn:dem":1775,
    "gn:feature_class":"P",
    "gn:feature_code":"PPLL",
    "gn:name":"Gahwenzi",
    "gn:population":0,
    "gn:timezone":"Africa/Bujumbura",
    "iso:country":"BI",
    "wof:name":"Gahwenzi",
    "wof:placetype":"locality"
},
  "geometry": {"coordinates":[29.69,-2.9615],"type":"Point"}
}