{
  "type": "Feature",
  "properties": {
    "gn:admin1_code":"17",
    "gn:asciiname":"Kiremba",
    "gn:country_code":"BI",
    "gn:dem":1705,
    "gn:feature_class":"P",
    "gn:feature_code":"PPLL",
    "gn:name":"Kiremba",
    "gn:population":0,
    "gn:timezone":"Africa/Bujumbura",
    "iso:country":"BI",
    "name:run_x_preferred":[
        "Kiremba"
    ],
    "name:ukr_x_preferred":[
        "\u041a\u0456\u0440\u0435\u043c\u0431\u0430"
    ],
    "wof:name":"Kiremba",
    "wof:placetype":"locality"
},
  "geometry": {"coordinates":[29.8581,-4.2779],"type":"Point"}
}