{
  "type": "Feature",
  "properties": {
    "gn:admin1_code":"21",
    "gn:asciiname":"Muhindo",
    "gn:country_code":"BI",
    "gn:dem":1278,
    "gn:feature_class":"P",
    "gn:feature_code":"PPLL",
    "gn:name":"Muhindo",
    "gn:population":0,
    "gn:timezone":"Africa/Bujumbura",
    "iso:country":"BI",
    "wof:name":"Muhindo",
    "wof:placetype":"locality"
},
  "geometry": {"coordinates":[30.54,-3.4878],"type":"Point"}
}