{
  "type": "Feature",
  "properties": {
    "gn:admin1_code":"20",
    "gn:asciiname":"Musenyi",
    "gn:country_code":"BI",
    "gn:dem":1203,
    "gn:feature_class":"P",
    "gn:feature_code":"PPLL",
    "gn:name":"Musenyi",
    "gn:population":0,
    "gn:timezone":"Africa/Bujumbura",
    "iso:country":"BI",
    "name:run_x_preferred":[
        "Musenyi"
    ],
    "wof:name":"Musenyi",
    "wof:placetype":"locality"
},
  "geometry": {"coordinates":[30.2401,-3.7327],"type":"Point"}
}