{
  "type": "Feature",
  "properties": {
    "gn:admin1_code":"13",
    "gn:asciiname":"Kiyange",
    "gn:country_code":"BI",
    "gn:dem":1697,
    "gn:feature_class":"P",
    "gn:feature_code":"PPLL",
    "gn:name":"Kiyange",
    "gn:population":0,
    "gn:timezone":"Africa/Bujumbura",
    "iso:country":"BI",
    "wof:name":"Kiyange",
    "wof:placetype":"locality"
},
  "geometry": {"coordinates":[29.9554,-3.5072],"type":"Point"}
}