{
  "type": "Feature",
  "properties": {
    "gn:admin1_code":"17",
    "gn:asciiname":"Musaswe",
    "gn:country_code":"BI",
    "gn:dem":1697,
    "gn:feature_class":"P",
    "gn:feature_code":"PPL",
    "gn:name":"Musaswe",
    "gn:population":0,
    "gn:timezone":"Africa/Bujumbura",
    "iso:country":"BI",
    "wof:name":"Musaswe",
    "wof:placetype":"locality"
},
  "geometry": {"coordinates":[29.8731,-4.2823],"type":"Point"}
}