{
  "type": "Feature",
  "properties": {
    "gn:admin1_code":"13",
    "gn:asciiname":"Nyarunazi",
    "gn:country_code":"BI",
    "gn:dem":1760,
    "gn:feature_class":"P",
    "gn:feature_code":"PPL",
    "gn:name":"Nyarunazi",
    "gn:population":0,
    "gn:timezone":"Africa/Bujumbura",
    "iso:country":"BI",
    "wof:name":"Nyarunazi",
    "wof:placetype":"locality"
},
  "geometry": {"coordinates":[29.9551,-3.781],"type":"Point"}
}