{
  "type": "Feature",
  "properties": {
    "gn:admin1_code":"22",
    "gn:asciiname":"Kinyamugera",
    "gn:country_code":"BI",
    "gn:dem":2091,
    "gn:feature_class":"P",
    "gn:feature_code":"PPLL",
    "gn:name":"Kinyamugera",
    "gn:population":0,
    "gn:timezone":"Africa/Bujumbura",
    "iso:country":"BI",
    "wof:name":"Kinyamugera",
    "wof:placetype":"locality"
},
  "geometry": {"coordinates":[29.5616,-3.2564],"type":"Point"}
}