{
  "type": "Feature",
  "properties": {
    "gn:admin1_code":"12.0",
    "gn:asciiname":"Rufuri",
    "gn:country_code":"BI",
    "gn:dem":1477,
    "gn:feature_class":"P",
    "gn:feature_code":"PPLL",
    "gn:name":"Rufuri",
    "gn:population":0,
    "gn:timezone":"Africa/Bujumbura",
    "iso:country":"BI",
    "wof:name":"Rufuri",
    "wof:placetype":"locality"
},
  "geometry": {"coordinates":[29.2466,-2.6994],"type":"Point"}
}