{
  "type": "Feature",
  "properties": {
    "gn:admin1_code":"11",
    "gn:asciiname":"Kabenga",
    "gn:country_code":"BI",
    "gn:dem":1348,
    "gn:feature_class":"P",
    "gn:feature_code":"PPLL",
    "gn:name":"Kabenga",
    "gn:population":0,
    "gn:timezone":"Africa/Bujumbura",
    "iso:country":"BI",
    "wof:name":"Kabenga",
    "wof:placetype":"locality"
},
  "geometry": {"coordinates":[30.6053,-3.2846],"type":"Point"}
}