{
  "type": "Feature",
  "properties": {
    "gn:admin1_code":"21",
    "gn:asciiname":"Kiryama",
    "gn:country_code":"BI",
    "gn:dem":1531,
    "gn:feature_class":"P",
    "gn:feature_code":"PPLL",
    "gn:name":"Kiryama",
    "gn:population":0,
    "gn:timezone":"Africa/Bujumbura",
    "iso:country":"BI",
    "wof:name":"Kiryama",
    "wof:placetype":"locality"
},
  "geometry": {"coordinates":[30.0701,-3.4695],"type":"Point"}
}