{
  "type": "Feature",
  "properties": {
    "gn:admin1_code":"11",
    "gn:asciiname":"Mucogorogo",
    "gn:country_code":"BI",
    "gn:dem":1429,
    "gn:feature_class":"P",
    "gn:feature_code":"PPLL",
    "gn:name":"Mucogorogo",
    "gn:population":0,
    "gn:timezone":"Africa/Bujumbura",
    "iso:country":"BI",
    "name:und_x_variant":[
        "Mucogocogo"
    ],
    "wof:name":"Mucogorogo",
    "wof:placetype":"locality"
},
  "geometry": {"coordinates":[30.59958,-3.26378],"type":"Point"}
}