{
  "type": "Feature",
  "properties": {
    "gn:admin1_code":"10",
    "gn:asciiname":"Nyamuhanga",
    "gn:country_code":"BI",
    "gn:dem":1846,
    "gn:feature_class":"P",
    "gn:feature_code":"PPLL",
    "gn:name":"Nyamuhanga",
    "gn:population":0,
    "gn:timezone":"Africa/Bujumbura",
    "iso:country":"BI",
    "wof:name":"Nyamuhanga",
    "wof:placetype":"locality"
},
  "geometry": {"coordinates":[29.5933,-3.8281],"type":"Point"}
}