{
  "type": "Feature",
  "properties": {
    "gn:admin1_code":"13",
    "gn:asciiname":"Nyarubenga",
    "gn:country_code":"BI",
    "gn:dem":1718,
    "gn:feature_class":"P",
    "gn:feature_code":"PPLL",
    "gn:name":"Nyarubenga",
    "gn:population":0,
    "gn:timezone":"Africa/Bujumbura",
    "iso:country":"BI",
    "wof:name":"Nyarubenga",
    "wof:placetype":"locality"
},
  "geometry": {"coordinates":[29.7955,-3.5494],"type":"Point"}
}