{
  "type": "Feature",
  "properties": {
    "gn:admin1_code":"21",
    "gn:asciiname":"Rukoyoyo",
    "gn:country_code":"BI",
    "gn:dem":1245,
    "gn:feature_class":"P",
    "gn:feature_code":"PPL",
    "gn:name":"Rukoyoyo",
    "gn:population":0,
    "gn:timezone":"Africa/Bujumbura",
    "iso:country":"BI",
    "wof:name":"Rukoyoyo",
    "wof:placetype":"locality"
},
  "geometry": {"coordinates":[30.43018,-3.45022],"type":"Point"}
}