{
  "type": "Feature",
  "properties": {
    "gn:admin1_code":"20",
    "gn:asciiname":"Gakwende",
    "gn:country_code":"BI",
    "gn:dem":1597,
    "gn:feature_class":"P",
    "gn:feature_code":"PPLL",
    "gn:name":"Gakwende",
    "gn:population":0,
    "gn:timezone":"Africa/Bujumbura",
    "iso:country":"BI",
    "name:und_x_variant":[
        "Gakwande"
    ],
    "wof:name":"Gakwende",
    "wof:placetype":"locality"
},
  "geometry": {"coordinates":[29.88300000000001,-3.9599],"type":"Point"}
}