{
  "type": "Feature",
  "properties": {
    "gn:admin1_code":"23",
    "gn:asciiname":"Rutongati",
    "gn:country_code":"BI",
    "gn:dem":2034,
    "gn:feature_class":"P",
    "gn:feature_code":"PPLL",
    "gn:name":"Rutongati",
    "gn:population":0,
    "gn:timezone":"Africa/Bujumbura",
    "iso:country":"BI",
    "wof:name":"Rutongati",
    "wof:placetype":"locality"
},
  "geometry": {"coordinates":[29.6669,-3.546],"type":"Point"}
}