{
  "type": "Feature",
  "properties": {
    "gn:admin1_code":"23",
    "gn:asciiname":"Karubanga",
    "gn:country_code":"BI",
    "gn:dem":1886,
    "gn:feature_class":"P",
    "gn:feature_code":"PPLL",
    "gn:name":"Karubanga",
    "gn:population":0,
    "gn:timezone":"Africa/Bujumbura",
    "iso:country":"BI",
    "wof:name":"Karubanga",
    "wof:placetype":"locality"
},
  "geometry": {"coordinates":[29.7192,-3.4088],"type":"Point"}
}