{
  "type": "Feature",
  "properties": {
    "gn:admin1_code":"10",
    "gn:asciiname":"Murara",
    "gn:country_code":"BI",
    "gn:dem":1870,
    "gn:feature_class":"P",
    "gn:feature_code":"PPLL",
    "gn:name":"Murara",
    "gn:population":0,
    "gn:timezone":"Africa/Bujumbura",
    "iso:country":"BI",
    "name:hun_x_preferred":[
        "Murara"
    ],
    "wof:name":"Murara",
    "wof:placetype":"locality"
},
  "geometry": {"coordinates":[29.8553,-3.8072],"type":"Point"}
}