{
  "type": "Feature",
  "properties": {
    "gn:admin1_code":"12.0",
    "gn:asciiname":"Gitera",
    "gn:country_code":"BI",
    "gn:dem":1377,
    "gn:feature_class":"P",
    "gn:feature_code":"PPLL",
    "gn:name":"Gitera",
    "gn:population":0,
    "gn:timezone":"Africa/Bujumbura",
    "iso:country":"BI",
    "wof:name":"Gitera",
    "wof:placetype":"locality"
},
  "geometry": {"coordinates":[29.3189,-2.9743],"type":"Point"}
}