{
  "type": "Feature",
  "properties": {
    "gn:admin1_code":"25",
    "gn:asciiname":"Ijenda",
    "gn:country_code":"BI",
    "gn:dem":2164,
    "gn:feature_class":"P",
    "gn:feature_code":"PPLL",
    "gn:name":"Ijenda",
    "gn:population":0,
    "gn:timezone":"Africa/Bujumbura",
    "iso:country":"BI",
    "wof:name":"Ijenda",
    "wof:placetype":"locality"
},
  "geometry": {"coordinates":[29.5823,-3.4721],"type":"Point"}
}