{
  "type": "Feature",
  "properties": {
    "gn:admin1_code":"19.0",
    "gn:asciiname":"Murama",
    "gn:country_code":"BI",
    "gn:dem":1715,
    "gn:feature_class":"P",
    "gn:feature_code":"PPLL",
    "gn:name":"Murama",
    "gn:population":0,
    "gn:timezone":"Africa/Bujumbura",
    "iso:country":"BI",
    "wof:name":"Murama",
    "wof:placetype":"locality"
},
  "geometry": {"coordinates":[29.9867,-2.8597],"type":"Point"}
}