{
  "type": "Feature",
  "properties": {
    "gn:admin1_code":"21",
    "gn:asciiname":"Mahara",
    "gn:country_code":"BI",
    "gn:dem":1512,
    "gn:feature_class":"P",
    "gn:feature_code":"PPLL",
    "gn:name":"Mahara",
    "gn:population":0,
    "gn:timezone":"Africa/Bujumbura",
    "iso:country":"BI",
    "name:ceb_x_preferred":[
        "Mahara"
    ],
    "name:fra_x_preferred":[
        "Mahara"
    ],
    "name:swe_x_preferred":[
        "Mahara"
    ],
    "wof:name":"Mahara",
    "wof:placetype":"locality"
},
  "geometry": {"coordinates":[30.0574,-3.391],"type":"Point"}
}