{
  "type": "Feature",
  "properties": {
    "gn:admin1_code":"16.0",
    "gn:asciiname":"Kiyaga",
    "gn:country_code":"BI",
    "gn:dem":1400,
    "gn:feature_class":"P",
    "gn:feature_code":"PPLL",
    "gn:name":"Kiyaga",
    "gn:population":0,
    "gn:timezone":"Africa/Bujumbura",
    "iso:country":"BI",
    "wof:name":"Kiyaga",
    "wof:placetype":"locality"
},
  "geometry": {"coordinates":[30.3535,-2.4974],"type":"Point"}
}