{
  "type": "Feature",
  "properties": {
    "gn:admin1_code":"19.0",
    "gn:asciiname":"Ragwe",
    "gn:country_code":"BI",
    "gn:dem":1476,
    "gn:feature_class":"P",
    "gn:feature_code":"PPLL",
    "gn:name":"Ragwe",
    "gn:population":0,
    "gn:timezone":"Africa/Bujumbura",
    "iso:country":"BI",
    "wof:name":"Ragwe",
    "wof:placetype":"locality"
},
  "geometry": {"coordinates":[30.0516,-2.7719],"type":"Point"}
}