{
  "type": "Feature",
  "properties": {
    "gn:admin1_code":"11",
    "gn:asciiname":"Cankuzo",
    "gn:country_code":"BI",
    "gn:dem":1604,
    "gn:feature_class":"P",
    "gn:feature_code":"PPLL",
    "gn:name":"Cankuzo",
    "gn:population":0,
    "gn:timezone":"Africa/Bujumbura",
    "iso:country":"BI",
    "wof:name":"Cankuzo",
    "wof:placetype":"locality"
},
  "geometry": {"coordinates":[30.5679,-3.2121],"type":"Point"}
}