{
  "type": "Feature",
  "properties": {
    "gn:admin1_code":"13",
    "gn:asciiname":"Nyagugo",
    "gn:country_code":"BI",
    "gn:dem":1716,
    "gn:feature_class":"P",
    "gn:feature_code":"PPLL",
    "gn:name":"Nyagugo",
    "gn:population":0,
    "gn:timezone":"Africa/Bujumbura",
    "iso:country":"BI",
    "wof:name":"Nyagugo",
    "wof:placetype":"locality"
},
  "geometry": {"coordinates":[29.8876,-3.5577],"type":"Point"}
}