{
  "type": "Feature",
  "properties": {
    "gn:admin1_code":"13",
    "gn:asciiname":"Kibande",
    "gn:country_code":"BI",
    "gn:dem":1796,
    "gn:feature_class":"P",
    "gn:feature_code":"PPLL",
    "gn:name":"Kibande",
    "gn:population":0,
    "gn:timezone":"Africa/Bujumbura",
    "iso:country":"BI",
    "wof:name":"Kibande",
    "wof:placetype":"locality"
},
  "geometry": {"coordinates":[29.8297,-3.5854],"type":"Point"}
}