{
  "type": "Feature",
  "properties": {
    "gn:admin1_code":"13",
    "gn:asciiname":"Ruhande",
    "gn:country_code":"BI",
    "gn:dem":1816,
    "gn:feature_class":"P",
    "gn:feature_code":"PPLL",
    "gn:name":"Ruhande",
    "gn:population":0,
    "gn:timezone":"Africa/Bujumbura",
    "iso:country":"BI",
    "wof:name":"Ruhande",
    "wof:placetype":"locality"
},
  "geometry": {"coordinates":[29.8522,-3.6302],"type":"Point"}
}