{
  "type": "Feature",
  "properties": {
    "gn:admin1_code":"26",
    "gn:asciiname":"Gikongoro",
    "gn:country_code":"BI",
    "gn:dem":2013,
    "gn:feature_class":"P",
    "gn:feature_code":"PPLL",
    "gn:name":"Gikongoro",
    "gn:population":0,
    "gn:timezone":"Africa/Bujumbura",
    "iso:country":"BI",
    "wof:name":"Gikongoro",
    "wof:placetype":"locality"
},
  "geometry": {"coordinates":[29.4598,-3.6126],"type":"Point"}
}