{
  "type": "Feature",
  "properties": {
    "gn:admin1_code":"26",
    "gn:asciiname":"Gikongoro",
    "gn:country_code":"BI",
    "gn:dem":2013,
    "gn:feature_class":"P",
    "gn:feature_code":"PPLL",
    "gn:name":"Gikongoro",
    "gn:population":0,
    "gn:timezone":"Africa/Bujumbura",
    "iso:country":"BI",
    "name:cat_x_preferred":[
        "Gikongoro"
    ],
    "name:ceb_x_preferred":[
        "Gikongoro"
    ],
    "name:ell_x_preferred":[
        "\u0393\u03ba\u03b9\u03ba\u03bf\u03bd\u03b3\u03ba\u03cc\u03c1\u03bf"
    ],
    "name:eus_x_preferred":[
        "Gikongoro"
    ],
    "name:fra_x_preferred":[
        "Gikongoro"
    ],
    "name:hrv_x_preferred":[
        "Gikongoro"
    ],
    "name:jpn_x_preferred":[
        "\u30ae\u30b3\u30f3\u30b4\u30ed"
    ],
    "name:kor_x_preferred":[
        "\uae30\ucf69\uace0\ub85c"
    ],
    "name:mrj_x_preferred":[
        "\u0413\u0438\u043a\u043e\u043d\u0433\u043e\u0440\u043e"
    ],
    "name:nld_x_preferred":[
        "Gikongoro"
    ],
    "name:pol_x_preferred":[
        "Gikongoro"
    ],
    "name:por_x_preferred":[
        "Gikongoro"
    ],
    "name:rus_x_preferred":[
        "\u0413\u0438\u043a\u043e\u043d\u0433\u043e\u0440\u043e"
    ],
    "name:zho_x_preferred":[
        "\u5409\u5b54\u6208\u7f85"
    ],
    "wof:name":"Gikongoro",
    "wof:placetype":"locality"
},
  "geometry": {"coordinates":[29.4598,-3.6126],"type":"Point"}
}