{
  "type": "Feature",
  "properties": {
    "gn:admin1_code":"21",
    "gn:asciiname":"Kumuvumu",
    "gn:country_code":"BI",
    "gn:dem":1647,
    "gn:feature_class":"P",
    "gn:feature_code":"PPL",
    "gn:name":"Kumuvumu",
    "gn:population":0,
    "gn:timezone":"Africa/Bujumbura",
    "iso:country":"BI",
    "wof:name":"Kumuvumu",
    "wof:placetype":"locality"
},
  "geometry": {"coordinates":[30.145,-3.6213],"type":"Point"}
}