{
  "type": "Feature",
  "properties": {
    "gn:admin1_code":"20",
    "gn:asciiname":"Mutwankoma",
    "gn:country_code":"BI",
    "gn:dem":2036,
    "gn:feature_class":"P",
    "gn:feature_code":"PPLL",
    "gn:name":"Mutwankoma",
    "gn:population":0,
    "gn:timezone":"Africa/Bujumbura",
    "iso:country":"BI",
    "wof:name":"Mutwankoma",
    "wof:placetype":"locality"
},
  "geometry": {"coordinates":[30.1425,-3.821],"type":"Point"}
}