{
  "type": "Feature",
  "properties": {
    "gn:admin1_code":"20",
    "gn:asciiname":"Rutana",
    "gn:country_code":"BI",
    "gn:dem":1659,
    "gn:feature_class":"P",
    "gn:feature_code":"PPLL",
    "gn:name":"Rutana",
    "gn:population":0,
    "gn:timezone":"Africa/Bujumbura",
    "iso:country":"BI",
    "wof:name":"Rutana",
    "wof:placetype":"locality"
},
  "geometry": {"coordinates":[30.009,-3.9228],"type":"Point"}
}