{
  "type": "Feature",
  "properties": {
    "gn:admin1_code":"23",
    "gn:asciiname":"Butora",
    "gn:country_code":"BI",
    "gn:dem":2069,
    "gn:feature_class":"P",
    "gn:feature_code":"PPL",
    "gn:name":"Butora",
    "gn:population":0,
    "gn:timezone":"Africa/Bujumbura",
    "iso:country":"BI",
    "wof:name":"Butora",
    "wof:placetype":"locality"
},
  "geometry": {"coordinates":[29.6427,-3.5127],"type":"Point"}
}