{
  "type": "Feature",
  "properties": {
    "gn:admin1_code":"21",
    "gn:asciiname":"Muryaruyigi",
    "gn:country_code":"BI",
    "gn:dem":1547,
    "gn:feature_class":"P",
    "gn:feature_code":"PPL",
    "gn:name":"Muryaruyigi",
    "gn:population":0,
    "gn:timezone":"Africa/Bujumbura",
    "iso:country":"BI",
    "wof:name":"Muryaruyigi",
    "wof:placetype":"locality"
},
  "geometry": {"coordinates":[30.28938,-3.32822],"type":"Point"}
}