{
  "type": "Feature",
  "properties": {
    "gn:admin1_code":"13",
    "gn:asciiname":"Nkuruba",
    "gn:country_code":"BI",
    "gn:dem":1881,
    "gn:feature_class":"P",
    "gn:feature_code":"PPLL",
    "gn:name":"Nkuruba",
    "gn:population":0,
    "gn:timezone":"Africa/Bujumbura",
    "iso:country":"BI",
    "wof:name":"Nkuruba",
    "wof:placetype":"locality"
},
  "geometry": {"coordinates":[29.7689,-3.8033],"type":"Point"}
}