{
  "type": "Feature",
  "properties": {
    "gn:admin1_code":"15.0",
    "gn:asciiname":"Mbogwe",
    "gn:country_code":"BI",
    "gn:dem":1697,
    "gn:feature_class":"P",
    "gn:feature_code":"PPLL",
    "gn:name":"Mbogwe",
    "gn:population":0,
    "gn:timezone":"Africa/Bujumbura",
    "iso:country":"BI",
    "wof:name":"Mbogwe",
    "wof:placetype":"locality"
},
  "geometry": {"coordinates":[29.7742,-2.9975],"type":"Point"}
}