{
  "type": "Feature",
  "properties": {
    "gn:admin1_code":"26",
    "gn:asciiname":"Cunda",
    "gn:country_code":"BI",
    "gn:dem":889,
    "gn:feature_class":"P",
    "gn:feature_code":"PPLL",
    "gn:name":"Cunda",
    "gn:population":0,
    "gn:timezone":"Africa/Bujumbura",
    "iso:country":"BI",
    "name:ceb_x_preferred":[
        "Cunda"
    ],
    "name:deu_x_preferred":[
        "Cunda"
    ],
    "name:swe_x_preferred":[
        "Cunda"
    ],
    "name:tam_x_preferred":[
        "\u0b9a\u0bc1\u0ba8\u0bcd\u0ba4\u0ba9\u0bcd"
    ],
    "wof:name":"Cunda",
    "wof:placetype":"locality"
},
  "geometry": {"coordinates":[29.4377,-3.9279],"type":"Point"}
}