{
  "type": "Feature",
  "properties": {
    "gn:admin1_code":"26",
    "gn:asciiname":"Cunda",
    "gn:country_code":"BI",
    "gn:dem":889,
    "gn:feature_class":"P",
    "gn:feature_code":"PPLL",
    "gn:name":"Cunda",
    "gn:population":0,
    "gn:timezone":"Africa/Bujumbura",
    "iso:country":"BI",
    "wof:name":"Cunda",
    "wof:placetype":"locality"
},
  "geometry": {"coordinates":[29.4377,-3.9279],"type":"Point"}
}