{
  "type": "Feature",
  "properties": {
    "gn:admin1_code":"14.0",
    "gn:asciiname":"Buhevyi",
    "gn:country_code":"BI",
    "gn:dem":1642,
    "gn:feature_class":"P",
    "gn:feature_code":"PPLL",
    "gn:name":"Buhevyi",
    "gn:population":0,
    "gn:timezone":"Africa/Bujumbura",
    "iso:country":"BI",
    "wof:name":"Buhevyi",
    "wof:placetype":"locality"
},
  "geometry": {"coordinates":[29.9832,-3.0384],"type":"Point"}
}