{
  "type": "Feature",
  "properties": {
    "gn:admin1_code":"13",
    "gn:asciiname":"Ndava",
    "gn:country_code":"BI",
    "gn:dem":1839,
    "gn:feature_class":"P",
    "gn:feature_code":"PPLL",
    "gn:name":"Ndava",
    "gn:population":0,
    "gn:timezone":"Africa/Bujumbura",
    "iso:country":"BI",
    "name:ceb_x_preferred":[
        "Ndava"
    ],
    "name:run_x_preferred":[
        "Ndava"
    ],
    "name:swe_x_preferred":[
        "Ndava"
    ],
    "wof:name":"Ndava",
    "wof:placetype":"locality"
},
  "geometry": {"coordinates":[29.8083,-3.7369],"type":"Point"}
}