{
  "type": "Feature",
  "properties": {
    "gn:admin1_code":"17",
    "gn:asciiname":"Musanga",
    "gn:country_code":"BI",
    "gn:dem":1586,
    "gn:feature_class":"P",
    "gn:feature_code":"PPLL",
    "gn:name":"Musanga",
    "gn:population":0,
    "gn:timezone":"Africa/Bujumbura",
    "iso:country":"BI",
    "wof:name":"Musanga",
    "wof:placetype":"locality"
},
  "geometry": {"coordinates":[29.7545,-4.1747],"type":"Point"}
}