{
  "type": "Feature",
  "properties": {
    "gn:admin1_code":"24",
    "gn:asciiname":"Musaga",
    "gn:country_code":"BI",
    "gn:dem":887,
    "gn:feature_class":"P",
    "gn:feature_code":"PPLL",
    "gn:name":"Musaga",
    "gn:population":0,
    "gn:timezone":"Africa/Bujumbura",
    "iso:country":"BI",
    "wof:name":"Musaga",
    "wof:placetype":"locality"
},
  "geometry": {"coordinates":[29.3747,-3.4158],"type":"Point"}
}