{
  "type": "Feature",
  "properties": {
    "gn:admin1_code":"11",
    "gn:asciiname":"Muhweza",
    "gn:country_code":"BI",
    "gn:dem":1662,
    "gn:feature_class":"P",
    "gn:feature_code":"PPLL",
    "gn:name":"Muhweza",
    "gn:population":0,
    "gn:timezone":"Africa/Bujumbura",
    "iso:country":"BI",
    "wof:name":"Muhweza",
    "wof:placetype":"locality"
},
  "geometry": {"coordinates":[30.636,-3.1515],"type":"Point"}
}