{
  "type": "Feature",
  "properties": {
    "gn:admin1_code":"10",
    "gn:asciiname":"Ntunda",
    "gn:country_code":"BI",
    "gn:dem":2035,
    "gn:feature_class":"P",
    "gn:feature_code":"PPLL",
    "gn:name":"Ntunda",
    "gn:population":0,
    "gn:timezone":"Africa/Bujumbura",
    "iso:country":"BI",
    "wof:name":"Ntunda",
    "wof:placetype":"locality"
},
  "geometry": {"coordinates":[29.6617,-4.0364],"type":"Point"}
}