{
  "type": "Feature",
  "properties": {
    "gn:admin1_code":"12.0",
    "gn:asciiname":"Manege",
    "gn:country_code":"BI",
    "gn:dem":1099,
    "gn:feature_class":"P",
    "gn:feature_code":"PPLL",
    "gn:name":"Manege",
    "gn:population":0,
    "gn:timezone":"Africa/Bujumbura",
    "iso:country":"BI",
    "name:deu_x_preferred":[
        "Manege"
    ],
    "name:fra_x_preferred":[
        "Man\u00e8ge"
    ],
    "name:lit_x_preferred":[
        "Manie\u017eas"
    ],
    "name:pol_x_preferred":[
        "Mane\u017c"
    ],
    "name:por_x_preferred":[
        "Manege"
    ],
    "name:rus_x_preferred":[
        "\u041c\u0430\u043d\u0435\u0436"
    ],
    "name:ukr_x_preferred":[
        "\u041c\u0430\u043d\u0435\u0436"
    ],
    "wof:name":"Manege",
    "wof:placetype":"locality"
},
  "geometry": {"coordinates":[29.1856,-2.9103],"type":"Point"}
}