{
  "type": "Feature",
  "properties": {
    "gn:admin1_code":"15.0",
    "gn:asciiname":"Kigwandi",
    "gn:country_code":"BI",
    "gn:dem":1872,
    "gn:feature_class":"P",
    "gn:feature_code":"PPLL",
    "gn:name":"Kigwandi",
    "gn:population":0,
    "gn:timezone":"Africa/Bujumbura",
    "iso:country":"BI",
    "wof:name":"Kigwandi",
    "wof:placetype":"locality"
},
  "geometry": {"coordinates":[29.6573,-3.1136],"type":"Point"}
}