{
  "type": "Feature",
  "properties": {
    "gn:admin1_code":"23",
    "gn:asciiname":"Bisoro",
    "gn:country_code":"BI",
    "gn:dem":1704,
    "gn:feature_class":"P",
    "gn:feature_code":"PPLL",
    "gn:name":"Bisoro",
    "gn:population":0,
    "gn:timezone":"Africa/Bujumbura",
    "iso:country":"BI",
    "name:bul_x_preferred":[
        "\u0411\u0438\u0441\u043e\u0440\u043e"
    ],
    "name:deu_x_preferred":[
        "Bisoro"
    ],
    "wof:name":"Bisoro",
    "wof:placetype":"locality"
},
  "geometry": {"coordinates":[29.7745,-3.5205],"type":"Point"}
}