{
  "type": "Feature",
  "properties": {
    "gn:admin1_code":"15.0",
    "gn:asciiname":"Gitwa",
    "gn:country_code":"BI",
    "gn:dem":1772,
    "gn:feature_class":"P",
    "gn:feature_code":"PPLL",
    "gn:name":"Gitwa",
    "gn:population":0,
    "gn:timezone":"Africa/Bujumbura",
    "iso:country":"BI",
    "wof:name":"Gitwa",
    "wof:placetype":"locality"
},
  "geometry": {"coordinates":[29.6212,-2.9998],"type":"Point"}
}