{
  "type": "Feature",
  "properties": {
    "gn:admin1_code":"21",
    "gn:asciiname":"Nyamiyaga",
    "gn:country_code":"BI",
    "gn:dem":1710,
    "gn:feature_class":"P",
    "gn:feature_code":"PPLL",
    "gn:name":"Nyamiyaga",
    "gn:population":0,
    "gn:timezone":"Africa/Bujumbura",
    "iso:country":"BI",
    "wof:name":"Nyamiyaga",
    "wof:placetype":"locality"
},
  "geometry": {"coordinates":[30.1089,-3.5246],"type":"Point"}
}