{
  "type": "Feature",
  "properties": {
    "gn:admin1_code":"22.0",
    "gn:asciiname":"Musabagi",
    "gn:country_code":"BI",
    "gn:dem":1873,
    "gn:feature_class":"P",
    "gn:feature_code":"PPLL",
    "gn:name":"Musabagi",
    "gn:population":0,
    "gn:timezone":"Africa/Bujumbura",
    "iso:country":"BI",
    "wof:name":"Musabagi",
    "wof:placetype":"locality"
},
  "geometry": {"coordinates":[29.6629,-3.2081],"type":"Point"}
}