{
  "type": "Feature",
  "properties": {
    "gn:admin1_code":"18.0",
    "gn:asciiname":"Mumigereka",
    "gn:country_code":"BI",
    "gn:dem":1728,
    "gn:feature_class":"P",
    "gn:feature_code":"PPLL",
    "gn:name":"Mumigereka",
    "gn:population":0,
    "gn:timezone":"Africa/Bujumbura",
    "iso:country":"BI",
    "wof:name":"Mumigereka",
    "wof:placetype":"locality"
},
  "geometry": {"coordinates":[30.2086,-2.7963],"type":"Point"}
}