{
  "type": "Feature",
  "properties": {
    "gn:admin1_code":"14.0",
    "gn:asciiname":"Kigozi",
    "gn:country_code":"BI",
    "gn:dem":1669,
    "gn:feature_class":"P",
    "gn:feature_code":"PPLL",
    "gn:name":"Kigozi",
    "gn:population":0,
    "gn:timezone":"Africa/Bujumbura",
    "iso:country":"BI",
    "wof:name":"Kigozi",
    "wof:placetype":"locality"
},
  "geometry": {"coordinates":[30.1206,-2.959],"type":"Point"}
}