{
  "type": "Feature",
  "properties": {
    "gn:admin1_code":"10",
    "gn:asciiname":"Kabwayi",
    "gn:country_code":"BI",
    "gn:dem":1287,
    "gn:feature_class":"P",
    "gn:feature_code":"PPLL",
    "gn:name":"Kabwayi",
    "gn:population":0,
    "gn:timezone":"Africa/Bujumbura",
    "iso:country":"BI",
    "wof:name":"Kabwayi",
    "wof:placetype":"locality"
},
  "geometry": {"coordinates":[29.5561,-4.0354],"type":"Point"}
}