{
  "type": "Feature",
  "properties": {
    "gn:admin1_code":"15.0",
    "gn:asciiname":"Kabungo",
    "gn:country_code":"BI",
    "gn:dem":1749,
    "gn:feature_class":"P",
    "gn:feature_code":"PPLL",
    "gn:name":"Kabungo",
    "gn:population":0,
    "gn:timezone":"Africa/Bujumbura",
    "iso:country":"BI",
    "wof:name":"Kabungo",
    "wof:placetype":"locality"
},
  "geometry": {"coordinates":[29.7059,-3.058],"type":"Point"}
}