{
  "type": "Feature",
  "properties": {
    "gn:admin1_code":"19.0",
    "gn:asciiname":"Cayi",
    "gn:country_code":"BI",
    "gn:dem":1681,
    "gn:feature_class":"P",
    "gn:feature_code":"PPLL",
    "gn:name":"Cayi",
    "gn:population":0,
    "gn:timezone":"Africa/Bujumbura",
    "iso:country":"BI",
    "wof:name":"Cayi",
    "wof:placetype":"locality"
},
  "geometry": {"coordinates":[30.0369,-2.8874],"type":"Point"}
}