{
  "type": "Feature",
  "properties": {
    "gn:admin1_code":"11",
    "gn:asciiname":"Kabogoye",
    "gn:country_code":"BI",
    "gn:dem":1295,
    "gn:feature_class":"P",
    "gn:feature_code":"PPLL",
    "gn:name":"Kabogoye",
    "gn:population":0,
    "gn:timezone":"Africa/Bujumbura",
    "iso:country":"BI",
    "wof:name":"Kabogoye",
    "wof:placetype":"locality"
},
  "geometry": {"coordinates":[30.6639,-3.2886],"type":"Point"}
}