{
  "type": "Feature",
  "properties": {
    "gn:admin1_code":"23",
    "gn:asciiname":"Irimwa",
    "gn:country_code":"BI",
    "gn:dem":2076,
    "gn:feature_class":"P",
    "gn:feature_code":"PPLL",
    "gn:name":"Irimwa",
    "gn:population":0,
    "gn:timezone":"Africa/Bujumbura",
    "iso:country":"BI",
    "wof:name":"Irimwa",
    "wof:placetype":"locality"
},
  "geometry": {"coordinates":[29.6158,-3.4026],"type":"Point"}
}