{
  "type": "Feature",
  "properties": {
    "gn:admin1_code":"12.0",
    "gn:asciiname":"Mushanga",
    "gn:country_code":"BI",
    "gn:dem":1236,
    "gn:feature_class":"P",
    "gn:feature_code":"PPLL",
    "gn:name":"Mushanga",
    "gn:population":0,
    "gn:timezone":"Africa/Bujumbura",
    "iso:country":"BI",
    "name:ceb_x_preferred":[
        "M\u016bshank\u0101"
    ],
    "name:fas_x_preferred":[
        "\u0645\u0648\u0634\u0646\u06af\u0627"
    ],
    "name:msa_x_preferred":[
        "Mushanga"
    ],
    "name:swe_x_preferred":[
        "M\u016bshank\u0101"
    ],
    "name:ukr_x_preferred":[
        "\u041c\u0443\u0448\u0430\u043d\u0491\u0430"
    ],
    "wof:name":"Mushanga",
    "wof:placetype":"locality"
},
  "geometry": {"coordinates":[29.1879,-2.86],"type":"Point"}
}