{
  "type": "Feature",
  "properties": {
    "gn:admin1_code":"20",
    "gn:asciiname":"Ngarama",
    "gn:country_code":"BI",
    "gn:dem":1663,
    "gn:feature_class":"P",
    "gn:feature_code":"PPLL",
    "gn:name":"Ngarama",
    "gn:population":0,
    "gn:timezone":"Africa/Bujumbura",
    "iso:country":"BI",
    "wof:name":"Ngarama",
    "wof:placetype":"locality"
},
  "geometry": {"coordinates":[30.1139,-3.7953],"type":"Point"}
}