{
  "type": "Feature",
  "properties": {
    "gn:admin1_code":"17.0",
    "gn:asciiname":"Nterema",
    "gn:country_code":"BI",
    "gn:dem":1571,
    "gn:feature_class":"P",
    "gn:feature_code":"PPLL",
    "gn:name":"Nterema",
    "gn:population":0,
    "gn:timezone":"Africa/Bujumbura",
    "iso:country":"BI",
    "wof:name":"Nterema",
    "wof:placetype":"locality"
},
  "geometry": {"coordinates":[29.7312,-4.2588],"type":"Point"}
}