{
  "type": "Feature",
  "properties": {
    "gn:admin1_code":"13.0",
    "gn:asciiname":"Gatunguru",
    "gn:country_code":"BI",
    "gn:dem":1577,
    "gn:feature_class":"P",
    "gn:feature_code":"PPL",
    "gn:name":"Gatunguru",
    "gn:population":0,
    "gn:timezone":"Africa/Bujumbura",
    "iso:country":"BI",
    "wof:name":"Gatunguru",
    "wof:placetype":"locality"
},
  "geometry": {"coordinates":[29.9764,-3.2186],"type":"Point"}
}