{
  "type": "Feature",
  "properties": {
    "gn:admin1_code":"21",
    "gn:asciiname":"Kirabo",
    "gn:country_code":"BI",
    "gn:dem":1554,
    "gn:feature_class":"P",
    "gn:feature_code":"PPLL",
    "gn:name":"Kirabo",
    "gn:population":0,
    "gn:timezone":"Africa/Bujumbura",
    "iso:country":"BI",
    "wof:name":"Kirabo",
    "wof:placetype":"locality"
},
  "geometry": {"coordinates":[30.1421,-3.4168],"type":"Point"}
}