{
  "type": "Feature",
  "properties": {
    "gn:admin1_code":"10.0",
    "gn:asciiname":"Makara",
    "gn:country_code":"BI",
    "gn:dem":1982,
    "gn:feature_class":"P",
    "gn:feature_code":"PPLL",
    "gn:name":"Makara",
    "gn:population":0,
    "gn:timezone":"Africa/Bujumbura",
    "iso:country":"BI",
    "name:ceb_x_preferred":[
        "Makara"
    ],
    "name:deu_x_preferred":[
        "Makara"
    ],
    "name:ita_x_preferred":[
        "Makara"
    ],
    "name:nld_x_preferred":[
        "Makara"
    ],
    "name:swe_x_preferred":[
        "Makara"
    ],
    "name:tur_x_preferred":[
        "Makara"
    ],
    "wof:name":"Makara",
    "wof:placetype":"locality"
},
  "geometry": {"coordinates":[29.8169,-3.9269],"type":"Point"}
}