{
  "type": "Feature",
  "properties": {
    "gn:admin1_code":"26",
    "gn:asciiname":"Buringa",
    "gn:country_code":"BI",
    "gn:dem":1841,
    "gn:feature_class":"P",
    "gn:feature_code":"PPLL",
    "gn:name":"Buringa",
    "gn:population":0,
    "gn:timezone":"Africa/Bujumbura",
    "iso:country":"BI",
    "wof:name":"Buringa",
    "wof:placetype":"locality"
},
  "geometry": {"coordinates":[29.4094,-3.6365],"type":"Point"}
}