{
  "type": "Feature",
  "properties": {
    "gn:admin1_code":"10",
    "gn:asciiname":"Musagara",
    "gn:country_code":"BI",
    "gn:dem":1567,
    "gn:feature_class":"P",
    "gn:feature_code":"PPLL",
    "gn:name":"Musagara",
    "gn:population":0,
    "gn:timezone":"Africa/Bujumbura",
    "iso:country":"BI",
    "wof:name":"Musagara",
    "wof:placetype":"locality"
},
  "geometry": {"coordinates":[29.5847,-4.0087],"type":"Point"}
}