{
  "type": "Feature",
  "properties": {
    "gn:admin1_code":"19.0",
    "gn:asciiname":"Kivuzo",
    "gn:country_code":"BI",
    "gn:dem":1617,
    "gn:feature_class":"P",
    "gn:feature_code":"PPLL",
    "gn:name":"Kivuzo",
    "gn:population":0,
    "gn:timezone":"Africa/Bujumbura",
    "iso:country":"BI",
    "wof:name":"Kivuzo",
    "wof:placetype":"locality"
},
  "geometry": {"coordinates":[29.8272,-2.996],"type":"Point"}
}