{
  "type": "Feature",
  "properties": {
    "gn:admin1_code":"18.0",
    "gn:asciiname":"Higiro",
    "gn:country_code":"BI",
    "gn:dem":1725,
    "gn:feature_class":"P",
    "gn:feature_code":"PPLL",
    "gn:name":"Higiro",
    "gn:population":0,
    "gn:timezone":"Africa/Bujumbura",
    "iso:country":"BI",
    "wof:name":"Higiro",
    "wof:placetype":"locality"
},
  "geometry": {"coordinates":[30.2577,-2.8281],"type":"Point"}
}