{
  "type": "Feature",
  "properties": {
    "gn:admin1_code":"20",
    "gn:asciiname":"Vyuma",
    "gn:country_code":"BI",
    "gn:dem":1802,
    "gn:feature_class":"P",
    "gn:feature_code":"PPL",
    "gn:name":"Vyuma",
    "gn:population":0,
    "gn:timezone":"Africa/Bujumbura",
    "iso:country":"BI",
    "wof:name":"Vyuma",
    "wof:placetype":"locality"
},
  "geometry": {"coordinates":[30.0251,-3.8101],"type":"Point"}
}