{
  "type": "Feature",
  "properties": {
    "gn:admin1_code":"13",
    "gn:asciiname":"Nyabibuye",
    "gn:country_code":"BI",
    "gn:dem":1692,
    "gn:feature_class":"P",
    "gn:feature_code":"PPLL",
    "gn:name":"Nyabibuye",
    "gn:population":0,
    "gn:timezone":"Africa/Bujumbura",
    "iso:country":"BI",
    "wof:name":"Nyabibuye",
    "wof:placetype":"locality"
},
  "geometry": {"coordinates":[30.0209,-3.5437],"type":"Point"}
}