{
  "type": "Feature",
  "properties": {
    "gn:admin1_code":"21",
    "gn:asciiname":"Nyarumanga",
    "gn:country_code":"BI",
    "gn:dem":1222,
    "gn:feature_class":"P",
    "gn:feature_code":"PPLL",
    "gn:name":"Nyarumanga",
    "gn:population":0,
    "gn:timezone":"Africa/Bujumbura",
    "iso:country":"BI",
    "wof:name":"Nyarumanga",
    "wof:placetype":"locality"
},
  "geometry": {"coordinates":[30.456,-3.538],"type":"Point"}
}