{
  "type": "Feature",
  "properties": {
    "gn:admin1_code":"22",
    "gn:asciiname":"Temere",
    "gn:country_code":"BI",
    "gn:dem":1729,
    "gn:feature_class":"P",
    "gn:feature_code":"PPLL",
    "gn:name":"Temere",
    "gn:population":0,
    "gn:timezone":"Africa/Bujumbura",
    "iso:country":"BI",
    "wof:name":"Temere",
    "wof:placetype":"locality"
},
  "geometry": {"coordinates":[29.7008,-3.2722],"type":"Point"}
}