{
  "type": "Feature",
  "properties": {
    "gn:admin1_code":"23",
    "gn:asciiname":"Makamba",
    "gn:country_code":"BI",
    "gn:dem":1972,
    "gn:feature_class":"P",
    "gn:feature_code":"PPLL",
    "gn:name":"Makamba",
    "gn:population":0,
    "gn:timezone":"Africa/Bujumbura",
    "iso:country":"BI",
    "name:ceb_x_preferred":[
        "Makamba"
    ],
    "name:nld_x_preferred":[
        "Makamba"
    ],
    "name:swe_x_preferred":[
        "Makamba"
    ],
    "wof:name":"Makamba",
    "wof:placetype":"locality"
},
  "geometry": {"coordinates":[29.6596,-3.4963],"type":"Point"}
}