{
  "type": "Feature",
  "properties": {
    "gn:admin1_code":"26",
    "gn:asciiname":"Rumonyi",
    "gn:country_code":"BI",
    "gn:dem":1206,
    "gn:feature_class":"P",
    "gn:feature_code":"PPLL",
    "gn:name":"Rumonyi",
    "gn:population":0,
    "gn:timezone":"Africa/Bujumbura",
    "iso:country":"BI",
    "wof:name":"Rumonyi",
    "wof:placetype":"locality"
},
  "geometry": {"coordinates":[29.3789,-3.7712],"type":"Point"}
}