{
  "type": "Feature",
  "properties": {
    "gn:admin1_code":"10",
    "gn:asciiname":"Mushishi",
    "gn:country_code":"BI",
    "gn:dem":1729,
    "gn:feature_class":"P",
    "gn:feature_code":"PPLL",
    "gn:name":"Mushishi",
    "gn:population":0,
    "gn:timezone":"Africa/Bujumbura",
    "iso:country":"BI",
    "name:ara_x_preferred":[
        "\u0645\u0648\u0634\u064a\u0634\u064a"
    ],
    "name:deu_x_preferred":[
        "Mushishi"
    ],
    "name:fas_x_preferred":[
        "\u0645\u0648\u0634\u06cc\u200c\u0634\u06cc"
    ],
    "name:fra_x_preferred":[
        "Mushishi"
    ],
    "name:glg_x_preferred":[
        "Mushishi"
    ],
    "name:hye_x_preferred":[
        "\u0544\u0578\u0582\u0577\u056b\u0577\u056b"
    ],
    "name:ind_x_preferred":[
        "Mushishi"
    ],
    "name:ita_x_preferred":[
        "Mushishi"
    ],
    "name:nld_x_preferred":[
        "Mushishi"
    ],
    "name:pol_x_preferred":[
        "Mushishi"
    ],
    "name:por_x_preferred":[
        "Mushishi"
    ],
    "name:rus_x_preferred":[
        "Mushishi"
    ],
    "name:spa_x_preferred":[
        "Mushishi"
    ],
    "name:swe_x_preferred":[
        "Mushishi"
    ],
    "name:tgl_x_preferred":[
        "Mushishi"
    ],
    "name:ukr_x_preferred":[
        "Mushishi"
    ],
    "wof:name":"Mushishi",
    "wof:placetype":"locality"
},
  "geometry": {"coordinates":[29.5976,-4.0115],"type":"Point"}
}