{
  "type": "Feature",
  "properties": {
    "gn:admin1_code":"10",
    "gn:asciiname":"Mushishi",
    "gn:country_code":"BI",
    "gn:dem":1729,
    "gn:feature_class":"P",
    "gn:feature_code":"PPLL",
    "gn:name":"Mushishi",
    "gn:population":0,
    "gn:timezone":"Africa/Bujumbura",
    "iso:country":"BI",
    "wof:name":"Mushishi",
    "wof:placetype":"locality"
},
  "geometry": {"coordinates":[29.5976,-4.0115],"type":"Point"}
}