{
  "type": "Feature",
  "properties": {
    "gn:admin1_code":"20",
    "gn:asciiname":"Gihinga",
    "gn:country_code":"BI",
    "gn:dem":1801,
    "gn:feature_class":"P",
    "gn:feature_code":"PPLL",
    "gn:name":"Gihinga",
    "gn:population":0,
    "gn:timezone":"Africa/Bujumbura",
    "iso:country":"BI",
    "wof:name":"Gihinga",
    "wof:placetype":"locality"
},
  "geometry": {"coordinates":[30.1925,-3.757],"type":"Point"}
}