{
  "type": "Feature",
  "properties": {
    "gn:admin1_code":"21",
    "gn:asciiname":"Rusange",
    "gn:country_code":"BI",
    "gn:dem":1296,
    "gn:feature_class":"P",
    "gn:feature_code":"PPLL",
    "gn:name":"Rusange",
    "gn:population":0,
    "gn:timezone":"Africa/Bujumbura",
    "iso:country":"BI",
    "wof:name":"Rusange",
    "wof:placetype":"locality"
},
  "geometry": {"coordinates":[30.5204,-3.3996],"type":"Point"}
}