{
  "type": "Feature",
  "properties": {
    "gn:admin1_code":"9.0",
    "gn:asciiname":"Muhanza",
    "gn:country_code":"BI",
    "gn:dem":1416,
    "gn:feature_class":"P",
    "gn:feature_code":"PPL",
    "gn:name":"Muhanza",
    "gn:population":0,
    "gn:timezone":"Africa/Bujumbura",
    "iso:country":"BI",
    "wof:name":"Muhanza",
    "wof:placetype":"locality"
},
  "geometry": {"coordinates":[29.3063,-3.0201],"type":"Point"}
}