{
  "type": "Feature",
  "properties": {
    "gn:admin1_code":"18.0",
    "gn:asciiname":"Migongo",
    "gn:country_code":"BI",
    "gn:dem":1685,
    "gn:feature_class":"P",
    "gn:feature_code":"PPLL",
    "gn:name":"Migongo",
    "gn:population":0,
    "gn:timezone":"Africa/Bujumbura",
    "iso:country":"BI",
    "wof:name":"Migongo",
    "wof:placetype":"locality"
},
  "geometry": {"coordinates":[30.2301,-2.74],"type":"Point"}
}