{
  "type": "Feature",
  "properties": {
    "gn:admin1_code":"10",
    "gn:asciiname":"Nyakabenga",
    "gn:country_code":"BI",
    "gn:dem":1795,
    "gn:feature_class":"P",
    "gn:feature_code":"PPLL",
    "gn:name":"Nyakabenga",
    "gn:population":0,
    "gn:timezone":"Africa/Bujumbura",
    "iso:country":"BI",
    "wof:name":"Nyakabenga",
    "wof:placetype":"locality"
},
  "geometry": {"coordinates":[29.6005,-4.1227],"type":"Point"}
}