{
  "type": "Feature",
  "properties": {
    "gn:admin1_code":"17",
    "gn:asciiname":"Bukeye",
    "gn:country_code":"BI",
    "gn:dem":803,
    "gn:feature_class":"P",
    "gn:feature_code":"PPL",
    "gn:name":"Bukeye",
    "gn:population":0,
    "gn:timezone":"Africa/Bujumbura",
    "iso:country":"BI",
    "wof:name":"Bukeye",
    "wof:placetype":"locality"
},
  "geometry": {"coordinates":[29.61972,-4.3345],"type":"Point"}
}