{
  "type": "Feature",
  "properties": {
    "gn:admin1_code":"15.0",
    "gn:asciiname":"Mwuzumure",
    "gn:country_code":"BI",
    "gn:dem":1690,
    "gn:feature_class":"P",
    "gn:feature_code":"PPLL",
    "gn:name":"Mwuzumure",
    "gn:population":0,
    "gn:timezone":"Africa/Bujumbura",
    "iso:country":"BI",
    "wof:name":"Mwuzumure",
    "wof:placetype":"locality"
},
  "geometry": {"coordinates":[29.7594,-3.1477],"type":"Point"}
}