{
  "type": "Feature",
  "properties": {
    "gn:admin1_code":"20",
    "gn:asciiname":"Bareremba",
    "gn:country_code":"BI",
    "gn:dem":1236,
    "gn:feature_class":"P",
    "gn:feature_code":"PPLL",
    "gn:name":"Bareremba",
    "gn:population":0,
    "gn:timezone":"Africa/Bujumbura",
    "iso:country":"BI",
    "wof:name":"Bareremba",
    "wof:placetype":"locality"
},
  "geometry": {"coordinates":[30.108,-4.0498],"type":"Point"}
}