{
  "type": "Feature",
  "properties": {
    "gn:admin1_code":"22",
    "gn:asciiname":"Kigarika",
    "gn:country_code":"BI",
    "gn:dem":1925,
    "gn:feature_class":"P",
    "gn:feature_code":"PPLL",
    "gn:name":"Kigarika",
    "gn:population":0,
    "gn:timezone":"Africa/Bujumbura",
    "iso:country":"BI",
    "wof:name":"Kigarika",
    "wof:placetype":"locality"
},
  "geometry": {"coordinates":[29.6677,-3.3663],"type":"Point"}
}