{
  "type": "Feature",
  "properties": {
    "gn:admin1_code":"20",
    "gn:asciiname":"Gasaka",
    "gn:country_code":"BI",
    "gn:dem":1197,
    "gn:feature_class":"P",
    "gn:feature_code":"PPLL",
    "gn:name":"Gasaka",
    "gn:population":0,
    "gn:timezone":"Africa/Bujumbura",
    "iso:country":"BI",
    "name:und_x_variant":[
        "Kasaka",
        "Gasaka"
    ],
    "wof:name":"Gasaka",
    "wof:placetype":"locality"
},
  "geometry": {"coordinates":[30.2395,-3.7633],"type":"Point"}
}