{
  "type": "Feature",
  "properties": {
    "gn:admin1_code":"18.0",
    "gn:asciiname":"Ruvumu",
    "gn:country_code":"BI",
    "gn:dem":1543,
    "gn:feature_class":"P",
    "gn:feature_code":"PPL",
    "gn:name":"Ruvumu",
    "gn:population":0,
    "gn:timezone":"Africa/Bujumbura",
    "iso:country":"BI",
    "wof:name":"Ruvumu",
    "wof:placetype":"locality"
},
  "geometry": {"coordinates":[30.31419,-3.07106],"type":"Point"}
}