{
  "type": "Feature",
  "properties": {
    "gn:admin1_code":"13",
    "gn:asciiname":"Gitaba",
    "gn:country_code":"BI",
    "gn:dem":1724,
    "gn:feature_class":"P",
    "gn:feature_code":"PPLL",
    "gn:name":"Gitaba",
    "gn:population":0,
    "gn:timezone":"Africa/Bujumbura",
    "iso:country":"BI",
    "wof:name":"Gitaba",
    "wof:placetype":"locality"
},
  "geometry": {"coordinates":[29.9695,-3.4015],"type":"Point"}
}