{
  "type": "Feature",
  "properties": {
    "gn:admin1_code":"16.0",
    "gn:asciiname":"Kiriba",
    "gn:country_code":"BI",
    "gn:dem":1581,
    "gn:feature_class":"P",
    "gn:feature_code":"PPLL",
    "gn:name":"Kiriba",
    "gn:population":0,
    "gn:timezone":"Africa/Bujumbura",
    "iso:country":"BI",
    "wof:name":"Kiriba",
    "wof:placetype":"locality"
},
  "geometry": {"coordinates":[30.1322,-2.7345],"type":"Point"}
}