{
  "type": "Feature",
  "properties": {
    "gn:admin1_code":"12.0",
    "gn:asciiname":"Kajumba",
    "gn:country_code":"BI",
    "gn:dem":1335,
    "gn:feature_class":"P",
    "gn:feature_code":"PPL",
    "gn:name":"Kajumba",
    "gn:population":0,
    "gn:timezone":"Africa/Bujumbura",
    "iso:country":"BI",
    "wof:name":"Kajumba",
    "wof:placetype":"locality"
},
  "geometry": {"coordinates":[29.1791,-2.7017],"type":"Point"}
}