{
  "type": "Feature",
  "properties": {
    "gn:admin1_code":"19.0",
    "gn:asciiname":"Rweya",
    "gn:country_code":"BI",
    "gn:dem":1577,
    "gn:feature_class":"P",
    "gn:feature_code":"PPLL",
    "gn:name":"Rweya",
    "gn:population":0,
    "gn:timezone":"Africa/Bujumbura",
    "iso:country":"BI",
    "wof:name":"Rweya",
    "wof:placetype":"locality"
},
  "geometry": {"coordinates":[30.0053,-2.8584],"type":"Point"}
}