{
  "type": "Feature",
  "properties": {
    "gn:admin1_code":"19.0",
    "gn:asciiname":"Rubaya",
    "gn:country_code":"BI",
    "gn:dem":1572,
    "gn:feature_class":"P",
    "gn:feature_code":"PPL",
    "gn:name":"Rubaya",
    "gn:population":0,
    "gn:timezone":"Africa/Bujumbura",
    "iso:country":"BI",
    "wof:name":"Rubaya",
    "wof:placetype":"locality"
},
  "geometry": {"coordinates":[29.9976,-2.6987],"type":"Point"}
}