{
  "type": "Feature",
  "properties": {
    "gn:admin1_code":"19.0",
    "gn:asciiname":"Kanyomvyi",
    "gn:country_code":"BI",
    "gn:dem":1556,
    "gn:feature_class":"P",
    "gn:feature_code":"PPLL",
    "gn:name":"Kanyomvyi",
    "gn:population":0,
    "gn:timezone":"Africa/Bujumbura",
    "iso:country":"BI",
    "wof:name":"Kanyomvyi",
    "wof:placetype":"locality"
},
  "geometry": {"coordinates":[30.0782,-2.797],"type":"Point"}
}