{
  "type": "Feature",
  "properties": {
    "gn:admin1_code":"15.0",
    "gn:asciiname":"Nyakabindi",
    "gn:country_code":"BI",
    "gn:dem":1825,
    "gn:feature_class":"P",
    "gn:feature_code":"PPLL",
    "gn:name":"Nyakabindi",
    "gn:population":0,
    "gn:timezone":"Africa/Bujumbura",
    "iso:country":"BI",
    "wof:name":"Nyakabindi",
    "wof:placetype":"locality"
},
  "geometry": {"coordinates":[29.687,-3.0169],"type":"Point"}
}