{
  "type": "Feature",
  "properties": {
    "gn:admin1_code":"19.0",
    "gn:asciiname":"Gahini",
    "gn:country_code":"BI",
    "gn:dem":1790,
    "gn:feature_class":"P",
    "gn:feature_code":"PPLL",
    "gn:name":"Gahini",
    "gn:population":0,
    "gn:timezone":"Africa/Bujumbura",
    "iso:country":"BI",
    "wof:name":"Gahini",
    "wof:placetype":"locality"
},
  "geometry": {"coordinates":[29.6728,-2.8203],"type":"Point"}
}