{
  "type": "Feature",
  "properties": {
    "gn:admin1_code":"16.0",
    "gn:asciiname":"Buringa",
    "gn:country_code":"BI",
    "gn:dem":1505,
    "gn:feature_class":"P",
    "gn:feature_code":"PPLL",
    "gn:name":"Buringa",
    "gn:population":0,
    "gn:timezone":"Africa/Bujumbura",
    "iso:country":"BI",
    "wof:name":"Buringa",
    "wof:placetype":"locality"
},
  "geometry": {"coordinates":[30.0299,-2.6475],"type":"Point"}
}