{
  "type": "Feature",
  "properties": {
    "gn:admin1_code":"22",
    "gn:asciiname":"Kirehe",
    "gn:country_code":"BI",
    "gn:dem":1737,
    "gn:feature_class":"P",
    "gn:feature_code":"PPLL",
    "gn:name":"Kirehe",
    "gn:population":0,
    "gn:timezone":"Africa/Bujumbura",
    "iso:country":"BI",
    "wof:name":"Kirehe",
    "wof:placetype":"locality"
},
  "geometry": {"coordinates":[29.712,-3.2758],"type":"Point"}
}