{
  "type": "Feature",
  "properties": {
    "gn:admin1_code":"14.0",
    "gn:asciiname":"Rushombo",
    "gn:country_code":"BI",
    "gn:dem":1535,
    "gn:feature_class":"P",
    "gn:feature_code":"PPL",
    "gn:name":"Rushombo",
    "gn:population":0,
    "gn:timezone":"Africa/Bujumbura",
    "iso:country":"BI",
    "wof:name":"Rushombo",
    "wof:placetype":"locality"
},
  "geometry": {"coordinates":[30.0925,-3.133],"type":"Point"}
}