{
  "type": "Feature",
  "properties": {
    "gn:admin1_code":"23",
    "gn:asciiname":"Nyarurambi",
    "gn:country_code":"BI",
    "gn:dem":1581,
    "gn:feature_class":"P",
    "gn:feature_code":"PPLL",
    "gn:name":"Nyarurambi",
    "gn:population":0,
    "gn:timezone":"Africa/Bujumbura",
    "iso:country":"BI",
    "wof:name":"Nyarurambi",
    "wof:placetype":"locality"
},
  "geometry": {"coordinates":[29.8465,-3.381],"type":"Point"}
}