{
  "type": "Feature",
  "properties": {
    "gn:admin1_code":"19.0",
    "gn:asciiname":"Kinyami",
    "gn:country_code":"BI",
    "gn:dem":1725,
    "gn:feature_class":"P",
    "gn:feature_code":"PPLL",
    "gn:name":"Kinyami",
    "gn:population":0,
    "gn:timezone":"Africa/Bujumbura",
    "iso:country":"BI",
    "wof:name":"Kinyami",
    "wof:placetype":"locality"
},
  "geometry": {"coordinates":[29.6891,-2.827],"type":"Point"}
}