{
  "type": "Feature",
  "properties": {
    "gn:admin1_code":"23",
    "gn:asciiname":"Cakaka",
    "gn:country_code":"BI",
    "gn:dem":1899,
    "gn:feature_class":"P",
    "gn:feature_code":"PPLL",
    "gn:name":"Cakaka",
    "gn:population":0,
    "gn:timezone":"Africa/Bujumbura",
    "iso:country":"BI",
    "name:und_x_variant":[
        "Gakaka",
        "Cakaka"
    ],
    "wof:name":"Cakaka",
    "wof:placetype":"locality"
},
  "geometry": {"coordinates":[29.7656,-3.3921],"type":"Point"}
}