{
  "type": "Feature",
  "properties": {
    "gn:admin1_code":"20.0",
    "gn:asciiname":"Ramvya",
    "gn:country_code":"BI",
    "gn:dem":1700,
    "gn:feature_class":"P",
    "gn:feature_code":"PPLL",
    "gn:name":"Ramvya",
    "gn:population":0,
    "gn:timezone":"Africa/Bujumbura",
    "iso:country":"BI",
    "wof:name":"Ramvya",
    "wof:placetype":"locality"
},
  "geometry": {"coordinates":[29.9264,-3.8674],"type":"Point"}
}