{
  "type": "Feature",
  "properties": {
    "gn:admin1_code":"18",
    "gn:asciiname":"Giheru",
    "gn:country_code":"BI",
    "gn:dem":1409,
    "gn:feature_class":"P",
    "gn:feature_code":"PPL",
    "gn:name":"Giheru",
    "gn:population":0,
    "gn:timezone":"Africa/Bujumbura",
    "iso:country":"BI",
    "wof:name":"Giheru",
    "wof:placetype":"locality"
},
  "geometry": {"coordinates":[30.40226,-3.0199],"type":"Point"}
}