{
  "type": "Feature",
  "properties": {
    "gn:admin1_code":"13",
    "gn:asciiname":"Higiro",
    "gn:country_code":"BI",
    "gn:dem":1687,
    "gn:feature_class":"P",
    "gn:feature_code":"PPLL",
    "gn:name":"Higiro",
    "gn:population":0,
    "gn:timezone":"Africa/Bujumbura",
    "iso:country":"BI",
    "wof:name":"Higiro",
    "wof:placetype":"locality"
},
  "geometry": {"coordinates":[29.9696,-3.4043],"type":"Point"}
}