{
  "type": "Feature",
  "properties": {
    "gn:admin1_code":"14.0",
    "gn:asciiname":"Kibande",
    "gn:country_code":"BI",
    "gn:dem":1583,
    "gn:feature_class":"P",
    "gn:feature_code":"PPLL",
    "gn:name":"Kibande",
    "gn:population":0,
    "gn:timezone":"Africa/Bujumbura",
    "iso:country":"BI",
    "wof:name":"Kibande",
    "wof:placetype":"locality"
},
  "geometry": {"coordinates":[30.1336,-2.9481],"type":"Point"}
}