{
  "type": "Feature",
  "properties": {
    "gn:admin1_code":"14.0",
    "gn:asciiname":"Gikombe",
    "gn:country_code":"BI",
    "gn:dem":1562,
    "gn:feature_class":"P",
    "gn:feature_code":"PPLL",
    "gn:name":"Gikombe",
    "gn:population":0,
    "gn:timezone":"Africa/Bujumbura",
    "iso:country":"BI",
    "wof:name":"Gikombe",
    "wof:placetype":"locality"
},
  "geometry": {"coordinates":[29.9874,-3.184],"type":"Point"}
}