{
  "type": "Feature",
  "properties": {
    "gn:admin1_code":"18.0",
    "gn:asciiname":"Kayogoro",
    "gn:country_code":"BI",
    "gn:dem":1504,
    "gn:feature_class":"P",
    "gn:feature_code":"PPLL",
    "gn:name":"Kayogoro",
    "gn:population":0,
    "gn:timezone":"Africa/Bujumbura",
    "iso:country":"BI",
    "wof:name":"Kayogoro",
    "wof:placetype":"locality"
},
  "geometry": {"coordinates":[30.3581,-2.9994],"type":"Point"}
}