{
  "type": "Feature",
  "properties": {
    "gn:admin1_code":"12.0",
    "gn:asciiname":"Bugobora",
    "gn:country_code":"BI",
    "gn:dem":1215,
    "gn:feature_class":"P",
    "gn:feature_code":"PPLL",
    "gn:name":"Bugobora",
    "gn:population":0,
    "gn:timezone":"Africa/Bujumbura",
    "iso:country":"BI",
    "wof:name":"Bugobora",
    "wof:placetype":"locality"
},
  "geometry": {"coordinates":[29.1938,-2.8515],"type":"Point"}
}