{
  "type": "Feature",
  "properties": {
    "gn:admin1_code":"22",
    "gn:asciiname":"Nyarukenke",
    "gn:country_code":"BI",
    "gn:dem":1907,
    "gn:feature_class":"P",
    "gn:feature_code":"PPLL",
    "gn:name":"Nyarukenke",
    "gn:population":0,
    "gn:timezone":"Africa/Bujumbura",
    "iso:country":"BI",
    "wof:name":"Nyarukenke",
    "wof:placetype":"locality"
},
  "geometry": {"coordinates":[29.7291,-3.2676],"type":"Point"}
}