{
  "type": "Feature",
  "properties": {
    "gn:admin1_code":"25",
    "gn:asciiname":"Bubanza",
    "gn:country_code":"BI",
    "gn:dem":1927,
    "gn:feature_class":"P",
    "gn:feature_code":"PPLL",
    "gn:name":"Bubanza",
    "gn:population":0,
    "gn:timezone":"Africa/Bujumbura",
    "iso:country":"BI",
    "wof:name":"Bubanza",
    "wof:placetype":"locality"
},
  "geometry": {"coordinates":[29.4669,-3.5303],"type":"Point"}
}