{
  "type": "Feature",
  "properties": {
    "gn:admin1_code":"25",
    "gn:asciiname":"Bubanza",
    "gn:country_code":"BI",
    "gn:dem":1927,
    "gn:feature_class":"P",
    "gn:feature_code":"PPLL",
    "gn:name":"Bubanza",
    "gn:population":0,
    "gn:timezone":"Africa/Bujumbura",
    "iso:country":"BI",
    "name:ara_x_preferred":[
        "\u0628\u0648\u0628\u0627\u0646\u0632\u0627"
    ],
    "name:azb_x_preferred":[
        "\u0628\u0648\u062f\u0627\u0646\u0632\u0627"
    ],
    "name:ceb_x_preferred":[
        "Bubanza"
    ],
    "name:dan_x_preferred":[
        "Bubanza"
    ],
    "name:deu_x_preferred":[
        "Bubanza"
    ],
    "name:epo_x_preferred":[
        "Bubanza"
    ],
    "name:fas_x_preferred":[
        "\u0628\u0648\u062f\u0627\u0646\u0632\u0627"
    ],
    "name:fra_x_preferred":[
        "Bubanza"
    ],
    "name:frr_x_preferred":[
        "Bubanza"
    ],
    "name:ind_x_preferred":[
        "Bubanza"
    ],
    "name:ita_x_preferred":[
        "Bubanza"
    ],
    "name:nld_x_preferred":[
        "Bubanza"
    ],
    "name:pol_x_preferred":[
        "Bubanza"
    ],
    "name:por_x_preferred":[
        "Bubanza"
    ],
    "name:ron_x_preferred":[
        "Bubanza"
    ],
    "name:run_x_preferred":[
        "Bubanza"
    ],
    "name:rus_x_preferred":[
        "\u0411\u0443\u0431\u0430\u043d\u0437\u0430"
    ],
    "name:spa_x_preferred":[
        "Bubanza"
    ],
    "name:swa_x_preferred":[
        "Bubanza"
    ],
    "name:swe_x_preferred":[
        "Bubanza"
    ],
    "name:urd_x_preferred":[
        "\u0628\u0648\u0628\u0648\u0646\u0632\u0627"
    ],
    "name:zho_x_preferred":[
        "\u5e03\u73ed\u624e"
    ],
    "wof:name":"Bubanza",
    "wof:placetype":"locality"
},
  "geometry": {"coordinates":[29.4669,-3.5303],"type":"Point"}
}