{
  "type": "Feature",
  "properties": {
    "gn:admin1_code":"18.0",
    "gn:asciiname":"Runyozi",
    "gn:country_code":"BI",
    "gn:dem":1423,
    "gn:feature_class":"P",
    "gn:feature_code":"PPLL",
    "gn:name":"Runyozi",
    "gn:population":0,
    "gn:timezone":"Africa/Bujumbura",
    "iso:country":"BI",
    "wof:name":"Runyozi",
    "wof:placetype":"locality"
},
  "geometry": {"coordinates":[30.4371,-2.5132],"type":"Point"}
}