{
  "type": "Feature",
  "properties": {
    "gn:admin1_code":"13",
    "gn:asciiname":"Simba",
    "gn:country_code":"BI",
    "gn:dem":1712,
    "gn:feature_class":"P",
    "gn:feature_code":"PPLL",
    "gn:name":"Simba",
    "gn:population":0,
    "gn:timezone":"Africa/Bujumbura",
    "iso:country":"BI",
    "wof:name":"Simba",
    "wof:placetype":"locality"
},
  "geometry": {"coordinates":[29.9834,-3.5032],"type":"Point"}
}