{
  "type": "Feature",
  "properties": {
    "gn:admin1_code":"11",
    "gn:asciiname":"Muremera",
    "gn:country_code":"BI",
    "gn:dem":1339,
    "gn:feature_class":"P",
    "gn:feature_code":"PPLL",
    "gn:name":"Muremera",
    "gn:population":0,
    "gn:timezone":"Africa/Bujumbura",
    "iso:country":"BI",
    "wof:name":"Muremera",
    "wof:placetype":"locality"
},
  "geometry": {"coordinates":[30.6639,-3.2783],"type":"Point"}
}