{
  "type": "Feature",
  "properties": {
    "gn:admin1_code":"26",
    "gn:asciiname":"Busesa",
    "gn:country_code":"BI",
    "gn:dem":1382,
    "gn:feature_class":"P",
    "gn:feature_code":"PPLL",
    "gn:name":"Busesa",
    "gn:population":0,
    "gn:timezone":"Africa/Bujumbura",
    "iso:country":"BI",
    "wof:name":"Busesa",
    "wof:placetype":"locality"
},
  "geometry": {"coordinates":[29.43889,-3.87222],"type":"Point"}
}