{
  "type": "Feature",
  "properties": {
    "gn:admin1_code":"25",
    "gn:asciiname":"Kavyirame",
    "gn:country_code":"BI",
    "gn:dem":1518,
    "gn:feature_class":"P",
    "gn:feature_code":"PPLL",
    "gn:name":"Kavyirame",
    "gn:population":0,
    "gn:timezone":"Africa/Bujumbura",
    "iso:country":"BI",
    "wof:name":"Kavyirame",
    "wof:placetype":"locality"
},
  "geometry": {"coordinates":[29.4581,-3.4173],"type":"Point"}
}