{
  "type": "Feature",
  "properties": {
    "gn:admin1_code":"20.0",
    "gn:asciiname":"Nyabisindu",
    "gn:country_code":"BI",
    "gn:dem":1717,
    "gn:feature_class":"P",
    "gn:feature_code":"PPLL",
    "gn:name":"Nyabisindu",
    "gn:population":0,
    "gn:timezone":"Africa/Bujumbura",
    "iso:country":"BI",
    "wof:name":"Nyabisindu",
    "wof:placetype":"locality"
},
  "geometry": {"coordinates":[29.9916,-3.8559],"type":"Point"}
}