{
  "type": "Feature",
  "properties": {
    "gn:admin1_code":"15.0",
    "gn:asciiname":"Mbirizi",
    "gn:country_code":"BI",
    "gn:dem":1755,
    "gn:feature_class":"P",
    "gn:feature_code":"PPLL",
    "gn:name":"Mbirizi",
    "gn:population":0,
    "gn:timezone":"Africa/Bujumbura",
    "iso:country":"BI",
    "wof:name":"Mbirizi",
    "wof:placetype":"locality"
},
  "geometry": {"coordinates":[29.6908,-2.9664],"type":"Point"}
}