{
  "type": "Feature",
  "properties": {
    "gn:admin1_code":"10.0",
    "gn:asciiname":"Nyabisiga",
    "gn:country_code":"BI",
    "gn:dem":1728,
    "gn:feature_class":"P",
    "gn:feature_code":"PPLL",
    "gn:name":"Nyabisiga",
    "gn:population":0,
    "gn:timezone":"Africa/Bujumbura",
    "iso:country":"BI",
    "wof:name":"Nyabisiga",
    "wof:placetype":"locality"
},
  "geometry": {"coordinates":[29.8733,-3.8817],"type":"Point"}
}