{
  "type": "Feature",
  "properties": {
    "gn:admin1_code":"16.0",
    "gn:asciiname":"Nkondo",
    "gn:country_code":"BI",
    "gn:dem":1523,
    "gn:feature_class":"P",
    "gn:feature_code":"PPLL",
    "gn:name":"Nkondo",
    "gn:population":0,
    "gn:timezone":"Africa/Bujumbura",
    "iso:country":"BI",
    "wof:name":"Nkondo",
    "wof:placetype":"locality"
},
  "geometry": {"coordinates":[30.3688,-2.5085],"type":"Point"}
}