{
  "type": "Feature",
  "properties": {
    "gn:admin1_code":"19.0",
    "gn:asciiname":"Kagari",
    "gn:country_code":"BI",
    "gn:dem":1640,
    "gn:feature_class":"P",
    "gn:feature_code":"PPLL",
    "gn:name":"Kagari",
    "gn:population":0,
    "gn:timezone":"Africa/Bujumbura",
    "iso:country":"BI",
    "wof:name":"Kagari",
    "wof:placetype":"locality"
},
  "geometry": {"coordinates":[29.8584,-2.9623],"type":"Point"}
}