{
  "type": "Feature",
  "properties": {
    "gn:admin1_code":"14.0",
    "gn:asciiname":"Budaga",
    "gn:country_code":"BI",
    "gn:dem":1699,
    "gn:feature_class":"P",
    "gn:feature_code":"PPL",
    "gn:name":"Budaga",
    "gn:population":0,
    "gn:timezone":"Africa/Bujumbura",
    "iso:country":"BI",
    "wof:name":"Budaga",
    "wof:placetype":"locality"
},
  "geometry": {"coordinates":[30.1109,-2.9807],"type":"Point"}
}