{
  "type": "Feature",
  "properties": {
    "gn:admin1_code":"14.0",
    "gn:asciiname":"Burarana",
    "gn:country_code":"BI",
    "gn:dem":1607,
    "gn:feature_class":"P",
    "gn:feature_code":"PPL",
    "gn:name":"Burarana",
    "gn:population":0,
    "gn:timezone":"Africa/Bujumbura",
    "iso:country":"BI",
    "wof:name":"Burarana",
    "wof:placetype":"locality"
},
  "geometry": {"coordinates":[30.13221,-3.00463],"type":"Point"}
}