{
  "type": "Feature",
  "properties": {
    "gn:admin1_code":"19.0",
    "gn:asciiname":"Kambati",
    "gn:country_code":"BI",
    "gn:dem":1715,
    "gn:feature_class":"P",
    "gn:feature_code":"PPLL",
    "gn:name":"Kambati",
    "gn:population":0,
    "gn:timezone":"Africa/Bujumbura",
    "iso:country":"BI",
    "wof:name":"Kambati",
    "wof:placetype":"locality"
},
  "geometry": {"coordinates":[29.7757,-2.9495],"type":"Point"}
}