{
  "type": "Feature",
  "properties": {
    "gn:admin1_code":"25",
    "gn:asciiname":"Gasasira",
    "gn:country_code":"BI",
    "gn:dem":1959,
    "gn:feature_class":"P",
    "gn:feature_code":"PPLL",
    "gn:name":"Gasasira",
    "gn:population":0,
    "gn:timezone":"Africa/Bujumbura",
    "iso:country":"BI",
    "wof:name":"Gasasira",
    "wof:placetype":"locality"
},
  "geometry": {"coordinates":[29.4521,-3.5818],"type":"Point"}
}