{
  "type": "Feature",
  "properties": {
    "iso:country":"BI",
    "name:fra_x_preferred":[
        "Ngagara"
    ],
    "name:unk_x_variant":[
        "Ngagara"
    ],
    "qs:gn_adm0_cc":"BI",
    "qs:gn_fcode":"PPLX",
    "qs:gn_local":425378,
    "qs:gn_nam_loc":"Bujumbura, Bujumbura Mairie, Bujumbura, BI",
    "qs:gn_namadm1":"24",
    "qs:gn_name":"Ngagara",
    "qs:local_max":318,
    "qs:local_sum":318,
    "qs:localhoods":1,
    "qs:name":"Ngagara",
    "qs:name_adm0":"Burundi",
    "qs:name_adm1":"Bujumbura Mairie",
    "qs:name_adm2":"Bujumbura",
    "qs:name_local":"Bujumbura",
    "qs:photo_max":192,
    "qs:photo_sum":318,
    "qs:placetype":"Suburb",
    "qs:quad_count":12,
    "qs:woe_adm0":23424774,
    "qs:woe_adm1":2344900,
    "qs:woe_adm2":56017455,
    "qs:woe_lau":0,
    "qs:woe_local":1269399,
    "qs:woe_ver":"7.10.0",
    "wof:lang":[
        "fre"
    ],
    "wof:name":"Ngagara",
    "wof:placetype":"neighbourhood"
},
  "geometry": {"coordinates":[29.351933,-3.37149],"type":"Point"}
}