{
  "type": "Feature",
  "properties": {
    "gn:admin1_code":"13",
    "gn:asciiname":"Kavumu",
    "gn:country_code":"BI",
    "gn:dem":1830,
    "gn:feature_class":"P",
    "gn:feature_code":"PPLL",
    "gn:name":"Kavumu",
    "gn:population":0,
    "gn:timezone":"Africa/Bujumbura",
    "iso:country":"BI",
    "wof:name":"Kavumu",
    "wof:placetype":"locality"
},
  "geometry": {"coordinates":[29.7659,-3.6359],"type":"Point"}
}