{
  "type": "Feature",
  "properties": {
    "gn:admin1_code":"20.0",
    "gn:asciiname":"Busigo",
    "gn:country_code":"BI",
    "gn:dem":1771,
    "gn:feature_class":"P",
    "gn:feature_code":"PPLL",
    "gn:name":"Busigo",
    "gn:population":0,
    "gn:timezone":"Africa/Bujumbura",
    "iso:country":"BI",
    "wof:name":"Busigo",
    "wof:placetype":"locality"
},
  "geometry": {"coordinates":[29.9795,-3.9008],"type":"Point"}
}