{
  "type": "Feature",
  "properties": {
    "gn:admin1_code":"24",
    "gn:asciiname":"Kibenga",
    "gn:country_code":"BI",
    "gn:dem":778,
    "gn:feature_class":"P",
    "gn:feature_code":"PPLL",
    "gn:name":"Kibenga",
    "gn:population":0,
    "gn:timezone":"Africa/Bujumbura",
    "iso:country":"BI",
    "wof:name":"Kibenga",
    "wof:placetype":"locality"
},
  "geometry": {"coordinates":[29.3462,-3.4235],"type":"Point"}
}