{
  "type": "Feature",
  "properties": {
    "gn:admin1_code":"22",
    "gn:asciiname":"Mubuga",
    "gn:country_code":"BI",
    "gn:dem":1847,
    "gn:feature_class":"P",
    "gn:feature_code":"PPLL",
    "gn:name":"Mubuga",
    "gn:population":0,
    "gn:timezone":"Africa/Bujumbura",
    "iso:country":"BI",
    "wof:name":"Mubuga",
    "wof:placetype":"locality"
},
  "geometry": {"coordinates":[29.7232,-3.2749],"type":"Point"}
}