{
  "type": "Feature",
  "properties": {
    "gn:admin1_code":"20",
    "gn:asciiname":"Bugongo II",
    "gn:country_code":"BI",
    "gn:dem":1243,
    "gn:feature_class":"P",
    "gn:feature_code":"PPLL",
    "gn:name":"Bugongo II",
    "gn:population":0,
    "gn:timezone":"Africa/Bujumbura",
    "iso:country":"BI",
    "name:und_x_variant":[
        "Bugongo 2"
    ],
    "wof:name":"Bugongo II",
    "wof:placetype":"locality"
},
  "geometry": {"coordinates":[30.3393,-3.7147],"type":"Point"}
}