{
  "type": "Feature",
  "properties": {
    "gn:admin1_code":"14.0",
    "gn:asciiname":"Muzenga 2",
    "gn:country_code":"BI",
    "gn:dem":1569,
    "gn:feature_class":"P",
    "gn:feature_code":"PPL",
    "gn:name":"Muzenga 2",
    "gn:population":0,
    "gn:timezone":"Africa/Bujumbura",
    "iso:country":"BI",
    "wof:name":"Muzenga 2",
    "wof:placetype":"locality"
},
  "geometry": {"coordinates":[30.0083,-3.187],"type":"Point"}
}