{
  "type": "Feature",
  "properties": {
    "gn:admin1_code":"10",
    "gn:asciiname":"Kagongo",
    "gn:country_code":"BI",
    "gn:dem":2132,
    "gn:feature_class":"P",
    "gn:feature_code":"PPLL",
    "gn:name":"Kagongo",
    "gn:population":0,
    "gn:timezone":"Africa/Bujumbura",
    "iso:country":"BI",
    "wof:name":"Kagongo",
    "wof:placetype":"locality"
},
  "geometry": {"coordinates":[29.6544,-3.6695],"type":"Point"}
}