{
  "type": "Feature",
  "properties": {
    "gn:admin1_code":"21",
    "gn:asciiname":"Kurugabano",
    "gn:country_code":"BI",
    "gn:dem":1672,
    "gn:feature_class":"P",
    "gn:feature_code":"PPLL",
    "gn:name":"Kurugabano",
    "gn:population":0,
    "gn:timezone":"Africa/Bujumbura",
    "iso:country":"BI",
    "wof:name":"Kurugabano",
    "wof:placetype":"locality"
},
  "geometry": {"coordinates":[30.1817,-3.6012],"type":"Point"}
}