{
  "type": "Feature",
  "properties": {
    "gn:admin1_code":"20",
    "gn:asciiname":"Gasange",
    "gn:country_code":"BI",
    "gn:dem":1767,
    "gn:feature_class":"P",
    "gn:feature_code":"PPLL",
    "gn:name":"Gasange",
    "gn:population":0,
    "gn:timezone":"Africa/Bujumbura",
    "iso:country":"BI",
    "wof:name":"Gasange",
    "wof:placetype":"locality"
},
  "geometry": {"coordinates":[29.9519,-3.8206],"type":"Point"}
}