{
  "type": "Feature",
  "properties": {
    "gn:admin1_code":"15.0",
    "gn:asciiname":"Vyoga",
    "gn:country_code":"BI",
    "gn:dem":1808,
    "gn:feature_class":"P",
    "gn:feature_code":"PPLL",
    "gn:name":"Vyoga",
    "gn:population":0,
    "gn:timezone":"Africa/Bujumbura",
    "iso:country":"BI",
    "wof:name":"Vyoga",
    "wof:placetype":"locality"
},
  "geometry": {"coordinates":[29.7314,-3.2097],"type":"Point"}
}