{
  "type": "Feature",
  "properties": {
    "gn:admin1_code":"21",
    "gn:asciiname":"Senga",
    "gn:country_code":"BI",
    "gn:dem":1638,
    "gn:feature_class":"P",
    "gn:feature_code":"PPLL",
    "gn:name":"Senga",
    "gn:population":0,
    "gn:timezone":"Africa/Bujumbura",
    "iso:country":"BI",
    "name:ceb_x_preferred":[
        "Senga"
    ],
    "name:ita_x_preferred":[
        "Senga"
    ],
    "name:swa_x_preferred":[
        "Senga"
    ],
    "name:swe_x_preferred":[
        "Senga"
    ],
    "wof:name":"Senga",
    "wof:placetype":"locality"
},
  "geometry": {"coordinates":[30.226,-3.3792],"type":"Point"}
}