{
  "type": "Feature",
  "properties": {
    "gn:admin1_code":"11.0",
    "gn:asciiname":"Kabuga",
    "gn:country_code":"BI",
    "gn:dem":1455,
    "gn:feature_class":"P",
    "gn:feature_code":"PPLL",
    "gn:name":"Kabuga",
    "gn:population":0,
    "gn:timezone":"Africa/Bujumbura",
    "iso:country":"BI",
    "name:cat_x_preferred":[
        "Kabuga"
    ],
    "name:fra_x_preferred":[
        "Kabuga"
    ],
    "name:pol_x_preferred":[
        "Kabuga"
    ],
    "wof:name":"Kabuga",
    "wof:placetype":"locality"
},
  "geometry": {"coordinates":[30.677,-2.9994],"type":"Point"}
}