{
  "type": "Feature",
  "properties": {
    "gn:admin1_code":"18.0",
    "gn:asciiname":"Gaseme",
    "gn:country_code":"BI",
    "gn:dem":1483,
    "gn:feature_class":"P",
    "gn:feature_code":"PPLL",
    "gn:name":"Gaseme",
    "gn:population":0,
    "gn:timezone":"Africa/Bujumbura",
    "iso:country":"BI",
    "wof:name":"Gaseme",
    "wof:placetype":"locality"
},
  "geometry": {"coordinates":[30.3545,-2.8683],"type":"Point"}
}