{
  "type": "Feature",
  "properties": {
    "gn:admin1_code":"12.0",
    "gn:asciiname":"Muremera",
    "gn:country_code":"BI",
    "gn:dem":1957,
    "gn:feature_class":"P",
    "gn:feature_code":"PPLL",
    "gn:name":"Muremera",
    "gn:population":0,
    "gn:timezone":"Africa/Bujumbura",
    "iso:country":"BI",
    "wof:name":"Muremera",
    "wof:placetype":"locality"
},
  "geometry": {"coordinates":[29.2018,-2.6402],"type":"Point"}
}