{
  "type": "Feature",
  "properties": {
    "gn:admin1_code":"19.0",
    "gn:asciiname":"Kadimbagu",
    "gn:country_code":"BI",
    "gn:dem":1625,
    "gn:feature_class":"P",
    "gn:feature_code":"PPLL",
    "gn:name":"Kadimbagu",
    "gn:population":0,
    "gn:timezone":"Africa/Bujumbura",
    "iso:country":"BI",
    "wof:name":"Kadimbagu",
    "wof:placetype":"locality"
},
  "geometry": {"coordinates":[30.0774,-2.8555],"type":"Point"}
}