{
  "type": "Feature",
  "properties": {
    "gn:admin1_code":"21",
    "gn:asciiname":"Munterana",
    "gn:country_code":"BI",
    "gn:dem":1653,
    "gn:feature_class":"P",
    "gn:feature_code":"PPL",
    "gn:name":"Munterana",
    "gn:population":0,
    "gn:timezone":"Africa/Bujumbura",
    "iso:country":"BI",
    "wof:name":"Munterana",
    "wof:placetype":"locality"
},
  "geometry": {"coordinates":[30.456,-3.32807],"type":"Point"}
}