{
  "type": "Feature",
  "properties": {
    "gn:admin1_code":"16.0",
    "gn:asciiname":"Santunda",
    "gn:country_code":"BI",
    "gn:dem":1427,
    "gn:feature_class":"P",
    "gn:feature_code":"PPLL",
    "gn:name":"Santunda",
    "gn:population":0,
    "gn:timezone":"Africa/Bujumbura",
    "iso:country":"BI",
    "wof:name":"Santunda",
    "wof:placetype":"locality"
},
  "geometry": {"coordinates":[30.2956,-2.5979],"type":"Point"}
}