{
  "type": "Feature",
  "properties": {
    "gn:admin1_code":"14.0",
    "gn:asciiname":"Mwishorero",
    "gn:country_code":"BI",
    "gn:dem":1494,
    "gn:feature_class":"P",
    "gn:feature_code":"PPLL",
    "gn:name":"Mwishorero",
    "gn:population":0,
    "gn:timezone":"Africa/Bujumbura",
    "iso:country":"BI",
    "wof:name":"Mwishorero",
    "wof:placetype":"locality"
},
  "geometry": {"coordinates":[30.2894,-3.1641],"type":"Point"}
}