{
  "type": "Feature",
  "properties": {
    "gn:admin1_code":"20",
    "gn:asciiname":"Jenda",
    "gn:country_code":"BI",
    "gn:dem":1762,
    "gn:feature_class":"P",
    "gn:feature_code":"PPLL",
    "gn:name":"Jenda",
    "gn:population":0,
    "gn:timezone":"Africa/Bujumbura",
    "iso:country":"BI",
    "name:und_x_variant":[
        "Yenda",
        "Jenda"
    ],
    "wof:name":"Jenda",
    "wof:placetype":"locality"
},
  "geometry": {"coordinates":[30.1072,-3.7137],"type":"Point"}
}