{
  "type": "Feature",
  "properties": {
    "gn:admin1_code":"20",
    "gn:asciiname":"Busango",
    "gn:country_code":"BI",
    "gn:dem":1397,
    "gn:feature_class":"P",
    "gn:feature_code":"PPLL",
    "gn:name":"Busango",
    "gn:population":0,
    "gn:timezone":"Africa/Bujumbura",
    "iso:country":"BI",
    "wof:name":"Busango",
    "wof:placetype":"locality"
},
  "geometry": {"coordinates":[29.9618,-4.0786],"type":"Point"}
}