{
  "type": "Feature",
  "properties": {
    "gn:admin1_code":"18.0",
    "gn:asciiname":"Kinazi",
    "gn:country_code":"BI",
    "gn:dem":1560,
    "gn:feature_class":"P",
    "gn:feature_code":"PPL",
    "gn:name":"Kinazi",
    "gn:population":0,
    "gn:timezone":"Africa/Bujumbura",
    "iso:country":"BI",
    "wof:name":"Kinazi",
    "wof:placetype":"locality"
},
  "geometry": {"coordinates":[30.404,-2.703],"type":"Point"}
}