{
  "type": "Feature",
  "properties": {
    "gn:admin1_code":"14.0",
    "gn:asciiname":"Muramba",
    "gn:country_code":"BI",
    "gn:dem":1633,
    "gn:feature_class":"P",
    "gn:feature_code":"PPL",
    "gn:name":"Muramba",
    "gn:population":0,
    "gn:timezone":"Africa/Bujumbura",
    "iso:country":"BI",
    "wof:name":"Muramba",
    "wof:placetype":"locality"
},
  "geometry": {"coordinates":[30.0909,-3.091],"type":"Point"}
}