{
  "type": "Feature",
  "properties": {
    "gn:admin1_code":"13",
    "gn:asciiname":"Gashingwe",
    "gn:country_code":"BI",
    "gn:dem":1712,
    "gn:feature_class":"P",
    "gn:feature_code":"PPLL",
    "gn:name":"Gashingwe",
    "gn:population":0,
    "gn:timezone":"Africa/Bujumbura",
    "iso:country":"BI",
    "wof:name":"Gashingwe",
    "wof:placetype":"locality"
},
  "geometry": {"coordinates":[30.0639,-3.6597],"type":"Point"}
}