{
  "type": "Feature",
  "properties": {
    "gn:admin1_code":"15.0",
    "gn:asciiname":"Taba",
    "gn:country_code":"BI",
    "gn:dem":1629,
    "gn:feature_class":"P",
    "gn:feature_code":"PPLL",
    "gn:name":"Taba",
    "gn:population":0,
    "gn:timezone":"Africa/Bujumbura",
    "iso:country":"BI",
    "name:ceb_x_preferred":[
        "Taba"
    ],
    "name:deu_x_preferred":[
        "Taba"
    ],
    "name:fra_x_preferred":[
        "Taba"
    ],
    "name:nld_x_preferred":[
        "Taba"
    ],
    "name:spa_x_preferred":[
        "Taba"
    ],
    "name:swe_x_preferred":[
        "Taba"
    ],
    "wof:name":"Taba",
    "wof:placetype":"locality"
},
  "geometry": {"coordinates":[29.7545,-3.0316],"type":"Point"}
}