{
  "type": "Feature",
  "properties": {
    "gn:admin1_code":"12.0",
    "gn:asciiname":"Bwegera",
    "gn:country_code":"BI",
    "gn:dem":1064,
    "gn:feature_class":"P",
    "gn:feature_code":"PPLL",
    "gn:name":"Bwegera",
    "gn:population":0,
    "gn:timezone":"Africa/Bujumbura",
    "iso:country":"BI",
    "wof:name":"Bwegera",
    "wof:placetype":"locality"
},
  "geometry": {"coordinates":[29.2553,-2.9552],"type":"Point"}
}