{
  "type": "Feature",
  "properties": {
    "gn:admin1_code":"19.0",
    "gn:asciiname":"Gatare",
    "gn:country_code":"BI",
    "gn:dem":1603,
    "gn:feature_class":"P",
    "gn:feature_code":"PPLL",
    "gn:name":"Gatare",
    "gn:population":0,
    "gn:timezone":"Africa/Bujumbura",
    "iso:country":"BI",
    "wof:name":"Gatare",
    "wof:placetype":"locality"
},
  "geometry": {"coordinates":[29.9071,-2.9349],"type":"Point"}
}