{
  "type": "Feature",
  "properties": {
    "gn:admin1_code":"23",
    "gn:asciiname":"Gitara",
    "gn:country_code":"BI",
    "gn:dem":2127,
    "gn:feature_class":"P",
    "gn:feature_code":"PPL",
    "gn:name":"Gitara",
    "gn:population":0,
    "gn:timezone":"Africa/Bujumbura",
    "iso:country":"BI",
    "wof:name":"Gitara",
    "wof:placetype":"locality"
},
  "geometry": {"coordinates":[29.6455,-3.5628],"type":"Point"}
}