{
  "type": "Feature",
  "properties": {
    "gn:admin1_code":"26",
    "gn:asciiname":"Midodo",
    "gn:country_code":"BI",
    "gn:dem":1598,
    "gn:feature_class":"P",
    "gn:feature_code":"PPLL",
    "gn:name":"Midodo",
    "gn:population":0,
    "gn:timezone":"Africa/Bujumbura",
    "iso:country":"BI",
    "wof:name":"Midodo",
    "wof:placetype":"locality"
},
  "geometry": {"coordinates":[29.3991,-3.727],"type":"Point"}
}