{
  "type": "Feature",
  "properties": {
    "gn:admin1_code":"18.0",
    "gn:asciiname":"Mugongora",
    "gn:country_code":"BI",
    "gn:dem":1708,
    "gn:feature_class":"P",
    "gn:feature_code":"PPLL",
    "gn:name":"Mugongora",
    "gn:population":0,
    "gn:timezone":"Africa/Bujumbura",
    "iso:country":"BI",
    "wof:name":"Mugongora",
    "wof:placetype":"locality"
},
  "geometry": {"coordinates":[30.2872,-2.8285],"type":"Point"}
}