{
  "type": "Feature",
  "properties": {
    "gn:admin1_code":"19.0",
    "gn:asciiname":"Mumigende",
    "gn:country_code":"BI",
    "gn:dem":1566,
    "gn:feature_class":"P",
    "gn:feature_code":"PPLL",
    "gn:name":"Mumigende",
    "gn:population":0,
    "gn:timezone":"Africa/Bujumbura",
    "iso:country":"BI",
    "wof:name":"Mumigende",
    "wof:placetype":"locality"
},
  "geometry": {"coordinates":[30.0204,-2.9779],"type":"Point"}
}