{
  "type": "Feature",
  "properties": {
    "gn:admin1_code":"20",
    "gn:asciiname":"Rumina",
    "gn:country_code":"BI",
    "gn:dem":1726,
    "gn:feature_class":"P",
    "gn:feature_code":"PPLL",
    "gn:name":"Rumina",
    "gn:population":0,
    "gn:timezone":"Africa/Bujumbura",
    "iso:country":"BI",
    "wof:name":"Rumina",
    "wof:placetype":"locality"
},
  "geometry": {"coordinates":[29.8693,-3.9978],"type":"Point"}
}