{
  "type": "Feature",
  "properties": {
    "gn:admin1_code":"23",
    "gn:asciiname":"Magoro",
    "gn:country_code":"BI",
    "gn:dem":1974,
    "gn:feature_class":"P",
    "gn:feature_code":"PPLL",
    "gn:name":"Magoro",
    "gn:population":0,
    "gn:timezone":"Africa/Bujumbura",
    "iso:country":"BI",
    "wof:name":"Magoro",
    "wof:placetype":"locality"
},
  "geometry": {"coordinates":[29.645,-3.455],"type":"Point"}
}