{
  "type": "Feature",
  "properties": {
    "gn:admin1_code":"14.0",
    "gn:asciiname":"Butangaza",
    "gn:country_code":"BI",
    "gn:dem":1732,
    "gn:feature_class":"P",
    "gn:feature_code":"PPL",
    "gn:name":"Butangaza",
    "gn:population":0,
    "gn:timezone":"Africa/Bujumbura",
    "iso:country":"BI",
    "wof:name":"Butangaza",
    "wof:placetype":"locality"
},
  "geometry": {"coordinates":[30.07467,-3.02566],"type":"Point"}
}