{
  "type": "Feature",
  "properties": {
    "gn:admin1_code":"13",
    "gn:asciiname":"Mwamira",
    "gn:country_code":"BI",
    "gn:dem":1685,
    "gn:feature_class":"P",
    "gn:feature_code":"PPLL",
    "gn:name":"Mwamira",
    "gn:population":0,
    "gn:timezone":"Africa/Bujumbura",
    "iso:country":"BI",
    "wof:name":"Mwamira",
    "wof:placetype":"locality"
},
  "geometry": {"coordinates":[29.8488,-3.5421],"type":"Point"}
}