{
  "type": "Feature",
  "properties": {
    "gn:admin1_code":"11",
    "gn:asciiname":"Nyamugari",
    "gn:country_code":"BI",
    "gn:dem":1604,
    "gn:feature_class":"P",
    "gn:feature_code":"PPLL",
    "gn:name":"Nyamugari",
    "gn:population":0,
    "gn:timezone":"Africa/Bujumbura",
    "iso:country":"BI",
    "wof:name":"Nyamugari",
    "wof:placetype":"locality"
},
  "geometry": {"coordinates":[30.6219,-3.1694],"type":"Point"}
}