{
  "type": "Feature",
  "properties": {
    "gn:admin1_code":"15.0",
    "gn:asciiname":"Gahororo",
    "gn:country_code":"BI",
    "gn:dem":1696,
    "gn:feature_class":"P",
    "gn:feature_code":"PPLL",
    "gn:name":"Gahororo",
    "gn:population":0,
    "gn:timezone":"Africa/Bujumbura",
    "iso:country":"BI",
    "wof:name":"Gahororo",
    "wof:placetype":"locality"
},
  "geometry": {"coordinates":[29.7244,-3.026],"type":"Point"}
}