{
  "type": "Feature",
  "properties": {
    "gn:admin1_code":"14.0",
    "gn:asciiname":"Kidahwe",
    "gn:country_code":"BI",
    "gn:dem":1662,
    "gn:feature_class":"P",
    "gn:feature_code":"PPL",
    "gn:name":"Kidahwe",
    "gn:population":0,
    "gn:timezone":"Africa/Bujumbura",
    "iso:country":"BI",
    "wof:name":"Kidahwe",
    "wof:placetype":"locality"
},
  "geometry": {"coordinates":[30.00771,-3.01432],"type":"Point"}
}