{
  "type": "Feature",
  "properties": {
    "gn:admin1_code":"20",
    "gn:asciiname":"Butanya",
    "gn:country_code":"BI",
    "gn:dem":1585,
    "gn:feature_class":"P",
    "gn:feature_code":"PPLL",
    "gn:name":"Butanya",
    "gn:population":0,
    "gn:timezone":"Africa/Bujumbura",
    "iso:country":"BI",
    "wof:name":"Butanya",
    "wof:placetype":"locality"
},
  "geometry": {"coordinates":[30.1338,-3.7587],"type":"Point"}
}