{
  "type": "Feature",
  "properties": {
    "gn:admin1_code":"13",
    "gn:asciiname":"Nyamutobo",
    "gn:country_code":"BI",
    "gn:dem":1725,
    "gn:feature_class":"P",
    "gn:feature_code":"PPLL",
    "gn:name":"Nyamutobo",
    "gn:population":0,
    "gn:timezone":"Africa/Bujumbura",
    "iso:country":"BI",
    "wof:name":"Nyamutobo",
    "wof:placetype":"locality"
},
  "geometry": {"coordinates":[29.8865,-3.549],"type":"Point"}
}