{
  "type": "Feature",
  "properties": {
    "gn:admin1_code":"20",
    "gn:asciiname":"Kinwa",
    "gn:country_code":"BI",
    "gn:dem":1653,
    "gn:feature_class":"P",
    "gn:feature_code":"PPLL",
    "gn:name":"Kinwa",
    "gn:population":0,
    "gn:timezone":"Africa/Bujumbura",
    "iso:country":"BI",
    "wof:name":"Kinwa",
    "wof:placetype":"locality"
},
  "geometry": {"coordinates":[30.1812,-3.6856],"type":"Point"}
}