{
  "type": "Feature",
  "properties": {
    "gn:admin1_code":"17",
    "gn:asciiname":"Rabiro",
    "gn:country_code":"BI",
    "gn:dem":1854,
    "gn:feature_class":"P",
    "gn:feature_code":"PPLL",
    "gn:name":"Rabiro",
    "gn:population":0,
    "gn:timezone":"Africa/Bujumbura",
    "iso:country":"BI",
    "wof:name":"Rabiro",
    "wof:placetype":"locality"
},
  "geometry": {"coordinates":[29.702,-4.1819],"type":"Point"}
}