{
  "type": "Feature",
  "properties": {
    "gn:admin1_code":"12.0",
    "gn:asciiname":"Kibaya",
    "gn:country_code":"BI",
    "gn:dem":1531,
    "gn:feature_class":"P",
    "gn:feature_code":"PPLL",
    "gn:name":"Kibaya",
    "gn:population":0,
    "gn:timezone":"Africa/Bujumbura",
    "iso:country":"BI",
    "name:ron_x_preferred":[
        "Kibaya"
    ],
    "wof:name":"Kibaya",
    "wof:placetype":"locality"
},
  "geometry": {"coordinates":[29.3712,-2.9061],"type":"Point"}
}