{
  "type": "Feature",
  "properties": {
    "gn:admin1_code":"10",
    "gn:asciiname":"Uwurugo",
    "gn:country_code":"BI",
    "gn:dem":2308,
    "gn:feature_class":"P",
    "gn:feature_code":"PPLL",
    "gn:name":"Uwurugo",
    "gn:population":0,
    "gn:timezone":"Africa/Bujumbura",
    "iso:country":"BI",
    "wof:name":"Uwurugo",
    "wof:placetype":"locality"
},
  "geometry": {"coordinates":[29.5599,-3.6059],"type":"Point"}
}