{
  "type": "Feature",
  "properties": {
    "gn:admin1_code":"13",
    "gn:asciiname":"Gasaraga",
    "gn:country_code":"BI",
    "gn:dem":1766,
    "gn:feature_class":"P",
    "gn:feature_code":"PPLL",
    "gn:name":"Gasaraga",
    "gn:population":0,
    "gn:timezone":"Africa/Bujumbura",
    "iso:country":"BI",
    "wof:name":"Gasaraga",
    "wof:placetype":"locality"
},
  "geometry": {"coordinates":[29.8695,-3.5578],"type":"Point"}
}