{
  "type": "Feature",
  "properties": {
    "gn:admin1_code":"17",
    "gn:asciiname":"Kinyiganyiga",
    "gn:country_code":"BI",
    "gn:dem":1277,
    "gn:feature_class":"P",
    "gn:feature_code":"PPLL",
    "gn:name":"Kinyiganyiga",
    "gn:population":0,
    "gn:timezone":"Africa/Bujumbura",
    "iso:country":"BI",
    "wof:name":"Kinyiganyiga",
    "wof:placetype":"locality"
},
  "geometry": {"coordinates":[30.0874,-4.1003],"type":"Point"}
}