{
  "type": "Feature",
  "properties": {
    "gn:admin1_code":"21",
    "gn:asciiname":"Gikongo",
    "gn:country_code":"BI",
    "gn:dem":1673,
    "gn:feature_class":"P",
    "gn:feature_code":"PPL",
    "gn:name":"Gikongo",
    "gn:population":0,
    "gn:timezone":"Africa/Bujumbura",
    "iso:country":"BI",
    "wof:name":"Gikongo",
    "wof:placetype":"locality"
},
  "geometry": {"coordinates":[30.44526,-3.27021],"type":"Point"}
}