{
  "type": "Feature",
  "properties": {
    "gn:admin1_code":"9.0",
    "gn:asciiname":"Rugazi",
    "gn:country_code":"BI",
    "gn:dem":1262,
    "gn:feature_class":"P",
    "gn:feature_code":"PPLL",
    "gn:name":"Rugazi",
    "gn:population":0,
    "gn:timezone":"Africa/Bujumbura",
    "iso:country":"BI",
    "wof:name":"Rugazi",
    "wof:placetype":"locality"
},
  "geometry": {"coordinates":[29.4605,-3.2469],"type":"Point"}
}