{
  "type": "Feature",
  "properties": {
    "gn:admin1_code":"13",
    "gn:asciiname":"Sesero",
    "gn:country_code":"BI",
    "gn:dem":1690,
    "gn:feature_class":"P",
    "gn:feature_code":"PPLL",
    "gn:name":"Sesero",
    "gn:population":0,
    "gn:timezone":"Africa/Bujumbura",
    "iso:country":"BI",
    "wof:name":"Sesero",
    "wof:placetype":"locality"
},
  "geometry": {"coordinates":[30.0492,-3.5606],"type":"Point"}
}