{
  "type": "Feature",
  "properties": {
    "gn:admin1_code":"13",
    "gn:asciiname":"Rwaza",
    "gn:country_code":"BI",
    "gn:dem":1707,
    "gn:feature_class":"P",
    "gn:feature_code":"PPLL",
    "gn:name":"Rwaza",
    "gn:population":0,
    "gn:timezone":"Africa/Bujumbura",
    "iso:country":"BI",
    "wof:name":"Rwaza",
    "wof:placetype":"locality"
},
  "geometry": {"coordinates":[30.0509,-3.5967],"type":"Point"}
}