{
  "type": "Feature",
  "properties": {
    "gn:admin1_code":"14.0",
    "gn:asciiname":"Mariza",
    "gn:country_code":"BI",
    "gn:dem":1554,
    "gn:feature_class":"P",
    "gn:feature_code":"PPL",
    "gn:name":"Mariza",
    "gn:population":0,
    "gn:timezone":"Africa/Bujumbura",
    "iso:country":"BI",
    "wof:name":"Mariza",
    "wof:placetype":"locality"
},
  "geometry": {"coordinates":[30.12994,-3.02606],"type":"Point"}
}