{
  "type": "Feature",
  "properties": {
    "gn:admin1_code":"14.0",
    "gn:asciiname":"Mariza",
    "gn:country_code":"BI",
    "gn:dem":1554,
    "gn:feature_class":"P",
    "gn:feature_code":"PPL",
    "gn:name":"Mariza",
    "gn:population":0,
    "gn:timezone":"Africa/Bujumbura",
    "iso:country":"BI",
    "name:ast_x_preferred":[
        "Mariza"
    ],
    "name:azb_x_preferred":[
        "\u0645\u0627\u0631\u06cc\u0632\u0627"
    ],
    "name:bre_x_preferred":[
        "Mariza"
    ],
    "name:bul_x_preferred":[
        "\u041c\u0430\u0440\u0438\u0437\u0430"
    ],
    "name:cat_x_preferred":[
        "Mariza"
    ],
    "name:ces_x_preferred":[
        "Mariza"
    ],
    "name:deu_x_preferred":[
        "Mariza"
    ],
    "name:epo_x_preferred":[
        "Mariza"
    ],
    "name:eus_x_preferred":[
        "Mariza"
    ],
    "name:fas_x_preferred":[
        "\u0645\u0627\u0631\u06cc\u0632\u0627"
    ],
    "name:fin_x_preferred":[
        "Mariza"
    ],
    "name:fra_x_preferred":[
        "Mariza"
    ],
    "name:glg_x_preferred":[
        "Mariza"
    ],
    "name:hun_x_preferred":[
        "Mariza"
    ],
    "name:hye_x_preferred":[
        "\u0544\u0561\u0580\u056b\u0566\u0561"
    ],
    "name:ita_x_preferred":[
        "Mariza"
    ],
    "name:kor_x_preferred":[
        "\ub9c8\ub9ac\uc790"
    ],
    "name:nld_x_preferred":[
        "Mariza"
    ],
    "name:oci_x_preferred":[
        "Mariza"
    ],
    "name:pol_x_preferred":[
        "Mariza"
    ],
    "name:por_x_preferred":[
        "Mariza"
    ],
    "name:ron_x_preferred":[
        "Mariza"
    ],
    "name:rus_x_preferred":[
        "\u041c\u0430\u0440\u0438\u0437\u0430"
    ],
    "name:scn_x_preferred":[
        "Mariza"
    ],
    "name:sco_x_preferred":[
        "Mariza"
    ],
    "name:spa_x_preferred":[
        "Mariza"
    ],
    "name:srd_x_preferred":[
        "Mariza"
    ],
    "name:srp_x_preferred":[
        "\u041c\u0430\u0440\u0438\u0437\u0430"
    ],
    "name:swe_x_preferred":[
        "Mariza"
    ],
    "name:ukr_x_preferred":[
        "\u041c\u0430\u0440\u0456\u0437\u0430"
    ],
    "name:vie_x_preferred":[
        "Mariza"
    ],
    "name:vol_x_preferred":[
        "Mariza"
    ],
    "name:war_x_preferred":[
        "Mariza"
    ],
    "wof:name":"Mariza",
    "wof:placetype":"locality"
},
  "geometry": {"coordinates":[30.12994,-3.02606],"type":"Point"}
}