{
  "type": "Feature",
  "properties": {
    "gn:admin1_code":"18.0",
    "gn:asciiname":"Rusagara",
    "gn:country_code":"BI",
    "gn:dem":1501,
    "gn:feature_class":"P",
    "gn:feature_code":"PPLL",
    "gn:name":"Rusagara",
    "gn:population":0,
    "gn:timezone":"Africa/Bujumbura",
    "iso:country":"BI",
    "wof:name":"Rusagara",
    "wof:placetype":"locality"
},
  "geometry": {"coordinates":[30.4228,-2.6936],"type":"Point"}
}