{
  "type": "Feature",
  "properties": {
    "gn:admin1_code":"12.0",
    "gn:asciiname":"Rwiri",
    "gn:country_code":"BI",
    "gn:dem":1334,
    "gn:feature_class":"P",
    "gn:feature_code":"PPLL",
    "gn:name":"Rwiri",
    "gn:population":0,
    "gn:timezone":"Africa/Bujumbura",
    "iso:country":"BI",
    "wof:name":"Rwiri",
    "wof:placetype":"locality"
},
  "geometry": {"coordinates":[29.2885,-2.9344],"type":"Point"}
}