{
  "type": "Feature",
  "properties": {
    "gn:admin1_code":"26",
    "gn:asciiname":"Kinama",
    "gn:country_code":"BI",
    "gn:dem":1895,
    "gn:feature_class":"P",
    "gn:feature_code":"PPL",
    "gn:name":"Kinama",
    "gn:population":0,
    "gn:timezone":"Africa/Bujumbura",
    "iso:country":"BI",
    "wof:name":"Kinama",
    "wof:placetype":"locality"
},
  "geometry": {"coordinates":[29.4066,-3.6441],"type":"Point"}
}