{
  "type": "Feature",
  "properties": {
    "gn:admin1_code":"13",
    "gn:asciiname":"Kayenzi",
    "gn:country_code":"BI",
    "gn:dem":1848,
    "gn:feature_class":"P",
    "gn:feature_code":"PPLL",
    "gn:name":"Kayenzi",
    "gn:population":0,
    "gn:timezone":"Africa/Bujumbura",
    "iso:country":"BI",
    "wof:name":"Kayenzi",
    "wof:placetype":"locality"
},
  "geometry": {"coordinates":[29.9529,-3.7435],"type":"Point"}
}