{
  "type": "Feature",
  "properties": {
    "gn:admin1_code":"10",
    "gn:asciiname":"Sakinyonga",
    "gn:country_code":"BI",
    "gn:dem":1909,
    "gn:feature_class":"P",
    "gn:feature_code":"PPLL",
    "gn:name":"Sakinyonga",
    "gn:population":0,
    "gn:timezone":"Africa/Bujumbura",
    "iso:country":"BI",
    "wof:name":"Sakinyonga",
    "wof:placetype":"locality"
},
  "geometry": {"coordinates":[29.7592,-3.7072],"type":"Point"}
}