{
  "type": "Feature",
  "properties": {
    "gn:admin1_code":"9.0",
    "gn:asciiname":"Murira",
    "gn:country_code":"BI",
    "gn:dem":1351,
    "gn:feature_class":"P",
    "gn:feature_code":"PPL",
    "gn:name":"Murira",
    "gn:population":0,
    "gn:timezone":"Africa/Bujumbura",
    "iso:country":"BI",
    "wof:name":"Murira",
    "wof:placetype":"locality"
},
  "geometry": {"coordinates":[29.3949,-3.0224],"type":"Point"}
}