{
  "type": "Feature",
  "properties": {
    "gn:admin1_code":"14.0",
    "gn:asciiname":"Bukanya",
    "gn:country_code":"BI",
    "gn:dem":1672,
    "gn:feature_class":"P",
    "gn:feature_code":"PPL",
    "gn:name":"Bukanya",
    "gn:population":0,
    "gn:timezone":"Africa/Bujumbura",
    "iso:country":"BI",
    "wof:name":"Bukanya",
    "wof:placetype":"locality"
},
  "geometry": {"coordinates":[30.20303,-3.13862],"type":"Point"}
}