{
  "type": "Feature",
  "properties": {
    "gn:admin1_code":"20",
    "gn:asciiname":"Mugarama",
    "gn:country_code":"BI",
    "gn:dem":1624,
    "gn:feature_class":"P",
    "gn:feature_code":"PPLL",
    "gn:name":"Mugarama",
    "gn:population":0,
    "gn:timezone":"Africa/Bujumbura",
    "iso:country":"BI",
    "wof:name":"Mugarama",
    "wof:placetype":"locality"
},
  "geometry": {"coordinates":[30.0306,-3.8531],"type":"Point"}
}