{
  "type": "Feature",
  "properties": {
    "gn:admin1_code":"21",
    "gn:asciiname":"Kumubuga",
    "gn:country_code":"BI",
    "gn:dem":1247,
    "gn:feature_class":"P",
    "gn:feature_code":"PPLL",
    "gn:name":"Kumubuga",
    "gn:population":0,
    "gn:timezone":"Africa/Bujumbura",
    "iso:country":"BI",
    "wof:name":"Kumubuga",
    "wof:placetype":"locality"
},
  "geometry": {"coordinates":[30.3462,-3.5474],"type":"Point"}
}