{
  "type": "Feature",
  "properties": {
    "gn:admin1_code":"21.0",
    "gn:asciiname":"Nyambaragasa",
    "gn:country_code":"BI",
    "gn:dem":1802,
    "gn:feature_class":"P",
    "gn:feature_code":"PPL",
    "gn:name":"Nyambaragasa",
    "gn:population":0,
    "gn:timezone":"Africa/Bujumbura",
    "iso:country":"BI",
    "wof:name":"Nyambaragasa",
    "wof:placetype":"locality"
},
  "geometry": {"coordinates":[30.42844,-3.29599],"type":"Point"}
}