{
  "type": "Feature",
  "properties": {
    "gn:admin1_code":"23",
    "gn:asciiname":"Gahahe",
    "gn:country_code":"BI",
    "gn:dem":1607,
    "gn:feature_class":"P",
    "gn:feature_code":"PPLL",
    "gn:name":"Gahahe",
    "gn:population":0,
    "gn:timezone":"Africa/Bujumbura",
    "iso:country":"BI",
    "wof:name":"Gahahe",
    "wof:placetype":"locality"
},
  "geometry": {"coordinates":[29.8238,-3.3309],"type":"Point"}
}