{
  "type": "Feature",
  "properties": {
    "gn:admin1_code":"20",
    "gn:asciiname":"Gitara",
    "gn:country_code":"BI",
    "gn:dem":1188,
    "gn:feature_class":"P",
    "gn:feature_code":"PPLL",
    "gn:name":"Gitara",
    "gn:population":0,
    "gn:timezone":"Africa/Bujumbura",
    "iso:country":"BI",
    "wof:name":"Gitara",
    "wof:placetype":"locality"
},
  "geometry": {"coordinates":[30.2198,-3.9061],"type":"Point"}
}