{
  "type": "Feature",
  "properties": {
    "gn:admin1_code":"12.0",
    "gn:asciiname":"Nyarutovu",
    "gn:country_code":"BI",
    "gn:dem":1697,
    "gn:feature_class":"P",
    "gn:feature_code":"PPLL",
    "gn:name":"Nyarutovu",
    "gn:population":0,
    "gn:timezone":"Africa/Bujumbura",
    "iso:country":"BI",
    "wof:name":"Nyarutovu",
    "wof:placetype":"locality"
},
  "geometry": {"coordinates":[29.3201,-2.8592],"type":"Point"}
}