{
  "type": "Feature",
  "properties": {
    "gn:admin1_code":"19.0",
    "gn:asciiname":"Mirango",
    "gn:country_code":"BI",
    "gn:dem":1737,
    "gn:feature_class":"P",
    "gn:feature_code":"PPLL",
    "gn:name":"Mirango",
    "gn:population":0,
    "gn:timezone":"Africa/Bujumbura",
    "iso:country":"BI",
    "wof:name":"Mirango",
    "wof:placetype":"locality"
},
  "geometry": {"coordinates":[29.7651,-2.9422],"type":"Point"}
}