{
  "type": "Feature",
  "properties": {
    "gn:admin1_code":"23",
    "gn:asciiname":"Musama",
    "gn:country_code":"BI",
    "gn:dem":1767,
    "gn:feature_class":"P",
    "gn:feature_code":"PPLL",
    "gn:name":"Musama",
    "gn:population":0,
    "gn:timezone":"Africa/Bujumbura",
    "iso:country":"BI",
    "wof:name":"Musama",
    "wof:placetype":"locality"
},
  "geometry": {"coordinates":[29.7566,-3.5225],"type":"Point"}
}