{
  "type": "Feature",
  "properties": {
    "gn:admin1_code":"12.0",
    "gn:asciiname":"Nyarwumba",
    "gn:country_code":"BI",
    "gn:dem":2012,
    "gn:feature_class":"P",
    "gn:feature_code":"PPLL",
    "gn:name":"Nyarwumba",
    "gn:population":0,
    "gn:timezone":"Africa/Bujumbura",
    "iso:country":"BI",
    "name:und_x_variant":[
        "Nyarwmba",
        "Nyarwumba"
    ],
    "wof:name":"Nyarwumba",
    "wof:placetype":"locality"
},
  "geometry": {"coordinates":[29.437,-2.9238],"type":"Point"}
}