{
  "type": "Feature",
  "properties": {
    "gn:admin1_code":"21",
    "gn:asciiname":"Gacokwe",
    "gn:country_code":"BI",
    "gn:dem":1256,
    "gn:feature_class":"P",
    "gn:feature_code":"PPLL",
    "gn:name":"Gacokwe",
    "gn:population":0,
    "gn:timezone":"Africa/Bujumbura",
    "iso:country":"BI",
    "wof:name":"Gacokwe",
    "wof:placetype":"locality"
},
  "geometry": {"coordinates":[30.5726,-3.4173],"type":"Point"}
}