{
  "type": "Feature",
  "properties": {
    "gn:admin1_code":"26",
    "gn:asciiname":"Sebeyi",
    "gn:country_code":"BI",
    "gn:dem":1543,
    "gn:feature_class":"P",
    "gn:feature_code":"PPLL",
    "gn:name":"Sebeyi",
    "gn:population":0,
    "gn:timezone":"Africa/Bujumbura",
    "iso:country":"BI",
    "wof:name":"Sebeyi",
    "wof:placetype":"locality"
},
  "geometry": {"coordinates":[29.5205,-3.8593],"type":"Point"}
}