{
  "type": "Feature",
  "properties": {
    "gn:admin1_code":"14.0",
    "gn:asciiname":"Jogo",
    "gn:country_code":"BI",
    "gn:dem":1781,
    "gn:feature_class":"P",
    "gn:feature_code":"PPL",
    "gn:name":"Jogo",
    "gn:population":0,
    "gn:timezone":"Africa/Bujumbura",
    "iso:country":"BI",
    "wof:name":"Jogo",
    "wof:placetype":"locality"
},
  "geometry": {"coordinates":[30.1772,-3.2185],"type":"Point"}
}