{
  "type": "Feature",
  "properties": {
    "gn:admin1_code":"14.0",
    "gn:asciiname":"Gaharo",
    "gn:country_code":"BI",
    "gn:dem":1541,
    "gn:feature_class":"P",
    "gn:feature_code":"PPL",
    "gn:name":"Gaharo",
    "gn:population":0,
    "gn:timezone":"Africa/Bujumbura",
    "iso:country":"BI",
    "wof:name":"Gaharo",
    "wof:placetype":"locality"
},
  "geometry": {"coordinates":[30.09099,-3.22388],"type":"Point"}
}