{
  "type": "Feature",
  "properties": {
    "gn:admin1_code":"25",
    "gn:asciiname":"Maramvya",
    "gn:country_code":"BI",
    "gn:dem":800,
    "gn:feature_class":"P",
    "gn:feature_code":"PPLL",
    "gn:name":"Maramvya",
    "gn:population":0,
    "gn:timezone":"Africa/Bujumbura",
    "iso:country":"BI",
    "wof:name":"Maramvya",
    "wof:placetype":"locality"
},
  "geometry": {"coordinates":[29.3462,-3.2887],"type":"Point"}
}