{
  "type": "Feature",
  "properties": {
    "gn:admin1_code":"20",
    "gn:asciiname":"Mpomvu",
    "gn:country_code":"BI",
    "gn:dem":1682,
    "gn:feature_class":"P",
    "gn:feature_code":"PPLL",
    "gn:name":"Mpomvu",
    "gn:population":0,
    "gn:timezone":"Africa/Bujumbura",
    "iso:country":"BI",
    "wof:name":"Mpomvu",
    "wof:placetype":"locality"
},
  "geometry": {"coordinates":[29.9041,-3.992],"type":"Point"}
}