{
  "type": "Feature",
  "properties": {
    "gn:admin1_code":"9.0",
    "gn:asciiname":"Cabira",
    "gn:country_code":"BI",
    "gn:dem":991,
    "gn:feature_class":"P",
    "gn:feature_code":"PPLL",
    "gn:name":"Cabira",
    "gn:population":0,
    "gn:timezone":"Africa/Bujumbura",
    "iso:country":"BI",
    "name:run_x_preferred":[
        "Cabire"
    ],
    "name:und_x_variant":[
        "Cabire"
    ],
    "wof:name":"Cabira",
    "wof:placetype":"locality"
},
  "geometry": {"coordinates":[29.3511,-3.0859],"type":"Point"}
}