{
  "type": "Feature",
  "properties": {
    "gn:admin1_code":"16.0",
    "gn:asciiname":"Ruremba",
    "gn:country_code":"BI",
    "gn:dem":1510,
    "gn:feature_class":"P",
    "gn:feature_code":"PPLL",
    "gn:name":"Ruremba",
    "gn:population":0,
    "gn:timezone":"Africa/Bujumbura",
    "iso:country":"BI",
    "wof:name":"Ruremba",
    "wof:placetype":"locality"
},
  "geometry": {"coordinates":[30.3239,-2.5314],"type":"Point"}
}