{
  "type": "Feature",
  "properties": {
    "gn:admin1_code":"11",
    "gn:asciiname":"Musongati",
    "gn:country_code":"BI",
    "gn:dem":1611,
    "gn:feature_class":"P",
    "gn:feature_code":"PPLL",
    "gn:name":"Musongati",
    "gn:population":0,
    "gn:timezone":"Africa/Bujumbura",
    "iso:country":"BI",
    "name:run_x_preferred":[
        "Musongati"
    ],
    "wof:name":"Musongati",
    "wof:placetype":"locality"
},
  "geometry": {"coordinates":[30.5214,-3.2739],"type":"Point"}
}