{
  "type": "Feature",
  "properties": {
    "gn:admin1_code":"18.0",
    "gn:asciiname":"Bukanya",
    "gn:country_code":"BI",
    "gn:dem":1524,
    "gn:feature_class":"P",
    "gn:feature_code":"PPLL",
    "gn:name":"Bukanya",
    "gn:population":0,
    "gn:timezone":"Africa/Bujumbura",
    "iso:country":"BI",
    "wof:name":"Bukanya",
    "wof:placetype":"locality"
},
  "geometry": {"coordinates":[30.3386,-2.7964],"type":"Point"}
}