{
  "type": "Feature",
  "properties": {
    "gn:admin1_code":"26",
    "gn:asciiname":"Makaba",
    "gn:country_code":"BI",
    "gn:dem":2120,
    "gn:feature_class":"P",
    "gn:feature_code":"PPLL",
    "gn:name":"Makaba",
    "gn:population":0,
    "gn:timezone":"Africa/Bujumbura",
    "iso:country":"BI",
    "wof:name":"Makaba",
    "wof:placetype":"locality"
},
  "geometry": {"coordinates":[29.5867,-3.7707],"type":"Point"}
}