{
  "type": "Feature",
  "properties": {
    "gn:admin1_code":"23.0",
    "gn:asciiname":"Karenga",
    "gn:country_code":"BI",
    "gn:dem":1940,
    "gn:feature_class":"P",
    "gn:feature_code":"PPLL",
    "gn:name":"Karenga",
    "gn:population":0,
    "gn:timezone":"Africa/Bujumbura",
    "iso:country":"BI",
    "name:ceb_x_preferred":[
        "Karenga"
    ],
    "name:swe_x_preferred":[
        "Karenga"
    ],
    "wof:name":"Karenga",
    "wof:placetype":"locality"
},
  "geometry": {"coordinates":[29.785,-3.38],"type":"Point"}
}