{
  "type": "Feature",
  "properties": {
    "gn:admin1_code":"26",
    "gn:asciiname":"Kirama",
    "gn:country_code":"BI",
    "gn:dem":1051,
    "gn:feature_class":"P",
    "gn:feature_code":"PPLL",
    "gn:name":"Kirama",
    "gn:population":0,
    "gn:timezone":"Africa/Bujumbura",
    "iso:country":"BI",
    "wof:name":"Kirama",
    "wof:placetype":"locality"
},
  "geometry": {"coordinates":[29.4763,-3.9217],"type":"Point"}
}