{
  "type": "Feature",
  "properties": {
    "gn:admin1_code":"16.0",
    "gn:asciiname":"Nyabihanga",
    "gn:country_code":"BI",
    "gn:dem":1759,
    "gn:feature_class":"P",
    "gn:feature_code":"PPLL",
    "gn:name":"Nyabihanga",
    "gn:population":0,
    "gn:timezone":"Africa/Bujumbura",
    "iso:country":"BI",
    "wof:name":"Nyabihanga",
    "wof:placetype":"locality"
},
  "geometry": {"coordinates":[30.0454,-2.6691],"type":"Point"}
}