{
  "type": "Feature",
  "properties": {
    "gn:admin1_code":"9.0",
    "gn:asciiname":"Ngara",
    "gn:country_code":"BI",
    "gn:dem":1330,
    "gn:feature_class":"P",
    "gn:feature_code":"PPLL",
    "gn:name":"Ngara",
    "gn:population":0,
    "gn:timezone":"Africa/Bujumbura",
    "iso:country":"BI",
    "name:ceb_x_preferred":[
        "Ngara"
    ],
    "name:nor_x_preferred":[
        "Ngara"
    ],
    "name:ron_x_preferred":[
        "Ngara"
    ],
    "name:rus_x_preferred":[
        "\u041d\u0433\u0430\u0440\u0430"
    ],
    "name:tur_x_preferred":[
        "Ngara"
    ],
    "wof:name":"Ngara",
    "wof:placetype":"locality"
},
  "geometry": {"coordinates":[29.3703,-3.0239],"type":"Point"}
}