{
  "type": "Feature",
  "properties": {
    "gn:admin1_code":"23",
    "gn:asciiname":"Muhaganya",
    "gn:country_code":"BI",
    "gn:dem":1760,
    "gn:feature_class":"P",
    "gn:feature_code":"PPL",
    "gn:name":"Muhaganya",
    "gn:population":0,
    "gn:timezone":"Africa/Bujumbura",
    "iso:country":"BI",
    "wof:name":"Muhaganya",
    "wof:placetype":"locality"
},
  "geometry": {"coordinates":[29.77006,-3.45812],"type":"Point"}
}