{
  "type": "Feature",
  "properties": {
    "gn:admin1_code":"11",
    "gn:asciiname":"Nyakatsi",
    "gn:country_code":"BI",
    "gn:dem":1634,
    "gn:feature_class":"P",
    "gn:feature_code":"PPL",
    "gn:name":"Nyakatsi",
    "gn:population":0,
    "gn:timezone":"Africa/Bujumbura",
    "iso:country":"BI",
    "wof:name":"Nyakatsi",
    "wof:placetype":"locality"
},
  "geometry": {"coordinates":[30.63,-3.1556],"type":"Point"}
}