{
  "type": "Feature",
  "properties": {
    "gn:admin1_code":"18.0",
    "gn:asciiname":"Gasenyi",
    "gn:country_code":"BI",
    "gn:dem":1432,
    "gn:feature_class":"P",
    "gn:feature_code":"PPLL",
    "gn:name":"Gasenyi",
    "gn:population":0,
    "gn:timezone":"Africa/Bujumbura",
    "iso:country":"BI",
    "wof:name":"Gasenyi",
    "wof:placetype":"locality"
},
  "geometry": {"coordinates":[30.3982,-2.9015],"type":"Point"}
}