{
  "type": "Feature",
  "properties": {
    "gn:admin1_code":"15.0",
    "gn:asciiname":"Butanyerera",
    "gn:country_code":"BI",
    "gn:dem":1676,
    "gn:feature_class":"P",
    "gn:feature_code":"PPLL",
    "gn:name":"Butanyerera",
    "gn:population":0,
    "gn:timezone":"Africa/Bujumbura",
    "iso:country":"BI",
    "wof:name":"Butanyerera",
    "wof:placetype":"locality"
},
  "geometry": {"coordinates":[29.7114,-3.1417],"type":"Point"}
}