{
  "type": "Feature",
  "properties": {
    "gn:admin1_code":"17",
    "gn:asciiname":"Kange",
    "gn:country_code":"BI",
    "gn:dem":1499,
    "gn:feature_class":"P",
    "gn:feature_code":"PPLL",
    "gn:name":"Kange",
    "gn:population":0,
    "gn:timezone":"Africa/Bujumbura",
    "iso:country":"BI",
    "wof:name":"Kange",
    "wof:placetype":"locality"
},
  "geometry": {"coordinates":[29.9107,-4.1119],"type":"Point"}
}