{
  "type": "Feature",
  "properties": {
    "gn:admin1_code":"21",
    "gn:asciiname":"Masazi",
    "gn:country_code":"BI",
    "gn:dem":1663,
    "gn:feature_class":"P",
    "gn:feature_code":"PPLL",
    "gn:name":"Masazi",
    "gn:population":0,
    "gn:timezone":"Africa/Bujumbura",
    "iso:country":"BI",
    "wof:name":"Masazi",
    "wof:placetype":"locality"
},
  "geometry": {"coordinates":[30.1266,-3.5016],"type":"Point"}
}