{
  "type": "Feature",
  "properties": {
    "gn:admin1_code":"9.0",
    "gn:asciiname":"Ruziba",
    "gn:country_code":"BI",
    "gn:dem":1017,
    "gn:feature_class":"P",
    "gn:feature_code":"PPLL",
    "gn:name":"Ruziba",
    "gn:population":0,
    "gn:timezone":"Africa/Bujumbura",
    "iso:country":"BI",
    "wof:name":"Ruziba",
    "wof:placetype":"locality"
},
  "geometry": {"coordinates":[29.424,-3.1267],"type":"Point"}
}