{
  "type": "Feature",
  "properties": {
    "gn:admin1_code":"20",
    "gn:asciiname":"Nyabigura",
    "gn:country_code":"BI",
    "gn:dem":1224,
    "gn:feature_class":"P",
    "gn:feature_code":"PPLL",
    "gn:name":"Nyabigura",
    "gn:population":0,
    "gn:timezone":"Africa/Bujumbura",
    "iso:country":"BI",
    "wof:name":"Nyabigura",
    "wof:placetype":"locality"
},
  "geometry": {"coordinates":[30.2429,-3.6972],"type":"Point"}
}