{
  "type": "Feature",
  "properties": {
    "gn:admin1_code":"13",
    "gn:asciiname":"Gihovu",
    "gn:country_code":"BI",
    "gn:dem":1718,
    "gn:feature_class":"P",
    "gn:feature_code":"PPLL",
    "gn:name":"Gihovu",
    "gn:population":0,
    "gn:timezone":"Africa/Bujumbura",
    "iso:country":"BI",
    "wof:name":"Gihovu",
    "wof:placetype":"locality"
},
  "geometry": {"coordinates":[30.035,-3.6766],"type":"Point"}
}