{
  "type": "Feature",
  "properties": {
    "gn:admin1_code":"20",
    "gn:asciiname":"Nyabweru",
    "gn:country_code":"BI",
    "gn:dem":1247,
    "gn:feature_class":"P",
    "gn:feature_code":"PPLL",
    "gn:name":"Nyabweru",
    "gn:population":0,
    "gn:timezone":"Africa/Bujumbura",
    "iso:country":"BI",
    "wof:name":"Nyabweru",
    "wof:placetype":"locality"
},
  "geometry": {"coordinates":[30.3389,-3.7206],"type":"Point"}
}