{
  "type": "Feature",
  "properties": {
    "gn:admin1_code":"15.0",
    "gn:asciiname":"Karahura",
    "gn:country_code":"BI",
    "gn:dem":1799,
    "gn:feature_class":"P",
    "gn:feature_code":"PPLL",
    "gn:name":"Karahura",
    "gn:population":0,
    "gn:timezone":"Africa/Bujumbura",
    "iso:country":"BI",
    "wof:name":"Karahura",
    "wof:placetype":"locality"
},
  "geometry": {"coordinates":[29.6999,-2.9678],"type":"Point"}
}