{
  "type": "Feature",
  "properties": {
    "gn:admin1_code":"16.0",
    "gn:asciiname":"Kajego",
    "gn:country_code":"BI",
    "gn:dem":1329,
    "gn:feature_class":"P",
    "gn:feature_code":"PPLL",
    "gn:name":"Kajego",
    "gn:population":0,
    "gn:timezone":"Africa/Bujumbura",
    "iso:country":"BI",
    "wof:name":"Kajego",
    "wof:placetype":"locality"
},
  "geometry": {"coordinates":[30.3103,-2.4478],"type":"Point"}
}