{
  "type": "Feature",
  "properties": {
    "gn:admin1_code":"25",
    "gn:asciiname":"Kirasa",
    "gn:country_code":"BI",
    "gn:dem":1929,
    "gn:feature_class":"P",
    "gn:feature_code":"PPLL",
    "gn:name":"Kirasa",
    "gn:population":0,
    "gn:timezone":"Africa/Bujumbura",
    "iso:country":"BI",
    "wof:name":"Kirasa",
    "wof:placetype":"locality"
},
  "geometry": {"coordinates":[29.4272,-3.5819],"type":"Point"}
}