{
  "type": "Feature",
  "properties": {
    "gn:admin1_code":"16.0",
    "gn:asciiname":"Rambo",
    "gn:country_code":"BI",
    "gn:dem":1471,
    "gn:feature_class":"P",
    "gn:feature_code":"PPLL",
    "gn:name":"Rambo",
    "gn:population":0,
    "gn:timezone":"Africa/Bujumbura",
    "iso:country":"BI",
    "wof:name":"Rambo",
    "wof:placetype":"locality"
},
  "geometry": {"coordinates":[30.0648,-2.5933],"type":"Point"}
}