{
  "type": "Feature",
  "properties": {
    "gn:admin1_code":"11",
    "gn:asciiname":"Mwibuya",
    "gn:country_code":"BI",
    "gn:dem":1748,
    "gn:feature_class":"P",
    "gn:feature_code":"PPLL",
    "gn:name":"Mwibuya",
    "gn:population":0,
    "gn:timezone":"Africa/Bujumbura",
    "iso:country":"BI",
    "wof:name":"Mwibuya",
    "wof:placetype":"locality"
},
  "geometry": {"coordinates":[30.7545,-3.2075],"type":"Point"}
}