{
  "type": "Feature",
  "properties": {
    "gn:admin1_code":"18.0",
    "gn:asciiname":"Bukobe",
    "gn:country_code":"BI",
    "gn:dem":1615,
    "gn:feature_class":"P",
    "gn:feature_code":"PPLL",
    "gn:name":"Bukobe",
    "gn:population":0,
    "gn:timezone":"Africa/Bujumbura",
    "iso:country":"BI",
    "wof:name":"Bukobe",
    "wof:placetype":"locality"
},
  "geometry": {"coordinates":[30.4653,-2.4985],"type":"Point"}
}