{
  "type": "Feature",
  "properties": {
    "gn:admin1_code":"26",
    "gn:asciiname":"Muhanda",
    "gn:country_code":"BI",
    "gn:dem":1638,
    "gn:feature_class":"P",
    "gn:feature_code":"PPLL",
    "gn:name":"Muhanda",
    "gn:population":0,
    "gn:timezone":"Africa/Bujumbura",
    "iso:country":"BI",
    "wof:name":"Muhanda",
    "wof:placetype":"locality"
},
  "geometry": {"coordinates":[29.3789,-3.7072],"type":"Point"}
}