{
  "type": "Feature",
  "properties": {
    "gn:admin1_code":"19.0",
    "gn:asciiname":"Gitaro",
    "gn:country_code":"BI",
    "gn:dem":1523,
    "gn:feature_class":"P",
    "gn:feature_code":"PPLL",
    "gn:name":"Gitaro",
    "gn:population":0,
    "gn:timezone":"Africa/Bujumbura",
    "iso:country":"BI",
    "wof:name":"Gitaro",
    "wof:placetype":"locality"
},
  "geometry": {"coordinates":[29.9946,-2.8304],"type":"Point"}
}