{
  "type": "Feature",
  "properties": {
    "gn:admin1_code":"20",
    "gn:asciiname":"Kabanga",
    "gn:country_code":"BI",
    "gn:dem":1275,
    "gn:feature_class":"P",
    "gn:feature_code":"PPLL",
    "gn:name":"Kabanga",
    "gn:population":0,
    "gn:timezone":"Africa/Bujumbura",
    "iso:country":"BI",
    "name:ceb_x_preferred":[
        "Kabanga"
    ],
    "name:fra_x_preferred":[
        "Kabanga"
    ],
    "name:swe_x_preferred":[
        "Kabanga"
    ],
    "wof:name":"Kabanga",
    "wof:placetype":"locality"
},
  "geometry": {"coordinates":[30.08944,-4.02972],"type":"Point"}
}