{
  "type": "Feature",
  "properties": {
    "gn:admin1_code":"17",
    "gn:asciiname":"Kariba",
    "gn:country_code":"BI",
    "gn:dem":1637,
    "gn:feature_class":"P",
    "gn:feature_code":"PPL",
    "gn:name":"Kariba",
    "gn:population":0,
    "gn:timezone":"Africa/Bujumbura",
    "iso:country":"BI",
    "name:bar_x_preferred":[
        "Kariba"
    ],
    "name:ben_x_preferred":[
        "\u0995\u09be\u09b0\u09bf\u09ac\u09be"
    ],
    "name:ceb_x_preferred":[
        "Kariba"
    ],
    "name:ell_x_preferred":[
        "\u039a\u03b1\u03c1\u03af\u03bc\u03c0\u03b1"
    ],
    "name:eus_x_preferred":[
        "Kariba"
    ],
    "name:fas_x_preferred":[
        "\u06a9\u0627\u0631\u06cc\u0628\u0627"
    ],
    "name:hin_x_preferred":[
        "\u0915\u0930\u093f\u092c\u093e"
    ],
    "name:hun_x_preferred":[
        "Kariba"
    ],
    "name:ind_x_preferred":[
        "Kariba"
    ],
    "name:ita_x_preferred":[
        "Kariba"
    ],
    "name:nor_x_preferred":[
        "Kariba"
    ],
    "name:pol_x_preferred":[
        "Kariba"
    ],
    "name:rus_x_preferred":[
        "\u041a\u0430\u0440\u0438\u0431\u0430"
    ],
    "name:spa_x_preferred":[
        "Kariba"
    ],
    "name:swe_x_preferred":[
        "Kariba"
    ],
    "name:tur_x_preferred":[
        "Kariba"
    ],
    "name:vie_x_preferred":[
        "Kariba"
    ],
    "wof:name":"Kariba",
    "wof:placetype":"locality"
},
  "geometry": {"coordinates":[29.7806,-4.1133],"type":"Point"}
}