{
  "type": "Feature",
  "properties": {
    "gn:admin1_code":"17",
    "gn:asciiname":"Kariba",
    "gn:country_code":"BI",
    "gn:dem":1637,
    "gn:feature_class":"P",
    "gn:feature_code":"PPL",
    "gn:name":"Kariba",
    "gn:population":0,
    "gn:timezone":"Africa/Bujumbura",
    "iso:country":"BI",
    "name:bar_x_preferred":[
        "Kariba"
    ],
    "name:ceb_x_preferred":[
        "Kariba"
    ],
    "name:eus_x_preferred":[
        "Kariba"
    ],
    "name:ita_x_preferred":[
        "Kariba"
    ],
    "name:nor_x_preferred":[
        "Kariba"
    ],
    "name:pol_x_preferred":[
        "Kariba"
    ],
    "name:rus_x_preferred":[
        "\u041a\u0430\u0440\u0438\u0431\u0430"
    ],
    "name:swe_x_preferred":[
        "Kariba"
    ],
    "name:tur_x_preferred":[
        "Kariba"
    ],
    "wof:name":"Kariba",
    "wof:placetype":"locality"
},
  "geometry": {"coordinates":[29.7806,-4.1133],"type":"Point"}
}