{
  "type": "Feature",
  "properties": {
    "gn:admin1_code":"9.0",
    "gn:asciiname":"Rugunga",
    "gn:country_code":"BI",
    "gn:dem":1024,
    "gn:feature_class":"P",
    "gn:feature_code":"PPLL",
    "gn:name":"Rugunga",
    "gn:population":0,
    "gn:timezone":"Africa/Bujumbura",
    "iso:country":"BI",
    "name:und_x_variant":[
        "Rugunda"
    ],
    "wof:name":"Rugunga",
    "wof:placetype":"locality"
},
  "geometry": {"coordinates":[29.3492,-3.0678],"type":"Point"}
}