{
  "type": "Feature",
  "properties": {
    "gn:admin1_code":"12.0",
    "gn:asciiname":"Rwamisambo",
    "gn:country_code":"BI",
    "gn:dem":1847,
    "gn:feature_class":"P",
    "gn:feature_code":"PPLL",
    "gn:name":"Rwamisambo",
    "gn:population":0,
    "gn:timezone":"Africa/Bujumbura",
    "iso:country":"BI",
    "wof:name":"Rwamisambo",
    "wof:placetype":"locality"
},
  "geometry": {"coordinates":[29.2878,-2.7289],"type":"Point"}
}