{
  "type": "Feature",
  "properties": {
    "gn:admin1_code":"19.0",
    "gn:asciiname":"Bwiza-Bweranka",
    "gn:country_code":"BI",
    "gn:dem":1581,
    "gn:feature_class":"P",
    "gn:feature_code":"PPL",
    "gn:name":"Bwiza-Bweranka",
    "gn:population":0,
    "gn:timezone":"Africa/Bujumbura",
    "iso:country":"BI",
    "name:und_x_variant":[
        "Bwiza",
        "Bweranka"
    ],
    "wof:name":"Bwiza-Bweranka",
    "wof:placetype":"locality"
},
  "geometry": {"coordinates":[29.8848,-2.9496],"type":"Point"}
}