{
  "type": "Feature",
  "properties": {
    "gn:admin1_code":"14.0",
    "gn:asciiname":"Intamba",
    "gn:country_code":"BI",
    "gn:dem":1595,
    "gn:feature_class":"P",
    "gn:feature_code":"PPLL",
    "gn:name":"Intamba",
    "gn:population":0,
    "gn:timezone":"Africa/Bujumbura",
    "iso:country":"BI",
    "wof:name":"Intamba",
    "wof:placetype":"locality"
},
  "geometry": {"coordinates":[30.1675,-2.9243],"type":"Point"}
}