{
  "type": "Feature",
  "properties": {
    "gn:admin1_code":"15.0",
    "gn:asciiname":"Burengo",
    "gn:country_code":"BI",
    "gn:dem":1938,
    "gn:feature_class":"P",
    "gn:feature_code":"PPLL",
    "gn:name":"Burengo",
    "gn:population":0,
    "gn:timezone":"Africa/Bujumbura",
    "iso:country":"BI",
    "wof:name":"Burengo",
    "wof:placetype":"locality"
},
  "geometry": {"coordinates":[29.6192,-3.0725],"type":"Point"}
}