{
  "type": "Feature",
  "properties": {
    "gn:admin1_code":"12.0",
    "gn:asciiname":"Rugano",
    "gn:country_code":"BI",
    "gn:dem":1292,
    "gn:feature_class":"P",
    "gn:feature_code":"PPLL",
    "gn:name":"Rugano",
    "gn:population":0,
    "gn:timezone":"Africa/Bujumbura",
    "iso:country":"BI",
    "wof:name":"Rugano",
    "wof:placetype":"locality"
},
  "geometry": {"coordinates":[29.2756,-2.9439],"type":"Point"}
}