{
  "type": "Feature",
  "properties": {
    "gn:admin1_code":"22.0",
    "gn:asciiname":"Kirika",
    "gn:country_code":"BI",
    "gn:dem":1896,
    "gn:feature_class":"P",
    "gn:feature_code":"PPLL",
    "gn:name":"Kirika",
    "gn:population":0,
    "gn:timezone":"Africa/Bujumbura",
    "iso:country":"BI",
    "wof:name":"Kirika",
    "wof:placetype":"locality"
},
  "geometry": {"coordinates":[29.7541,-3.2337],"type":"Point"}
}