{
  "type": "Feature",
  "properties": {
    "gn:admin1_code":"16.0",
    "gn:asciiname":"Nyakarama",
    "gn:country_code":"BI",
    "gn:dem":1375,
    "gn:feature_class":"P",
    "gn:feature_code":"PPLL",
    "gn:name":"Nyakarama",
    "gn:population":0,
    "gn:timezone":"Africa/Bujumbura",
    "iso:country":"BI",
    "wof:name":"Nyakarama",
    "wof:placetype":"locality"
},
  "geometry": {"coordinates":[29.9857,-2.4201],"type":"Point"}
}