{
  "type": "Feature",
  "properties": {
    "gn:admin1_code":"14.0",
    "gn:asciiname":"Bugenyuzi",
    "gn:country_code":"BI",
    "gn:dem":1718,
    "gn:feature_class":"P",
    "gn:feature_code":"PPL",
    "gn:name":"Bugenyuzi",
    "gn:population":0,
    "gn:timezone":"Africa/Bujumbura",
    "iso:country":"BI",
    "wof:name":"Bugenyuzi",
    "wof:placetype":"locality"
},
  "geometry": {"coordinates":[30.06183,-3.08875],"type":"Point"}
}