{
  "type": "Feature",
  "properties": {
    "gn:admin1_code":"11",
    "gn:asciiname":"Kwimanume",
    "gn:country_code":"BI",
    "gn:dem":1602,
    "gn:feature_class":"P",
    "gn:feature_code":"PPLL",
    "gn:name":"Kwimanume",
    "gn:population":0,
    "gn:timezone":"Africa/Bujumbura",
    "iso:country":"BI",
    "wof:name":"Kwimanume",
    "wof:placetype":"locality"
},
  "geometry": {"coordinates":[30.5644,-3.0184],"type":"Point"}
}