{
  "type": "Feature",
  "properties": {
    "gn:admin1_code":"20",
    "gn:asciiname":"Nyampereza",
    "gn:country_code":"BI",
    "gn:dem":1541,
    "gn:feature_class":"P",
    "gn:feature_code":"PPLL",
    "gn:name":"Nyampereza",
    "gn:population":0,
    "gn:timezone":"Africa/Bujumbura",
    "iso:country":"BI",
    "wof:name":"Nyampereza",
    "wof:placetype":"locality"
},
  "geometry": {"coordinates":[30.1004,-3.7407],"type":"Point"}
}