{
  "type": "Feature",
  "properties": {
    "gn:admin1_code":"16.0",
    "gn:asciiname":"Gasura",
    "gn:country_code":"BI",
    "gn:dem":1574,
    "gn:feature_class":"P",
    "gn:feature_code":"PPL",
    "gn:name":"Gasura",
    "gn:population":0,
    "gn:timezone":"Africa/Bujumbura",
    "iso:country":"BI",
    "wof:name":"Gasura",
    "wof:placetype":"locality"
},
  "geometry": {"coordinates":[30.1035,-2.6876],"type":"Point"}
}