{
  "type": "Feature",
  "properties": {
    "gn:admin1_code":"26",
    "gn:asciiname":"Gabaniro",
    "gn:country_code":"BI",
    "gn:dem":1045,
    "gn:feature_class":"P",
    "gn:feature_code":"PPLL",
    "gn:name":"Gabaniro",
    "gn:population":0,
    "gn:timezone":"Africa/Bujumbura",
    "iso:country":"BI",
    "wof:name":"Gabaniro",
    "wof:placetype":"locality"
},
  "geometry": {"coordinates":[29.3555,-3.6064],"type":"Point"}
}