{
  "type": "Feature",
  "properties": {
    "gn:admin1_code":"18.0",
    "gn:asciiname":"Rukuri",
    "gn:country_code":"BI",
    "gn:dem":1483,
    "gn:feature_class":"P",
    "gn:feature_code":"PPLL",
    "gn:name":"Rukuri",
    "gn:population":0,
    "gn:timezone":"Africa/Bujumbura",
    "iso:country":"BI",
    "wof:name":"Rukuri",
    "wof:placetype":"locality"
},
  "geometry": {"coordinates":[30.3147,-2.7915],"type":"Point"}
}