{
  "type": "Feature",
  "properties": {
    "gn:admin1_code":"16.0",
    "gn:asciiname":"Muramba",
    "gn:country_code":"BI",
    "gn:dem":1583,
    "gn:feature_class":"P",
    "gn:feature_code":"PPLL",
    "gn:name":"Muramba",
    "gn:population":0,
    "gn:timezone":"Africa/Bujumbura",
    "iso:country":"BI",
    "wof:name":"Muramba",
    "wof:placetype":"locality"
},
  "geometry": {"coordinates":[30.0298,-2.6774],"type":"Point"}
}