{
  "type": "Feature",
  "properties": {
    "gn:admin1_code":"17",
    "gn:asciiname":"Mugu",
    "gn:country_code":"BI",
    "gn:dem":1672,
    "gn:feature_class":"P",
    "gn:feature_code":"PPLL",
    "gn:name":"Mugu",
    "gn:population":0,
    "gn:timezone":"Africa/Bujumbura",
    "iso:country":"BI",
    "name:ceb_x_preferred":[
        "Mugu"
    ],
    "name:ibo_x_preferred":[
        "Mugu"
    ],
    "name:swe_x_preferred":[
        "Mugu"
    ],
    "wof:name":"Mugu",
    "wof:placetype":"locality"
},
  "geometry": {"coordinates":[29.6887,-4.1662],"type":"Point"}
}