{
  "type": "Feature",
  "properties": {
    "gn:admin1_code":"11.0",
    "gn:asciiname":"Muzirangerera",
    "gn:country_code":"BI",
    "gn:dem":1454,
    "gn:feature_class":"P",
    "gn:feature_code":"PPLL",
    "gn:name":"Muzirangerera",
    "gn:population":0,
    "gn:timezone":"Africa/Bujumbura",
    "iso:country":"BI",
    "wof:name":"Muzirangerera",
    "wof:placetype":"locality"
},
  "geometry": {"coordinates":[30.6912,-2.9852],"type":"Point"}
}