{
  "type": "Feature",
  "properties": {
    "gn:admin1_code":"9.0",
    "gn:asciiname":"Ndonde",
    "gn:country_code":"BI",
    "gn:dem":1196,
    "gn:feature_class":"P",
    "gn:feature_code":"PPLL",
    "gn:name":"Ndonde",
    "gn:population":0,
    "gn:timezone":"Africa/Bujumbura",
    "iso:country":"BI",
    "wof:name":"Ndonde",
    "wof:placetype":"locality"
},
  "geometry": {"coordinates":[29.4564,-3.1074],"type":"Point"}
}