{
  "type": "Feature",
  "properties": {
    "gn:admin1_code":"23",
    "gn:asciiname":"Mugero",
    "gn:country_code":"BI",
    "gn:dem":2143,
    "gn:feature_class":"P",
    "gn:feature_code":"PPLL",
    "gn:name":"Mugero",
    "gn:population":0,
    "gn:timezone":"Africa/Bujumbura",
    "iso:country":"BI",
    "wof:name":"Mugero",
    "wof:placetype":"locality"
},
  "geometry": {"coordinates":[29.6262,-3.5552],"type":"Point"}
}