{
  "type": "Feature",
  "properties": {
    "gn:admin1_code":"15.0",
    "gn:asciiname":"Munini",
    "gn:country_code":"BI",
    "gn:dem":1742,
    "gn:feature_class":"P",
    "gn:feature_code":"PPLL",
    "gn:name":"Munini",
    "gn:population":0,
    "gn:timezone":"Africa/Bujumbura",
    "iso:country":"BI",
    "wof:name":"Munini",
    "wof:placetype":"locality"
},
  "geometry": {"coordinates":[29.6925,-2.9375],"type":"Point"}
}