{
  "type": "Feature",
  "properties": {
    "gn:admin1_code":"14.0",
    "gn:asciiname":"Gahera",
    "gn:country_code":"BI",
    "gn:dem":1548,
    "gn:feature_class":"P",
    "gn:feature_code":"PPL",
    "gn:name":"Gahera",
    "gn:population":0,
    "gn:timezone":"Africa/Bujumbura",
    "iso:country":"BI",
    "wof:name":"Gahera",
    "wof:placetype":"locality"
},
  "geometry": {"coordinates":[30.0847,-3.1976],"type":"Point"}
}