{
  "type": "Feature",
  "properties": {
    "gn:admin1_code":"21",
    "gn:asciiname":"Itahe",
    "gn:country_code":"BI",
    "gn:dem":1470,
    "gn:feature_class":"P",
    "gn:feature_code":"PPLL",
    "gn:name":"Itahe",
    "gn:population":0,
    "gn:timezone":"Africa/Bujumbura",
    "iso:country":"BI",
    "wof:name":"Itahe",
    "wof:placetype":"locality"
},
  "geometry": {"coordinates":[30.5367,-3.4449],"type":"Point"}
}