{
  "type": "Feature",
  "properties": {
    "gn:admin1_code":"19.0",
    "gn:asciiname":"Gatika",
    "gn:country_code":"BI",
    "gn:dem":1853,
    "gn:feature_class":"P",
    "gn:feature_code":"PPLL",
    "gn:name":"Gatika",
    "gn:population":0,
    "gn:timezone":"Africa/Bujumbura",
    "iso:country":"BI",
    "name:ara_x_preferred":[
        "\u063a\u0627\u062a\u064a\u0643\u0627"
    ],
    "name:arg_x_preferred":[
        "Gatika"
    ],
    "name:bre_x_preferred":[
        "Gatika"
    ],
    "name:cat_x_preferred":[
        "Gatika"
    ],
    "name:ceb_x_preferred":[
        "Gatika"
    ],
    "name:eus_x_preferred":[
        "Gatika"
    ],
    "name:fra_x_preferred":[
        "Gatika"
    ],
    "name:glg_x_preferred":[
        "Gatika"
    ],
    "name:hun_x_preferred":[
        "Gatika"
    ],
    "name:ita_x_preferred":[
        "Gatika"
    ],
    "name:lat_x_preferred":[
        "Gatica"
    ],
    "name:msa_x_preferred":[
        "Gatika"
    ],
    "name:nld_x_preferred":[
        "Gatika"
    ],
    "name:oci_x_preferred":[
        "Gatika"
    ],
    "name:pol_x_preferred":[
        "Gatika"
    ],
    "name:por_x_preferred":[
        "Gatica"
    ],
    "name:rus_x_preferred":[
        "\u0413\u0430\u0442\u0438\u043a\u0430"
    ],
    "name:sco_x_preferred":[
        "Gatika"
    ],
    "name:spa_x_preferred":[
        "Gatica"
    ],
    "name:swe_x_preferred":[
        "Gatika"
    ],
    "name:ukr_x_preferred":[
        "\u0413\u0430\u0442\u0456\u043a\u0430"
    ],
    "name:uzb_x_preferred":[
        "Gatica"
    ],
    "name:war_x_preferred":[
        "Gatika"
    ],
    "name:zho_x_preferred":[
        "\u52a0\u8482\u5361"
    ],
    "wof:name":"Gatika",
    "wof:placetype":"locality"
},
  "geometry": {"coordinates":[29.7324,-2.9123],"type":"Point"}
}