{
  "type": "Feature",
  "properties": {
    "gn:admin1_code":"19.0",
    "gn:asciiname":"Gatika",
    "gn:country_code":"BI",
    "gn:dem":1853,
    "gn:feature_class":"P",
    "gn:feature_code":"PPLL",
    "gn:name":"Gatika",
    "gn:population":0,
    "gn:timezone":"Africa/Bujumbura",
    "iso:country":"BI",
    "wof:name":"Gatika",
    "wof:placetype":"locality"
},
  "geometry": {"coordinates":[29.7324,-2.9123],"type":"Point"}
}