{
  "type": "Feature",
  "properties": {
    "gn:admin1_code":"9.0",
    "gn:asciiname":"Kayange",
    "gn:country_code":"BI",
    "gn:dem":1819,
    "gn:feature_class":"P",
    "gn:feature_code":"PPLL",
    "gn:name":"Kayange",
    "gn:population":0,
    "gn:timezone":"Africa/Bujumbura",
    "iso:country":"BI",
    "wof:name":"Kayange",
    "wof:placetype":"locality"
},
  "geometry": {"coordinates":[29.467,-2.9785],"type":"Point"}
}