{
  "type": "Feature",
  "properties": {
    "gn:admin1_code":"10",
    "gn:asciiname":"Munyegeri",
    "gn:country_code":"BI",
    "gn:dem":1837,
    "gn:feature_class":"P",
    "gn:feature_code":"PPLL",
    "gn:name":"Munyegeri",
    "gn:population":0,
    "gn:timezone":"Africa/Bujumbura",
    "iso:country":"BI",
    "wof:name":"Munyegeri",
    "wof:placetype":"locality"
},
  "geometry": {"coordinates":[29.8079,-3.7981],"type":"Point"}
}