{
  "type": "Feature",
  "properties": {
    "gn:admin1_code":"13.0",
    "gn:asciiname":"Kagari",
    "gn:country_code":"BI",
    "gn:dem":1573,
    "gn:feature_class":"P",
    "gn:feature_code":"PPLL",
    "gn:name":"Kagari",
    "gn:population":0,
    "gn:timezone":"Africa/Bujumbura",
    "iso:country":"BI",
    "wof:name":"Kagari",
    "wof:placetype":"locality"
},
  "geometry": {"coordinates":[29.9148,-3.2241],"type":"Point"}
}