{
  "type": "Feature",
  "properties": {
    "gn:admin1_code":"16.0",
    "gn:asciiname":"Rukore",
    "gn:country_code":"BI",
    "gn:dem":1434,
    "gn:feature_class":"P",
    "gn:feature_code":"PPLL",
    "gn:name":"Rukore",
    "gn:population":0,
    "gn:timezone":"Africa/Bujumbura",
    "iso:country":"BI",
    "wof:name":"Rukore",
    "wof:placetype":"locality"
},
  "geometry": {"coordinates":[29.9624,-2.6556],"type":"Point"}
}