{
  "type": "Feature",
  "properties": {
    "gn:admin1_code":"18.0",
    "gn:asciiname":"Rukashi",
    "gn:country_code":"BI",
    "gn:dem":1695,
    "gn:feature_class":"P",
    "gn:feature_code":"PPLL",
    "gn:name":"Rukashi",
    "gn:population":0,
    "gn:timezone":"Africa/Bujumbura",
    "iso:country":"BI",
    "wof:name":"Rukashi",
    "wof:placetype":"locality"
},
  "geometry": {"coordinates":[30.2734,-2.7636],"type":"Point"}
}