{
  "type": "Feature",
  "properties": {
    "gn:admin1_code":"13",
    "gn:asciiname":"Cogo",
    "gn:country_code":"BI",
    "gn:dem":1964,
    "gn:feature_class":"P",
    "gn:feature_code":"PPLL",
    "gn:name":"Cogo",
    "gn:population":0,
    "gn:timezone":"Africa/Bujumbura",
    "iso:country":"BI",
    "name:ceb_x_preferred":[
        "Cogo"
    ],
    "name:deu_x_preferred":[
        "Cogo"
    ],
    "name:fra_x_preferred":[
        "Cogo"
    ],
    "name:ita_x_preferred":[
        "Cogo"
    ],
    "name:swe_x_preferred":[
        "Cogo"
    ],
    "wof:name":"Cogo",
    "wof:placetype":"locality"
},
  "geometry": {"coordinates":[29.9736,-3.7283],"type":"Point"}
}