{
  "type": "Feature",
  "properties": {
    "gn:admin1_code":"16.0",
    "gn:asciiname":"Kigaga",
    "gn:country_code":"BI",
    "gn:dem":1477,
    "gn:feature_class":"P",
    "gn:feature_code":"PPLL",
    "gn:name":"Kigaga",
    "gn:population":0,
    "gn:timezone":"Africa/Bujumbura",
    "iso:country":"BI",
    "wof:name":"Kigaga",
    "wof:placetype":"locality"
},
  "geometry": {"coordinates":[29.9536,-2.6038],"type":"Point"}
}