{
  "type": "Feature",
  "properties": {
    "gn:admin1_code":"23",
    "gn:asciiname":"Rurtyazo",
    "gn:country_code":"BI",
    "gn:dem":1916,
    "gn:feature_class":"P",
    "gn:feature_code":"PPLL",
    "gn:name":"Rurtyazo",
    "gn:population":0,
    "gn:timezone":"Africa/Bujumbura",
    "iso:country":"BI",
    "wof:name":"Rurtyazo",
    "wof:placetype":"locality"
},
  "geometry": {"coordinates":[29.7139,-3.4671],"type":"Point"}
}