{
  "type": "Feature",
  "properties": {
    "gn:admin1_code":"19.0",
    "gn:asciiname":"Gisura",
    "gn:country_code":"BI",
    "gn:dem":1692,
    "gn:feature_class":"P",
    "gn:feature_code":"PPLL",
    "gn:name":"Gisura",
    "gn:population":0,
    "gn:timezone":"Africa/Bujumbura",
    "iso:country":"BI",
    "wof:name":"Gisura",
    "wof:placetype":"locality"
},
  "geometry": {"coordinates":[29.9876,-2.9366],"type":"Point"}
}