{
  "type": "Feature",
  "properties": {
    "gn:admin1_code":"12.0",
    "gn:asciiname":"Shimwe",
    "gn:country_code":"BI",
    "gn:dem":1796,
    "gn:feature_class":"P",
    "gn:feature_code":"PPLL",
    "gn:name":"Shimwe",
    "gn:population":0,
    "gn:timezone":"Africa/Bujumbura",
    "iso:country":"BI",
    "wof:name":"Shimwe",
    "wof:placetype":"locality"
},
  "geometry": {"coordinates":[29.3005,-2.8506],"type":"Point"}
}