{
  "type": "Feature",
  "properties": {
    "gn:admin1_code":"13",
    "gn:asciiname":"Muhurika",
    "gn:country_code":"BI",
    "gn:dem":1641,
    "gn:feature_class":"P",
    "gn:feature_code":"PPLL",
    "gn:name":"Muhurika",
    "gn:population":0,
    "gn:timezone":"Africa/Bujumbura",
    "iso:country":"BI",
    "wof:name":"Muhurika",
    "wof:placetype":"locality"
},
  "geometry": {"coordinates":[29.9417,-3.5274],"type":"Point"}
}