{
  "type": "Feature",
  "properties": {
    "gn:admin1_code":"12.0",
    "gn:asciiname":"Ruronge",
    "gn:country_code":"BI",
    "gn:dem":1418,
    "gn:feature_class":"P",
    "gn:feature_code":"PPLL",
    "gn:name":"Ruronge",
    "gn:population":0,
    "gn:timezone":"Africa/Bujumbura",
    "iso:country":"BI",
    "wof:name":"Ruronge",
    "wof:placetype":"locality"
},
  "geometry": {"coordinates":[29.246,-2.7183],"type":"Point"}
}