{
  "type": "Feature",
  "properties": {
    "gn:admin1_code":"20",
    "gn:asciiname":"Kagari",
    "gn:country_code":"BI",
    "gn:dem":1202,
    "gn:feature_class":"P",
    "gn:feature_code":"PPLL",
    "gn:name":"Kagari",
    "gn:population":0,
    "gn:timezone":"Africa/Bujumbura",
    "iso:country":"BI",
    "wof:name":"Kagari",
    "wof:placetype":"locality"
},
  "geometry": {"coordinates":[30.2159,-3.9214],"type":"Point"}
}