{
  "type": "Feature",
  "properties": {
    "gn:admin1_code":"10.0",
    "gn:asciiname":"Burambi",
    "gn:country_code":"BI",
    "gn:dem":1901,
    "gn:feature_class":"P",
    "gn:feature_code":"PPLL",
    "gn:name":"Burambi",
    "gn:population":0,
    "gn:timezone":"Africa/Bujumbura",
    "iso:country":"BI",
    "wof:name":"Burambi",
    "wof:placetype":"locality"
},
  "geometry": {"coordinates":[29.8415,-3.95819],"type":"Point"}
}