{
  "type": "Feature",
  "properties": {
    "gn:admin1_code":"16.0",
    "gn:asciiname":"Gitwenzi",
    "gn:country_code":"BI",
    "gn:dem":1439,
    "gn:feature_class":"P",
    "gn:feature_code":"PPLL",
    "gn:name":"Gitwenzi",
    "gn:population":0,
    "gn:timezone":"Africa/Bujumbura",
    "iso:country":"BI",
    "wof:name":"Gitwenzi",
    "wof:placetype":"locality"
},
  "geometry": {"coordinates":[30.0411,-2.5934],"type":"Point"}
}