{
  "type": "Feature",
  "properties": {
    "gn:admin1_code":"13",
    "gn:asciiname":"Kanyinya",
    "gn:country_code":"BI",
    "gn:dem":1618,
    "gn:feature_class":"P",
    "gn:feature_code":"PPLL",
    "gn:name":"Kanyinya",
    "gn:population":0,
    "gn:timezone":"Africa/Bujumbura",
    "iso:country":"BI",
    "wof:name":"Kanyinya",
    "wof:placetype":"locality"
},
  "geometry": {"coordinates":[30.0105,-3.436],"type":"Point"}
}