{
  "type": "Feature",
  "properties": {
    "gn:admin1_code":"20",
    "gn:asciiname":"Gitare",
    "gn:country_code":"BI",
    "gn:dem":1606,
    "gn:feature_class":"P",
    "gn:feature_code":"PPLL",
    "gn:name":"Gitare",
    "gn:population":0,
    "gn:timezone":"Africa/Bujumbura",
    "iso:country":"BI",
    "wof:name":"Gitare",
    "wof:placetype":"locality"
},
  "geometry": {"coordinates":[30.0951,-3.8019],"type":"Point"}
}