{
  "type": "Feature",
  "properties": {
    "gn:admin1_code":"23",
    "gn:asciiname":"Vyuma",
    "gn:country_code":"BI",
    "gn:dem":1923,
    "gn:feature_class":"P",
    "gn:feature_code":"PPLL",
    "gn:name":"Vyuma",
    "gn:population":0,
    "gn:timezone":"Africa/Bujumbura",
    "iso:country":"BI",
    "wof:name":"Vyuma",
    "wof:placetype":"locality"
},
  "geometry": {"coordinates":[29.7254,-3.4578],"type":"Point"}
}