{
  "type": "Feature",
  "properties": {
    "gn:admin1_code":"19.0",
    "gn:asciiname":"Kimerajana",
    "gn:country_code":"BI",
    "gn:dem":1639,
    "gn:feature_class":"P",
    "gn:feature_code":"PPLL",
    "gn:name":"Kimerajana",
    "gn:population":0,
    "gn:timezone":"Africa/Bujumbura",
    "iso:country":"BI",
    "wof:name":"Kimerajana",
    "wof:placetype":"locality"
},
  "geometry": {"coordinates":[29.9444,-3.0047],"type":"Point"}
}