{
  "type": "Feature",
  "properties": {
    "gn:admin1_code":"21",
    "gn:asciiname":"Buhigwe",
    "gn:country_code":"BI",
    "gn:dem":1447,
    "gn:feature_class":"P",
    "gn:feature_code":"PPLL",
    "gn:name":"Buhigwe",
    "gn:population":0,
    "gn:timezone":"Africa/Bujumbura",
    "iso:country":"BI",
    "name:ell_x_preferred":[
        "\u039c\u03c0\u03bf\u03c5\u03c7\u03af\u03b3\u03ba\u03bf\u03c5\u03b5"
    ],
    "name:swa_x_preferred":[
        "Buhigwe"
    ],
    "name:und_x_variant":[
        "Buhigwa",
        "Buhigwe"
    ],
    "wof:name":"Buhigwe",
    "wof:placetype":"locality"
},
  "geometry": {"coordinates":[30.1162,-3.3625],"type":"Point"}
}