{
  "type": "Feature",
  "properties": {
    "gn:admin1_code":"15.0",
    "gn:asciiname":"Mwokora",
    "gn:country_code":"BI",
    "gn:dem":2350,
    "gn:feature_class":"P",
    "gn:feature_code":"PPLL",
    "gn:name":"Mwokora",
    "gn:population":0,
    "gn:timezone":"Africa/Bujumbura",
    "iso:country":"BI",
    "wof:name":"Mwokora",
    "wof:placetype":"locality"
},
  "geometry": {"coordinates":[29.4469,-2.8036],"type":"Point"}
}