{
  "type": "Feature",
  "properties": {
    "gn:admin1_code":"14.0",
    "gn:asciiname":"Kituma",
    "gn:country_code":"BI",
    "gn:dem":1598,
    "gn:feature_class":"P",
    "gn:feature_code":"PPLL",
    "gn:name":"Kituma",
    "gn:population":0,
    "gn:timezone":"Africa/Bujumbura",
    "iso:country":"BI",
    "wof:name":"Kituma",
    "wof:placetype":"locality"
},
  "geometry": {"coordinates":[30.1453,-2.9627],"type":"Point"}
}