{
  "type": "Feature",
  "properties": {
    "gn:admin1_code":"19.0",
    "gn:asciiname":"Kabarabara",
    "gn:country_code":"BI",
    "gn:dem":1674,
    "gn:feature_class":"P",
    "gn:feature_code":"PPLL",
    "gn:name":"Kabarabara",
    "gn:population":0,
    "gn:timezone":"Africa/Bujumbura",
    "iso:country":"BI",
    "wof:name":"Kabarabara",
    "wof:placetype":"locality"
},
  "geometry": {"coordinates":[30.1336,-2.9051],"type":"Point"}
}