{
  "type": "Feature",
  "properties": {
    "gn:admin1_code":"20",
    "gn:asciiname":"Nkanka",
    "gn:country_code":"BI",
    "gn:dem":1263,
    "gn:feature_class":"P",
    "gn:feature_code":"PPLL",
    "gn:name":"Nkanka",
    "gn:population":0,
    "gn:timezone":"Africa/Bujumbura",
    "iso:country":"BI",
    "wof:name":"Nkanka",
    "wof:placetype":"locality"
},
  "geometry": {"coordinates":[30.1799,-3.904],"type":"Point"}
}