{
  "type": "Feature",
  "properties": {
    "gn:admin1_code":"10",
    "gn:asciiname":"Kayenzi",
    "gn:country_code":"BI",
    "gn:dem":2115,
    "gn:feature_class":"P",
    "gn:feature_code":"PPLL",
    "gn:name":"Kayenzi",
    "gn:population":0,
    "gn:timezone":"Africa/Bujumbura",
    "iso:country":"BI",
    "wof:name":"Kayenzi",
    "wof:placetype":"locality"
},
  "geometry": {"coordinates":[29.6368,-3.6343],"type":"Point"}
}