{
  "type": "Feature",
  "properties": {
    "gn:admin1_code":"18.0",
    "gn:asciiname":"Musama",
    "gn:country_code":"BI",
    "gn:dem":1574,
    "gn:feature_class":"P",
    "gn:feature_code":"PPLL",
    "gn:name":"Musama",
    "gn:population":0,
    "gn:timezone":"Africa/Bujumbura",
    "iso:country":"BI",
    "wof:name":"Musama",
    "wof:placetype":"locality"
},
  "geometry": {"coordinates":[30.2249,-2.7316],"type":"Point"}
}