{
  "type": "Feature",
  "properties": {
    "gn:admin1_code":"25",
    "gn:asciiname":"Mubone",
    "gn:country_code":"BI",
    "gn:dem":1037,
    "gn:feature_class":"P",
    "gn:feature_code":"PPLL",
    "gn:name":"Mubone",
    "gn:population":0,
    "gn:timezone":"Africa/Bujumbura",
    "iso:country":"BI",
    "wof:name":"Mubone",
    "wof:placetype":"locality"
},
  "geometry": {"coordinates":[29.3757,-3.49],"type":"Point"}
}