{
  "type": "Feature",
  "properties": {
    "gn:admin1_code":"17",
    "gn:asciiname":"Kibuye",
    "gn:country_code":"BI",
    "gn:dem":1746,
    "gn:feature_class":"P",
    "gn:feature_code":"PPLL",
    "gn:name":"Kibuye",
    "gn:population":0,
    "gn:timezone":"Africa/Bujumbura",
    "iso:country":"BI",
    "name:ceb_x_preferred":[
        "Kibuye"
    ],
    "name:swe_x_preferred":[
        "Kibuye"
    ],
    "wof:name":"Kibuye",
    "wof:placetype":"locality"
},
  "geometry": {"coordinates":[29.7572,-4.1377],"type":"Point"}
}