{
  "type": "Feature",
  "properties": {
    "gn:admin1_code":"17.0",
    "gn:asciiname":"Bogogwa",
    "gn:country_code":"BI",
    "gn:dem":804,
    "gn:feature_class":"P",
    "gn:feature_code":"PPL",
    "gn:name":"Bogogwa",
    "gn:population":0,
    "gn:timezone":"Africa/Bujumbura",
    "iso:country":"BI",
    "wof:name":"Bogogwa",
    "wof:placetype":"locality"
},
  "geometry": {"coordinates":[29.604,-4.3384],"type":"Point"}
}