{
  "type": "Feature",
  "properties": {
    "gn:admin1_code":"23",
    "gn:asciiname":"Ruvumu",
    "gn:country_code":"BI",
    "gn:dem":1966,
    "gn:feature_class":"P",
    "gn:feature_code":"PPLL",
    "gn:name":"Ruvumu",
    "gn:population":0,
    "gn:timezone":"Africa/Bujumbura",
    "iso:country":"BI",
    "wof:name":"Ruvumu",
    "wof:placetype":"locality"
},
  "geometry": {"coordinates":[29.6739,-3.4335],"type":"Point"}
}