{
  "type": "Feature",
  "properties": {
    "gn:admin1_code":"18.0",
    "gn:asciiname":"Ruhama",
    "gn:country_code":"BI",
    "gn:dem":1803,
    "gn:feature_class":"P",
    "gn:feature_code":"PPLL",
    "gn:name":"Ruhama",
    "gn:population":0,
    "gn:timezone":"Africa/Bujumbura",
    "iso:country":"BI",
    "name:ces_x_preferred":[
        "Ruchama"
    ],
    "name:fra_x_preferred":[
        "Rouhama"
    ],
    "name:heb_x_preferred":[
        "\u05e8\u05d5\u05d7\u05de\u05d4"
    ],
    "name:nno_x_preferred":[
        "Ruhama"
    ],
    "name:pol_x_preferred":[
        "Ruchama"
    ],
    "name:rus_x_preferred":[
        "\u0420\u0443\u0445\u0430\u043c\u0430"
    ],
    "wof:name":"Ruhama",
    "wof:placetype":"locality"
},
  "geometry": {"coordinates":[30.2535,-2.7962],"type":"Point"}
}