{
  "type": "Feature",
  "properties": {
    "gn:admin1_code":"10",
    "gn:asciiname":"Shembe",
    "gn:country_code":"BI",
    "gn:dem":1916,
    "gn:feature_class":"P",
    "gn:feature_code":"PPLL",
    "gn:name":"Shembe",
    "gn:population":0,
    "gn:timezone":"Africa/Bujumbura",
    "iso:country":"BI",
    "name:ceb_x_preferred":[
        "Shembe"
    ],
    "name:swe_x_preferred":[
        "Shembe"
    ],
    "wof:name":"Shembe",
    "wof:placetype":"locality"
},
  "geometry": {"coordinates":[29.592,-3.908],"type":"Point"}
}