{
  "type": "Feature",
  "properties": {
    "gn:admin1_code":"22.0",
    "gn:asciiname":"Kabirumba",
    "gn:country_code":"BI",
    "gn:dem":1862,
    "gn:feature_class":"P",
    "gn:feature_code":"PPLL",
    "gn:name":"Kabirumba",
    "gn:population":0,
    "gn:timezone":"Africa/Bujumbura",
    "iso:country":"BI",
    "name:und_x_variant":[
        "Kabirumbi",
        "Kabirumba"
    ],
    "wof:name":"Kabirumba",
    "wof:placetype":"locality"
},
  "geometry": {"coordinates":[29.6236,-3.2316],"type":"Point"}
}