{
  "type": "Feature",
  "properties": {
    "gn:admin1_code":"11",
    "gn:asciiname":"Nyagisovu",
    "gn:country_code":"BI",
    "gn:dem":1292,
    "gn:feature_class":"P",
    "gn:feature_code":"PPLL",
    "gn:name":"Nyagisovu",
    "gn:population":0,
    "gn:timezone":"Africa/Bujumbura",
    "iso:country":"BI",
    "wof:name":"Nyagisovu",
    "wof:placetype":"locality"
},
  "geometry": {"coordinates":[30.6263,-3.314],"type":"Point"}
}