{
  "type": "Feature",
  "properties": {
    "gn:admin1_code":"19.0",
    "gn:asciiname":"Kabaremera",
    "gn:country_code":"BI",
    "gn:dem":1647,
    "gn:feature_class":"P",
    "gn:feature_code":"PPLL",
    "gn:name":"Kabaremera",
    "gn:population":0,
    "gn:timezone":"Africa/Bujumbura",
    "iso:country":"BI",
    "wof:name":"Kabaremera",
    "wof:placetype":"locality"
},
  "geometry": {"coordinates":[30.0712,-2.9214],"type":"Point"}
}