{
  "type": "Feature",
  "properties": {
    "gn:admin1_code":"10",
    "gn:asciiname":"Rukanda",
    "gn:country_code":"BI",
    "gn:dem":1215,
    "gn:feature_class":"P",
    "gn:feature_code":"PPLL",
    "gn:name":"Rukanda",
    "gn:population":0,
    "gn:timezone":"Africa/Bujumbura",
    "iso:country":"BI",
    "wof:name":"Rukanda",
    "wof:placetype":"locality"
},
  "geometry": {"coordinates":[29.5674,-3.9306],"type":"Point"}
}