{
  "type": "Feature",
  "properties": {
    "gn:admin1_code":"21",
    "gn:asciiname":"Ruvumu",
    "gn:country_code":"BI",
    "gn:dem":1622,
    "gn:feature_class":"P",
    "gn:feature_code":"PPLL",
    "gn:name":"Ruvumu",
    "gn:population":0,
    "gn:timezone":"Africa/Bujumbura",
    "iso:country":"BI",
    "wof:name":"Ruvumu",
    "wof:placetype":"locality"
},
  "geometry": {"coordinates":[30.1098,-3.415],"type":"Point"}
}