{
  "type": "Feature",
  "properties": {
    "gn:admin1_code":"21",
    "gn:asciiname":"Gasema",
    "gn:country_code":"BI",
    "gn:dem":1518,
    "gn:feature_class":"P",
    "gn:feature_code":"PPLL",
    "gn:name":"Gasema",
    "gn:population":0,
    "gn:timezone":"Africa/Bujumbura",
    "iso:country":"BI",
    "wof:name":"Gasema",
    "wof:placetype":"locality"
},
  "geometry": {"coordinates":[30.1065,-3.4718],"type":"Point"}
}