{
  "type": "Feature",
  "properties": {
    "gn:admin1_code":"12.0",
    "gn:asciiname":"Rubirizi",
    "gn:country_code":"BI",
    "gn:dem":1072,
    "gn:feature_class":"P",
    "gn:feature_code":"PPLL",
    "gn:name":"Rubirizi",
    "gn:population":0,
    "gn:timezone":"Africa/Bujumbura",
    "iso:country":"BI",
    "name:lug_x_preferred":[
        "Rubirizi"
    ],
    "name:urd_x_preferred":[
        "\u0631\u0648\u0628\u06cc\u0631\u06cc\u0632\u06cc"
    ],
    "wof:name":"Rubirizi",
    "wof:placetype":"locality"
},
  "geometry": {"coordinates":[29.0766,-2.7404],"type":"Point"}
}