{
  "type": "Feature",
  "properties": {
    "gn:admin1_code":"18.0",
    "gn:asciiname":"Kigarama",
    "gn:country_code":"BI",
    "gn:dem":1468,
    "gn:feature_class":"P",
    "gn:feature_code":"PPLL",
    "gn:name":"Kigarama",
    "gn:population":0,
    "gn:timezone":"Africa/Bujumbura",
    "iso:country":"BI",
    "wof:name":"Kigarama",
    "wof:placetype":"locality"
},
  "geometry": {"coordinates":[30.3993,-2.657],"type":"Point"}
}