{
  "type": "Feature",
  "properties": {
    "gn:admin1_code":"25",
    "gn:asciiname":"Matara",
    "gn:country_code":"BI",
    "gn:dem":1620,
    "gn:feature_class":"P",
    "gn:feature_code":"PPLL",
    "gn:name":"Matara",
    "gn:population":0,
    "gn:timezone":"Africa/Bujumbura",
    "iso:country":"BI",
    "wof:name":"Matara",
    "wof:placetype":"locality"
},
  "geometry": {"coordinates":[29.4752,-3.2867],"type":"Point"}
}