{
  "type": "Feature",
  "properties": {
    "gn:admin1_code":"25",
    "gn:asciiname":"Matara",
    "gn:country_code":"BI",
    "gn:dem":1620,
    "gn:feature_class":"P",
    "gn:feature_code":"PPLL",
    "gn:name":"Matara",
    "gn:population":0,
    "gn:timezone":"Africa/Bujumbura",
    "iso:country":"BI",
    "name:ceb_x_preferred":[
        "Matara"
    ],
    "name:ind_x_preferred":[
        "Matara"
    ],
    "name:ita_x_preferred":[
        "Matara"
    ],
    "name:nld_x_preferred":[
        "Matara"
    ],
    "name:pol_x_preferred":[
        "Matara"
    ],
    "name:por_x_preferred":[
        "Matara"
    ],
    "name:por_x_variant":[
        "Matar\u00e1"
    ],
    "name:rus_x_preferred":[
        "\u041c\u0430\u0442\u0430\u0440\u0430"
    ],
    "name:spa_x_preferred":[
        "Matar\u00e1"
    ],
    "name:swe_x_preferred":[
        "Matara"
    ],
    "wof:name":"Matara",
    "wof:placetype":"locality"
},
  "geometry": {"coordinates":[29.4752,-3.2867],"type":"Point"}
}