{
  "type": "Feature",
  "properties": {
    "gn:admin1_code":"10",
    "gn:asciiname":"Gifugutu",
    "gn:country_code":"BI",
    "gn:dem":2096,
    "gn:feature_class":"P",
    "gn:feature_code":"PPLL",
    "gn:name":"Gifugutu",
    "gn:population":0,
    "gn:timezone":"Africa/Bujumbura",
    "iso:country":"BI",
    "wof:name":"Gifugutu",
    "wof:placetype":"locality"
},
  "geometry": {"coordinates":[29.613,-3.7156],"type":"Point"}
}