{
  "type": "Feature",
  "properties": {
    "gn:admin1_code":"13",
    "gn:asciiname":"Gatoza",
    "gn:country_code":"BI",
    "gn:dem":1702,
    "gn:feature_class":"P",
    "gn:feature_code":"PPLL",
    "gn:name":"Gatoza",
    "gn:population":0,
    "gn:timezone":"Africa/Bujumbura",
    "iso:country":"BI",
    "wof:name":"Gatoza",
    "wof:placetype":"locality"
},
  "geometry": {"coordinates":[29.9108,-3.6333],"type":"Point"}
}