{
  "type": "Feature",
  "properties": {
    "gn:admin1_code":"17",
    "gn:asciiname":"Gahororo",
    "gn:country_code":"BI",
    "gn:dem":1406,
    "gn:feature_class":"P",
    "gn:feature_code":"PPL",
    "gn:name":"Gahororo",
    "gn:population":0,
    "gn:timezone":"Africa/Bujumbura",
    "iso:country":"BI",
    "wof:name":"Gahororo",
    "wof:placetype":"locality"
},
  "geometry": {"coordinates":[29.8066,-4.2223],"type":"Point"}
}