{
  "type": "Feature",
  "properties": {
    "gn:admin1_code":"12.0",
    "gn:asciiname":"Gatoke",
    "gn:country_code":"BI",
    "gn:dem":1289,
    "gn:feature_class":"P",
    "gn:feature_code":"PPLL",
    "gn:name":"Gatoke",
    "gn:population":0,
    "gn:timezone":"Africa/Bujumbura",
    "iso:country":"BI",
    "wof:name":"Gatoke",
    "wof:placetype":"locality"
},
  "geometry": {"coordinates":[29.2862,-2.9927],"type":"Point"}
}