{
  "type": "Feature",
  "properties": {
    "gn:admin1_code":"16.0",
    "gn:asciiname":"Kimeza",
    "gn:country_code":"BI",
    "gn:dem":1480,
    "gn:feature_class":"P",
    "gn:feature_code":"PPLL",
    "gn:name":"Kimeza",
    "gn:population":0,
    "gn:timezone":"Africa/Bujumbura",
    "iso:country":"BI",
    "wof:name":"Kimeza",
    "wof:placetype":"locality"
},
  "geometry": {"coordinates":[30.37917,-2.55833],"type":"Point"}
}