{
  "type": "Feature",
  "properties": {
    "gn:admin1_code":"18.0",
    "gn:asciiname":"Nyange",
    "gn:country_code":"BI",
    "gn:dem":1532,
    "gn:feature_class":"P",
    "gn:feature_code":"PPLL",
    "gn:name":"Nyange",
    "gn:population":0,
    "gn:timezone":"Africa/Bujumbura",
    "iso:country":"BI",
    "wof:name":"Nyange",
    "wof:placetype":"locality"
},
  "geometry": {"coordinates":[30.4578,-2.4863],"type":"Point"}
}