{
  "type": "Feature",
  "properties": {
    "gn:admin1_code":"15.0",
    "gn:asciiname":"Kibakwe",
    "gn:country_code":"BI",
    "gn:dem":2039,
    "gn:feature_class":"P",
    "gn:feature_code":"PPLL",
    "gn:name":"Kibakwe",
    "gn:population":0,
    "gn:timezone":"Africa/Bujumbura",
    "iso:country":"BI",
    "name:ceb_x_preferred":[
        "Kibakwe"
    ],
    "name:ita_x_preferred":[
        "Kibakwe"
    ],
    "name:swa_x_preferred":[
        "Kibakwe"
    ],
    "wof:name":"Kibakwe",
    "wof:placetype":"locality"
},
  "geometry": {"coordinates":[29.5817,-2.9086],"type":"Point"}
}