{
  "type": "Feature",
  "properties": {
    "gn:admin1_code":"13",
    "gn:asciiname":"Kwibuka",
    "gn:country_code":"BI",
    "gn:dem":1646,
    "gn:feature_class":"P",
    "gn:feature_code":"PPL",
    "gn:name":"Kwibuka",
    "gn:population":0,
    "gn:timezone":"Africa/Bujumbura",
    "iso:country":"BI",
    "wof:name":"Kwibuka",
    "wof:placetype":"locality"
},
  "geometry": {"coordinates":[29.90865,-3.40743],"type":"Point"}
}