{
  "type": "Feature",
  "properties": {
    "gn:admin1_code":"14",
    "gn:asciiname":"Zanandore",
    "gn:country_code":"BI",
    "gn:dem":1543,
    "gn:feature_class":"P",
    "gn:feature_code":"PPL",
    "gn:name":"Zanandore",
    "gn:population":0,
    "gn:timezone":"Africa/Bujumbura",
    "iso:country":"BI",
    "wof:name":"Zanandore",
    "wof:placetype":"locality"
},
  "geometry": {"coordinates":[30.11404000000001,-3.2548],"type":"Point"}
}