{
  "type": "Feature",
  "properties": {
    "gn:admin1_code":"10.0",
    "gn:asciiname":"Murwa",
    "gn:country_code":"BI",
    "gn:dem":1921,
    "gn:feature_class":"P",
    "gn:feature_code":"PPLL",
    "gn:name":"Murwa",
    "gn:population":0,
    "gn:timezone":"Africa/Bujumbura",
    "iso:country":"BI",
    "wof:name":"Murwa",
    "wof:placetype":"locality"
},
  "geometry": {"coordinates":[29.7632,-3.9124],"type":"Point"}
}