{
  "type": "Feature",
  "properties": {
    "gn:admin1_code":"22.0",
    "gn:asciiname":"Kibogoye",
    "gn:country_code":"BI",
    "gn:dem":1918,
    "gn:feature_class":"P",
    "gn:feature_code":"PPLL",
    "gn:name":"Kibogoye",
    "gn:population":0,
    "gn:timezone":"Africa/Bujumbura",
    "iso:country":"BI",
    "wof:name":"Kibogoye",
    "wof:placetype":"locality"
},
  "geometry": {"coordinates":[29.6041,-3.2177],"type":"Point"}
}