{
  "type": "Feature",
  "properties": {
    "gn:admin1_code":"24",
    "gn:asciiname":"Kamesa",
    "gn:country_code":"BI",
    "gn:dem":1116,
    "gn:feature_class":"P",
    "gn:feature_code":"PPLL",
    "gn:name":"Kamesa",
    "gn:population":0,
    "gn:timezone":"Africa/Bujumbura",
    "iso:country":"BI",
    "wof:name":"Kamesa",
    "wof:placetype":"locality"
},
  "geometry": {"coordinates":[29.3863,-3.4198],"type":"Point"}
}