{
  "type": "Feature",
  "properties": {
    "gn:admin1_code":"12.0",
    "gn:asciiname":"Buhoro",
    "gn:country_code":"BI",
    "gn:dem":1416,
    "gn:feature_class":"P",
    "gn:feature_code":"PPLL",
    "gn:name":"Buhoro",
    "gn:population":0,
    "gn:timezone":"Africa/Bujumbura",
    "iso:country":"BI",
    "wof:name":"Buhoro",
    "wof:placetype":"locality"
},
  "geometry": {"coordinates":[29.1881,-2.6999],"type":"Point"}
}