{
  "type": "Feature",
  "properties": {
    "gn:admin1_code":"11",
    "gn:asciiname":"Kumana",
    "gn:country_code":"BI",
    "gn:dem":1900,
    "gn:feature_class":"P",
    "gn:feature_code":"PPLL",
    "gn:name":"Kumana",
    "gn:population":0,
    "gn:timezone":"Africa/Bujumbura",
    "iso:country":"BI",
    "wof:name":"Kumana",
    "wof:placetype":"locality"
},
  "geometry": {"coordinates":[30.6498,-3.1978],"type":"Point"}
}