{
  "type": "Feature",
  "properties": {
    "gn:admin1_code":"25",
    "gn:asciiname":"Rubanda",
    "gn:country_code":"BI",
    "gn:dem":1652,
    "gn:feature_class":"P",
    "gn:feature_code":"PPLL",
    "gn:name":"Rubanda",
    "gn:population":0,
    "gn:timezone":"Africa/Bujumbura",
    "iso:country":"BI",
    "wof:name":"Rubanda",
    "wof:placetype":"locality"
},
  "geometry": {"coordinates":[29.431,-3.5145],"type":"Point"}
}