{
  "type": "Feature",
  "properties": {
    "gn:admin1_code":"21",
    "gn:asciiname":"Ndemeka",
    "gn:country_code":"BI",
    "gn:dem":1647,
    "gn:feature_class":"P",
    "gn:feature_code":"PPLL",
    "gn:name":"Ndemeka",
    "gn:population":0,
    "gn:timezone":"Africa/Bujumbura",
    "iso:country":"BI",
    "wof:name":"Ndemeka",
    "wof:placetype":"locality"
},
  "geometry": {"coordinates":[30.6005,-3.4194],"type":"Point"}
}