{
  "type": "Feature",
  "properties": {
    "gn:admin1_code":"14.0",
    "gn:asciiname":"Murago",
    "gn:country_code":"BI",
    "gn:dem":1580,
    "gn:feature_class":"P",
    "gn:feature_code":"PPLL",
    "gn:name":"Murago",
    "gn:population":0,
    "gn:timezone":"Africa/Bujumbura",
    "iso:country":"BI",
    "wof:name":"Murago",
    "wof:placetype":"locality"
},
  "geometry": {"coordinates":[29.9924,-3.1489],"type":"Point"}
}