{
  "type": "Feature",
  "properties": {
    "gn:admin1_code":"21",
    "gn:asciiname":"Gitondo",
    "gn:country_code":"BI",
    "gn:dem":1545,
    "gn:feature_class":"P",
    "gn:feature_code":"PPL",
    "gn:name":"Gitondo",
    "gn:population":0,
    "gn:timezone":"Africa/Bujumbura",
    "iso:country":"BI",
    "wof:name":"Gitondo",
    "wof:placetype":"locality"
},
  "geometry": {"coordinates":[30.46083,-3.34913],"type":"Point"}
}