{
  "type": "Feature",
  "properties": {
    "gn:admin1_code":"22",
    "gn:asciiname":"Kivyeyi",
    "gn:country_code":"BI",
    "gn:dem":1969,
    "gn:feature_class":"P",
    "gn:feature_code":"PPLL",
    "gn:name":"Kivyeyi",
    "gn:population":0,
    "gn:timezone":"Africa/Bujumbura",
    "iso:country":"BI",
    "wof:name":"Kivyeyi",
    "wof:placetype":"locality"
},
  "geometry": {"coordinates":[29.6573,-3.2981],"type":"Point"}
}