{
  "type": "Feature",
  "properties": {
    "gn:admin1_code":"14.0",
    "gn:asciiname":"Nyarutambika",
    "gn:country_code":"BI",
    "gn:dem":1637,
    "gn:feature_class":"P",
    "gn:feature_code":"PPLL",
    "gn:name":"Nyarutambika",
    "gn:population":0,
    "gn:timezone":"Africa/Bujumbura",
    "iso:country":"BI",
    "wof:name":"Nyarutambika",
    "wof:placetype":"locality"
},
  "geometry": {"coordinates":[29.9837,-3.1611],"type":"Point"}
}