{
  "type": "Feature",
  "properties": {
    "gn:admin1_code":"26",
    "gn:asciiname":"Nyarugati",
    "gn:country_code":"BI",
    "gn:dem":2186,
    "gn:feature_class":"P",
    "gn:feature_code":"PPLL",
    "gn:name":"Nyarugati",
    "gn:population":0,
    "gn:timezone":"Africa/Bujumbura",
    "iso:country":"BI",
    "wof:name":"Nyarugati",
    "wof:placetype":"locality"
},
  "geometry": {"coordinates":[29.467,-3.6452],"type":"Point"}
}