{
  "type": "Feature",
  "properties": {
    "gn:admin1_code":"20",
    "gn:asciiname":"Nyagahara",
    "gn:country_code":"BI",
    "gn:dem":1219,
    "gn:feature_class":"P",
    "gn:feature_code":"PPLL",
    "gn:name":"Nyagahara",
    "gn:population":0,
    "gn:timezone":"Africa/Bujumbura",
    "iso:country":"BI",
    "wof:name":"Nyagahara",
    "wof:placetype":"locality"
},
  "geometry": {"coordinates":[30.26,-3.6755],"type":"Point"}
}