{
  "type": "Feature",
  "properties": {
    "gn:admin1_code":"10",
    "gn:asciiname":"Ruhinga",
    "gn:country_code":"BI",
    "gn:dem":2153,
    "gn:feature_class":"P",
    "gn:feature_code":"PPLL",
    "gn:name":"Ruhinga",
    "gn:population":0,
    "gn:timezone":"Africa/Bujumbura",
    "iso:country":"BI",
    "wof:name":"Ruhinga",
    "wof:placetype":"locality"
},
  "geometry": {"coordinates":[29.6016,-3.691],"type":"Point"}
}