{
  "type": "Feature",
  "properties": {
    "gn:admin1_code":"21",
    "gn:asciiname":"Gasigati",
    "gn:country_code":"BI",
    "gn:dem":1449,
    "gn:feature_class":"P",
    "gn:feature_code":"PPLL",
    "gn:name":"Gasigati",
    "gn:population":0,
    "gn:timezone":"Africa/Bujumbura",
    "iso:country":"BI",
    "wof:name":"Gasigati",
    "wof:placetype":"locality"
},
  "geometry": {"coordinates":[30.0863,-3.3744],"type":"Point"}
}