{
  "type": "Feature",
  "properties": {
    "gn:admin1_code":"21",
    "gn:asciiname":"Muyange",
    "gn:country_code":"BI",
    "gn:dem":1530,
    "gn:feature_class":"P",
    "gn:feature_code":"PPLL",
    "gn:name":"Muyange",
    "gn:population":0,
    "gn:timezone":"Africa/Bujumbura",
    "iso:country":"BI",
    "name:run_x_preferred":[
        "Muyange"
    ],
    "wof:name":"Muyange",
    "wof:placetype":"locality"
},
  "geometry": {"coordinates":[30.1226,-3.3623],"type":"Point"}
}