{
  "type": "Feature",
  "properties": {
    "gn:admin1_code":"20",
    "gn:asciiname":"Kimina",
    "gn:country_code":"BI",
    "gn:dem":1564,
    "gn:feature_class":"P",
    "gn:feature_code":"PPLL",
    "gn:name":"Kimina",
    "gn:population":0,
    "gn:timezone":"Africa/Bujumbura",
    "iso:country":"BI",
    "wof:name":"Kimina",
    "wof:placetype":"locality"
},
  "geometry": {"coordinates":[30.0705,-3.8016],"type":"Point"}
}