{
  "type": "Feature",
  "properties": {
    "gn:admin1_code":"13",
    "gn:asciiname":"Buhinyuza",
    "gn:country_code":"BI",
    "gn:dem":1909,
    "gn:feature_class":"P",
    "gn:feature_code":"PPLL",
    "gn:name":"Buhinyuza",
    "gn:population":0,
    "gn:timezone":"Africa/Bujumbura",
    "iso:country":"BI",
    "wof:name":"Buhinyuza",
    "wof:placetype":"locality"
},
  "geometry": {"coordinates":[29.8817,-3.764],"type":"Point"}
}