{
  "type": "Feature",
  "properties": {
    "gn:admin1_code":"16.0",
    "gn:asciiname":"Mugongo",
    "gn:country_code":"BI",
    "gn:dem":1568,
    "gn:feature_class":"P",
    "gn:feature_code":"PPLL",
    "gn:name":"Mugongo",
    "gn:population":0,
    "gn:timezone":"Africa/Bujumbura",
    "iso:country":"BI",
    "wof:name":"Mugongo",
    "wof:placetype":"locality"
},
  "geometry": {"coordinates":[30.2982,-2.5129],"type":"Point"}
}