{
  "type": "Feature",
  "properties": {
    "gn:admin1_code":"23",
    "gn:asciiname":"Kiguruka",
    "gn:country_code":"BI",
    "gn:dem":1753,
    "gn:feature_class":"P",
    "gn:feature_code":"PPLL",
    "gn:name":"Kiguruka",
    "gn:population":0,
    "gn:timezone":"Africa/Bujumbura",
    "iso:country":"BI",
    "wof:name":"Kiguruka",
    "wof:placetype":"locality"
},
  "geometry": {"coordinates":[29.7955,-3.624],"type":"Point"}
}