{
  "type": "Feature",
  "properties": {
    "gn:admin1_code":"26",
    "gn:asciiname":"Rwaniro",
    "gn:country_code":"BI",
    "gn:dem":1500,
    "gn:feature_class":"P",
    "gn:feature_code":"PPLL",
    "gn:name":"Rwaniro",
    "gn:population":0,
    "gn:timezone":"Africa/Bujumbura",
    "iso:country":"BI",
    "wof:name":"Rwaniro",
    "wof:placetype":"locality"
},
  "geometry": {"coordinates":[29.4223,-3.8054],"type":"Point"}
}