{
  "type": "Feature",
  "properties": {
    "gn:admin1_code":"13",
    "gn:asciiname":"Buriza",
    "gn:country_code":"BI",
    "gn:dem":1950,
    "gn:feature_class":"P",
    "gn:feature_code":"PPLL",
    "gn:name":"Buriza",
    "gn:population":0,
    "gn:timezone":"Africa/Bujumbura",
    "iso:country":"BI",
    "wof:name":"Buriza",
    "wof:placetype":"locality"
},
  "geometry": {"coordinates":[29.869,-3.788],"type":"Point"}
}