{
  "type": "Feature",
  "properties": {
    "gn:admin1_code":"13",
    "gn:asciiname":"Mwaro Mavuvu",
    "gn:country_code":"BI",
    "gn:dem":1754,
    "gn:feature_class":"P",
    "gn:feature_code":"PPLL",
    "gn:name":"Mwaro Mavuvu",
    "gn:population":0,
    "gn:timezone":"Africa/Bujumbura",
    "iso:country":"BI",
    "wof:name":"Mwaro Mavuvu",
    "wof:placetype":"locality"
},
  "geometry": {"coordinates":[29.9759,-3.587],"type":"Point"}
}