{
  "type": "Feature",
  "properties": {
    "gn:admin1_code":"16.0",
    "gn:asciiname":"Cendajuru",
    "gn:country_code":"BI",
    "gn:dem":1655,
    "gn:feature_class":"P",
    "gn:feature_code":"PPLL",
    "gn:name":"Cendajuru",
    "gn:population":0,
    "gn:timezone":"Africa/Bujumbura",
    "iso:country":"BI",
    "wof:name":"Cendajuru",
    "wof:placetype":"locality"
},
  "geometry": {"coordinates":[30.1397,-2.6829],"type":"Point"}
}