{
  "type": "Feature",
  "properties": {
    "gn:admin1_code":"21",
    "gn:asciiname":"Bartye",
    "gn:country_code":"BI",
    "gn:dem":1625,
    "gn:feature_class":"P",
    "gn:feature_code":"PPLL",
    "gn:name":"Bartye",
    "gn:population":0,
    "gn:timezone":"Africa/Bujumbura",
    "iso:country":"BI",
    "wof:name":"Bartye",
    "wof:placetype":"locality"
},
  "geometry": {"coordinates":[30.1895,-3.5288],"type":"Point"}
}