{
  "type": "Feature",
  "properties": {
    "gn:admin1_code":"20",
    "gn:asciiname":"Bitare",
    "gn:country_code":"BI",
    "gn:dem":1226,
    "gn:feature_class":"P",
    "gn:feature_code":"PPLL",
    "gn:name":"Bitare",
    "gn:population":0,
    "gn:timezone":"Africa/Bujumbura",
    "iso:country":"BI",
    "wof:name":"Bitare",
    "wof:placetype":"locality"
},
  "geometry": {"coordinates":[30.2012,-3.8701],"type":"Point"}
}