{
  "type": "Feature",
  "properties": {
    "gn:admin1_code":"11",
    "gn:asciiname":"Rubango",
    "gn:country_code":"BI",
    "gn:dem":1350,
    "gn:feature_class":"P",
    "gn:feature_code":"PPLL",
    "gn:name":"Rubango",
    "gn:population":0,
    "gn:timezone":"Africa/Bujumbura",
    "iso:country":"BI",
    "wof:name":"Rubango",
    "wof:placetype":"locality"
},
  "geometry": {"coordinates":[30.6385,-3.2629],"type":"Point"}
}