{
  "type": "Feature",
  "properties": {
    "gn:admin1_code":"21",
    "gn:asciiname":"Nini",
    "gn:country_code":"BI",
    "gn:dem":1630,
    "gn:feature_class":"P",
    "gn:feature_code":"PPLL",
    "gn:name":"Nini",
    "gn:population":0,
    "gn:timezone":"Africa/Bujumbura",
    "iso:country":"BI",
    "name:ceb_x_preferred":[
        "Nini"
    ],
    "name:deu_x_preferred":[
        "Nini"
    ],
    "name:fra_x_preferred":[
        "Nini"
    ],
    "name:heb_x_preferred":[
        "\u05e0\u05d9\u05e0\u05d9"
    ],
    "name:ita_x_preferred":[
        "Nini"
    ],
    "name:nld_x_preferred":[
        "Nini"
    ],
    "name:rus_x_preferred":[
        "\u041d\u0438\u043d\u0438"
    ],
    "name:spa_x_preferred":[
        "Nini"
    ],
    "name:swe_x_preferred":[
        "Nini"
    ],
    "name:ukr_x_preferred":[
        "\u041d\u0456\u043d\u0456"
    ],
    "wof:name":"Nini",
    "wof:placetype":"locality"
},
  "geometry": {"coordinates":[30.1641,-3.5431],"type":"Point"}
}