{
  "type": "Feature",
  "properties": {
    "gn:admin1_code":"11.0",
    "gn:asciiname":"Mwenene",
    "gn:country_code":"BI",
    "gn:dem":1584,
    "gn:feature_class":"P",
    "gn:feature_code":"PPL",
    "gn:name":"Mwenene",
    "gn:population":0,
    "gn:timezone":"Africa/Bujumbura",
    "iso:country":"BI",
    "wof:name":"Mwenene",
    "wof:placetype":"locality"
},
  "geometry": {"coordinates":[30.48737,-3.15562],"type":"Point"}
}