{
  "type": "Feature",
  "properties": {
    "gn:admin1_code":"20.0",
    "gn:asciiname":"Jobe",
    "gn:country_code":"BI",
    "gn:dem":1834,
    "gn:feature_class":"P",
    "gn:feature_code":"PPLL",
    "gn:name":"Jobe",
    "gn:population":0,
    "gn:timezone":"Africa/Bujumbura",
    "iso:country":"BI",
    "name:deu_x_preferred":[
        "Jobe"
    ],
    "wof:name":"Jobe",
    "wof:placetype":"locality"
},
  "geometry": {"coordinates":[29.9723,-3.904],"type":"Point"}
}