{
  "type": "Feature",
  "properties": {
    "gn:admin1_code":"11",
    "gn:asciiname":"Rukwega",
    "gn:country_code":"BI",
    "gn:dem":1391,
    "gn:feature_class":"P",
    "gn:feature_code":"PPLL",
    "gn:name":"Rukwega",
    "gn:population":0,
    "gn:timezone":"Africa/Bujumbura",
    "iso:country":"BI",
    "wof:name":"Rukwega",
    "wof:placetype":"locality"
},
  "geometry": {"coordinates":[30.7468,-3.0717],"type":"Point"}
}