{
  "type": "Feature",
  "properties": {
    "gn:admin1_code":"12.0",
    "gn:asciiname":"Maranga",
    "gn:country_code":"BI",
    "gn:dem":1324,
    "gn:feature_class":"P",
    "gn:feature_code":"PPLL",
    "gn:name":"Maranga",
    "gn:population":0,
    "gn:timezone":"Africa/Bujumbura",
    "iso:country":"BI",
    "wof:name":"Maranga",
    "wof:placetype":"locality"
},
  "geometry": {"coordinates":[29.3387,-2.9937],"type":"Point"}
}