{
  "type": "Feature",
  "properties": {
    "gn:admin1_code":"12.0",
    "gn:asciiname":"Mpumyu",
    "gn:country_code":"BI",
    "gn:dem":857,
    "gn:feature_class":"P",
    "gn:feature_code":"PPLL",
    "gn:name":"Mpumyu",
    "gn:population":0,
    "gn:timezone":"Africa/Bujumbura",
    "iso:country":"BI",
    "wof:name":"Mpumyu",
    "wof:placetype":"locality"
},
  "geometry": {"coordinates":[29.2329,-2.975],"type":"Point"}
}