{
  "type": "Feature",
  "properties": {
    "gn:admin1_code":"11",
    "gn:asciiname":"Murore",
    "gn:country_code":"BI",
    "gn:dem":1851,
    "gn:feature_class":"P",
    "gn:feature_code":"PPL",
    "gn:name":"Murore",
    "gn:population":0,
    "gn:timezone":"Africa/Bujumbura",
    "iso:country":"BI",
    "wof:name":"Murore",
    "wof:placetype":"locality"
},
  "geometry": {"coordinates":[30.6631,-3.1871],"type":"Point"}
}