{
  "type": "Feature",
  "properties": {
    "gn:admin1_code":"14.0",
    "gn:asciiname":"Gikonko",
    "gn:country_code":"BI",
    "gn:dem":1636,
    "gn:feature_class":"P",
    "gn:feature_code":"PPLL",
    "gn:name":"Gikonko",
    "gn:population":0,
    "gn:timezone":"Africa/Bujumbura",
    "iso:country":"BI",
    "wof:name":"Gikonko",
    "wof:placetype":"locality"
},
  "geometry": {"coordinates":[30.1978,-2.9359],"type":"Point"}
}