{
  "type": "Feature",
  "properties": {
    "gn:admin1_code":"19.0",
    "gn:asciiname":"Mubanga",
    "gn:country_code":"BI",
    "gn:dem":1738,
    "gn:feature_class":"P",
    "gn:feature_code":"PPL",
    "gn:name":"Mubanga",
    "gn:population":0,
    "gn:timezone":"Africa/Bujumbura",
    "iso:country":"BI",
    "wof:name":"Mubanga",
    "wof:placetype":"locality"
},
  "geometry": {"coordinates":[29.9643,-2.9848],"type":"Point"}
}