{
  "type": "Feature",
  "properties": {
    "gn:admin1_code":"26",
    "gn:asciiname":"Mugara",
    "gn:country_code":"BI",
    "gn:dem":911,
    "gn:feature_class":"P",
    "gn:feature_code":"PPLL",
    "gn:name":"Mugara",
    "gn:population":0,
    "gn:timezone":"Africa/Bujumbura",
    "iso:country":"BI",
    "wof:name":"Mugara",
    "wof:placetype":"locality"
},
  "geometry": {"coordinates":[29.50528,-4.05838],"type":"Point"}
}