{
  "type": "Feature",
  "properties": {
    "gn:admin1_code":"20",
    "gn:asciiname":"Kibimba",
    "gn:country_code":"BI",
    "gn:dem":1250,
    "gn:feature_class":"P",
    "gn:feature_code":"PPLL",
    "gn:name":"Kibimba",
    "gn:population":0,
    "gn:timezone":"Africa/Bujumbura",
    "iso:country":"BI",
    "name:lug_x_preferred":[
        "Kibimba"
    ],
    "wof:name":"Kibimba",
    "wof:placetype":"locality"
},
  "geometry": {"coordinates":[30.2409,-3.6624],"type":"Point"}
}