{
  "type": "Feature",
  "properties": {
    "gn:admin1_code":"16.0",
    "gn:asciiname":"Gatare",
    "gn:country_code":"BI",
    "gn:dem":1626,
    "gn:feature_class":"P",
    "gn:feature_code":"PPLL",
    "gn:name":"Gatare",
    "gn:population":0,
    "gn:timezone":"Africa/Bujumbura",
    "iso:country":"BI",
    "wof:name":"Gatare",
    "wof:placetype":"locality"
},
  "geometry": {"coordinates":[30.0592,-2.6716],"type":"Point"}
}