{
  "type": "Feature",
  "properties": {
    "gn:admin1_code":"18.0",
    "gn:asciiname":"Bavumu",
    "gn:country_code":"BI",
    "gn:dem":1705,
    "gn:feature_class":"P",
    "gn:feature_code":"PPLL",
    "gn:name":"Bavumu",
    "gn:population":0,
    "gn:timezone":"Africa/Bujumbura",
    "iso:country":"BI",
    "wof:name":"Bavumu",
    "wof:placetype":"locality"
},
  "geometry": {"coordinates":[30.2294,-2.7937],"type":"Point"}
}