{
  "type": "Feature",
  "properties": {
    "gn:admin1_code":"18.0",
    "gn:asciiname":"Mugano",
    "gn:country_code":"BI",
    "gn:dem":1638,
    "gn:feature_class":"P",
    "gn:feature_code":"PPL",
    "gn:name":"Mugano",
    "gn:population":0,
    "gn:timezone":"Africa/Bujumbura",
    "iso:country":"BI",
    "wof:name":"Mugano",
    "wof:placetype":"locality"
},
  "geometry": {"coordinates":[30.2365,-3.1187],"type":"Point"}
}