{
  "type": "Feature",
  "properties": {
    "gn:admin1_code":"19.0",
    "gn:asciiname":"Ryirengeye",
    "gn:country_code":"BI",
    "gn:dem":1608,
    "gn:feature_class":"P",
    "gn:feature_code":"PPLL",
    "gn:name":"Ryirengeye",
    "gn:population":0,
    "gn:timezone":"Africa/Bujumbura",
    "iso:country":"BI",
    "wof:name":"Ryirengeye",
    "wof:placetype":"locality"
},
  "geometry": {"coordinates":[29.9507,-2.983],"type":"Point"}
}