{
  "type": "Feature",
  "properties": {
    "gn:admin1_code":"19.0",
    "gn:asciiname":"Vyuma",
    "gn:country_code":"BI",
    "gn:dem":1657,
    "gn:feature_class":"P",
    "gn:feature_code":"PPLL",
    "gn:name":"Vyuma",
    "gn:population":0,
    "gn:timezone":"Africa/Bujumbura",
    "iso:country":"BI",
    "wof:name":"Vyuma",
    "wof:placetype":"locality"
},
  "geometry": {"coordinates":[30.032,-2.7743],"type":"Point"}
}