{
  "type": "Feature",
  "properties": {
    "gn:admin1_code":"11.0",
    "gn:asciiname":"Minyare",
    "gn:country_code":"BI",
    "gn:dem":1629,
    "gn:feature_class":"P",
    "gn:feature_code":"PPL",
    "gn:name":"Minyare",
    "gn:population":0,
    "gn:timezone":"Africa/Bujumbura",
    "iso:country":"BI",
    "wof:name":"Minyare",
    "wof:placetype":"locality"
},
  "geometry": {"coordinates":[30.49092000000001,-3.22277],"type":"Point"}
}