{
  "type": "Feature",
  "properties": {
    "gn:admin1_code":"10",
    "gn:asciiname":"Mazinga",
    "gn:country_code":"BI",
    "gn:dem":1834,
    "gn:feature_class":"P",
    "gn:feature_code":"PPLL",
    "gn:name":"Mazinga",
    "gn:population":0,
    "gn:timezone":"Africa/Bujumbura",
    "iso:country":"BI",
    "wof:name":"Mazinga",
    "wof:placetype":"locality"
},
  "geometry": {"coordinates":[29.5663,-4.0962],"type":"Point"}
}