{
  "type": "Feature",
  "properties": {
    "gn:admin1_code":"17",
    "gn:asciiname":"Nyagatovu",
    "gn:country_code":"BI",
    "gn:dem":1950,
    "gn:feature_class":"P",
    "gn:feature_code":"PPLL",
    "gn:name":"Nyagatovu",
    "gn:population":0,
    "gn:timezone":"Africa/Bujumbura",
    "iso:country":"BI",
    "wof:name":"Nyagatovu",
    "wof:placetype":"locality"
},
  "geometry": {"coordinates":[29.7334,-4.1288],"type":"Point"}
}