{
  "type": "Feature",
  "properties": {
    "gn:admin1_code":"15.0",
    "gn:asciiname":"Sakariro",
    "gn:country_code":"BI",
    "gn:dem":1760,
    "gn:feature_class":"P",
    "gn:feature_code":"PPLL",
    "gn:name":"Sakariro",
    "gn:population":0,
    "gn:timezone":"Africa/Bujumbura",
    "iso:country":"BI",
    "wof:name":"Sakariro",
    "wof:placetype":"locality"
},
  "geometry": {"coordinates":[29.6311,-2.8143],"type":"Point"}
}