{
  "type": "Feature",
  "properties": {
    "gn:admin1_code":"19.0",
    "gn:asciiname":"Burenza",
    "gn:country_code":"BI",
    "gn:dem":1684,
    "gn:feature_class":"P",
    "gn:feature_code":"PPLL",
    "gn:name":"Burenza",
    "gn:population":0,
    "gn:timezone":"Africa/Bujumbura",
    "iso:country":"BI",
    "wof:name":"Burenza",
    "wof:placetype":"locality"
},
  "geometry": {"coordinates":[29.7758,-2.814],"type":"Point"}
}