{
  "type": "Feature",
  "properties": {
    "gn:admin1_code":"22",
    "gn:asciiname":"Samwinyo",
    "gn:country_code":"BI",
    "gn:dem":2045,
    "gn:feature_class":"P",
    "gn:feature_code":"PPLL",
    "gn:name":"Samwinyo",
    "gn:population":0,
    "gn:timezone":"Africa/Bujumbura",
    "iso:country":"BI",
    "wof:name":"Samwinyo",
    "wof:placetype":"locality"
},
  "geometry": {"coordinates":[29.6517,-3.4178],"type":"Point"}
}