{
  "type": "Feature",
  "properties": {
    "gn:admin1_code":"9.0",
    "gn:asciiname":"Rutake",
    "gn:country_code":"BI",
    "gn:dem":1597,
    "gn:feature_class":"P",
    "gn:feature_code":"PPLL",
    "gn:name":"Rutake",
    "gn:population":0,
    "gn:timezone":"Africa/Bujumbura",
    "iso:country":"BI",
    "wof:name":"Rutake",
    "wof:placetype":"locality"
},
  "geometry": {"coordinates":[29.4863,-3.1642],"type":"Point"}
}