{
  "type": "Feature",
  "properties": {
    "gn:admin1_code":"14.0",
    "gn:asciiname":"Rabiro",
    "gn:country_code":"BI",
    "gn:dem":1702,
    "gn:feature_class":"P",
    "gn:feature_code":"PPL",
    "gn:name":"Rabiro",
    "gn:population":0,
    "gn:timezone":"Africa/Bujumbura",
    "iso:country":"BI",
    "wof:name":"Rabiro",
    "wof:placetype":"locality"
},
  "geometry": {"coordinates":[30.1644,-3.2465],"type":"Point"}
}