{
  "type": "Feature",
  "properties": {
    "gn:admin1_code":"13",
    "gn:asciiname":"Kirambi",
    "gn:country_code":"BI",
    "gn:dem":1858,
    "gn:feature_class":"P",
    "gn:feature_code":"PPLL",
    "gn:name":"Kirambi",
    "gn:population":0,
    "gn:timezone":"Africa/Bujumbura",
    "iso:country":"BI",
    "wof:name":"Kirambi",
    "wof:placetype":"locality"
},
  "geometry": {"coordinates":[29.7553,-3.6292],"type":"Point"}
}