{
  "type": "Feature",
  "properties": {
    "gn:admin1_code":"10",
    "gn:asciiname":"Gihoro",
    "gn:country_code":"BI",
    "gn:dem":2018,
    "gn:feature_class":"P",
    "gn:feature_code":"PPL",
    "gn:name":"Gihoro",
    "gn:population":0,
    "gn:timezone":"Africa/Bujumbura",
    "iso:country":"BI",
    "wof:name":"Gihoro",
    "wof:placetype":"locality"
},
  "geometry": {"coordinates":[29.6117,-3.8709],"type":"Point"}
}