{
  "type": "Feature",
  "properties": {
    "gn:admin1_code":"21",
    "gn:asciiname":"Muriza",
    "gn:country_code":"BI",
    "gn:dem":1624,
    "gn:feature_class":"P",
    "gn:feature_code":"PPLL",
    "gn:name":"Muriza",
    "gn:population":0,
    "gn:timezone":"Africa/Bujumbura",
    "iso:country":"BI",
    "name:und_x_variant":[
        "Mulidza",
        "Muliza",
        "Muriza"
    ],
    "wof:name":"Muriza",
    "wof:placetype":"locality"
},
  "geometry": {"coordinates":[30.1373,-3.5764],"type":"Point"}
}