{
  "type": "Feature",
  "properties": {
    "gn:admin1_code":"19.0",
    "gn:asciiname":"Rwamiko",
    "gn:country_code":"BI",
    "gn:dem":1666,
    "gn:feature_class":"P",
    "gn:feature_code":"PPLL",
    "gn:name":"Rwamiko",
    "gn:population":0,
    "gn:timezone":"Africa/Bujumbura",
    "iso:country":"BI",
    "wof:name":"Rwamiko",
    "wof:placetype":"locality"
},
  "geometry": {"coordinates":[29.8874,-3.0356],"type":"Point"}
}