{
  "type": "Feature",
  "properties": {
    "gn:admin1_code":"23",
    "gn:asciiname":"Buburu",
    "gn:country_code":"BI",
    "gn:dem":2057,
    "gn:feature_class":"P",
    "gn:feature_code":"PPLL",
    "gn:name":"Buburu",
    "gn:population":0,
    "gn:timezone":"Africa/Bujumbura",
    "iso:country":"BI",
    "wof:name":"Buburu",
    "wof:placetype":"locality"
},
  "geometry": {"coordinates":[29.6834,-3.5526],"type":"Point"}
}