{
  "type": "Feature",
  "properties": {
    "gn:admin1_code":"16.0",
    "gn:asciiname":"Gashoka",
    "gn:country_code":"BI",
    "gn:dem":1419,
    "gn:feature_class":"P",
    "gn:feature_code":"PPLL",
    "gn:name":"Gashoka",
    "gn:population":0,
    "gn:timezone":"Africa/Bujumbura",
    "iso:country":"BI",
    "wof:name":"Gashoka",
    "wof:placetype":"locality"
},
  "geometry": {"coordinates":[30.1594,-2.5379],"type":"Point"}
}