{
  "type": "Feature",
  "properties": {
    "gn:admin1_code":"13",
    "gn:asciiname":"Murangara",
    "gn:country_code":"BI",
    "gn:dem":1631,
    "gn:feature_class":"P",
    "gn:feature_code":"PPLL",
    "gn:name":"Murangara",
    "gn:population":0,
    "gn:timezone":"Africa/Bujumbura",
    "iso:country":"BI",
    "wof:name":"Murangara",
    "wof:placetype":"locality"
},
  "geometry": {"coordinates":[29.8649,-3.4356],"type":"Point"}
}