{
  "type": "Feature",
  "properties": {
    "gn:admin1_code":"21",
    "gn:asciiname":"Kinombe",
    "gn:country_code":"BI",
    "gn:dem":1522,
    "gn:feature_class":"P",
    "gn:feature_code":"PPL",
    "gn:name":"Kinombe",
    "gn:population":0,
    "gn:timezone":"Africa/Bujumbura",
    "iso:country":"BI",
    "wof:name":"Kinombe",
    "wof:placetype":"locality"
},
  "geometry": {"coordinates":[30.31921,-3.31436],"type":"Point"}
}