{
  "type": "Feature",
  "properties": {
    "gn:admin1_code":"13",
    "gn:asciiname":"Kirima",
    "gn:country_code":"BI",
    "gn:dem":1623,
    "gn:feature_class":"P",
    "gn:feature_code":"PPLL",
    "gn:name":"Kirima",
    "gn:population":0,
    "gn:timezone":"Africa/Bujumbura",
    "iso:country":"BI",
    "wof:name":"Kirima",
    "wof:placetype":"locality"
},
  "geometry": {"coordinates":[29.9067,-3.2838],"type":"Point"}
}