{
  "type": "Feature",
  "properties": {
    "gn:admin1_code":"0.0",
    "gn:asciiname":"Gwanira",
    "gn:country_code":"BI",
    "gn:dem":985,
    "gn:feature_class":"P",
    "gn:feature_code":"PPL",
    "gn:name":"Gwanira",
    "gn:population":0,
    "gn:timezone":"Africa/Bujumbura",
    "iso:country":"BI",
    "wof:name":"Gwanira",
    "wof:placetype":"locality"
},
  "geometry": {"coordinates":[29.1375,-2.8375],"type":"Point"}
}