{
  "type": "Feature",
  "properties": {
    "gn:admin1_code":"19.0",
    "gn:asciiname":"Kidobori",
    "gn:country_code":"BI",
    "gn:dem":1430,
    "gn:feature_class":"P",
    "gn:feature_code":"PPLL",
    "gn:name":"Kidobori",
    "gn:population":0,
    "gn:timezone":"Africa/Bujumbura",
    "iso:country":"BI",
    "wof:name":"Kidobori",
    "wof:placetype":"locality"
},
  "geometry": {"coordinates":[29.9356,-2.6878],"type":"Point"}
}