{
  "type": "Feature",
  "properties": {
    "gn:admin1_code":"19.0",
    "gn:asciiname":"Giheta",
    "gn:country_code":"BI",
    "gn:dem":1419,
    "gn:feature_class":"P",
    "gn:feature_code":"PPL",
    "gn:name":"Giheta",
    "gn:population":0,
    "gn:timezone":"Africa/Bujumbura",
    "iso:country":"BI",
    "wof:name":"Giheta",
    "wof:placetype":"locality"
},
  "geometry": {"coordinates":[29.9694,-2.7229],"type":"Point"}
}