{
  "type": "Feature",
  "properties": {
    "gn:admin1_code":"15.0",
    "gn:asciiname":"Macorwe",
    "gn:country_code":"BI",
    "gn:dem":2058,
    "gn:feature_class":"P",
    "gn:feature_code":"PPLL",
    "gn:name":"Macorwe",
    "gn:population":0,
    "gn:timezone":"Africa/Bujumbura",
    "iso:country":"BI",
    "wof:name":"Macorwe",
    "wof:placetype":"locality"
},
  "geometry": {"coordinates":[29.5991,-3.1046],"type":"Point"}
}