{
  "type": "Feature",
  "properties": {
    "gn:admin1_code":"19.0",
    "gn:asciiname":"Rumbaga",
    "gn:country_code":"BI",
    "gn:dem":1601,
    "gn:feature_class":"P",
    "gn:feature_code":"PPLL",
    "gn:name":"Rumbaga",
    "gn:population":0,
    "gn:timezone":"Africa/Bujumbura",
    "iso:country":"BI",
    "wof:name":"Rumbaga",
    "wof:placetype":"locality"
},
  "geometry": {"coordinates":[29.7056,-2.8776],"type":"Point"}
}