{
  "type": "Feature",
  "properties": {
    "gn:admin1_code":"11",
    "gn:asciiname":"Bugendajoro",
    "gn:country_code":"BI",
    "gn:dem":1623,
    "gn:feature_class":"P",
    "gn:feature_code":"PPL",
    "gn:name":"Bugendajoro",
    "gn:population":0,
    "gn:timezone":"Africa/Bujumbura",
    "iso:country":"BI",
    "wof:name":"Bugendajoro",
    "wof:placetype":"locality"
},
  "geometry": {"coordinates":[30.6155,-3.0313],"type":"Point"}
}