{
  "type": "Feature",
  "properties": {
    "gn:admin1_code":"14.0",
    "gn:asciiname":"Gahanga",
    "gn:country_code":"BI",
    "gn:dem":1652,
    "gn:feature_class":"P",
    "gn:feature_code":"PPLL",
    "gn:name":"Gahanga",
    "gn:population":0,
    "gn:timezone":"Africa/Bujumbura",
    "iso:country":"BI",
    "wof:name":"Gahanga",
    "wof:placetype":"locality"
},
  "geometry": {"coordinates":[30.0883,-2.999],"type":"Point"}
}