{
  "type": "Feature",
  "properties": {
    "gn:admin1_code":"21",
    "gn:asciiname":"Nyamyumba",
    "gn:country_code":"BI",
    "gn:dem":1588,
    "gn:feature_class":"P",
    "gn:feature_code":"PPLL",
    "gn:name":"Nyamyumba",
    "gn:population":0,
    "gn:timezone":"Africa/Bujumbura",
    "iso:country":"BI",
    "wof:name":"Nyamyumba",
    "wof:placetype":"locality"
},
  "geometry": {"coordinates":[30.13,-3.5592],"type":"Point"}
}