{
  "type": "Feature",
  "properties": {
    "gn:admin1_code":"20",
    "gn:asciiname":"Mugondo",
    "gn:country_code":"BI",
    "gn:dem":1273,
    "gn:feature_class":"P",
    "gn:feature_code":"PPLL",
    "gn:name":"Mugondo",
    "gn:population":0,
    "gn:timezone":"Africa/Bujumbura",
    "iso:country":"BI",
    "wof:name":"Mugondo",
    "wof:placetype":"locality"
},
  "geometry": {"coordinates":[30.1854,-3.662],"type":"Point"}
}