{
  "type": "Feature",
  "properties": {
    "gn:admin1_code":"21",
    "gn:asciiname":"Kaniro",
    "gn:country_code":"BI",
    "gn:dem":1270,
    "gn:feature_class":"P",
    "gn:feature_code":"PPL",
    "gn:name":"Kaniro",
    "gn:population":0,
    "gn:timezone":"Africa/Bujumbura",
    "iso:country":"BI",
    "wof:name":"Kaniro",
    "wof:placetype":"locality"
},
  "geometry": {"coordinates":[30.39895,-3.49035],"type":"Point"}
}