{
  "type": "Feature",
  "properties": {
    "gn:admin1_code":"15.0",
    "gn:asciiname":"Kibayi",
    "gn:country_code":"BI",
    "gn:dem":1753,
    "gn:feature_class":"P",
    "gn:feature_code":"PPLL",
    "gn:name":"Kibayi",
    "gn:population":0,
    "gn:timezone":"Africa/Bujumbura",
    "iso:country":"BI",
    "wof:name":"Kibayi",
    "wof:placetype":"locality"
},
  "geometry": {"coordinates":[29.709,-2.9542],"type":"Point"}
}