{
  "type": "Feature",
  "properties": {
    "gn:admin1_code":"21",
    "gn:asciiname":"Gifunzo",
    "gn:country_code":"BI",
    "gn:dem":1351,
    "gn:feature_class":"P",
    "gn:feature_code":"PPLL",
    "gn:name":"Gifunzo",
    "gn:population":0,
    "gn:timezone":"Africa/Bujumbura",
    "iso:country":"BI",
    "wof:name":"Gifunzo",
    "wof:placetype":"locality"
},
  "geometry": {"coordinates":[30.4935,-3.504],"type":"Point"}
}