{
  "type": "Feature",
  "properties": {
    "gn:admin1_code":"10",
    "gn:asciiname":"Murehe",
    "gn:country_code":"BI",
    "gn:dem":1968,
    "gn:feature_class":"P",
    "gn:feature_code":"PPL",
    "gn:name":"Murehe",
    "gn:population":0,
    "gn:timezone":"Africa/Bujumbura",
    "iso:country":"BI",
    "name:run_x_preferred":[
        "Murehe"
    ],
    "wof:name":"Murehe",
    "wof:placetype":"locality"
},
  "geometry": {"coordinates":[29.7124,-4.0284],"type":"Point"}
}