{
  "type": "Feature",
  "properties": {
    "gn:admin1_code":"11.0",
    "gn:asciiname":"Rusange",
    "gn:country_code":"BI",
    "gn:dem":1626,
    "gn:feature_class":"P",
    "gn:feature_code":"PPL",
    "gn:name":"Rusange",
    "gn:population":0,
    "gn:timezone":"Africa/Bujumbura",
    "iso:country":"BI",
    "wof:name":"Rusange",
    "wof:placetype":"locality"
},
  "geometry": {"coordinates":[30.4885,-3.0712],"type":"Point"}
}