{
  "type": "Feature",
  "properties": {
    "gn:admin1_code":"10",
    "gn:asciiname":"Maramuya",
    "gn:country_code":"BI",
    "gn:dem":1857,
    "gn:feature_class":"P",
    "gn:feature_code":"PPLL",
    "gn:name":"Maramuya",
    "gn:population":0,
    "gn:timezone":"Africa/Bujumbura",
    "iso:country":"BI",
    "wof:name":"Maramuya",
    "wof:placetype":"locality"
},
  "geometry": {"coordinates":[29.7632,-3.6661],"type":"Point"}
}