{
  "type": "Feature",
  "properties": {
    "gn:admin1_code":"15.0",
    "gn:asciiname":"Kabuga",
    "gn:country_code":"BI",
    "gn:dem":1761,
    "gn:feature_class":"P",
    "gn:feature_code":"PPL",
    "gn:name":"Kabuga",
    "gn:population":0,
    "gn:timezone":"Africa/Bujumbura",
    "iso:country":"BI",
    "wof:name":"Kabuga",
    "wof:placetype":"locality"
},
  "geometry": {"coordinates":[29.72898,-3.08358],"type":"Point"}
}