{
  "type": "Feature",
  "properties": {
    "gn:admin1_code":"18.0",
    "gn:asciiname":"Gahama",
    "gn:country_code":"BI",
    "gn:dem":1467,
    "gn:feature_class":"P",
    "gn:feature_code":"PPLL",
    "gn:name":"Gahama",
    "gn:population":0,
    "gn:timezone":"Africa/Bujumbura",
    "iso:country":"BI",
    "wof:name":"Gahama",
    "wof:placetype":"locality"
},
  "geometry": {"coordinates":[30.4793,-2.4667],"type":"Point"}
}