{
  "type": "Feature",
  "properties": {
    "gn:admin1_code":"25",
    "gn:asciiname":"Mpinga",
    "gn:country_code":"BI",
    "gn:dem":1777,
    "gn:feature_class":"P",
    "gn:feature_code":"PPLL",
    "gn:name":"Mpinga",
    "gn:population":0,
    "gn:timezone":"Africa/Bujumbura",
    "iso:country":"BI",
    "wof:name":"Mpinga",
    "wof:placetype":"locality"
},
  "geometry": {"coordinates":[29.4586,-3.365],"type":"Point"}
}