{
  "type": "Feature",
  "properties": {
    "gn:admin1_code":"13",
    "gn:asciiname":"Karambi",
    "gn:country_code":"BI",
    "gn:dem":1728,
    "gn:feature_class":"P",
    "gn:feature_code":"PPLL",
    "gn:name":"Karambi",
    "gn:population":0,
    "gn:timezone":"Africa/Bujumbura",
    "iso:country":"BI",
    "wof:name":"Karambi",
    "wof:placetype":"locality"
},
  "geometry": {"coordinates":[29.862,-3.6875],"type":"Point"}
}