{
  "type": "Feature",
  "properties": {
    "gn:admin1_code":"10",
    "gn:asciiname":"Muramba",
    "gn:country_code":"BI",
    "gn:dem":2144,
    "gn:feature_class":"P",
    "gn:feature_code":"PPLL",
    "gn:name":"Muramba",
    "gn:population":0,
    "gn:timezone":"Africa/Bujumbura",
    "iso:country":"BI",
    "wof:name":"Muramba",
    "wof:placetype":"locality"
},
  "geometry": {"coordinates":[29.5937,-3.6679],"type":"Point"}
}