{
  "type": "Feature",
  "properties": {
    "gn:admin1_code":"25",
    "gn:asciiname":"Gomvyi",
    "gn:country_code":"BI",
    "gn:dem":1597,
    "gn:feature_class":"P",
    "gn:feature_code":"PPLL",
    "gn:name":"Gomvyi",
    "gn:population":0,
    "gn:timezone":"Africa/Bujumbura",
    "iso:country":"BI",
    "wof:name":"Gomvyi",
    "wof:placetype":"locality"
},
  "geometry": {"coordinates":[29.4064,-3.5538],"type":"Point"}
}