{
  "type": "Feature",
  "properties": {
    "gn:admin1_code":"9.0",
    "gn:asciiname":"Ruvuruga",
    "gn:country_code":"BI",
    "gn:dem":1341,
    "gn:feature_class":"P",
    "gn:feature_code":"PPLL",
    "gn:name":"Ruvuruga",
    "gn:population":0,
    "gn:timezone":"Africa/Bujumbura",
    "iso:country":"BI",
    "wof:name":"Ruvuruga",
    "wof:placetype":"locality"
},
  "geometry": {"coordinates":[29.4662,-3.193],"type":"Point"}
}