{
  "type": "Feature",
  "properties": {
    "gn:admin1_code":"20",
    "gn:asciiname":"Kwitaba",
    "gn:country_code":"BI",
    "gn:dem":2022,
    "gn:feature_class":"P",
    "gn:feature_code":"PPLL",
    "gn:name":"Kwitaba",
    "gn:population":0,
    "gn:timezone":"Africa/Bujumbura",
    "iso:country":"BI",
    "wof:name":"Kwitaba",
    "wof:placetype":"locality"
},
  "geometry": {"coordinates":[30.1408,-3.8626],"type":"Point"}
}