{
  "type": "Feature",
  "properties": {
    "gn:admin1_code":"20",
    "gn:asciiname":"Nyakabanda",
    "gn:country_code":"BI",
    "gn:dem":1400,
    "gn:feature_class":"P",
    "gn:feature_code":"PPLL",
    "gn:name":"Nyakabanda",
    "gn:population":0,
    "gn:timezone":"Africa/Bujumbura",
    "iso:country":"BI",
    "wof:name":"Nyakabanda",
    "wof:placetype":"locality"
},
  "geometry": {"coordinates":[30.061,-3.9044],"type":"Point"}
}