{
  "type": "Feature",
  "properties": {
    "gn:admin1_code":"13",
    "gn:asciiname":"Rwintamba",
    "gn:country_code":"BI",
    "gn:dem":1664,
    "gn:feature_class":"P",
    "gn:feature_code":"PPLL",
    "gn:name":"Rwintamba",
    "gn:population":0,
    "gn:timezone":"Africa/Bujumbura",
    "iso:country":"BI",
    "wof:name":"Rwintamba",
    "wof:placetype":"locality"
},
  "geometry": {"coordinates":[29.9103,-3.5828],"type":"Point"}
}