{
  "type": "Feature",
  "properties": {
    "gn:admin1_code":"13",
    "gn:asciiname":"Kwinzero",
    "gn:country_code":"BI",
    "gn:dem":1724,
    "gn:feature_class":"P",
    "gn:feature_code":"PPLL",
    "gn:name":"Kwinzero",
    "gn:population":0,
    "gn:timezone":"Africa/Bujumbura",
    "iso:country":"BI",
    "wof:name":"Kwinzero",
    "wof:placetype":"locality"
},
  "geometry": {"coordinates":[29.8662,-3.6789],"type":"Point"}
}