{
  "type": "Feature",
  "properties": {
    "gn:admin1_code":"17.0",
    "gn:asciiname":"Rukonwe",
    "gn:country_code":"BI",
    "gn:dem":1486,
    "gn:feature_class":"P",
    "gn:feature_code":"PPLL",
    "gn:name":"Rukonwe",
    "gn:population":0,
    "gn:timezone":"Africa/Bujumbura",
    "iso:country":"BI",
    "wof:name":"Rukonwe",
    "wof:placetype":"locality"
},
  "geometry": {"coordinates":[29.7369,-4.276],"type":"Point"}
}