{
  "type": "Feature",
  "properties": {
    "gn:admin1_code":"18.0",
    "gn:asciiname":"Nonwe",
    "gn:country_code":"BI",
    "gn:dem":1491,
    "gn:feature_class":"P",
    "gn:feature_code":"PPLL",
    "gn:name":"Nonwe",
    "gn:population":0,
    "gn:timezone":"Africa/Bujumbura",
    "iso:country":"BI",
    "wof:name":"Nonwe",
    "wof:placetype":"locality"
},
  "geometry": {"coordinates":[30.4131,-2.5082],"type":"Point"}
}