{
  "type": "Feature",
  "properties": {
    "gn:admin1_code":"10",
    "gn:asciiname":"Nyagishiha",
    "gn:country_code":"BI",
    "gn:dem":2414,
    "gn:feature_class":"P",
    "gn:feature_code":"PPLL",
    "gn:name":"Nyagishiha",
    "gn:population":0,
    "gn:timezone":"Africa/Bujumbura",
    "iso:country":"BI",
    "wof:name":"Nyagishiha",
    "wof:placetype":"locality"
},
  "geometry": {"coordinates":[29.5381,-3.6619],"type":"Point"}
}