{
  "type": "Feature",
  "properties": {
    "gn:admin1_code":"21",
    "gn:asciiname":"Butaganzwa",
    "gn:country_code":"BI",
    "gn:dem":1596,
    "gn:feature_class":"P",
    "gn:feature_code":"PPL",
    "gn:name":"Butaganzwa",
    "gn:population":0,
    "gn:timezone":"Africa/Bujumbura",
    "iso:country":"BI",
    "wof:name":"Butaganzwa",
    "wof:placetype":"locality"
},
  "geometry": {"coordinates":[30.1404,-3.5676],"type":"Point"}
}