{
  "type": "Feature",
  "properties": {
    "gn:admin1_code":"16.0",
    "gn:asciiname":"Carubambo",
    "gn:country_code":"BI",
    "gn:dem":1479,
    "gn:feature_class":"P",
    "gn:feature_code":"PPL",
    "gn:name":"Carubambo",
    "gn:population":0,
    "gn:timezone":"Africa/Bujumbura",
    "iso:country":"BI",
    "wof:name":"Carubambo",
    "wof:placetype":"locality"
},
  "geometry": {"coordinates":[29.9649,-2.5625],"type":"Point"}
}