{
  "type": "Feature",
  "properties": {
    "gn:admin1_code":"18.0",
    "gn:asciiname":"Bunywana",
    "gn:country_code":"BI",
    "gn:dem":1485,
    "gn:feature_class":"P",
    "gn:feature_code":"PPLL",
    "gn:name":"Bunywana",
    "gn:population":0,
    "gn:timezone":"Africa/Bujumbura",
    "iso:country":"BI",
    "wof:name":"Bunywana",
    "wof:placetype":"locality"
},
  "geometry": {"coordinates":[30.3709,-2.7415],"type":"Point"}
}