{
  "type": "Feature",
  "properties": {
    "gn:admin1_code":"13",
    "gn:asciiname":"Nyamweru",
    "gn:country_code":"BI",
    "gn:dem":1645,
    "gn:feature_class":"P",
    "gn:feature_code":"PPLL",
    "gn:name":"Nyamweru",
    "gn:population":0,
    "gn:timezone":"Africa/Bujumbura",
    "iso:country":"BI",
    "wof:name":"Nyamweru",
    "wof:placetype":"locality"
},
  "geometry": {"coordinates":[29.9457,-3.3435],"type":"Point"}
}