{
  "type": "Feature",
  "properties": {
    "gn:admin1_code":"25",
    "gn:asciiname":"Kwigere",
    "gn:country_code":"BI",
    "gn:dem":1438,
    "gn:feature_class":"P",
    "gn:feature_code":"PPLL",
    "gn:name":"Kwigere",
    "gn:population":0,
    "gn:timezone":"Africa/Bujumbura",
    "iso:country":"BI",
    "wof:name":"Kwigere",
    "wof:placetype":"locality"
},
  "geometry": {"coordinates":[29.4535,-3.3519],"type":"Point"}
}