{
  "type": "Feature",
  "properties": {
    "gn:admin1_code":"16.0",
    "gn:asciiname":"Rubuga",
    "gn:country_code":"BI",
    "gn:dem":1416,
    "gn:feature_class":"P",
    "gn:feature_code":"PPL",
    "gn:name":"Rubuga",
    "gn:population":0,
    "gn:timezone":"Africa/Bujumbura",
    "iso:country":"BI",
    "wof:name":"Rubuga",
    "wof:placetype":"locality"
},
  "geometry": {"coordinates":[30.0378,-2.3829],"type":"Point"}
}