{
  "type": "Feature",
  "properties": {
    "gn:admin1_code":"12.0",
    "gn:asciiname":"Rurinzi",
    "gn:country_code":"BI",
    "gn:dem":1626,
    "gn:feature_class":"P",
    "gn:feature_code":"PPL",
    "gn:name":"Rurinzi",
    "gn:population":0,
    "gn:timezone":"Africa/Bujumbura",
    "iso:country":"BI",
    "wof:name":"Rurinzi",
    "wof:placetype":"locality"
},
  "geometry": {"coordinates":[29.24303,-2.67009],"type":"Point"}
}