{
  "type": "Feature",
  "properties": {
    "gn:admin1_code":"17",
    "gn:asciiname":"Gasanda",
    "gn:country_code":"BI",
    "gn:dem":1565,
    "gn:feature_class":"P",
    "gn:feature_code":"PPLL",
    "gn:name":"Gasanda",
    "gn:population":0,
    "gn:timezone":"Africa/Bujumbura",
    "iso:country":"BI",
    "name:run_x_preferred":[
        "Gasanda"
    ],
    "wof:name":"Gasanda",
    "wof:placetype":"locality"
},
  "geometry": {"coordinates":[29.8166,-4.3084],"type":"Point"}
}