{
  "type": "Feature",
  "properties": {
    "gn:admin1_code":"13",
    "gn:asciiname":"Musenga",
    "gn:country_code":"BI",
    "gn:dem":1844,
    "gn:feature_class":"P",
    "gn:feature_code":"PPLL",
    "gn:name":"Musenga",
    "gn:population":0,
    "gn:timezone":"Africa/Bujumbura",
    "iso:country":"BI",
    "wof:name":"Musenga",
    "wof:placetype":"locality"
},
  "geometry": {"coordinates":[29.8953,-3.6404],"type":"Point"}
}