{
  "type": "Feature",
  "properties": {
    "gn:admin1_code":"19.0",
    "gn:asciiname":"Nyagasebeyi",
    "gn:country_code":"BI",
    "gn:dem":1595,
    "gn:feature_class":"P",
    "gn:feature_code":"PPLL",
    "gn:name":"Nyagasebeyi",
    "gn:population":0,
    "gn:timezone":"Africa/Bujumbura",
    "iso:country":"BI",
    "wof:name":"Nyagasebeyi",
    "wof:placetype":"locality"
},
  "geometry": {"coordinates":[30.013,-2.9571],"type":"Point"}
}