{
  "type": "Feature",
  "properties": {
    "gn:admin1_code":"19.0",
    "gn:asciiname":"Mubuga",
    "gn:country_code":"BI",
    "gn:dem":1644,
    "gn:feature_class":"P",
    "gn:feature_code":"PPLL",
    "gn:name":"Mubuga",
    "gn:population":0,
    "gn:timezone":"Africa/Bujumbura",
    "iso:country":"BI",
    "wof:name":"Mubuga",
    "wof:placetype":"locality"
},
  "geometry": {"coordinates":[29.8643,-2.9579],"type":"Point"}
}