{
  "type": "Feature",
  "properties": {
    "gn:admin1_code":"13",
    "gn:asciiname":"Gatega",
    "gn:country_code":"BI",
    "gn:dem":1703,
    "gn:feature_class":"P",
    "gn:feature_code":"PPLL",
    "gn:name":"Gatega",
    "gn:population":0,
    "gn:timezone":"Africa/Bujumbura",
    "iso:country":"BI",
    "wof:name":"Gatega",
    "wof:placetype":"locality"
},
  "geometry": {"coordinates":[29.8061,-3.5455],"type":"Point"}
}