{
  "type": "Feature",
  "properties": {
    "gn:admin1_code":"17",
    "gn:asciiname":"Mpinga",
    "gn:country_code":"BI",
    "gn:dem":1927,
    "gn:feature_class":"P",
    "gn:feature_code":"PPLL",
    "gn:name":"Mpinga",
    "gn:population":0,
    "gn:timezone":"Africa/Bujumbura",
    "iso:country":"BI",
    "wof:name":"Mpinga",
    "wof:placetype":"locality"
},
  "geometry": {"coordinates":[29.7513,-4.0487],"type":"Point"}
}