{
  "type": "Feature",
  "properties": {
    "gn:admin1_code":"20",
    "gn:asciiname":"Gisuma",
    "gn:country_code":"BI",
    "gn:dem":1477,
    "gn:feature_class":"P",
    "gn:feature_code":"PPLL",
    "gn:name":"Gisuma",
    "gn:population":0,
    "gn:timezone":"Africa/Bujumbura",
    "iso:country":"BI",
    "wof:name":"Gisuma",
    "wof:placetype":"locality"
},
  "geometry": {"coordinates":[30.0748,-3.8318],"type":"Point"}
}