{
  "type": "Feature",
  "properties": {
    "gn:admin1_code":"9.0",
    "gn:asciiname":"Rambwe",
    "gn:country_code":"BI",
    "gn:dem":849,
    "gn:feature_class":"P",
    "gn:feature_code":"PPLL",
    "gn:name":"Rambwe",
    "gn:population":0,
    "gn:timezone":"Africa/Bujumbura",
    "iso:country":"BI",
    "name:run_x_preferred":[
        "Rambwe"
    ],
    "wof:name":"Rambwe",
    "wof:placetype":"locality"
},
  "geometry": {"coordinates":[29.3887,-3.1607],"type":"Point"}
}