{
  "type": "Feature",
  "properties": {
    "gn:admin1_code":"22.0",
    "gn:asciiname":"Rwuya",
    "gn:country_code":"BI",
    "gn:dem":1880,
    "gn:feature_class":"P",
    "gn:feature_code":"PPLL",
    "gn:name":"Rwuya",
    "gn:population":0,
    "gn:timezone":"Africa/Bujumbura",
    "iso:country":"BI",
    "wof:name":"Rwuya",
    "wof:placetype":"locality"
},
  "geometry": {"coordinates":[29.6755,-3.2466],"type":"Point"}
}