{
  "type": "Feature",
  "properties": {
    "gn:admin1_code":"16.0",
    "gn:asciiname":"Nciri",
    "gn:country_code":"BI",
    "gn:dem":1460,
    "gn:feature_class":"P",
    "gn:feature_code":"PPL",
    "gn:name":"Nciri",
    "gn:population":0,
    "gn:timezone":"Africa/Bujumbura",
    "iso:country":"BI",
    "wof:name":"Nciri",
    "wof:placetype":"locality"
},
  "geometry": {"coordinates":[30.1751,-2.4986],"type":"Point"}
}