{
  "type": "Feature",
  "properties": {
    "gn:admin1_code":"13",
    "gn:asciiname":"Bungere",
    "gn:country_code":"BI",
    "gn:dem":1708,
    "gn:feature_class":"P",
    "gn:feature_code":"PPLL",
    "gn:name":"Bungere",
    "gn:population":0,
    "gn:timezone":"Africa/Bujumbura",
    "iso:country":"BI",
    "wof:name":"Bungere",
    "wof:placetype":"locality"
},
  "geometry": {"coordinates":[29.9886,-3.5195],"type":"Point"}
}