{
  "type": "Feature",
  "properties": {
    "gn:admin1_code":"13",
    "gn:asciiname":"Muhororo",
    "gn:country_code":"BI",
    "gn:dem":1721,
    "gn:feature_class":"P",
    "gn:feature_code":"PPLL",
    "gn:name":"Muhororo",
    "gn:population":0,
    "gn:timezone":"Africa/Bujumbura",
    "iso:country":"BI",
    "wof:name":"Muhororo",
    "wof:placetype":"locality"
},
  "geometry": {"coordinates":[29.8524,-3.5608],"type":"Point"}
}