{
  "type": "Feature",
  "properties": {
    "gn:admin1_code":"20.0",
    "gn:asciiname":"Gitaba",
    "gn:country_code":"BI",
    "gn:dem":1656,
    "gn:feature_class":"P",
    "gn:feature_code":"PPL",
    "gn:name":"Gitaba",
    "gn:population":0,
    "gn:timezone":"Africa/Bujumbura",
    "iso:country":"BI",
    "wof:name":"Gitaba",
    "wof:placetype":"locality"
},
  "geometry": {"coordinates":[29.96948,-3.87284],"type":"Point"}
}