{
  "type": "Feature",
  "properties": {
    "gn:admin1_code":"10",
    "gn:asciiname":"Vyuya",
    "gn:country_code":"BI",
    "gn:dem":1854,
    "gn:feature_class":"P",
    "gn:feature_code":"PPL",
    "gn:name":"Vyuya",
    "gn:population":0,
    "gn:timezone":"Africa/Bujumbura",
    "iso:country":"BI",
    "wof:name":"Vyuya",
    "wof:placetype":"locality"
},
  "geometry": {"coordinates":[29.6599,-3.7062],"type":"Point"}
}