{
  "type": "Feature",
  "properties": {
    "gn:admin1_code":"22",
    "gn:asciiname":"Kanyami",
    "gn:country_code":"BI",
    "gn:dem":1936,
    "gn:feature_class":"P",
    "gn:feature_code":"PPLL",
    "gn:name":"Kanyami",
    "gn:population":0,
    "gn:timezone":"Africa/Bujumbura",
    "iso:country":"BI",
    "wof:name":"Kanyami",
    "wof:placetype":"locality"
},
  "geometry": {"coordinates":[29.6483,-3.3674],"type":"Point"}
}