{
  "type": "Feature",
  "properties": {
    "gn:admin1_code":"14",
    "gn:asciiname":"Kigo",
    "gn:country_code":"BI",
    "gn:dem":1576,
    "gn:feature_class":"P",
    "gn:feature_code":"PPLL",
    "gn:name":"Kigo",
    "gn:population":0,
    "gn:timezone":"Africa/Bujumbura",
    "iso:country":"BI",
    "name:deu_x_preferred":[
        "Kigo"
    ],
    "name:epo_x_preferred":[
        "Kigo"
    ],
    "name:fra_x_preferred":[
        "Kigo"
    ],
    "name:hrv_x_preferred":[
        "Kigo"
    ],
    "name:hun_x_preferred":[
        "Kigo"
    ],
    "name:ltz_x_preferred":[
        "Kigo"
    ],
    "name:nld_x_preferred":[
        "Kigo"
    ],
    "name:pan_x_preferred":[
        "\u0a15\u0a40\u0a17\u0a4b"
    ],
    "name:pol_x_preferred":[
        "Kigo"
    ],
    "name:rus_x_preferred":[
        "\u041a\u0438\u0433\u043e"
    ],
    "name:spa_x_preferred":[
        "Kigo"
    ],
    "name:und_x_variant":[
        "Mukigo",
        "Kigo"
    ],
    "wof:name":"Kigo",
    "wof:placetype":"locality"
},
  "geometry": {"coordinates":[30.0492,-3.3341],"type":"Point"}
}