{
  "type": "Feature",
  "properties": {
    "gn:admin1_code":"22",
    "gn:asciiname":"Nyakarambi",
    "gn:country_code":"BI",
    "gn:dem":1716,
    "gn:feature_class":"P",
    "gn:feature_code":"PPLL",
    "gn:name":"Nyakarambi",
    "gn:population":0,
    "gn:timezone":"Africa/Bujumbura",
    "iso:country":"BI",
    "wof:name":"Nyakarambi",
    "wof:placetype":"locality"
},
  "geometry": {"coordinates":[29.7702,-3.3286],"type":"Point"}
}