{
  "type": "Feature",
  "properties": {
    "gn:admin1_code":"20",
    "gn:asciiname":"Nkurye",
    "gn:country_code":"BI",
    "gn:dem":1193,
    "gn:feature_class":"P",
    "gn:feature_code":"PPLL",
    "gn:name":"Nkurye",
    "gn:population":0,
    "gn:timezone":"Africa/Bujumbura",
    "iso:country":"BI",
    "wof:name":"Nkurye",
    "wof:placetype":"locality"
},
  "geometry": {"coordinates":[30.26139,-3.78143],"type":"Point"}
}