{
  "type": "Feature",
  "properties": {
    "gn:admin1_code":"22",
    "gn:asciiname":"Kizenga",
    "gn:country_code":"BI",
    "gn:dem":1999,
    "gn:feature_class":"P",
    "gn:feature_code":"PPLL",
    "gn:name":"Kizenga",
    "gn:population":0,
    "gn:timezone":"Africa/Bujumbura",
    "iso:country":"BI",
    "name:por_x_preferred":[
        "Kizenga"
    ],
    "wof:name":"Kizenga",
    "wof:placetype":"locality"
},
  "geometry": {"coordinates":[29.6347,-3.3667],"type":"Point"}
}