{
  "type": "Feature",
  "properties": {
    "gn:admin1_code":"13",
    "gn:asciiname":"Ndago",
    "gn:country_code":"BI",
    "gn:dem":1745,
    "gn:feature_class":"P",
    "gn:feature_code":"PPLL",
    "gn:name":"Ndago",
    "gn:population":0,
    "gn:timezone":"Africa/Bujumbura",
    "iso:country":"BI",
    "wof:name":"Ndago",
    "wof:placetype":"locality"
},
  "geometry": {"coordinates":[29.9219,-3.8116],"type":"Point"}
}