{
  "type": "Feature",
  "properties": {
    "gn:admin1_code":"19.0",
    "gn:asciiname":"Masama-Buhiga",
    "gn:country_code":"BI",
    "gn:dem":1719,
    "gn:feature_class":"P",
    "gn:feature_code":"PPLL",
    "gn:name":"Masama-Buhiga",
    "gn:population":0,
    "gn:timezone":"Africa/Bujumbura",
    "iso:country":"BI",
    "name:und_x_variant":[
        "Masama",
        "Buhiga"
    ],
    "wof:name":"Masama-Buhiga",
    "wof:placetype":"locality"
},
  "geometry": {"coordinates":[29.768,-2.9077],"type":"Point"}
}