{
  "type": "Feature",
  "properties": {
    "gn:admin1_code":"19.0",
    "gn:asciiname":"Muramvya",
    "gn:country_code":"BI",
    "gn:dem":1591,
    "gn:feature_class":"P",
    "gn:feature_code":"PPL",
    "gn:name":"Muramvya",
    "gn:population":0,
    "gn:timezone":"Africa/Bujumbura",
    "iso:country":"BI",
    "wof:name":"Muramvya",
    "wof:placetype":"locality"
},
  "geometry": {"coordinates":[30.1265,-2.942],"type":"Point"}
}