{
  "type": "Feature",
  "properties": {
    "gn:admin1_code":"19.0",
    "gn:asciiname":"Muramvya",
    "gn:country_code":"BI",
    "gn:dem":1591,
    "gn:feature_class":"P",
    "gn:feature_code":"PPL",
    "gn:name":"Muramvya",
    "gn:population":0,
    "gn:timezone":"Africa/Bujumbura",
    "iso:country":"BI",
    "name:ara_x_preferred":[
        "\u0645\u0648\u0631\u0627\u0645\u0641\u064a\u0627"
    ],
    "name:azb_x_preferred":[
        "\u0645\u0648\u0631\u0627\u0645\u0648\u06cc\u0627"
    ],
    "name:ceb_x_preferred":[
        "Muramvya"
    ],
    "name:deu_x_preferred":[
        "Muramvya"
    ],
    "name:ell_x_preferred":[
        "\u039c\u03bf\u03c5\u03c1\u03ac\u03bc\u03b2\u03b9\u03b1"
    ],
    "name:fas_x_preferred":[
        "\u0645\u0648\u0631\u0627\u0645\u0648\u06cc\u0627"
    ],
    "name:fra_x_preferred":[
        "Muramvya"
    ],
    "name:frr_x_preferred":[
        "Muramvya"
    ],
    "name:hye_x_preferred":[
        "\u0544\u0578\u0582\u0580\u0561\u0574\u057e\u0575\u0561"
    ],
    "name:ita_x_preferred":[
        "Muramvya"
    ],
    "name:nld_x_preferred":[
        "Muramvya"
    ],
    "name:pol_x_preferred":[
        "Muramvya"
    ],
    "name:ron_x_preferred":[
        "Muramvya"
    ],
    "name:run_x_preferred":[
        "Muramvya"
    ],
    "name:rus_x_preferred":[
        "\u041c\u0443\u0440\u0430\u043c\u0432\u044c\u044f"
    ],
    "name:spa_x_preferred":[
        "Muramvya"
    ],
    "name:swa_x_preferred":[
        "Muramvya"
    ],
    "name:swe_x_preferred":[
        "Muramvya"
    ],
    "name:ukr_x_preferred":[
        "\u041c\u0443\u0440\u0430\u043c\u0432\u0456\u044f"
    ],
    "name:urd_x_preferred":[
        "\u0645\u0648\u0631\u0627\u0645\u0648\u06cc\u0627"
    ],
    "name:zho_x_preferred":[
        "\u7a46\u62c9\u59c6\u7ef4\u4e9a"
    ],
    "wof:name":"Muramvya",
    "wof:placetype":"locality"
},
  "geometry": {"coordinates":[30.1265,-2.942],"type":"Point"}
}