{
  "type": "Feature",
  "properties": {
    "gn:admin1_code":"13",
    "gn:asciiname":"Nyamurenge",
    "gn:country_code":"BI",
    "gn:dem":1812,
    "gn:feature_class":"P",
    "gn:feature_code":"PPLL",
    "gn:name":"Nyamurenge",
    "gn:population":0,
    "gn:timezone":"Africa/Bujumbura",
    "iso:country":"BI",
    "wof:name":"Nyamurenge",
    "wof:placetype":"locality"
},
  "geometry": {"coordinates":[29.9531,-3.6265],"type":"Point"}
}