{
  "type": "Feature",
  "properties": {
    "gn:admin1_code":"15.0",
    "gn:asciiname":"Rwintare",
    "gn:country_code":"BI",
    "gn:dem":1977,
    "gn:feature_class":"P",
    "gn:feature_code":"PPLL",
    "gn:name":"Rwintare",
    "gn:population":0,
    "gn:timezone":"Africa/Bujumbura",
    "iso:country":"BI",
    "name:und_x_variant":[
        "Rwintabe",
        "Rwintare"
    ],
    "wof:name":"Rwintare",
    "wof:placetype":"locality"
},
  "geometry": {"coordinates":[29.6197,-2.8967],"type":"Point"}
}