{
  "type": "Feature",
  "properties": {
    "gn:admin1_code":"10",
    "gn:asciiname":"Rushemeza",
    "gn:country_code":"BI",
    "gn:dem":1903,
    "gn:feature_class":"P",
    "gn:feature_code":"PPLL",
    "gn:name":"Rushemeza",
    "gn:population":0,
    "gn:timezone":"Africa/Bujumbura",
    "iso:country":"BI",
    "wof:name":"Rushemeza",
    "wof:placetype":"locality"
},
  "geometry": {"coordinates":[29.7339,-3.9259],"type":"Point"}
}