{
  "type": "Feature",
  "properties": {
    "gn:admin1_code":"13",
    "gn:asciiname":"Kirinzi",
    "gn:country_code":"BI",
    "gn:dem":1895,
    "gn:feature_class":"P",
    "gn:feature_code":"PPLL",
    "gn:name":"Kirinzi",
    "gn:population":0,
    "gn:timezone":"Africa/Bujumbura",
    "iso:country":"BI",
    "wof:name":"Kirinzi",
    "wof:placetype":"locality"
},
  "geometry": {"coordinates":[29.8777,-3.7716],"type":"Point"}
}