{
  "type": "Feature",
  "properties": {
    "gn:admin1_code":"14.0",
    "gn:asciiname":"Ntatemwa",
    "gn:country_code":"BI",
    "gn:dem":1553,
    "gn:feature_class":"P",
    "gn:feature_code":"PPL",
    "gn:name":"Ntatemwa",
    "gn:population":0,
    "gn:timezone":"Africa/Bujumbura",
    "iso:country":"BI",
    "wof:name":"Ntatemwa",
    "wof:placetype":"locality"
},
  "geometry": {"coordinates":[30.1412,-3.07184],"type":"Point"}
}