{
  "type": "Feature",
  "properties": {
    "gn:admin1_code":"21",
    "gn:asciiname":"Kwisumo",
    "gn:country_code":"BI",
    "gn:dem":1550,
    "gn:feature_class":"P",
    "gn:feature_code":"PPL",
    "gn:name":"Kwisumo",
    "gn:population":0,
    "gn:timezone":"Africa/Bujumbura",
    "iso:country":"BI",
    "wof:name":"Kwisumo",
    "wof:placetype":"locality"
},
  "geometry": {"coordinates":[30.2689,-3.3627],"type":"Point"}
}