{
  "type": "Feature",
  "properties": {
    "gn:admin1_code":"25",
    "gn:asciiname":"Gisagara",
    "gn:country_code":"BI",
    "gn:dem":1544,
    "gn:feature_class":"P",
    "gn:feature_code":"PPLL",
    "gn:name":"Gisagara",
    "gn:population":0,
    "gn:timezone":"Africa/Bujumbura",
    "iso:country":"BI",
    "wof:name":"Gisagara",
    "wof:placetype":"locality"
},
  "geometry": {"coordinates":[29.4798,-3.2755],"type":"Point"}
}