{
  "type": "Feature",
  "properties": {
    "gn:admin1_code":"18.0",
    "gn:asciiname":"Kigwena",
    "gn:country_code":"BI",
    "gn:dem":1641,
    "gn:feature_class":"P",
    "gn:feature_code":"PPLL",
    "gn:name":"Kigwena",
    "gn:population":0,
    "gn:timezone":"Africa/Bujumbura",
    "iso:country":"BI",
    "wof:name":"Kigwena",
    "wof:placetype":"locality"
},
  "geometry": {"coordinates":[30.1616,-2.7381],"type":"Point"}
}