{
  "type": "Feature",
  "properties": {
    "gn:admin1_code":"25",
    "gn:asciiname":"Kinonko",
    "gn:country_code":"BI",
    "gn:dem":2015,
    "gn:feature_class":"P",
    "gn:feature_code":"PPL",
    "gn:name":"Kinonko",
    "gn:population":0,
    "gn:timezone":"Africa/Bujumbura",
    "iso:country":"BI",
    "wof:name":"Kinonko",
    "wof:placetype":"locality"
},
  "geometry": {"coordinates":[29.4716,-3.5377],"type":"Point"}
}