{
  "type": "Feature",
  "properties": {
    "gn:admin1_code":"21",
    "gn:asciiname":"Kavumwe",
    "gn:country_code":"BI",
    "gn:dem":1400,
    "gn:feature_class":"P",
    "gn:feature_code":"PPLL",
    "gn:name":"Kavumwe",
    "gn:population":0,
    "gn:timezone":"Africa/Bujumbura",
    "iso:country":"BI",
    "wof:name":"Kavumwe",
    "wof:placetype":"locality"
},
  "geometry": {"coordinates":[30.5739,-3.441],"type":"Point"}
}