{
  "type": "Feature",
  "properties": {
    "gn:admin1_code":"13",
    "gn:asciiname":"Maremba",
    "gn:country_code":"BI",
    "gn:dem":1543,
    "gn:feature_class":"P",
    "gn:feature_code":"PPLL",
    "gn:name":"Maremba",
    "gn:population":0,
    "gn:timezone":"Africa/Bujumbura",
    "iso:country":"BI",
    "wof:name":"Maremba",
    "wof:placetype":"locality"
},
  "geometry": {"coordinates":[30.0448,-3.4012],"type":"Point"}
}