{
  "type": "Feature",
  "properties": {
    "gn:admin1_code":"20",
    "gn:asciiname":"Gihofi",
    "gn:country_code":"BI",
    "gn:dem":1285,
    "gn:feature_class":"P",
    "gn:feature_code":"PPLL",
    "gn:name":"Gihofi",
    "gn:population":0,
    "gn:timezone":"Africa/Bujumbura",
    "iso:country":"BI",
    "name:run_x_preferred":[
        "Gihofi"
    ],
    "name:und_x_variant":[
        "Kiofi"
    ],
    "wof:name":"Gihofi",
    "wof:placetype":"locality"
},
  "geometry": {"coordinates":[30.1154,-4.0226],"type":"Point"}
}