{
  "type": "Feature",
  "properties": {
    "gn:admin1_code":"10",
    "gn:asciiname":"Nanira",
    "gn:country_code":"BI",
    "gn:dem":1938,
    "gn:feature_class":"P",
    "gn:feature_code":"PPLL",
    "gn:name":"Nanira",
    "gn:population":0,
    "gn:timezone":"Africa/Bujumbura",
    "iso:country":"BI",
    "wof:name":"Nanira",
    "wof:placetype":"locality"
},
  "geometry": {"coordinates":[29.6563,-3.9215],"type":"Point"}
}