{
  "type": "Feature",
  "properties": {
    "gn:admin1_code":"13",
    "gn:asciiname":"Gisoro",
    "gn:country_code":"BI",
    "gn:dem":1723,
    "gn:feature_class":"P",
    "gn:feature_code":"PPLL",
    "gn:name":"Gisoro",
    "gn:population":0,
    "gn:timezone":"Africa/Bujumbura",
    "iso:country":"BI",
    "wof:name":"Gisoro",
    "wof:placetype":"locality"
},
  "geometry": {"coordinates":[30.0172,-3.6458],"type":"Point"}
}