{
  "type": "Feature",
  "properties": {
    "gn:admin1_code":"17",
    "gn:asciiname":"Jongwe",
    "gn:country_code":"BI",
    "gn:dem":1846,
    "gn:feature_class":"P",
    "gn:feature_code":"PPLL",
    "gn:name":"Jongwe",
    "gn:population":0,
    "gn:timezone":"Africa/Bujumbura",
    "iso:country":"BI",
    "name:und_x_variant":[
        "Jungwe"
    ],
    "wof:name":"Jongwe",
    "wof:placetype":"locality"
},
  "geometry": {"coordinates":[29.6957,-4.1144],"type":"Point"}
}