{
  "type": "Feature",
  "properties": {
    "gn:admin1_code":"13",
    "gn:asciiname":"Kigarama",
    "gn:country_code":"BI",
    "gn:dem":1674,
    "gn:feature_class":"P",
    "gn:feature_code":"PPLL",
    "gn:name":"Kigarama",
    "gn:population":0,
    "gn:timezone":"Africa/Bujumbura",
    "iso:country":"BI",
    "wof:name":"Kigarama",
    "wof:placetype":"locality"
},
  "geometry": {"coordinates":[29.8241,-3.2989],"type":"Point"}
}