{
  "type": "Feature",
  "properties": {
    "gn:admin1_code":"15.0",
    "gn:asciiname":"Gasenyi",
    "gn:country_code":"BI",
    "gn:dem":1671,
    "gn:feature_class":"P",
    "gn:feature_code":"PPL",
    "gn:name":"Gasenyi",
    "gn:population":0,
    "gn:timezone":"Africa/Bujumbura",
    "iso:country":"BI",
    "wof:name":"Gasenyi",
    "wof:placetype":"locality"
},
  "geometry": {"coordinates":[29.7565,-3.1215],"type":"Point"}
}