{
  "type": "Feature",
  "properties": {
    "gn:admin1_code":"18.0",
    "gn:asciiname":"Ruyivyi",
    "gn:country_code":"BI",
    "gn:dem":1489,
    "gn:feature_class":"P",
    "gn:feature_code":"PPLL",
    "gn:name":"Ruyivyi",
    "gn:population":0,
    "gn:timezone":"Africa/Bujumbura",
    "iso:country":"BI",
    "wof:name":"Ruyivyi",
    "wof:placetype":"locality"
},
  "geometry": {"coordinates":[30.386,-2.7618],"type":"Point"}
}