{
  "type": "Feature",
  "properties": {
    "gn:admin1_code":"9.0",
    "gn:asciiname":"Mugombarima",
    "gn:country_code":"BI",
    "gn:dem":1086,
    "gn:feature_class":"P",
    "gn:feature_code":"PPLL",
    "gn:name":"Mugombarima",
    "gn:population":0,
    "gn:timezone":"Africa/Bujumbura",
    "iso:country":"BI",
    "wof:name":"Mugombarima",
    "wof:placetype":"locality"
},
  "geometry": {"coordinates":[29.4114,-3.1162],"type":"Point"}
}