{
  "type": "Feature",
  "properties": {
    "gn:admin1_code":"9.0",
    "gn:asciiname":"Kinyasheshe",
    "gn:country_code":"BI",
    "gn:dem":1659,
    "gn:feature_class":"P",
    "gn:feature_code":"PPLL",
    "gn:name":"Kinyasheshe",
    "gn:population":0,
    "gn:timezone":"Africa/Bujumbura",
    "iso:country":"BI",
    "name:run_x_preferred":[
        "Kinyasheshe"
    ],
    "wof:name":"Kinyasheshe",
    "wof:placetype":"locality"
},
  "geometry": {"coordinates":[29.5045,-3.1987],"type":"Point"}
}