{
  "type": "Feature",
  "properties": {
    "gn:admin1_code":"20",
    "gn:asciiname":"Kabingo",
    "gn:country_code":"BI",
    "gn:dem":1655,
    "gn:feature_class":"P",
    "gn:feature_code":"PPLL",
    "gn:name":"Kabingo",
    "gn:population":0,
    "gn:timezone":"Africa/Bujumbura",
    "iso:country":"BI",
    "wof:name":"Kabingo",
    "wof:placetype":"locality"
},
  "geometry": {"coordinates":[30.0888,-3.8562],"type":"Point"}
}