{
  "type": "Feature",
  "properties": {
    "gn:admin1_code":"19.0",
    "gn:asciiname":"Ruramb",
    "gn:country_code":"BI",
    "gn:dem":1657,
    "gn:feature_class":"P",
    "gn:feature_code":"PPLL",
    "gn:name":"Ruramb",
    "gn:population":0,
    "gn:timezone":"Africa/Bujumbura",
    "iso:country":"BI",
    "wof:name":"Ruramb",
    "wof:placetype":"locality"
},
  "geometry": {"coordinates":[30.0274,-2.7624],"type":"Point"}
}