{
  "type": "Feature",
  "properties": {
    "gn:admin1_code":"19.0",
    "gn:asciiname":"Musenyi",
    "gn:country_code":"BI",
    "gn:dem":1706,
    "gn:feature_class":"P",
    "gn:feature_code":"PPL",
    "gn:name":"Musenyi",
    "gn:population":0,
    "gn:timezone":"Africa/Bujumbura",
    "iso:country":"BI",
    "name:run_x_preferred":[
        "Musenyi"
    ],
    "wof:name":"Musenyi",
    "wof:placetype":"locality"
},
  "geometry": {"coordinates":[30.0357,-2.952],"type":"Point"}
}