{
  "type": "Feature",
  "properties": {
    "gn:admin1_code":"22.0",
    "gn:asciiname":"Teza",
    "gn:country_code":"BI",
    "gn:dem":2125,
    "gn:feature_class":"P",
    "gn:feature_code":"PPL",
    "gn:name":"Teza",
    "gn:population":0,
    "gn:timezone":"Africa/Bujumbura",
    "iso:country":"BI",
    "name:ceb_x_preferred":[
        "Teza"
    ],
    "name:deu_x_preferred":[
        "Teza"
    ],
    "name:fra_x_preferred":[
        "Teza"
    ],
    "name:rus_x_preferred":[
        "\u0422\u0435\u0437\u0430"
    ],
    "name:swe_x_preferred":[
        "Teza"
    ],
    "wof:name":"Teza",
    "wof:placetype":"locality"
},
  "geometry": {"coordinates":[29.5636,-3.2158],"type":"Point"}
}