{
  "type": "Feature",
  "properties": {
    "gn:admin1_code":"21",
    "gn:asciiname":"Rusagamba",
    "gn:country_code":"BI",
    "gn:dem":1629,
    "gn:feature_class":"P",
    "gn:feature_code":"PPLL",
    "gn:name":"Rusagamba",
    "gn:population":0,
    "gn:timezone":"Africa/Bujumbura",
    "iso:country":"BI",
    "wof:name":"Rusagamba",
    "wof:placetype":"locality"
},
  "geometry": {"coordinates":[30.1967,-3.4878],"type":"Point"}
}