{
  "type": "Feature",
  "properties": {
    "gn:admin1_code":"19.0",
    "gn:asciiname":"Gitega",
    "gn:country_code":"BI",
    "gn:dem":1597,
    "gn:feature_class":"P",
    "gn:feature_code":"PPLL",
    "gn:name":"Gitega",
    "gn:population":0,
    "gn:timezone":"Africa/Bujumbura",
    "iso:country":"BI",
    "wof:name":"Gitega",
    "wof:placetype":"locality"
},
  "geometry": {"coordinates":[30.1284,-2.8576],"type":"Point"}
}