{
  "type": "Feature",
  "properties": {
    "gn:admin1_code":"25",
    "gn:asciiname":"Martyazo",
    "gn:country_code":"BI",
    "gn:dem":1450,
    "gn:feature_class":"P",
    "gn:feature_code":"PPL",
    "gn:name":"Martyazo",
    "gn:population":0,
    "gn:timezone":"Africa/Bujumbura",
    "iso:country":"BI",
    "wof:name":"Martyazo",
    "wof:placetype":"locality"
},
  "geometry": {"coordinates":[29.4548,-3.2809],"type":"Point"}
}