{
  "type": "Feature",
  "properties": {
    "gn:admin1_code":"17",
    "gn:asciiname":"Gishiha",
    "gn:country_code":"BI",
    "gn:dem":1848,
    "gn:feature_class":"P",
    "gn:feature_code":"PPL",
    "gn:name":"Gishiha",
    "gn:population":0,
    "gn:timezone":"Africa/Bujumbura",
    "iso:country":"BI",
    "name:und_x_variant":[
        "Gishita",
        "Gishiha"
    ],
    "wof:name":"Gishiha",
    "wof:placetype":"locality"
},
  "geometry": {"coordinates":[29.7092,-4.1067],"type":"Point"}
}