{
  "type": "Feature",
  "properties": {
    "gn:admin1_code":"11",
    "gn:asciiname":"Nyabobo",
    "gn:country_code":"BI",
    "gn:dem":1645,
    "gn:feature_class":"P",
    "gn:feature_code":"PPLL",
    "gn:name":"Nyabobo",
    "gn:population":0,
    "gn:timezone":"Africa/Bujumbura",
    "iso:country":"BI",
    "name:und_x_variant":[
        "Nyankoba",
        "Nyabobo"
    ],
    "wof:name":"Nyabobo",
    "wof:placetype":"locality"
},
  "geometry": {"coordinates":[30.7899,-3.1882],"type":"Point"}
}