{
  "type": "Feature",
  "properties": {
    "gn:admin1_code":"15.0",
    "gn:asciiname":"Banga",
    "gn:country_code":"BI",
    "gn:dem":2073,
    "gn:feature_class":"P",
    "gn:feature_code":"PPLL",
    "gn:name":"Banga",
    "gn:population":0,
    "gn:timezone":"Africa/Bujumbura",
    "iso:country":"BI",
    "wof:name":"Banga",
    "wof:placetype":"locality"
},
  "geometry": {"coordinates":[29.6444,-3.1334],"type":"Point"}
}