{
  "type": "Feature",
  "properties": {
    "gn:admin1_code":"16.0",
    "gn:asciiname":"Mutarishwa",
    "gn:country_code":"BI",
    "gn:dem":1595,
    "gn:feature_class":"P",
    "gn:feature_code":"PPLL",
    "gn:name":"Mutarishwa",
    "gn:population":0,
    "gn:timezone":"Africa/Bujumbura",
    "iso:country":"BI",
    "wof:name":"Mutarishwa",
    "wof:placetype":"locality"
},
  "geometry": {"coordinates":[30.3026,-2.6288],"type":"Point"}
}