{
  "type": "Feature",
  "properties": {
    "gn:admin1_code":"17",
    "gn:asciiname":"Sampeke",
    "gn:country_code":"BI",
    "gn:dem":1404,
    "gn:feature_class":"P",
    "gn:feature_code":"PPLL",
    "gn:name":"Sampeke",
    "gn:population":0,
    "gn:timezone":"Africa/Bujumbura",
    "iso:country":"BI",
    "wof:name":"Sampeke",
    "wof:placetype":"locality"
},
  "geometry": {"coordinates":[29.9545,-4.1899],"type":"Point"}
}