{
  "type": "Feature",
  "properties": {
    "gn:admin1_code":"16.0",
    "gn:asciiname":"Rwinago",
    "gn:country_code":"BI",
    "gn:dem":1703,
    "gn:feature_class":"P",
    "gn:feature_code":"PPLL",
    "gn:name":"Rwinago",
    "gn:population":0,
    "gn:timezone":"Africa/Bujumbura",
    "iso:country":"BI",
    "wof:name":"Rwinago",
    "wof:placetype":"locality"
},
  "geometry": {"coordinates":[30.1479,-2.6598],"type":"Point"}
}