{
  "type": "Feature",
  "properties": {
    "gn:admin1_code":"19.0",
    "gn:asciiname":"Butare",
    "gn:country_code":"BI",
    "gn:dem":1587,
    "gn:feature_class":"P",
    "gn:feature_code":"PPLL",
    "gn:name":"Butare",
    "gn:population":0,
    "gn:timezone":"Africa/Bujumbura",
    "iso:country":"BI",
    "wof:name":"Butare",
    "wof:placetype":"locality"
},
  "geometry": {"coordinates":[29.9969,-2.8783],"type":"Point"}
}