{
  "type": "Feature",
  "properties": {
    "gn:admin1_code":"19.0",
    "gn:asciiname":"Butare",
    "gn:country_code":"BI",
    "gn:dem":1587,
    "gn:feature_class":"P",
    "gn:feature_code":"PPLL",
    "gn:name":"Butare",
    "gn:population":0,
    "gn:timezone":"Africa/Bujumbura",
    "iso:country":"BI",
    "name:afr_x_preferred":[
        "Butare"
    ],
    "name:azb_x_preferred":[
        "\u0628\u0648\u062a\u06cc\u0631"
    ],
    "name:aze_x_preferred":[
        "Butare"
    ],
    "name:bos_x_preferred":[
        "Butare"
    ],
    "name:cat_x_preferred":[
        "Butare"
    ],
    "name:ces_x_preferred":[
        "Butar\u00e9"
    ],
    "name:dan_x_preferred":[
        "Butare"
    ],
    "name:deu_x_preferred":[
        "Butare"
    ],
    "name:ell_x_preferred":[
        "\u039c\u03c0\u03bf\u03c5\u03c4\u03ac\u03c1\u03b5"
    ],
    "name:est_x_preferred":[
        "Butare"
    ],
    "name:eus_x_preferred":[
        "Butare"
    ],
    "name:fas_x_preferred":[
        "\u0628\u0648\u062a\u06cc\u0631"
    ],
    "name:fra_x_preferred":[
        "Butare"
    ],
    "name:grn_x_preferred":[
        "Mbut\u00e1re"
    ],
    "name:heb_x_preferred":[
        "\u05d1\u05d5\u05d8\u05e8\u05d4"
    ],
    "name:hrv_x_preferred":[
        "Huye"
    ],
    "name:hun_x_preferred":[
        "Butare"
    ],
    "name:ile_x_preferred":[
        "Butare"
    ],
    "name:ita_x_preferred":[
        "Butare"
    ],
    "name:jpn_x_preferred":[
        "\u30d6\u30bf\u30ec"
    ],
    "name:kor_x_preferred":[
        "\ubd80\ud0c0\ub808"
    ],
    "name:lav_x_preferred":[
        "Butare"
    ],
    "name:lit_x_preferred":[
        "Butar\u0117"
    ],
    "name:mrj_x_preferred":[
        "\u0411\u0443\u0442\u0430\u0440\u0435"
    ],
    "name:nld_x_preferred":[
        "Butare"
    ],
    "name:pol_x_preferred":[
        "Butare"
    ],
    "name:por_x_preferred":[
        "Butare"
    ],
    "name:rus_x_preferred":[
        "\u0411\u0443\u0442\u0430\u0440\u0435"
    ],
    "name:sin_x_preferred":[
        "\u0db6\u0dd4\u0dad\u0dcf\u0dbb\u0dda \u0db1\u0d9c\u0dbb\u0dba"
    ],
    "name:spa_x_preferred":[
        "Butare"
    ],
    "name:srp_x_preferred":[
        "\u0411\u0443\u0442\u0430\u0440\u0435"
    ],
    "name:swe_x_preferred":[
        "Butare"
    ],
    "name:szl_x_preferred":[
        "Butare"
    ],
    "name:tur_x_preferred":[
        "Butare"
    ],
    "name:ukr_x_preferred":[
        "\u0411\u0443\u0442\u0430\u0440\u0435"
    ],
    "name:urd_x_preferred":[
        "\u0628\u0648\u062a\u0627\u0631\u06d2"
    ],
    "name:zho_x_preferred":[
        "\u5e03\u5854\u96f7\u5e02"
    ],
    "wof:name":"Butare",
    "wof:placetype":"locality"
},
  "geometry": {"coordinates":[29.9969,-2.8783],"type":"Point"}
}