{
  "type": "Feature",
  "properties": {
    "gn:admin1_code":"20.0",
    "gn:asciiname":"Nkati",
    "gn:country_code":"BI",
    "gn:dem":1955,
    "gn:feature_class":"P",
    "gn:feature_code":"PPLL",
    "gn:name":"Nkati",
    "gn:population":0,
    "gn:timezone":"Africa/Bujumbura",
    "iso:country":"BI",
    "wof:name":"Nkati",
    "wof:placetype":"locality"
},
  "geometry": {"coordinates":[29.907,-3.8643],"type":"Point"}
}