{
  "type": "Feature",
  "properties": {
    "gn:admin1_code":"12.0",
    "gn:asciiname":"Ngoma",
    "gn:country_code":"BI",
    "gn:dem":1135,
    "gn:feature_class":"P",
    "gn:feature_code":"PPLL",
    "gn:name":"Ngoma",
    "gn:population":0,
    "gn:timezone":"Africa/Bujumbura",
    "iso:country":"BI",
    "name:bar_x_preferred":[
        "Ngoma"
    ],
    "name:ceb_x_preferred":[
        "Ngoma"
    ],
    "name:deu_x_preferred":[
        "Ngoma"
    ],
    "name:est_x_preferred":[
        "Ngoma"
    ],
    "name:fra_x_preferred":[
        "Ngoma"
    ],
    "name:ita_x_preferred":[
        "Ngoma"
    ],
    "name:pol_x_preferred":[
        "Ngoma"
    ],
    "name:swa_x_preferred":[
        "Ngoma"
    ],
    "name:swe_x_preferred":[
        "Ngoma"
    ],
    "wof:name":"Ngoma",
    "wof:placetype":"locality"
},
  "geometry": {"coordinates":[29.2462,-2.9304],"type":"Point"}
}