{
  "type": "Feature",
  "properties": {
    "gn:admin1_code":"18.0",
    "gn:asciiname":"Rabiro",
    "gn:country_code":"BI",
    "gn:dem":1653,
    "gn:feature_class":"P",
    "gn:feature_code":"PPLL",
    "gn:name":"Rabiro",
    "gn:population":0,
    "gn:timezone":"Africa/Bujumbura",
    "iso:country":"BI",
    "wof:name":"Rabiro",
    "wof:placetype":"locality"
},
  "geometry": {"coordinates":[30.1258,-2.8457],"type":"Point"}
}