{
  "type": "Feature",
  "properties": {
    "gn:admin1_code":"21",
    "gn:asciiname":"Musenga",
    "gn:country_code":"BI",
    "gn:dem":1592,
    "gn:feature_class":"P",
    "gn:feature_code":"PPL",
    "gn:name":"Musenga",
    "gn:population":0,
    "gn:timezone":"Africa/Bujumbura",
    "iso:country":"BI",
    "wof:name":"Musenga",
    "wof:placetype":"locality"
},
  "geometry": {"coordinates":[30.443,-3.32309],"type":"Point"}
}