{
  "type": "Feature",
  "properties": {
    "gn:admin1_code":"10",
    "gn:asciiname":"Nyamayenzi",
    "gn:country_code":"BI",
    "gn:dem":2082,
    "gn:feature_class":"P",
    "gn:feature_code":"PPLL",
    "gn:name":"Nyamayenzi",
    "gn:population":0,
    "gn:timezone":"Africa/Bujumbura",
    "iso:country":"BI",
    "wof:name":"Nyamayenzi",
    "wof:placetype":"locality"
},
  "geometry": {"coordinates":[29.6148,-3.6461],"type":"Point"}
}