{
  "type": "Feature",
  "properties": {
    "gn:admin1_code":"20",
    "gn:asciiname":"Museno",
    "gn:country_code":"BI",
    "gn:dem":1739,
    "gn:feature_class":"P",
    "gn:feature_code":"PPLL",
    "gn:name":"Museno",
    "gn:population":0,
    "gn:timezone":"Africa/Bujumbura",
    "iso:country":"BI",
    "wof:name":"Museno",
    "wof:placetype":"locality"
},
  "geometry": {"coordinates":[29.9432,-3.9584],"type":"Point"}
}