{
  "type": "Feature",
  "properties": {
    "gn:admin1_code":"15.0",
    "gn:asciiname":"Nyagatobo",
    "gn:country_code":"BI",
    "gn:dem":1689,
    "gn:feature_class":"P",
    "gn:feature_code":"PPLL",
    "gn:name":"Nyagatobo",
    "gn:population":0,
    "gn:timezone":"Africa/Bujumbura",
    "iso:country":"BI",
    "wof:name":"Nyagatobo",
    "wof:placetype":"locality"
},
  "geometry": {"coordinates":[29.7554,-2.9921],"type":"Point"}
}