{
  "type": "Feature",
  "properties": {
    "gn:admin1_code":"21",
    "gn:asciiname":"Kurubuye",
    "gn:country_code":"BI",
    "gn:dem":1243,
    "gn:feature_class":"P",
    "gn:feature_code":"PPLL",
    "gn:name":"Kurubuye",
    "gn:population":0,
    "gn:timezone":"Africa/Bujumbura",
    "iso:country":"BI",
    "wof:name":"Kurubuye",
    "wof:placetype":"locality"
},
  "geometry": {"coordinates":[30.504,-3.5171],"type":"Point"}
}