{
  "type": "Feature",
  "properties": {
    "gn:admin1_code":"14.0",
    "gn:asciiname":"Gikombe",
    "gn:country_code":"BI",
    "gn:dem":1654,
    "gn:feature_class":"P",
    "gn:feature_code":"PPL",
    "gn:name":"Gikombe",
    "gn:population":0,
    "gn:timezone":"Africa/Bujumbura",
    "iso:country":"BI",
    "wof:name":"Gikombe",
    "wof:placetype":"locality"
},
  "geometry": {"coordinates":[30.24454,-3.00889],"type":"Point"}
}