{
  "type": "Feature",
  "properties": {
    "gn:admin1_code":"19.0",
    "gn:asciiname":"Mwungere",
    "gn:country_code":"BI",
    "gn:dem":1655,
    "gn:feature_class":"P",
    "gn:feature_code":"PPLL",
    "gn:name":"Mwungere",
    "gn:population":0,
    "gn:timezone":"Africa/Bujumbura",
    "iso:country":"BI",
    "wof:name":"Mwungere",
    "wof:placetype":"locality"
},
  "geometry": {"coordinates":[29.7982,-2.9273],"type":"Point"}
}