{
  "type": "Feature",
  "properties": {
    "gn:admin1_code":"17",
    "gn:asciiname":"Gakara",
    "gn:country_code":"BI",
    "gn:dem":1783,
    "gn:feature_class":"P",
    "gn:feature_code":"PPLL",
    "gn:name":"Gakara",
    "gn:population":0,
    "gn:timezone":"Africa/Bujumbura",
    "iso:country":"BI",
    "wof:name":"Gakara",
    "wof:placetype":"locality"
},
  "geometry": {"coordinates":[29.7136,-4.216],"type":"Point"}
}