{
  "type": "Feature",
  "properties": {
    "gn:admin1_code":"15.0",
    "gn:asciiname":"Nyabigati",
    "gn:country_code":"BI",
    "gn:dem":1710,
    "gn:feature_class":"P",
    "gn:feature_code":"PPLL",
    "gn:name":"Nyabigati",
    "gn:population":0,
    "gn:timezone":"Africa/Bujumbura",
    "iso:country":"BI",
    "wof:name":"Nyabigati",
    "wof:placetype":"locality"
},
  "geometry": {"coordinates":[29.7129,-3.1035],"type":"Point"}
}