{
  "type": "Feature",
  "properties": {
    "gn:admin1_code":"10",
    "gn:asciiname":"Nyakigi",
    "gn:country_code":"BI",
    "gn:dem":1945,
    "gn:feature_class":"P",
    "gn:feature_code":"PPLL",
    "gn:name":"Nyakigi",
    "gn:population":0,
    "gn:timezone":"Africa/Bujumbura",
    "iso:country":"BI",
    "wof:name":"Nyakigi",
    "wof:placetype":"locality"
},
  "geometry": {"coordinates":[29.7013,-3.7956],"type":"Point"}
}