{
  "type": "Feature",
  "properties": {
    "gn:admin1_code":"13",
    "gn:asciiname":"Bugondo",
    "gn:country_code":"BI",
    "gn:dem":1887,
    "gn:feature_class":"P",
    "gn:feature_code":"PPLL",
    "gn:name":"Bugondo",
    "gn:population":0,
    "gn:timezone":"Africa/Bujumbura",
    "iso:country":"BI",
    "wof:name":"Bugondo",
    "wof:placetype":"locality"
},
  "geometry": {"coordinates":[29.8808,-3.6655],"type":"Point"}
}