{
  "type": "Feature",
  "properties": {
    "gn:admin1_code":"16.0",
    "gn:asciiname":"Marembo",
    "gn:country_code":"BI",
    "gn:dem":1579,
    "gn:feature_class":"P",
    "gn:feature_code":"PPLL",
    "gn:name":"Marembo",
    "gn:population":0,
    "gn:timezone":"Africa/Bujumbura",
    "iso:country":"BI",
    "wof:name":"Marembo",
    "wof:placetype":"locality"
},
  "geometry": {"coordinates":[30.2138,-2.6633],"type":"Point"}
}