{
  "type": "Feature",
  "properties": {
    "gn:admin1_code":"16.0",
    "gn:asciiname":"Muburiba",
    "gn:country_code":"BI",
    "gn:dem":1508,
    "gn:feature_class":"P",
    "gn:feature_code":"PPLL",
    "gn:name":"Muburiba",
    "gn:population":0,
    "gn:timezone":"Africa/Bujumbura",
    "iso:country":"BI",
    "wof:name":"Muburiba",
    "wof:placetype":"locality"
},
  "geometry": {"coordinates":[30.2043,-2.6886],"type":"Point"}
}