{
  "type": "Feature",
  "properties": {
    "gn:admin1_code":"13",
    "gn:asciiname":"Ryagahene",
    "gn:country_code":"BI",
    "gn:dem":1514,
    "gn:feature_class":"P",
    "gn:feature_code":"PPLL",
    "gn:name":"Ryagahene",
    "gn:population":0,
    "gn:timezone":"Africa/Bujumbura",
    "iso:country":"BI",
    "wof:name":"Ryagahene",
    "wof:placetype":"locality"
},
  "geometry": {"coordinates":[29.9925,-3.3756],"type":"Point"}
}