{
  "type": "Feature",
  "properties": {
    "gn:admin1_code":"23",
    "gn:asciiname":"Kamushiha",
    "gn:country_code":"BI",
    "gn:dem":1870,
    "gn:feature_class":"P",
    "gn:feature_code":"PPLL",
    "gn:name":"Kamushiha",
    "gn:population":0,
    "gn:timezone":"Africa/Bujumbura",
    "iso:country":"BI",
    "wof:name":"Kamushiha",
    "wof:placetype":"locality"
},
  "geometry": {"coordinates":[29.7893,-3.348],"type":"Point"}
}