{
  "type": "Feature",
  "properties": {
    "gn:admin1_code":"16.0",
    "gn:asciiname":"Mbasi",
    "gn:country_code":"BI",
    "gn:dem":1557,
    "gn:feature_class":"P",
    "gn:feature_code":"PPLL",
    "gn:name":"Mbasi",
    "gn:population":0,
    "gn:timezone":"Africa/Bujumbura",
    "iso:country":"BI",
    "wof:name":"Mbasi",
    "wof:placetype":"locality"
},
  "geometry": {"coordinates":[30.0975,-2.7629],"type":"Point"}
}