{
  "type": "Feature",
  "properties": {
    "gn:admin1_code":"17",
    "gn:asciiname":"Mahembe",
    "gn:country_code":"BI",
    "gn:dem":1328,
    "gn:feature_class":"P",
    "gn:feature_code":"PPLL",
    "gn:name":"Mahembe",
    "gn:population":0,
    "gn:timezone":"Africa/Bujumbura",
    "iso:country":"BI",
    "wof:name":"Mahembe",
    "wof:placetype":"locality"
},
  "geometry": {"coordinates":[29.6321,-4.1437],"type":"Point"}
}