{
  "type": "Feature",
  "properties": {
    "gn:admin1_code":"18.0",
    "gn:asciiname":"Rusengo",
    "gn:country_code":"BI",
    "gn:dem":1683,
    "gn:feature_class":"P",
    "gn:feature_code":"PPLL",
    "gn:name":"Rusengo",
    "gn:population":0,
    "gn:timezone":"Africa/Bujumbura",
    "iso:country":"BI",
    "wof:name":"Rusengo",
    "wof:placetype":"locality"
},
  "geometry": {"coordinates":[30.2994,-2.9129],"type":"Point"}
}