{
  "type": "Feature",
  "properties": {
    "gn:admin1_code":"14.0",
    "gn:asciiname":"Maramvya",
    "gn:country_code":"BI",
    "gn:dem":1634,
    "gn:feature_class":"P",
    "gn:feature_code":"PPLL",
    "gn:name":"Maramvya",
    "gn:population":0,
    "gn:timezone":"Africa/Bujumbura",
    "iso:country":"BI",
    "wof:name":"Maramvya",
    "wof:placetype":"locality"
},
  "geometry": {"coordinates":[30.1709,-2.9379],"type":"Point"}
}