{
  "type": "Feature",
  "properties": {
    "gn:admin1_code":"17",
    "gn:asciiname":"Nyange",
    "gn:country_code":"BI",
    "gn:dem":1717,
    "gn:feature_class":"P",
    "gn:feature_code":"PPL",
    "gn:name":"Nyange",
    "gn:population":0,
    "gn:timezone":"Africa/Bujumbura",
    "iso:country":"BI",
    "wof:name":"Nyange",
    "wof:placetype":"locality"
},
  "geometry": {"coordinates":[29.8693,-4.1469],"type":"Point"}
}