{
  "type": "Feature",
  "properties": {
    "gn:admin1_code":"17",
    "gn:asciiname":"Gitaba",
    "gn:country_code":"BI",
    "gn:dem":1543,
    "gn:feature_class":"P",
    "gn:feature_code":"PPL",
    "gn:name":"Gitaba",
    "gn:population":0,
    "gn:timezone":"Africa/Bujumbura",
    "iso:country":"BI",
    "wof:name":"Gitaba",
    "wof:placetype":"locality"
},
  "geometry": {"coordinates":[29.7952,-4.0836],"type":"Point"}
}