{
  "type": "Feature",
  "properties": {
    "gn:admin1_code":"26",
    "gn:asciiname":"Gitongwe",
    "gn:country_code":"BI",
    "gn:dem":1359,
    "gn:feature_class":"P",
    "gn:feature_code":"PPLL",
    "gn:name":"Gitongwe",
    "gn:population":0,
    "gn:timezone":"Africa/Bujumbura",
    "iso:country":"BI",
    "wof:name":"Gitongwe",
    "wof:placetype":"locality"
},
  "geometry": {"coordinates":[29.456,-3.8582],"type":"Point"}
}