{
  "type": "Feature",
  "properties": {
    "gn:admin1_code":"25",
    "gn:asciiname":"Nyarukere",
    "gn:country_code":"BI",
    "gn:dem":1769,
    "gn:feature_class":"P",
    "gn:feature_code":"PPLL",
    "gn:name":"Nyarukere",
    "gn:population":0,
    "gn:timezone":"Africa/Bujumbura",
    "iso:country":"BI",
    "wof:name":"Nyarukere",
    "wof:placetype":"locality"
},
  "geometry": {"coordinates":[29.5088,-3.3746],"type":"Point"}
}