{
  "type": "Feature",
  "properties": {
    "gn:admin1_code":"20",
    "gn:asciiname":"Sananda",
    "gn:country_code":"BI",
    "gn:dem":1503,
    "gn:feature_class":"P",
    "gn:feature_code":"PPLL",
    "gn:name":"Sananda",
    "gn:population":0,
    "gn:timezone":"Africa/Bujumbura",
    "iso:country":"BI",
    "name:und_x_variant":[
        "Samanda",
        "Sananda"
    ],
    "wof:name":"Sananda",
    "wof:placetype":"locality"
},
  "geometry": {"coordinates":[30.0907,-3.7845],"type":"Point"}
}