{
  "type": "Feature",
  "properties": {
    "gn:admin1_code":"16.0",
    "gn:asciiname":"Ruyaga",
    "gn:country_code":"BI",
    "gn:dem":1658,
    "gn:feature_class":"P",
    "gn:feature_code":"PPLL",
    "gn:name":"Ruyaga",
    "gn:population":0,
    "gn:timezone":"Africa/Bujumbura",
    "iso:country":"BI",
    "wof:name":"Ruyaga",
    "wof:placetype":"locality"
},
  "geometry": {"coordinates":[30.2431,-2.56],"type":"Point"}
}