{
  "type": "Feature",
  "properties": {
    "gn:admin1_code":"20",
    "gn:asciiname":"Gisuriro",
    "gn:country_code":"BI",
    "gn:dem":1720,
    "gn:feature_class":"P",
    "gn:feature_code":"PPLL",
    "gn:name":"Gisuriro",
    "gn:population":0,
    "gn:timezone":"Africa/Bujumbura",
    "iso:country":"BI",
    "name:und_x_variant":[
        "Kisuriro",
        "Gisuriro"
    ],
    "wof:name":"Gisuriro",
    "wof:placetype":"locality"
},
  "geometry": {"coordinates":[30.068,-3.7458],"type":"Point"}
}