{
  "type": "Feature",
  "properties": {
    "gn:admin1_code":"13",
    "gn:asciiname":"Gasumo",
    "gn:country_code":"BI",
    "gn:dem":1622,
    "gn:feature_class":"P",
    "gn:feature_code":"PPLL",
    "gn:name":"Gasumo",
    "gn:population":0,
    "gn:timezone":"Africa/Bujumbura",
    "iso:country":"BI",
    "wof:name":"Gasumo",
    "wof:placetype":"locality"
},
  "geometry": {"coordinates":[30.0504,-3.5094],"type":"Point"}
}