{
  "type": "Feature",
  "properties": {
    "gn:admin1_code":"19.0",
    "gn:asciiname":"Gakenke",
    "gn:country_code":"BI",
    "gn:dem":1786,
    "gn:feature_class":"P",
    "gn:feature_code":"PPLL",
    "gn:name":"Gakenke",
    "gn:population":0,
    "gn:timezone":"Africa/Bujumbura",
    "iso:country":"BI",
    "wof:name":"Gakenke",
    "wof:placetype":"locality"
},
  "geometry": {"coordinates":[29.7621,-2.8623],"type":"Point"}
}