{
  "type": "Feature",
  "properties": {
    "gn:admin1_code":"9.0",
    "gn:asciiname":"Gakindo",
    "gn:country_code":"BI",
    "gn:dem":1184,
    "gn:feature_class":"P",
    "gn:feature_code":"PPLL",
    "gn:name":"Gakindo",
    "gn:population":0,
    "gn:timezone":"Africa/Bujumbura",
    "iso:country":"BI",
    "wof:name":"Gakindo",
    "wof:placetype":"locality"
},
  "geometry": {"coordinates":[29.3978,-3.0567],"type":"Point"}
}