{
  "type": "Feature",
  "properties": {
    "gn:admin1_code":"22",
    "gn:asciiname":"Gashingwa",
    "gn:country_code":"BI",
    "gn:dem":1894,
    "gn:feature_class":"P",
    "gn:feature_code":"PPLL",
    "gn:name":"Gashingwa",
    "gn:population":0,
    "gn:timezone":"Africa/Bujumbura",
    "iso:country":"BI",
    "wof:name":"Gashingwa",
    "wof:placetype":"locality"
},
  "geometry": {"coordinates":[29.7434,-3.3503],"type":"Point"}
}