{
  "type": "Feature",
  "properties": {
    "gn:admin1_code":"12.0",
    "gn:asciiname":"Negene",
    "gn:country_code":"BI",
    "gn:dem":1742,
    "gn:feature_class":"P",
    "gn:feature_code":"PPLL",
    "gn:name":"Negene",
    "gn:population":0,
    "gn:timezone":"Africa/Bujumbura",
    "iso:country":"BI",
    "wof:name":"Negene",
    "wof:placetype":"locality"
},
  "geometry": {"coordinates":[29.2902,-2.8023],"type":"Point"}
}