{
  "type": "Feature",
  "properties": {
    "gn:admin1_code":"13",
    "gn:asciiname":"Kangozi",
    "gn:country_code":"BI",
    "gn:dem":1760,
    "gn:feature_class":"P",
    "gn:feature_code":"PPLL",
    "gn:name":"Kangozi",
    "gn:population":0,
    "gn:timezone":"Africa/Bujumbura",
    "iso:country":"BI",
    "wof:name":"Kangozi",
    "wof:placetype":"locality"
},
  "geometry": {"coordinates":[29.9351,-3.7309],"type":"Point"}
}