{
  "type": "Feature",
  "properties": {
    "gn:admin1_code":"13",
    "gn:asciiname":"Burunga",
    "gn:country_code":"BI",
    "gn:dem":1707,
    "gn:feature_class":"P",
    "gn:feature_code":"PPLL",
    "gn:name":"Burunga",
    "gn:population":0,
    "gn:timezone":"Africa/Bujumbura",
    "iso:country":"BI",
    "name:ita_x_preferred":[
        "Burunga"
    ],
    "name:spa_x_preferred":[
        "Burunga"
    ],
    "name:zho_x_preferred":[
        "\u5e03\u502b\u52a0"
    ],
    "wof:name":"Burunga",
    "wof:placetype":"locality"
},
  "geometry": {"coordinates":[29.8972,-3.6865],"type":"Point"}
}