{
  "type": "Feature",
  "properties": {
    "gn:admin1_code":"18.0",
    "gn:asciiname":"Nkungu",
    "gn:country_code":"BI",
    "gn:dem":1481,
    "gn:feature_class":"P",
    "gn:feature_code":"PPLL",
    "gn:name":"Nkungu",
    "gn:population":0,
    "gn:timezone":"Africa/Bujumbura",
    "iso:country":"BI",
    "wof:name":"Nkungu",
    "wof:placetype":"locality"
},
  "geometry": {"coordinates":[30.4439,-2.4745],"type":"Point"}
}