{
  "type": "Feature",
  "properties": {
    "gn:admin1_code":"20",
    "gn:asciiname":"Butaha",
    "gn:country_code":"BI",
    "gn:dem":1395,
    "gn:feature_class":"P",
    "gn:feature_code":"PPLL",
    "gn:name":"Butaha",
    "gn:population":0,
    "gn:timezone":"Africa/Bujumbura",
    "iso:country":"BI",
    "wof:name":"Butaha",
    "wof:placetype":"locality"
},
  "geometry": {"coordinates":[30.199,-3.6636],"type":"Point"}
}