{
  "type": "Feature",
  "properties": {
    "gn:admin1_code":"10.0",
    "gn:asciiname":"Musenyi",
    "gn:country_code":"BI",
    "gn:dem":1921,
    "gn:feature_class":"P",
    "gn:feature_code":"PPLL",
    "gn:name":"Musenyi",
    "gn:population":0,
    "gn:timezone":"Africa/Bujumbura",
    "iso:country":"BI",
    "name:run_x_preferred":[
        "Musenyi"
    ],
    "wof:name":"Musenyi",
    "wof:placetype":"locality"
},
  "geometry": {"coordinates":[29.8137,-3.8826],"type":"Point"}
}