{
  "type": "Feature",
  "properties": {
    "gn:admin1_code":"17",
    "gn:asciiname":"Nyabitabo",
    "gn:country_code":"BI",
    "gn:dem":1605,
    "gn:feature_class":"P",
    "gn:feature_code":"PPLL",
    "gn:name":"Nyabitabo",
    "gn:population":0,
    "gn:timezone":"Africa/Bujumbura",
    "iso:country":"BI",
    "wof:name":"Nyabitabo",
    "wof:placetype":"locality"
},
  "geometry": {"coordinates":[29.7363,-4.1978],"type":"Point"}
}