{
  "type": "Feature",
  "properties": {
    "gn:admin1_code":"16.0",
    "gn:asciiname":"Nyabugeni",
    "gn:country_code":"BI",
    "gn:dem":1418,
    "gn:feature_class":"P",
    "gn:feature_code":"PPLL",
    "gn:name":"Nyabugeni",
    "gn:population":0,
    "gn:timezone":"Africa/Bujumbura",
    "iso:country":"BI",
    "wof:name":"Nyabugeni",
    "wof:placetype":"locality"
},
  "geometry": {"coordinates":[30.2326,-2.5224],"type":"Point"}
}