{
  "type": "Feature",
  "properties": {
    "gn:admin1_code":"23",
    "gn:asciiname":"Muramba",
    "gn:country_code":"BI",
    "gn:dem":2154,
    "gn:feature_class":"P",
    "gn:feature_code":"PPLL",
    "gn:name":"Muramba",
    "gn:population":0,
    "gn:timezone":"Africa/Bujumbura",
    "iso:country":"BI",
    "wof:name":"Muramba",
    "wof:placetype":"locality"
},
  "geometry": {"coordinates":[29.6323,-3.4217],"type":"Point"}
}