{
  "type": "Feature",
  "properties": {
    "gn:admin1_code":"13",
    "gn:asciiname":"Kivumu",
    "gn:country_code":"BI",
    "gn:dem":1525,
    "gn:feature_class":"P",
    "gn:feature_code":"PPLL",
    "gn:name":"Kivumu",
    "gn:population":0,
    "gn:timezone":"Africa/Bujumbura",
    "iso:country":"BI",
    "wof:name":"Kivumu",
    "wof:placetype":"locality"
},
  "geometry": {"coordinates":[30.0177,-3.2698],"type":"Point"}
}