{
  "type": "Feature",
  "properties": {
    "gn:admin1_code":"19.0",
    "gn:asciiname":"Kabamba",
    "gn:country_code":"BI",
    "gn:dem":1713,
    "gn:feature_class":"P",
    "gn:feature_code":"PPLL",
    "gn:name":"Kabamba",
    "gn:population":0,
    "gn:timezone":"Africa/Bujumbura",
    "iso:country":"BI",
    "wof:name":"Kabamba",
    "wof:placetype":"locality"
},
  "geometry": {"coordinates":[29.851,-2.8759],"type":"Point"}
}