{
  "type": "Feature",
  "properties": {
    "gn:admin1_code":"16.0",
    "gn:asciiname":"Kimirika",
    "gn:country_code":"BI",
    "gn:dem":1472,
    "gn:feature_class":"P",
    "gn:feature_code":"PPLL",
    "gn:name":"Kimirika",
    "gn:population":0,
    "gn:timezone":"Africa/Bujumbura",
    "iso:country":"BI",
    "wof:name":"Kimirika",
    "wof:placetype":"locality"
},
  "geometry": {"coordinates":[30.2274,-2.6757],"type":"Point"}
}