{
  "type": "Feature",
  "properties": {
    "gn:admin1_code":"11",
    "gn:asciiname":"Nyarutiti",
    "gn:country_code":"BI",
    "gn:dem":1745,
    "gn:feature_class":"P",
    "gn:feature_code":"PPLL",
    "gn:name":"Nyarutiti",
    "gn:population":0,
    "gn:timezone":"Africa/Bujumbura",
    "iso:country":"BI",
    "wof:name":"Nyarutiti",
    "wof:placetype":"locality"
},
  "geometry": {"coordinates":[30.5217,-3.2158],"type":"Point"}
}