{
  "type": "Feature",
  "properties": {
    "gn:admin1_code":"20",
    "gn:asciiname":"Kibinzi",
    "gn:country_code":"BI",
    "gn:dem":1942,
    "gn:feature_class":"P",
    "gn:feature_code":"PPLL",
    "gn:name":"Kibinzi",
    "gn:population":0,
    "gn:timezone":"Africa/Bujumbura",
    "iso:country":"BI",
    "wof:name":"Kibinzi",
    "wof:placetype":"locality"
},
  "geometry": {"coordinates":[30.1398,-3.8869],"type":"Point"}
}