{
  "type": "Feature",
  "properties": {
    "gn:admin1_code":"25",
    "gn:asciiname":"Rweza",
    "gn:country_code":"BI",
    "gn:dem":985,
    "gn:feature_class":"P",
    "gn:feature_code":"PPLL",
    "gn:name":"Rweza",
    "gn:population":0,
    "gn:timezone":"Africa/Bujumbura",
    "iso:country":"BI",
    "wof:name":"Rweza",
    "wof:placetype":"locality"
},
  "geometry": {"coordinates":[29.3873,-3.3969],"type":"Point"}
}