{
  "type": "Feature",
  "properties": {
    "gn:admin1_code":"19.0",
    "gn:asciiname":"Gatabo",
    "gn:country_code":"BI",
    "gn:dem":1683,
    "gn:feature_class":"P",
    "gn:feature_code":"PPLL",
    "gn:name":"Gatabo",
    "gn:population":0,
    "gn:timezone":"Africa/Bujumbura",
    "iso:country":"BI",
    "wof:name":"Gatabo",
    "wof:placetype":"locality"
},
  "geometry": {"coordinates":[29.9379,-2.9266],"type":"Point"}
}