{
  "type": "Feature",
  "properties": {
    "gn:admin1_code":"13.0",
    "gn:asciiname":"Rukorobwa",
    "gn:country_code":"BI",
    "gn:dem":1552,
    "gn:feature_class":"P",
    "gn:feature_code":"PPLL",
    "gn:name":"Rukorobwa",
    "gn:population":0,
    "gn:timezone":"Africa/Bujumbura",
    "iso:country":"BI",
    "name:und_x_variant":[
        "Bukorobwa",
        "Rukorobwa"
    ],
    "wof:name":"Rukorobwa",
    "wof:placetype":"locality"
},
  "geometry": {"coordinates":[29.895,-3.1275],"type":"Point"}
}