{
  "type": "Feature",
  "properties": {
    "gn:admin1_code":"25",
    "gn:asciiname":"Rutambiro",
    "gn:country_code":"BI",
    "gn:dem":1574,
    "gn:feature_class":"P",
    "gn:feature_code":"PPLL",
    "gn:name":"Rutambiro",
    "gn:population":0,
    "gn:timezone":"Africa/Bujumbura",
    "iso:country":"BI",
    "wof:name":"Rutambiro",
    "wof:placetype":"locality"
},
  "geometry": {"coordinates":[29.394,-3.5069],"type":"Point"}
}