{
  "type": "Feature",
  "properties": {
    "gn:admin1_code":"17",
    "gn:asciiname":"Nyabutere",
    "gn:country_code":"BI",
    "gn:dem":1534,
    "gn:feature_class":"P",
    "gn:feature_code":"PPLL",
    "gn:name":"Nyabutere",
    "gn:population":0,
    "gn:timezone":"Africa/Bujumbura",
    "iso:country":"BI",
    "wof:name":"Nyabutere",
    "wof:placetype":"locality"
},
  "geometry": {"coordinates":[29.7879,-4.3525],"type":"Point"}
}