{
  "type": "Feature",
  "properties": {
    "gn:admin1_code":"18.0",
    "gn:asciiname":"Rugari",
    "gn:country_code":"BI",
    "gn:dem":1655,
    "gn:feature_class":"P",
    "gn:feature_code":"PPL",
    "gn:name":"Rugari",
    "gn:population":0,
    "gn:timezone":"Africa/Bujumbura",
    "iso:country":"BI",
    "wof:name":"Rugari",
    "wof:placetype":"locality"
},
  "geometry": {"coordinates":[30.4014,-2.729],"type":"Point"}
}