{
  "type": "Feature",
  "properties": {
    "gn:admin1_code":"16.0",
    "gn:asciiname":"Rwimanzovu",
    "gn:country_code":"BI",
    "gn:dem":1586,
    "gn:feature_class":"P",
    "gn:feature_code":"PPLL",
    "gn:name":"Rwimanzovu",
    "gn:population":0,
    "gn:timezone":"Africa/Bujumbura",
    "iso:country":"BI",
    "wof:name":"Rwimanzovu",
    "wof:placetype":"locality"
},
  "geometry": {"coordinates":[30.1189,-2.7323],"type":"Point"}
}