{
  "type": "Feature",
  "properties": {
    "gn:admin1_code":"21",
    "gn:asciiname":"Curabugufi",
    "gn:country_code":"BI",
    "gn:dem":1552,
    "gn:feature_class":"P",
    "gn:feature_code":"PPLL",
    "gn:name":"Curabugufi",
    "gn:population":0,
    "gn:timezone":"Africa/Bujumbura",
    "iso:country":"BI",
    "wof:name":"Curabugufi",
    "wof:placetype":"locality"
},
  "geometry": {"coordinates":[30.1106,-3.5093],"type":"Point"}
}