{
  "type": "Feature",
  "properties": {
    "gn:admin1_code":"23",
    "gn:asciiname":"Kivoga",
    "gn:country_code":"BI",
    "gn:dem":1686,
    "gn:feature_class":"P",
    "gn:feature_code":"PPLL",
    "gn:name":"Kivoga",
    "gn:population":0,
    "gn:timezone":"Africa/Bujumbura",
    "iso:country":"BI",
    "wof:name":"Kivoga",
    "wof:placetype":"locality"
},
  "geometry": {"coordinates":[29.842,-3.4675],"type":"Point"}
}