{
  "type": "Feature",
  "properties": {
    "gn:admin1_code":"14.0",
    "gn:asciiname":"Bikinga",
    "gn:country_code":"BI",
    "gn:dem":1616,
    "gn:feature_class":"P",
    "gn:feature_code":"PPL",
    "gn:name":"Bikinga",
    "gn:population":0,
    "gn:timezone":"Africa/Bujumbura",
    "iso:country":"BI",
    "wof:name":"Bikinga",
    "wof:placetype":"locality"
},
  "geometry": {"coordinates":[30.12497,-3.03976],"type":"Point"}
}