{
  "type": "Feature",
  "properties": {
    "gn:admin1_code":"12.0",
    "gn:asciiname":"Ruseseka",
    "gn:country_code":"BI",
    "gn:dem":1343,
    "gn:feature_class":"P",
    "gn:feature_code":"PPL",
    "gn:name":"Ruseseka",
    "gn:population":0,
    "gn:timezone":"Africa/Bujumbura",
    "iso:country":"BI",
    "wof:name":"Ruseseka",
    "wof:placetype":"locality"
},
  "geometry": {"coordinates":[29.2167,-2.7438],"type":"Point"}
}