{
  "type": "Feature",
  "properties": {
    "gn:admin1_code":"21",
    "gn:asciiname":"Bigera",
    "gn:country_code":"BI",
    "gn:dem":1596,
    "gn:feature_class":"P",
    "gn:feature_code":"PPLL",
    "gn:name":"Bigera",
    "gn:population":0,
    "gn:timezone":"Africa/Bujumbura",
    "iso:country":"BI",
    "wof:name":"Bigera",
    "wof:placetype":"locality"
},
  "geometry": {"coordinates":[30.1768,-3.4061],"type":"Point"}
}