{
  "type": "Feature",
  "properties": {
    "gn:admin1_code":"26",
    "gn:asciiname":"Muyaga",
    "gn:country_code":"BI",
    "gn:dem":1525,
    "gn:feature_class":"P",
    "gn:feature_code":"PPL",
    "gn:name":"Muyaga",
    "gn:population":0,
    "gn:timezone":"Africa/Bujumbura",
    "iso:country":"BI",
    "wof:name":"Muyaga",
    "wof:placetype":"locality"
},
  "geometry": {"coordinates":[29.5492,-3.8426],"type":"Point"}
}