{
  "type": "Feature",
  "properties": {
    "gn:admin1_code":"12.0",
    "gn:asciiname":"Gitebe",
    "gn:country_code":"BI",
    "gn:dem":1243,
    "gn:feature_class":"P",
    "gn:feature_code":"PPLL",
    "gn:name":"Gitebe",
    "gn:population":0,
    "gn:timezone":"Africa/Bujumbura",
    "iso:country":"BI",
    "wof:name":"Gitebe",
    "wof:placetype":"locality"
},
  "geometry": {"coordinates":[29.0876,-2.7082],"type":"Point"}
}