{
  "type": "Feature",
  "properties": {
    "gn:admin1_code":"10",
    "gn:asciiname":"Nyarugera",
    "gn:country_code":"BI",
    "gn:dem":1962,
    "gn:feature_class":"P",
    "gn:feature_code":"PPLL",
    "gn:name":"Nyarugera",
    "gn:population":0,
    "gn:timezone":"Africa/Bujumbura",
    "iso:country":"BI",
    "wof:name":"Nyarugera",
    "wof:placetype":"locality"
},
  "geometry": {"coordinates":[29.7056,-4.0333],"type":"Point"}
}