{
  "type": "Feature",
  "properties": {
    "gn:admin1_code":"11",
    "gn:asciiname":"Bigarama",
    "gn:country_code":"BI",
    "gn:dem":1517,
    "gn:feature_class":"P",
    "gn:feature_code":"PPLL",
    "gn:name":"Bigarama",
    "gn:population":0,
    "gn:timezone":"Africa/Bujumbura",
    "iso:country":"BI",
    "wof:name":"Bigarama",
    "wof:placetype":"locality"
},
  "geometry": {"coordinates":[30.807,-3.2181],"type":"Point"}
}