{
  "type": "Feature",
  "properties": {
    "gn:admin1_code":"23",
    "gn:asciiname":"Magamba",
    "gn:country_code":"BI",
    "gn:dem":1720,
    "gn:feature_class":"P",
    "gn:feature_code":"PPLL",
    "gn:name":"Magamba",
    "gn:population":0,
    "gn:timezone":"Africa/Bujumbura",
    "iso:country":"BI",
    "wof:name":"Magamba",
    "wof:placetype":"locality"
},
  "geometry": {"coordinates":[29.8185,-3.504],"type":"Point"}
}