{
  "type": "Feature",
  "properties": {
    "gn:admin1_code":"13",
    "gn:asciiname":"Manogo",
    "gn:country_code":"BI",
    "gn:dem":1594,
    "gn:feature_class":"P",
    "gn:feature_code":"PPLL",
    "gn:name":"Manogo",
    "gn:population":0,
    "gn:timezone":"Africa/Bujumbura",
    "iso:country":"BI",
    "wof:name":"Manogo",
    "wof:placetype":"locality"
},
  "geometry": {"coordinates":[29.8762,-3.401],"type":"Point"}
}